Workbook

Sheet Paper_1
A1: Asset | B1: Threat type | C1: Security Attribute | D1: Damage Scenario | E1: Attack Path | F1: Attack vector | G1: Attack Vector Note / Motiv | H1: Safety Impact | I1: Safety Note / Motiv | J1: Financial Impact | K1: Financial Note / Motiv | L1: Operational Impact | M1: Operational Note / Motiv | N1: Privacy and Legislative Impact | O1: Privacy Note / Motiv | P1: Severity Level | Q1: Feasibility Level | R1: Risk Value | S1: Treatment Options | T1: Measures | U1: Affected Design Elements | V1: Justification (Treatment) | W1: Cybersecurity Goals | Y1: s | Z1: f | AA1: o | AB1: p | AC1: impact | AD1: feasibility val | AE1: Risk score
A2: DENM Management Container- StationType | B2: Tampering | C2: Integrity | D2: The sender changes the StationType between two consecutive DENMs. | E2: The attacker needs access to a legitimate or compromised OBU (On-Board Unit) in the vehicle. | F2: Network | G2: This attack involves manipulating the message content (StationType) within the communication network. | H2: Negligible | I2: No immediate safety impact, but misclassification may affect priority-based decision-making. | J2: Moderate | K2: The impact is minimal and does not lead to substantial losses or any financial threat to the organization. | L2: Moderate | M2: It could cause minor disruption or annoyance if the wrong vehicle type is displayed, but it does not affect core functions. | N2: Negligible | O2: Changing the StationType in a DENM does not involve any privacy-sensitive data (e.g., driver or vehicle-specific information) nor does it directly violate legislation. | P2: =IF(AC2>=Reference!$H$2, Reference!$G$2, IF(AC2>=Reference!$H$3, Reference!$G$3, IF(AC2>=Reference!$H$4, Reference!$G$4, IF(AC2>=Reference!$H$5, Reference!$G$5, "")))) -> Moderate | Q2: =IF(F2="Physical", "Very Low", IF(F2="Local", "Low", IF(F2="Adjacent", "Medium", IF(F2="Network", "High", "")))) -> High | R2: =IF(AE2>=Reference!$D$2, Reference!$G$2, IF(AE2>=Reference!$D$3, Reference!$E$3, IF(AE2>=Reference!$D$4, Reference!$E$4, IF(AE2>=Reference!$D$5, Reference!$E$5, "")))) -> Medium | S2: Mitigation | T2: CAM message verification, Digital Signatures, Anomaly Detection, Rate Limiting, Trust-Based Filtering | U2: Authentication (PKI, Certificates), Message Parsing, Trust Management, CAM Validation, Security Policies, Autonomous Decision-Making | V2: Low impact but needs cryptographic checks and cross-verification with CAM messages. | Y2: =IF(H2=Reference!$A$12, Reference!$C$12, IF(H2=Reference!$A$11, Reference!$C$11, IF(H2=Reference!$A$10, Reference!$C$10, IF(H2=Reference!$A$9, Reference!$C$9, 0)))) -> 1 | Z2: =IF(J2=Reference!$A$20, Reference!$C$20, IF(J2=Reference!$A$19, Reference!$C$19, IF(J2=Reference!$A$18, Reference!$C$18, IF(J2=Reference!$A$17, Reference!$C$17, 0)))) -> 4 | AA2: =IF(L2=Reference!$A$28, Reference!$C$28, IF(L2=Reference!$A$27, Reference!$C$27, IF(L2=Reference!$A$26, Reference!$C$26, IF(L2=Reference!$A$25, Reference!$C$25, 0)))) -> 4 | AB2: =IF(N2=Reference!$A$36, Reference!$C$36, IF(N2=Reference!$A$35, Reference!$C$35, IF(N2=Reference!$A$34, Reference!$C$34, IF(N2=Reference!$A$33, Reference!$C$33, 0)))) -> 1 | AC2: =(Reference!$B$2*Y2 + Reference!$B$3*AA2 + Reference!$B$4*Z2 + Reference!$B$5 * AB2)/4 -> 2.8125 | AD2: =IF(Q2=Reference!$C$41, Reference!$D$41, IF(Q2=Reference!$C$42, Reference!$D$42, IF(Q2=Reference!$C$43, Reference!$D$43, IF(Q2=Reference!$C$44, Reference!$D$44, 0)))) -> 10 | AE2: =1 + (AC2 * AD2) -> 29.125
B3: Spoofing | C3: Integrity | D3: The attacker alters the StationType field to falsely represent a roadside unit (RSU) as a vehicle or vice versa, misleading receiving ITS stations about the event source. | E3: Attacker gains network access to the vehicle or RSU communication module to manipulate the StationType field before DENM is broadcasted. | F3: Network | G3: The attacker intends to cause confusion or degrade trust in communication by falsifying the origin of hazard information. | H3: Moderate | I3: Misinformation regarding the station type could cause moderate confusion among drivers, reducing effective responses to hazards. | J3: Moderate | K3: Financial damage is minimal, mainly associated with operational inefficiencies and minor reputational concerns manageable by the organization. | L3: Moderate | M3: Operational inefficiencies due to misallocated attention or minor rerouting resulting from incorrect station type identification. | N3: Moderate | O3: Minimal legislative concerns, no significant privacy violations as StationType does not directly involve sensitive user data. | P3: =IF(AC3>=Reference!$H$2, Reference!$G$2, IF(AC3>=Reference!$H$3, Reference!$G$3, IF(AC3>=Reference!$H$4, Reference!$G$4, IF(AC3>=Reference!$H$5, Reference!$G$5, "")))) -> Major | Q3: =IF(F3="Physical", "Very Low", IF(F3="Local", "Low", IF(F3="Adjacent", "Medium", IF(F3="Network", "High", "")))) -> High | R3: =IF(AE3>=Reference!$D$2, Reference!$G$2, IF(AE3>=Reference!$D$3, Reference!$E$3, IF(AE3>=Reference!$D$4, Reference!$E$4, IF(AE3>=Reference!$D$5, Reference!$E$5, "")))) -> High | S3: Mitigation | T3: Cryptographic authentication and integrity checks on DENM messages.Station type verification protocols to validate incoming message authenticity.Anomaly detection systems monitoring unusual patterns of station type reporting. | U3: OBU and RSU message authentication modules.Backend validation systems for StationType verification.Monitoring and logging mechanisms. | V3: Accurate identification of message origin is critical for maintaining operational efficiency, hazard response reliability, and trustworthiness of the V2X communication system. | W3: Integrity, Authenticity, Non-repudiation. | Y3: =IF(H3=Reference!$A$12, Reference!$C$12, IF(H3=Reference!$A$11, Reference!$C$11, IF(H3=Reference!$A$10, Reference!$C$10, IF(H3=Reference!$A$9, Reference!$C$9, 0)))) -> 4 | Z3: =IF(J3=Reference!$A$20, Reference!$C$20, IF(J3=Reference!$A$19, Reference!$C$19, IF(J3=Reference!$A$18, Reference!$C$18, IF(J3=Reference!$A$17, Reference!$C$17, 0)))) -> 4 | AA3: =IF(L3=Reference!$A$28, Reference!$C$28, IF(L3=Reference!$A$27, Reference!$C$27, IF(L3=Reference!$A$26, Reference!$C$26, IF(L3=Reference!$A$25, Reference!$C$25, 0)))) -> 4 | AB3: =IF(N3=Reference!$A$36, Reference!$C$36, IF(N3=Reference!$A$35, Reference!$C$35, IF(N3=Reference!$A$34, Reference!$C$34, IF(N3=Reference!$A$33, Reference!$C$33, 0)))) -> 4 | AC3: =(Reference!$B$2*Y3 + Reference!$B$3*AA3 + Reference!$B$4*Z3 + Reference!$B$5 * AB3)/4 -> 6.75 | AD3: =IF(Q3=Reference!$C$41, Reference!$D$41, IF(Q3=Reference!$C$42, Reference!$D$42, IF(Q3=Reference!$C$43, Reference!$D$43, IF(Q3=Reference!$C$44, Reference!$D$44, 0)))) -> 10 | AE3: =1 + (AC3 * AD3) -> 68.5
B4: Information disclosure | C4: Confidentiality | D4: An attacker modifies the StationType to falsely identify a regular vehicle or RSU as an emergency vehicle (e.g., ambulance, police car), resulting in incorrect prioritization or response by other vehicles and infrastructure. | E4: Attacker remotely compromises vehicle or RSU communications to inject altered StationType value indicating an emergency vehicle. | F4: Network | G4: Attacker aims to disrupt traffic flow, obtain illegitimate traffic priority, or cause emergency response confusion. | H4: Major | I4: False emergency notifications may lead to sudden braking, confusion, or increased collision risks, potentially resulting in severe injuries. | J4: Major | K4: Substantial financial implications due to liability from potential accidents, significant reputational damage, and increased insurance premiums for stakeholders. | L4: Major | M4: Major operational disruption caused by unnecessary yielding, incorrect rerouting, and reduced efficiency of emergency response services. | N4: Major | O4: Unauthorized alteration of StationType, especially impersonating an emergency or special-purpose vehicle, is a serious privacy and confidentiality breach. This could lead to legal consequences, regulatory actions, and potential media attention. | P4: =IF(AC4>=Reference!$H$2, Reference!$G$2, IF(AC4>=Reference!$H$3, Reference!$G$3, IF(AC4>=Reference!$H$4, Reference!$G$4, IF(AC4>=Reference!$H$5, Reference!$G$5, "")))) -> Severe | Q4: =IF(F4="Physical", "Very Low", IF(F4="Local", "Low", IF(F4="Adjacent", "Medium", IF(F4="Network", "High", "")))) -> High | R4: =IF(AE4>=Reference!$D$2, Reference!$G$2, IF(AE4>=Reference!$D$3, Reference!$E$3, IF(AE4>=Reference!$D$4, Reference!$E$4, IF(AE4>=Reference!$D$5, Reference!$E$5, "")))) -> Severe | S4: Mitigation | T4: Implement stringent cryptographic verification of messages, particularly for special StationTypes (e.g., emergency vehicles).Enhanced access control and authentication measures for systems permitted to broadcast high-priority messages.Behavioral analytics to detect unexpected use of emergency-related StationTypes. | U4: Authentication and validation modules on OBUs and RSUs.Backend traffic management and monitoring systems.Emergency vehicle priority management systems. | V4: Ensuring authenticity of emergency vehicle messages is essential to maintaining public safety, operational traffic management, and preventing malicious exploitation of high-priority status. | W4: Integrity, Authenticity, Non-repudiation, Availability. | Y4: =IF(H4=Reference!$A$12, Reference!$C$12, IF(H4=Reference!$A$11, Reference!$C$11, IF(H4=Reference!$A$10, Reference!$C$10, IF(H4=Reference!$A$9, Reference!$C$9, 0)))) -> 7 | Z4: =IF(J4=Reference!$A$20, Reference!$C$20, IF(J4=Reference!$A$19, Reference!$C$19, IF(J4=Reference!$A$18, Reference!$C$18, IF(J4=Reference!$A$17, Reference!$C$17, 0)))) -> 7 | AA4: =IF(L4=Reference!$A$28, Reference!$C$28, IF(L4=Reference!$A$27, Reference!$C$27, IF(L4=Reference!$A$26, Reference!$C$26, IF(L4=Reference!$A$25, Reference!$C$25, 0)))) -> 7 | AB4: =IF(N4=Reference!$A$36, Reference!$C$36, IF(N4=Reference!$A$35, Reference!$C$35, IF(N4=Reference!$A$34, Reference!$C$34, IF(N4=Reference!$A$33, Reference!$C$33, 0)))) -> 7 | AC4: =(Reference!$B$2*Y4 + Reference!$B$3*AA4 + Reference!$B$4*Z4 + Reference!$B$5 * AB4)/4 -> 11.8125 | AD4: =IF(Q4=Reference!$C$41, Reference!$D$41, IF(Q4=Reference!$C$42, Reference!$D$42, IF(Q4=Reference!$C$43, Reference!$D$43, IF(Q4=Reference!$C$44, Reference!$D$44, 0)))) -> 10 | AE4: =1 + (AC4 * AD4) -> 119.125
A5: DENM Message Container | B5: Denial of service | C5: Availability | D5: Set a very small TxInterval | E5: The attacker gains access to the OBU software or message generation system. | F5: Network | G5: This attack modifies the transmission interval of DENMs, which occurs within the network layer responsible for message dissemination. | H5: Moderate | I5: Network congestion may delay safety-critical messages, affecting V2X efficiency and reaction times. | J5: Moderate | K5: The organization might incur minor additional costs related to bandwidth and network management | L5: Moderate | M5: while V2X network congestion can occur, vehicle operations remain unaffected. | N5: Negligible | O5: The attack does not involve personal data or compromise legal compliance. | P5: =IF(AC5>=Reference!$H$2, Reference!$G$2, IF(AC5>=Reference!$H$3, Reference!$G$3, IF(AC5>=Reference!$H$4, Reference!$G$4, IF(AC5>=Reference!$H$5, Reference!$G$5, "")))) -> Major | Q5: =IF(F5="Physical", "Very Low", IF(F5="Local", "Low", IF(F5="Adjacent", "Medium", IF(F5="Network", "High", "")))) -> High | R5: =IF(AE5>=Reference!$D$2, Reference!$G$2, IF(AE5>=Reference!$D$3, Reference!$E$3, IF(AE5>=Reference!$D$4, Reference!$E$4, IF(AE5>=Reference!$D$5, Reference!$E$5, "")))) -> High | S5: Mitigation | T5: Min TxInterval threshold, Rate Limiting, Congestion Control, IDS for flooding detection, RSU-Based Monitoring | U5: Network Congestion Control, Rate-Limiting, Priority-Based Handling, IDS & Anomaly Detection, OBU/RSU Processing, GeoNetworking | V5: Preventable by applying rate limits, congestion control, and anomaly detection. | Y5: =IF(H5=Reference!$A$12, Reference!$C$12, IF(H5=Reference!$A$11, Reference!$C$11, IF(H5=Reference!$A$10, Reference!$C$10, IF(H5=Reference!$A$9, Reference!$C$9, 0)))) -> 4 | Z5: =IF(J5=Reference!$A$20, Reference!$C$20, IF(J5=Reference!$A$19, Reference!$C$19, IF(J5=Reference!$A$18, Reference!$C$18, IF(J5=Reference!$A$17, Reference!$C$17, 0)))) -> 4 | AA5: =IF(L5=Reference!$A$28, Reference!$C$28, IF(L5=Reference!$A$27, Reference!$C$27, IF(L5=Reference!$A$26, Reference!$C$26, IF(L5=Reference!$A$25, Reference!$C$25, 0)))) -> 4 | AB5: =IF(N5=Reference!$A$36, Reference!$C$36, IF(N5=Reference!$A$35, Reference!$C$35, IF(N5=Reference!$A$34, Reference!$C$34, IF(N5=Reference!$A$33, Reference!$C$33, 0)))) -> 1 | AC5: =(Reference!$B$2*Y5 + Reference!$B$3*AA5 + Reference!$B$4*Z5 + Reference!$B$5 * AB5)/4 -> 6.5625 | AD5: =IF(Q5=Reference!$C$41, Reference!$D$41, IF(Q5=Reference!$C$42, Reference!$D$42, IF(Q5=Reference!$C$43, Reference!$D$43, IF(Q5=Reference!$C$44, Reference!$D$44, 0)))) -> 10 | AE5: =1 + (AC5 * AD5) -> 66.625
A6: DENM Message Container | B6: Tampering | C6: Integrity | D6: Set an inconsistent value of Sub-CauseCode with the context (e.g., requesting winter service during summer) | E6: the attacker modifies the Sub-CauseCode through OBU before broadcasting the manipulated DENM message. | F6: Network | G6: The attack is executed by modifying DENM messages within the OBU before they are broadcast over V2X communication channels (DSRC or C-V2X). | H6: Moderate | I6: The attack does not directly threaten vehicle safety, it can cause disruptions in automated decision-making, traffic inefficiencies, and misallocation of emergency resources. | J6: Moderate | K6: It can lead to waste of operational resources, traffic inefficiencies, and loss of trust in V2X technology, which can impact OEMs, fleet operators, and road authorities financially. | L6: Moderate | M6: It reduces the reliability of traffic event notifications, leading to inefficiencies in resource allocation and vehicle decision-making. | N6: Negligible | O6: No direct privacy violations occur, as the attack does not involve personal data or unauthorized access. | P6: =IF(AC6>=Reference!$H$2, Reference!$G$2, IF(AC6>=Reference!$H$3, Reference!$G$3, IF(AC6>=Reference!$H$4, Reference!$G$4, IF(AC6>=Reference!$H$5, Reference!$G$5, "")))) -> Major | Q6: =IF(F6="Physical", "Very Low", IF(F6="Local", "Low", IF(F6="Adjacent", "Medium", IF(F6="Network", "High", "")))) -> High | R6: =IF(AE6>=Reference!$D$2, Reference!$E$2, IF(AE6>=Reference!$D$3, Reference!$E$3, IF(AE6>=Reference!$D$4, Reference!$E$4, IF(AE6>=Reference!$D$5, Reference!$E$5, "")))) -> High | S6: Mitigation | T6: Cross-validation with sensors, digital signatures, anomaly detection, trust scoring | U6: V2X Message Authentication & Integrity (PKI, Certificates),Event Processing in Vehicles & RSUs | V6: Avoidance is not feasible, as DENMs are a fundamental part of V2X communication and cannot be eliminated. | Y6: =IF(H6=Reference!$A$12, Reference!$C$12, IF(H6=Reference!$A$11, Reference!$C$11, IF(H6=Reference!$A$10, Reference!$C$10, IF(H6=Reference!$A$9, Reference!$C$9, 0)))) -> 4 | Z6: =IF(J6=Reference!$A$20, Reference!$C$20, IF(J6=Reference!$A$19, Reference!$C$19, IF(J6=Reference!$A$18, Reference!$C$18, IF(J6=Reference!$A$17, Reference!$C$17, 0)))) -> 4 | AA6: =IF(L6=Reference!$A$28, Reference!$C$28, IF(L6=Reference!$A$27, Reference!$C$27, IF(L6=Reference!$A$26, Reference!$C$26, IF(L6=Reference!$A$25, Reference!$C$25, 0)))) -> 4 | AB6: =IF(N6=Reference!$A$36, Reference!$C$36, IF(N6=Reference!$A$35, Reference!$C$35, IF(N6=Reference!$A$34, Reference!$C$34, IF(N6=Reference!$A$33, Reference!$C$33, 0)))) -> 1 | AC6: =(Reference!$B$2*Y6 + Reference!$B$3*AA6 + Reference!$B$4*Z6 + Reference!$B$5 * AB6)/4 -> 6.5625 | AD6: =IF(Q6=Reference!$C$41, Reference!$D$41, IF(Q6=Reference!$C$42, Reference!$D$42, IF(Q6=Reference!$C$43, Reference!$D$43, IF(Q6=Reference!$C$44, Reference!$D$44, 0)))) -> 10 | AE6: =1 + (AC6 * AD6) -> 66.625
A7: DENM Message Container | B7: Tampering | C7: Integrity | D7: The attacker modifies the CauseCode field in the Situation Container of a DENM to provide false or misleading information.(e.g "Accident" is assigned to a simple roadwork event, possibly triggering unnecessary emergency responses.) | E7: Gain Access to the OBU’s V2X Communication Stack to Exploit firmware vulnerabilities, misconfigured permissions, or debugging interfaces. | F7: Network | G7: The attack is executed by modifying DENM messages within the OBU before they are broadcast over V2X communication channels. | H7: Major | I7: False reports can directly impact traffic safety, particularly for automated driving systems that rely on V2X data. | J7: Moderate | K7: While not catastrophic, misallocated resources, traffic congestion, and reputation damage can lead to financial losses. | L7: Major | M7: The attack does not fully disable V2X, but it can cause significant traffic disruptions, emergency misallocations, and trust degradation. | N7: Negligible | O7: No direct privacy violation, but false emergency responses could create legal issues over time. | P7: =IF(AC7>=Reference!$H$2, Reference!$G$2, IF(AC7>=Reference!$H$3, Reference!$G$3, IF(AC7>=Reference!$H$4, Reference!$G$4, IF(AC7>=Reference!$H$5, Reference!$G$5, "")))) -> Severe | Q7: =IF(F7="Physical", "Very Low", IF(F7="Local", "Low", IF(F7="Adjacent", "Medium", IF(F7="Network", "High", "")))) -> High | R7: =IF(AE7>=Reference!$D$2, Reference!$G$2, IF(AE7>=Reference!$D$3, Reference!$E$3, IF(AE7>=Reference!$D$4, Reference!$E$4, IF(AE7>=Reference!$D$5, Reference!$E$5, "")))) -> Severe | S7: Mitigation | T7: Cross-Validation with Sensor Data&Message Authentication & Digital Signatures | U7: V2X Message Authentication & Integrity,Event Processing in Vehicles & RSUs | Y7: =IF(H7=Reference!$A$12, Reference!$C$12, IF(H7=Reference!$A$11, Reference!$C$11, IF(H7=Reference!$A$10, Reference!$C$10, IF(H7=Reference!$A$9, Reference!$C$9, 0)))) -> 7 | Z7: =IF(J7=Reference!$A$20, Reference!$C$20, IF(J7=Reference!$A$19, Reference!$C$19, IF(J7=Reference!$A$18, Reference!$C$18, IF(J7=Reference!$A$17, Reference!$C$17, 0)))) -> 4 | AA7: =IF(L7=Reference!$A$28, Reference!$C$28, IF(L7=Reference!$A$27, Reference!$C$27, IF(L7=Reference!$A$26, Reference!$C$26, IF(L7=Reference!$A$25, Reference!$C$25, 0)))) -> 7 | AB7: =IF(N7=Reference!$A$36, Reference!$C$36, IF(N7=Reference!$A$35, Reference!$C$35, IF(N7=Reference!$A$34, Reference!$C$34, IF(N7=Reference!$A$33, Reference!$C$33, 0)))) -> 1 | AC7: =(Reference!$B$2*Y7 + Reference!$B$3*AA7 + Reference!$B$4*Z7 + Reference!$B$5 * AB7)/4 -> 11.0625 | AD7: =IF(Q7=Reference!$C$41, Reference!$D$41, IF(Q7=Reference!$C$42, Reference!$D$42, IF(Q7=Reference!$C$43, Reference!$D$43, IF(Q7=Reference!$C$44, Reference!$D$44, 0)))) -> 10 | AE7: =1 + (AC7 * AD7) -> 111.625
A8: DENM Message Container | B8: Tampering | C8: Integrity | D8: The attacker modifies or inserts new path points in the Traces field within the Location Container, creating an incorrect path history of a road event. | E8: Attacker gains access to the OBU’s V2X Communication Stack to exploit firmware vulnerabilities, misconfigured permissions, or debugging interfaces. | F8: Network | G8: The attack is executed by modifying DENM messages within the OBU before they are broadcast over V2X communication channels. | H8: Moderate | I8: False path data can disrupt navigation and vehicle decision-making, but does not directly compromise vehicle control. | J8: Moderate | K8: While not catastrophic, misallocated resources, traffic congestion, and reputation damage can lead to financial losses. | L8: Major | M8: The attack does not fully disable V2X, but it can cause significant traffic disruptions, emergency misallocations, and trust degradation. | N8: Negligible | O8: No direct privacy violation, but false emergency responses could create legal issues over time. | P8: =IF(AC8>=Reference!$H$2, Reference!$G$2, IF(AC8>=Reference!$H$3, Reference!$G$3, IF(AC8>=Reference!$H$4, Reference!$G$4, IF(AC8>=Reference!$H$5, Reference!$G$5, "")))) -> Major | Q8: =IF(F8="Physical", "Very Low", IF(F8="Local", "Low", IF(F8="Adjacent", "Medium", IF(F8="Network", "High", "")))) -> High | R8: =IF(AE8>=Reference!$D$2, Reference!$G$2, IF(AE8>=Reference!$D$3, Reference!$E$3, IF(AE8>=Reference!$D$4, Reference!$E$4, IF(AE8>=Reference!$D$5, Reference!$E$5, "")))) -> High | S8: Mitigation | T8: Cross-Validation with Sensor Data,Historical Consistency Checks | U8: V2X Message Authentication & Integrity, Event Processing in Vehicles & RSUs | Y8: =IF(H8=Reference!$A$12, Reference!$C$12, IF(H8=Reference!$A$11, Reference!$C$11, IF(H8=Reference!$A$10, Reference!$C$10, IF(H8=Reference!$A$9, Reference!$C$9, 0)))) -> 4 | Z8: =IF(J8=Reference!$A$20, Reference!$C$20, IF(J8=Reference!$A$19, Reference!$C$19, IF(J8=Reference!$A$18, Reference!$C$18, IF(J8=Reference!$A$17, Reference!$C$17, 0)))) -> 4 | AA8: =IF(L8=Reference!$A$28, Reference!$C$28, IF(L8=Reference!$A$27, Reference!$C$27, IF(L8=Reference!$A$26, Reference!$C$26, IF(L8=Reference!$A$25, Reference!$C$25, 0)))) -> 7 | AB8: =IF(N8=Reference!$A$36, Reference!$C$36, IF(N8=Reference!$A$35, Reference!$C$35, IF(N8=Reference!$A$34, Reference!$C$34, IF(N8=Reference!$A$33, Reference!$C$33, 0)))) -> 1 | AC8: =(Reference!$B$2*Y8 + Reference!$B$3*AA8 + Reference!$B$4*Z8 + Reference!$B$5 * AB8)/4 -> 7.3125 | AD8: =IF(Q8=Reference!$C$41, Reference!$D$41, IF(Q8=Reference!$C$42, Reference!$D$42, IF(Q8=Reference!$C$43, Reference!$D$43, IF(Q8=Reference!$C$44, Reference!$D$44, 0)))) -> 10 | AE8: =1 + (AC8 * AD8) -> 74.125
A9: DENM Message Container | B9: Spoofing | C9: Integrity | D9: The attacker modifies the VehicleIdentification field in the A La Carte Container, making it appear as if the DENM was sent from another legitimate vehicle. | E9: Attacker gains access to the OBU’s V2X Communication Stack to exploit firmware vulnerabilities, misconfigured permissions, or debugging interfaces. | F9: Network | G9: The attack is executed by modifying DENM messages within the OBU before they are broadcast over V2X communication channels. | H9: Negligible | I9: This attack does not pose a direct safety risk, but can degrade the trust and efficiency of V2X communications. | J9: Moderate | K9: The financial impact is minimal, as the attack does not cause direct economic losses but may require mitigation costs for improved authentication mechanisms. | L9: Negligible | M9: The attack does not fully disrupt V2X, but it can cause trust degradation and minor disruptions in vehicle identification systems. | N9: Major | O9: Spoofing vehicle identification in V2X communications can lead to privacy violations affecting vehicle owners and operators. Impersonation of a legitimate vehicle could result in legal issues, misuse of stolen identities for unauthorized actions, and potential financial penalties for affected stakeholders. | P9: =IF(AC9>=Reference!$H$2, Reference!$G$2, IF(AC9>=Reference!$H$3, Reference!$G$3, IF(AC9>=Reference!$H$4, Reference!$G$4, IF(AC9>=Reference!$H$5, Reference!$G$5, "")))) -> Negligible | Q9: =IF(F9="Physical", "Very Low", IF(F9="Local", "Low", IF(F9="Adjacent", "Medium", IF(F9="Network", "High", "")))) -> High | R9: =IF(AE9>=Reference!$D$2, Reference!$G$2, IF(AE9>=Reference!$D$3, Reference!$E$3, IF(AE9>=Reference!$D$4, Reference!$E$4, IF(AE9>=Reference!$D$5, Reference!$E$5, "")))) -> Medium | S9: Mitigation | T9: Public Key Infrastructure (PKI) for Vehicle Authentication | U9: V2X Message Authentication & Integrity | V9: Best approach, as authentication mechanisms can detect and prevent identity spoofing. | Y9: =IF(H9=Reference!$A$12, Reference!$C$12, IF(H9=Reference!$A$11, Reference!$C$11, IF(H9=Reference!$A$10, Reference!$C$10, IF(H9=Reference!$A$9, Reference!$C$9, 0)))) -> 1 | Z9: =IF(J9=Reference!$A$20, Reference!$C$20, IF(J9=Reference!$A$19, Reference!$C$19, IF(J9=Reference!$A$18, Reference!$C$18, IF(J9=Reference!$A$17, Reference!$C$17, 0)))) -> 4 | AA9: =IF(L9=Reference!$A$28, Reference!$C$28, IF(L9=Reference!$A$27, Reference!$C$27, IF(L9=Reference!$A$26, Reference!$C$26, IF(L9=Reference!$A$25, Reference!$C$25, 0)))) -> 1 | AB9: =IF(N9=Reference!$A$36, Reference!$C$36, IF(N9=Reference!$A$35, Reference!$C$35, IF(N9=Reference!$A$34, Reference!$C$34, IF(N9=Reference!$A$33, Reference!$C$33, 0)))) -> 7 | AC9: =(Reference!$B$2*Y9 + Reference!$B$3*AA9 + Reference!$B$4*Z9 + Reference!$B$5 * AB9)/4 -> 2.4375 | AD9: =IF(Q9=Reference!$C$41, Reference!$D$41, IF(Q9=Reference!$C$42, Reference!$D$42, IF(Q9=Reference!$C$43, Reference!$D$43, IF(Q9=Reference!$C$44, Reference!$D$44, 0)))) -> 10 | AE9: =1 + (AC9 * AD9) -> 25.375
B10: Information disclosure | C10: Confidentiality | D10: The attacker modifies the VehicleIdentification field in the A La Carte Container, making it appear as if the DENM was sent from another legitimate vehicle. | E10: Attacker gains access to the OBU’s V2X Communication Stack to exploit firmware vulnerabilities, misconfigured permissions, or debugging interfaces. | F10: Network | G10: The attack is executed by modifying DENM messages within the OBU before they are broadcast over V2X communication channels. | H10: Negligible | I10: This attack does not pose a direct safety risk, but can degrade the trust and efficiency of V2X communications. | J10: Moderate | K10: The financial impact is minimal, as the attack does not cause direct economic losses but may require mitigation costs for improved authentication mechanisms. | L10: Negligible | M10: The attack does not fully disrupt V2X, but it can cause trust degradation and minor disruptions in vehicle identification systems. | N10: Major | O10: Spoofing vehicle identification in V2X communications can lead to privacy violations affecting vehicle owners and operators. Impersonation of a legitimate vehicle could result in legal issues, misuse of stolen identities for unauthorized actions, and potential financial penalties for affected stakeholders. | P10: =IF(AC10>=Reference!$H$2, Reference!$G$2, IF(AC10>=Reference!$H$3, Reference!$G$3, IF(AC10>=Reference!$H$4, Reference!$G$4, IF(AC10>=Reference!$H$5, Reference!$G$5, "")))) -> Negligible | Q10: =IF(F10="Physical", "Very Low", IF(F10="Local", "Low", IF(F10="Adjacent", "Medium", IF(F10="Network", "High", "")))) -> High | R10: =IF(AE10>=Reference!$D$2, Reference!$G$2, IF(AE10>=Reference!$D$3, Reference!$E$3, IF(AE10>=Reference!$D$4, Reference!$E$4, IF(AE10>=Reference!$D$5, Reference!$E$5, "")))) -> Medium | S10: Mitigation | T10: Public Key Infrastructure (PKI) for Vehicle Authentication | U10: V2X Message Authentication & Integrity | V10: Best approach, as authentication mechanisms can detect and prevent identity spoofing. | Y10: =IF(H10=Reference!$A$12, Reference!$C$12, IF(H10=Reference!$A$11, Reference!$C$11, IF(H10=Reference!$A$10, Reference!$C$10, IF(H10=Reference!$A$9, Reference!$C$9, 0)))) -> 1 | Z10: =IF(J10=Reference!$A$20, Reference!$C$20, IF(J10=Reference!$A$19, Reference!$C$19, IF(J10=Reference!$A$18, Reference!$C$18, IF(J10=Reference!$A$17, Reference!$C$17, 0)))) -> 4 | AA10: =IF(L10=Reference!$A$28, Reference!$C$28, IF(L10=Reference!$A$27, Reference!$C$27, IF(L10=Reference!$A$26, Reference!$C$26, IF(L10=Reference!$A$25, Reference!$C$25, 0)))) -> 1 | AB10: =IF(N10=Reference!$A$36, Reference!$C$36, IF(N10=Reference!$A$35, Reference!$C$35, IF(N10=Reference!$A$34, Reference!$C$34, IF(N10=Reference!$A$33, Reference!$C$33, 0)))) -> 7 | AC10: =(Reference!$B$2*Y10 + Reference!$B$3*AA10 + Reference!$B$4*Z10 + Reference!$B$5 * AB10)/4 -> 2.4375 | AD10: =IF(Q10=Reference!$C$41, Reference!$D$41, IF(Q10=Reference!$C$42, Reference!$D$42, IF(Q10=Reference!$C$43, Reference!$D$43, IF(Q10=Reference!$C$44, Reference!$D$44, 0)))) -> 10 | AE10: =1 + (AC10 * AD10) -> 25.375
A11: DENM Message Container | B11: Tampering | C11: Integrity | D11: The attacker modifies the Lane Position field in the A La Carte Container, making it appear as if a road event (e.g., accident, road closure, stationary vehicle) is occurring in the wrong lane or road, causing vehicles to receive incorrect hazard locations, potentially leading to accidents. | E11: Attacker gains access to the OBU’s V2X Communication Stack to exploit firmware vulnerabilities, misconfigured permissions, or debugging interfaces. | F11: Network | G11: The attack is executed by modifying DENM messages within the OBU before they are broadcast over V2X communication channels. | H11: Severe | I11: False lane reports can directly impact traffic safety, particularly for automated driving systems that rely on V2X data. | J11: Severe | K11: Severe accidents due to incorrect lane positioning could lead to fatalities, lawsuits, regulatory fines, and reputational damage, posing an existential financial risk for OEMs and infrastructure operators. | L11: Severe | M11: Incorrect lane positioning can mislead vehicle control systems, potentially leading to incorrect lane changes or unsafe driving behavior, severely affecting vehicle operation and regulatory compliance. | N11: Negligible | O11: No direct privacy violation, but false lane reports could create legal concerns regarding accident liability. | P11: =IF(AC11>=Reference!$H$2, Reference!$G$2, IF(AC11>=Reference!$H$3, Reference!$G$3, IF(AC11>=Reference!$H$4, Reference!$G$4, IF(AC11>=Reference!$H$5, Reference!$G$5, "")))) -> Severe | Q11: =IF(F11="Physical", "Very Low", IF(F11="Local", "Low", IF(F11="Adjacent", "Medium", IF(F11="Network", "High", "")))) -> High | R11: =IF(AE11>=Reference!$D$2, Reference!$G$2, IF(AE11>=Reference!$D$3, Reference!$E$3, IF(AE11>=Reference!$D$4, Reference!$E$4, IF(AE11>=Reference!$D$5, Reference!$E$5, "")))) -> Severe | S11: Mitigation | T11: Cross-Validation with Sensor Data,Historical Consistency Checks,Message Authentication & Digital Signatures | U11: V2X Message Authentication & Integrity | V11: Authentication mechanisms can detect and prevent lane tampering. | Y11: =IF(H11=Reference!$A$12, Reference!$C$12, IF(H11=Reference!$A$11, Reference!$C$11, IF(H11=Reference!$A$10, Reference!$C$10, IF(H11=Reference!$A$9, Reference!$C$9, 0)))) -> 10 | Z11: =IF(J11=Reference!$A$20, Reference!$C$20, IF(J11=Reference!$A$19, Reference!$C$19, IF(J11=Reference!$A$18, Reference!$C$18, IF(J11=Reference!$A$17, Reference!$C$17, 0)))) -> 10 | AA11: =IF(L11=Reference!$A$28, Reference!$C$28, IF(L11=Reference!$A$27, Reference!$C$27, IF(L11=Reference!$A$26, Reference!$C$26, IF(L11=Reference!$A$25, Reference!$C$25, 0)))) -> 10 | AB11: =IF(N11=Reference!$A$36, Reference!$C$36, IF(N11=Reference!$A$35, Reference!$C$35, IF(N11=Reference!$A$34, Reference!$C$34, IF(N11=Reference!$A$33, Reference!$C$33, 0)))) -> 1 | AC11: =(Reference!$B$2*Y11 + Reference!$B$3*AA11 + Reference!$B$4*Z11 + Reference!$B$5 * AB11)/4 -> 16.3125 | AD11: =IF(Q11=Reference!$C$41, Reference!$D$41, IF(Q11=Reference!$C$42, Reference!$D$42, IF(Q11=Reference!$C$43, Reference!$D$43, IF(Q11=Reference!$C$44, Reference!$D$44, 0)))) -> 10 | AE11: =1 + (AC11 * AD11) -> 164.125
A12: DENM Message Container | B12: Elevation of privilege | C12: Integrity | D12: The attacker modifies the VehicleIdentification field to impersonate or access resources specific to high-value or critical vehicles (e.g., emergency vehicles, luxury cars). | E12: Attacker gains access to the OBU’s V2X Communication Stack to exploit firmware vulnerabilities or debugging interfaces and inject malicious software via physical access or over-the-air updates. | F12: Network | G12: The attack is executed by modifying outgoing DENM messages through the OBU, and the malicious messages are transmitted over the network to other entities. | H12: Severe | I12: Misuse of VehicleIdentification can lead to severe accidents, life-threatening injuries, or fatalities. | J12: Severe | K12: Vehicle theft or misuse can cause significant financial damage that could threaten organizational sustainability. | L12: Severe | M12: Exploiting high-value vehicles or resource allocation mechanisms can significantly degrade system functionality. | N12: Severe | O12: Widespread misuse of VehicleIdentification can trigger legal consequences and media attention. | P12: =IF(AC12>=Reference!$H$2, Reference!$G$2, IF(AC12>=Reference!$H$3, Reference!$G$3, IF(AC12>=Reference!$H$4, Reference!$G$4, IF(AC12>=Reference!$H$5, Reference!$G$5, "")))) -> Severe | Q12: =IF(F12="Physical", "Very Low", IF(F12="Local", "Low", IF(F12="Adjacent", "Medium", IF(F12="Network", "High", "")))) -> High | R12: =IF(AE12>=Reference!$D$2, Reference!$G$2, IF(AE12>=Reference!$D$3, Reference!$E$3, IF(AE12>=Reference!$D$4, Reference!$E$4, IF(AE12>=Reference!$D$5, Reference!$E$5, "")))) -> Severe | S12: Mitigation | T12: Public Key Infrastructure (PKI) for Vehicle Authentication ,Rate Limiting for VehicleIdentification Updates | U12: V2X Message Authentication & Integrity,Trust & Reputation Systems,Event Processing in Vehicles & RSUs | V12: Best approach, involving detection, authentication, and anomaly detection | Y12: =IF(H12=Reference!$A$12, Reference!$C$12, IF(H12=Reference!$A$11, Reference!$C$11, IF(H12=Reference!$A$10, Reference!$C$10, IF(H12=Reference!$A$9, Reference!$C$9, 0)))) -> 10 | Z12: =IF(J12=Reference!$A$20, Reference!$C$20, IF(J12=Reference!$A$19, Reference!$C$19, IF(J12=Reference!$A$18, Reference!$C$18, IF(J12=Reference!$A$17, Reference!$C$17, 0)))) -> 10 | AA12: =IF(L12=Reference!$A$28, Reference!$C$28, IF(L12=Reference!$A$27, Reference!$C$27, IF(L12=Reference!$A$26, Reference!$C$26, IF(L12=Reference!$A$25, Reference!$C$25, 0)))) -> 10 | AB12: =IF(N12=Reference!$A$36, Reference!$C$36, IF(N12=Reference!$A$35, Reference!$C$35, IF(N12=Reference!$A$34, Reference!$C$34, IF(N12=Reference!$A$33, Reference!$C$33, 0)))) -> 10 | AC12: =(Reference!$B$2*Y12 + Reference!$B$3*AA12 + Reference!$B$4*Z12 + Reference!$B$5 * AB12)/4 -> 16.875 | AD12: =IF(Q12=Reference!$C$41, Reference!$D$41, IF(Q12=Reference!$C$42, Reference!$D$42, IF(Q12=Reference!$C$43, Reference!$D$43, IF(Q12=Reference!$C$44, Reference!$D$44, 0)))) -> 10 | AE12: =1 + (AC12 * AD12) -> 169.75
A13: High Frequency (HF) Container in CAM Messages | B13: Tampering | C13: Integrity | D13: An attacker modifies the speed value within the HF container of outgoing CAM messages to falsely indicate that the vehicle ahead is moving slower or is stationary. | E13: Attacker gains access to the OBU’s V2X Communication System to exploit vulnerabilities in the vehicle’s firmware or OBU and inject malicious software or commands through physical or wireless access. | F13: Network | G13: The tampered speed value is broadcast via compromised CAM messages over the V2X network, impacting other vehicles. | H13: Severe | I13: The HF container includes vehicle speed, critical for detecting collisions. Tampering with this can cause hard braking, evasive maneuvers, or incorrect responses, leading to life-threatening situations and potential fatalities. This risk is especially high for autonomous vehicles. | J13: Severe | K13: Severe collisions could result in vehicle damage, emergency response costs, legal penalties, and loss of trust in V2X technology, affecting OEMs financially. | L13: Severe | M13: Severe collisions could result in vehicle damage, emergency response costs, legal penalties, and loss of trust in V2X technology, affecting OEMs financially. | N13: Moderate | O13: Since the HF container doesn’t contain personal identifiers, the privacy impact is low, but legal liability may arise from collisions caused by tampered data. | P13: =IF(AC13>=Reference!$H$2, Reference!$G$2, IF(AC13>=Reference!$H$3, Reference!$G$3, IF(AC13>=Reference!$H$4, Reference!$G$4, IF(AC13>=Reference!$H$5, Reference!$G$5, "")))) -> Severe | Q13: =IF(F13="Physical", "Very Low", IF(F13="Local", "Low", IF(F13="Adjacent", "Medium", IF(F13="Network", "High", "")))) -> High | R13: =IF(AE13>=Reference!$D$2, Reference!$G$2, IF(AE13>=Reference!$D$3, Reference!$E$3, IF(AE13>=Reference!$D$4, Reference!$E$4, IF(AE13>=Reference!$D$5, Reference!$E$5, "")))) -> Severe | S13: Mitigation | T13: Message Authentication & Digital Signatures,Anomaly Detection Systems,Cross-Validation with Onboard Sensors | V13: Best approach, involving message authentication, cross-verification, and anomaly detection. | Y13: =IF(H13=Reference!$A$12, Reference!$C$12, IF(H13=Reference!$A$11, Reference!$C$11, IF(H13=Reference!$A$10, Reference!$C$10, IF(H13=Reference!$A$9, Reference!$C$9, 0)))) -> 10 | Z13: =IF(J13=Reference!$A$20, Reference!$C$20, IF(J13=Reference!$A$19, Reference!$C$19, IF(J13=Reference!$A$18, Reference!$C$18, IF(J13=Reference!$A$17, Reference!$C$17, 0)))) -> 10 | AA13: =IF(L13=Reference!$A$28, Reference!$C$28, IF(L13=Reference!$A$27, Reference!$C$27, IF(L13=Reference!$A$26, Reference!$C$26, IF(L13=Reference!$A$25, Reference!$C$25, 0)))) -> 10 | AB13: =IF(N13=Reference!$A$36, Reference!$C$36, IF(N13=Reference!$A$35, Reference!$C$35, IF(N13=Reference!$A$34, Reference!$C$34, IF(N13=Reference!$A$33, Reference!$C$33, 0)))) -> 4 | AC13: =(Reference!$B$2*Y13 + Reference!$B$3*AA13 + Reference!$B$4*Z13 + Reference!$B$5 * AB13)/4 -> 16.5 | AD13: =IF(Q13=Reference!$C$41, Reference!$D$41, IF(Q13=Reference!$C$42, Reference!$D$42, IF(Q13=Reference!$C$43, Reference!$D$43, IF(Q13=Reference!$C$44, Reference!$D$44, 0)))) -> 10 | AE13: =1 + (AC13 * AD13) -> 166
A14: High Frequency (HF) Container in CAM Messages | B14: Spoofing | C14: Integrity | D14: An attacker injects false CAM messages with incorrect position data, causing the receiving vehicle to believe that an adjacent lane is occupied when it’s actually clear or vice versa. | E14: Through Externally Injected or Compromised OBU CAM Messages | F14: Network | G14: The spoofed vehicle position is transmitted via compromised CAM messages over the V2X network, impacting the lane change logic of other vehicles. | H14: Major | I14: Spoofed vehicle positions can cause side collisions during lane changes, especially at high speeds or in heavy traffic. The threat is particularly critical for autonomous and semi-autonomous vehicles relying on CAMs for situational awareness. | J14: Major | K14: Damage to vehicles due to side collisions could lead to repair costs, insurance claims, and legal liabilities for the OEM or vehicle owners. | L14: Major | M14: Incorrect lane change warnings could cause delays or temporary traffic disruptions, but these would be localized unless multiple vehicles are affected simultaneously. | N14: Major | O14: Limited privacy concerns, but if collisions occur, regulatory investigations or legal action may arise due to improper handling of spoofed messages. | P14: =IF(AC14>=Reference!$H$2, Reference!$G$2, IF(AC14>=Reference!$H$3, Reference!$G$3, IF(AC14>=Reference!$H$4, Reference!$G$4, IF(AC14>=Reference!$H$5, Reference!$G$5, "")))) -> Severe | Q14: =IF(F14="Physical", "Very Low", IF(F14="Local", "Low", IF(F14="Adjacent", "Medium", IF(F14="Network", "High", "")))) -> High | R14: =IF(AE14>=Reference!$D$2, Reference!$G$2, IF(AE14>=Reference!$D$3, Reference!$E$3, IF(AE14>=Reference!$D$4, Reference!$E$4, IF(AE14>=Reference!$D$5, Reference!$E$5, "")))) -> Severe | S14: Mitigation | T14: Message Authentication & Digital Signatures,Cross-Validation with Onboard Sensors,Anomaly Detection Systems | U14: High Frequency (HF) Container,Position Verification Mechanisms,Lane Change Assistance Systems,Traffic Coordination Systems | V14: Best approach, involving message authentication, cross-validation, and anomaly detection. | Y14: =IF(H14=Reference!$A$12, Reference!$C$12, IF(H14=Reference!$A$11, Reference!$C$11, IF(H14=Reference!$A$10, Reference!$C$10, IF(H14=Reference!$A$9, Reference!$C$9, 0)))) -> 7 | Z14: =IF(J14=Reference!$A$20, Reference!$C$20, IF(J14=Reference!$A$19, Reference!$C$19, IF(J14=Reference!$A$18, Reference!$C$18, IF(J14=Reference!$A$17, Reference!$C$17, 0)))) -> 7 | AA14: =IF(L14=Reference!$A$28, Reference!$C$28, IF(L14=Reference!$A$27, Reference!$C$27, IF(L14=Reference!$A$26, Reference!$C$26, IF(L14=Reference!$A$25, Reference!$C$25, 0)))) -> 7 | AB14: =IF(N14=Reference!$A$36, Reference!$C$36, IF(N14=Reference!$A$35, Reference!$C$35, IF(N14=Reference!$A$34, Reference!$C$34, IF(N14=Reference!$A$33, Reference!$C$33, 0)))) -> 7 | AC14: =(Reference!$B$2*Y14 + Reference!$B$3*AA14 + Reference!$B$4*Z14 + Reference!$B$5 * AB14)/4 -> 11.8125 | AD14: =IF(Q14=Reference!$C$41, Reference!$D$41, IF(Q14=Reference!$C$42, Reference!$D$42, IF(Q14=Reference!$C$43, Reference!$D$43, IF(Q14=Reference!$C$44, Reference!$D$44, 0)))) -> 10 | AE14: =1 + (AC14 * AD14) -> 119.125
A15: Basic Container in CAM Messages | B15: Spoofing | C15: Integrity | D15: The attacker broadcasts CAM messages indicating that their vehicle is an emergency vehicle using a spoofed Vehicle Role or Vehicle Identification in the Basic Container. | E15: Through Compromised OBU or Externally Spoofed CAMs | F15: Network | G15: The spoofed emergency vehicle CAMs are transmitted over the V2X network, impacting multiple vehicles and traffic systems. | H15: Major | I15: Delays in yielding to actual emergency vehicles can result in life-threatening injuries if medical or police assistance is delayed. False yielding could also cause accidents if vehicles react incorrectly. | J15: Major | K15: False yielding could cause damage to vehicles, delays in goods transportation, and legal liabilities for OEMs and traffic system operators. | L15: Severe | M15: Emergency response delays and misuse of traffic resources could cause widespread traffic disruptions. | N15: Severe | O15: High legislative impact due to potential regulatory violations involving misuse of emergency vehicle privileges. Repeated incidents could result in legal action against system operators or OEMs | P15: =IF(AC15>=Reference!$H$2, Reference!$G$2, IF(AC15>=Reference!$H$3, Reference!$G$3, IF(AC15>=Reference!$H$4, Reference!$G$4, IF(AC15>=Reference!$H$5, Reference!$G$5, "")))) -> Severe | Q15: =IF(F15="Physical", "Very Low", IF(F15="Local", "Low", IF(F15="Adjacent", "Medium", IF(F15="Network", "High", "")))) -> High | R15: =IF(AE15>=Reference!$D$2, Reference!$G$2, IF(AE15>=Reference!$D$3, Reference!$E$3, IF(AE15>=Reference!$D$4, Reference!$E$4, IF(AE15>=Reference!$D$5, Reference!$E$5, "")))) -> Severe | S15: Mitigation | T15: Certificate-Based Authentication,Cross-Validation with Other Sensors or Traffic Cameras,SSP Permissions Enforcement | U15: Basic Container (Vehicle Role/Identification),V2X Message Verification & Trust Mechanisms,Traffic Light Control Systems | V15: Best option, involving message authentication, cross-validation, and privilege-based access. | Y15: =IF(H15=Reference!$A$12, Reference!$C$12, IF(H15=Reference!$A$11, Reference!$C$11, IF(H15=Reference!$A$10, Reference!$C$10, IF(H15=Reference!$A$9, Reference!$C$9, 0)))) -> 7 | Z15: =IF(J15=Reference!$A$20, Reference!$C$20, IF(J15=Reference!$A$19, Reference!$C$19, IF(J15=Reference!$A$18, Reference!$C$18, IF(J15=Reference!$A$17, Reference!$C$17, 0)))) -> 7 | AA15: =IF(L15=Reference!$A$28, Reference!$C$28, IF(L15=Reference!$A$27, Reference!$C$27, IF(L15=Reference!$A$26, Reference!$C$26, IF(L15=Reference!$A$25, Reference!$C$25, 0)))) -> 10 | AB15: =IF(N15=Reference!$A$36, Reference!$C$36, IF(N15=Reference!$A$35, Reference!$C$35, IF(N15=Reference!$A$34, Reference!$C$34, IF(N15=Reference!$A$33, Reference!$C$33, 0)))) -> 10 | AC15: =(Reference!$B$2*Y15 + Reference!$B$3*AA15 + Reference!$B$4*Z15 + Reference!$B$5 * AB15)/4 -> 12.75 | AD15: =IF(Q15=Reference!$C$41, Reference!$D$41, IF(Q15=Reference!$C$42, Reference!$D$42, IF(Q15=Reference!$C$43, Reference!$D$43, IF(Q15=Reference!$C$44, Reference!$D$44, 0)))) -> 10 | AE15: =1 + (AC15 * AD15) -> 128.5
B16: Tampering | C16: Integrity | D16: The attacker intentionally alters the Station Type field within the Basic Container of the CAM message, switching it between valid types (e.g., from personal vehicle to public transport or infrastructure unit). This manipulation can be used to bypass access controls, filtering, or prioritization mechanisms in receiving ITS-S nodes or RSUs, allowing malicious data to be accepted or propagated. | E16: The attacker, having access to the ITS-S stack (via software exploit or unauthorized configuration), modifies the Station Type field during CAM composition. CAMs are then periodically sent via standard CA service routines, but now with misleading identity type, triggering wrong trust assumptions. | F16: Local | G16: The attacker has internal access to the originating ITS-S software (e.g., compromised onboard unit). | H16: Moderate | I16: A spoofed station type could cause traffic to respond inappropriately (e.g., yielding to a fake emergency vehicle or treating a malicious node as an RSU), potentially causing unsafe behavior. | J16: Moderate | K16: Minimal direct financial damage unless used as part of broader attack (e.g., toll evasion or infrastructure abuse). | L16: Major | M16: Disrupts traffic flow logic, network prioritization, and service-specific policies (e.g., rerouting, prioritization). | N16: Moderate | O16: Misuse of station identity can breach regulatory compliance (e.g., impersonating emergency vehicles) and may expose legal liability to OEMs or operators. | P16: =IF(AC16>=Reference!$H$2, Reference!$G$2, IF(AC16>=Reference!$H$3, Reference!$G$3, IF(AC16>=Reference!$H$4, Reference!$G$4, IF(AC16>=Reference!$H$5, Reference!$G$5, "")))) -> Major | Q16: =IF(F16="Physical", "Very Low", IF(F16="Local", "Low", IF(F16="Adjacent", "Medium", IF(F16="Network", "High", "")))) -> Low | R16: =IF(AE16>=Reference!$D$2, Reference!$G$2, IF(AE16>=Reference!$D$3, Reference!$E$3, IF(AE16>=Reference!$D$4, Reference!$E$4, IF(AE16>=Reference!$D$5, Reference!$E$5, "")))) -> Medium | S16: Mitigation | T16: Certificate-based authentication (ETSI TS 103 097) Plausibility checks: e.g., does "RSU" have a fixed position and no dynamics? Logging sudden station type changes and linking to system alerts. | U16: CAM CA service (generation logic) ITS-S security credential provisioning RSU/V2X trust policies in receivers | V16: Altering the StationType misleads ITS-S nodes into applying incorrect trust models, which may suppress scrutiny, prioritize malicious traffic, or trigger traffic adaptations based on false roles (e.g., route clearance for "emergency vehicle"). | W16: G2: Message Integrity G4: Source Authentication G6: Message Freshness (indirectly if trust assumptions delay validation or revoke logic) | Y16: =IF(H16=Reference!$A$12, Reference!$C$12, IF(H16=Reference!$A$11, Reference!$C$11, IF(H16=Reference!$A$10, Reference!$C$10, IF(H16=Reference!$A$9, Reference!$C$9, 0)))) -> 4 | Z16: =IF(J16=Reference!$A$20, Reference!$C$20, IF(J16=Reference!$A$19, Reference!$C$19, IF(J16=Reference!$A$18, Reference!$C$18, IF(J16=Reference!$A$17, Reference!$C$17, 0)))) -> 4 | AA16: =IF(L16=Reference!$A$28, Reference!$C$28, IF(L16=Reference!$A$27, Reference!$C$27, IF(L16=Reference!$A$26, Reference!$C$26, IF(L16=Reference!$A$25, Reference!$C$25, 0)))) -> 7 | AB16: =IF(N16=Reference!$A$36, Reference!$C$36, IF(N16=Reference!$A$35, Reference!$C$35, IF(N16=Reference!$A$34, Reference!$C$34, IF(N16=Reference!$A$33, Reference!$C$33, 0)))) -> 4 | AC16: =(Reference!$B$2*Y16 + Reference!$B$3*AA16 + Reference!$B$4*Z16 + Reference!$B$5 * AB16)/4 -> 7.5 | AD16: =IF(Q16=Reference!$C$41, Reference!$D$41, IF(Q16=Reference!$C$42, Reference!$D$42, IF(Q16=Reference!$C$43, Reference!$D$43, IF(Q16=Reference!$C$44, Reference!$D$44, 0)))) -> 4 | AE16: =1 + (AC16 * AD16) -> 31
B17: Repudiation | C17: Integrity | D17: The attacker intentionally alters the Station Type field within the Basic Container of the CAM message, switching it between valid types (e.g., from personal vehicle to public transport or infrastructure unit). This manipulation can be used to bypass access controls, filtering, or prioritization mechanisms in receiving ITS-S nodes or RSUs, allowing malicious data to be accepted or propagated. | E17: The attacker, having access to the ITS-S stack (via software exploit or unauthorized configuration), modifies the Station Type field during CAM composition. CAMs are then periodically sent via standard CA service routines, but now with misleading identity type, triggering wrong trust assumptions. | F17: Adjacent | G17: The attacker might spoof messages via another nearby device that broadcasts falsified Station Type. | H17: Moderate | I17: A spoofed station type could cause traffic to respond inappropriately (e.g., yielding to a fake emergency vehicle or treating a malicious node as an RSU), potentially causing unsafe behavior. | J17: Moderate | K17: Minimal direct financial damage unless used as part of broader attack (e.g., toll evasion or infrastructure abuse). | L17: Major | M17: Disrupts traffic flow logic, network prioritization, and service-specific policies (e.g., rerouting, prioritization). | N17: Moderate | O17: Misuse of station identity can breach regulatory compliance (e.g., impersonating emergency vehicles) and may expose legal liability to OEMs or operators. | P17: =IF(AC17>=Reference!$H$2, Reference!$G$2, IF(AC17>=Reference!$H$3, Reference!$G$3, IF(AC17>=Reference!$H$4, Reference!$G$4, IF(AC17>=Reference!$H$5, Reference!$G$5, "")))) -> Major | Q17: =IF(F17="Physical", "Very Low", IF(F17="Local", "Low", IF(F17="Adjacent", "Medium", IF(F17="Network", "High", "")))) -> Medium | R17: =IF(AE17>=Reference!$D$2, Reference!$G$2, IF(AE17>=Reference!$D$3, Reference!$E$3, IF(AE17>=Reference!$D$4, Reference!$E$4, IF(AE17>=Reference!$D$5, Reference!$E$5, "")))) -> High | S17: Mitigation | T17: Certificate-based authentication (ETSI TS 103 097) Plausibility checks: e.g., does "RSU" have a fixed position and no dynamics? Logging sudden station type changes and linking to system alerts. | U17: CAM CA service (generation logic) ITS-S security credential provisioning RSU/V2X trust policies in receivers | V17: Altering the StationType misleads ITS-S nodes into applying incorrect trust models, which may suppress scrutiny, prioritize malicious traffic, or trigger traffic adaptations based on false roles (e.g., route clearance for "emergency vehicle"). | W17: G2: Message Integrity G4: Source Authentication G6: Message Freshness (indirectly if trust assumptions delay validation or revoke logic) | Y17: =IF(H17=Reference!$A$12, Reference!$C$12, IF(H17=Reference!$A$11, Reference!$C$11, IF(H17=Reference!$A$10, Reference!$C$10, IF(H17=Reference!$A$9, Reference!$C$9, 0)))) -> 4 | Z17: =IF(J17=Reference!$A$20, Reference!$C$20, IF(J17=Reference!$A$19, Reference!$C$19, IF(J17=Reference!$A$18, Reference!$C$18, IF(J17=Reference!$A$17, Reference!$C$17, 0)))) -> 4 | AA17: =IF(L17=Reference!$A$28, Reference!$C$28, IF(L17=Reference!$A$27, Reference!$C$27, IF(L17=Reference!$A$26, Reference!$C$26, IF(L17=Reference!$A$25, Reference!$C$25, 0)))) -> 7 | AB17: =IF(N17=Reference!$A$36, Reference!$C$36, IF(N17=Reference!$A$35, Reference!$C$35, IF(N17=Reference!$A$34, Reference!$C$34, IF(N17=Reference!$A$33, Reference!$C$33, 0)))) -> 4 | AC17: =(Reference!$B$2*Y17 + Reference!$B$3*AA17 + Reference!$B$4*Z17 + Reference!$B$5 * AB17)/4 -> 7.5 | AD17: =IF(Q17=Reference!$C$41, Reference!$D$41, IF(Q17=Reference!$C$42, Reference!$D$42, IF(Q17=Reference!$C$43, Reference!$D$43, IF(Q17=Reference!$C$44, Reference!$D$44, 0)))) -> 7 | AE17: =1 + (AC17 * AD17) -> 53.5
A18: Low Frequency (LF) Container in CAM messages | B18: Tampering | C18: Integrity | D18: An attacker modifies or injects false location data for roadworks in CAM messages, misinforming nearby vehicles and traffic systems. | E18: Through Compromised RSU or OBU Transmitting CAMs | F18: Network | G18: The tampered location data is transmitted through compromised CAM messages over the V2X network, impacting vehicles and road infrastructure systems. | H18: Major | I18: Incorrect roadwork warnings could cause vehicles to take unsafe detours, enter restricted zones, or collide with obstacles. | J18: Major | K18: Financial losses due to damaged vehicles, delayed deliveries, road repair expenses, and potential legal claims against road authorities. | L18: Major | M18: Misallocation of traffic could lead to temporary congestion and traffic flow disruption, but these impacts may be localized unless widely exploited. | N18: Moderate | O18: Minor privacy concerns, but regulatory liabilities may arise if tampered warnings lead to accidents or road damage. | P18: =IF(AC18>=Reference!$H$2, Reference!$G$2, IF(AC18>=Reference!$H$3, Reference!$G$3, IF(AC18>=Reference!$H$4, Reference!$G$4, IF(AC18>=Reference!$H$5, Reference!$G$5, "")))) -> Severe | Q18: =IF(F18="Physical", "Very Low", IF(F18="Local", "Low", IF(F18="Adjacent", "Medium", IF(F18="Network", "High", "")))) -> High | R18: =IF(AE18>=Reference!$D$2, Reference!$G$2, IF(AE18>=Reference!$D$3, Reference!$E$3, IF(AE18>=Reference!$D$4, Reference!$E$4, IF(AE18>=Reference!$D$5, Reference!$E$5, "")))) -> Severe | S18: Mitigation | T18: Digital Signatures and Message Authentication,Cross-Validation of Location Data,Traffic Camera or Lidar Integration | U18: Low Frequency (LF) Container (Location Data),Traffic Management Systems,V2X Message Integrity Verification,Navigation and Route Planning Systems | V18: Best approach, involving digital signatures, GPS-based validation, and anomaly detection. | Y18: =IF(H18=Reference!$A$12, Reference!$C$12, IF(H18=Reference!$A$11, Reference!$C$11, IF(H18=Reference!$A$10, Reference!$C$10, IF(H18=Reference!$A$9, Reference!$C$9, 0)))) -> 7 | Z18: =IF(J18=Reference!$A$20, Reference!$C$20, IF(J18=Reference!$A$19, Reference!$C$19, IF(J18=Reference!$A$18, Reference!$C$18, IF(J18=Reference!$A$17, Reference!$C$17, 0)))) -> 7 | AA18: =IF(L18=Reference!$A$28, Reference!$C$28, IF(L18=Reference!$A$27, Reference!$C$27, IF(L18=Reference!$A$26, Reference!$C$26, IF(L18=Reference!$A$25, Reference!$C$25, 0)))) -> 7 | AB18: =IF(N18=Reference!$A$36, Reference!$C$36, IF(N18=Reference!$A$35, Reference!$C$35, IF(N18=Reference!$A$34, Reference!$C$34, IF(N18=Reference!$A$33, Reference!$C$33, 0)))) -> 4 | AC18: =(Reference!$B$2*Y18 + Reference!$B$3*AA18 + Reference!$B$4*Z18 + Reference!$B$5 * AB18)/4 -> 11.625 | AD18: =IF(Q18=Reference!$C$41, Reference!$D$41, IF(Q18=Reference!$C$42, Reference!$D$42, IF(Q18=Reference!$C$43, Reference!$D$43, IF(Q18=Reference!$C$44, Reference!$D$44, 0)))) -> 10 | AE18: =1 + (AC18 * AD18) -> 117.25
A19: HF Container in CAM Messages | B19: Tampering | C19: Integrity | D19: The attacker modifies the speed or position data in the CAM messages of the lead or following vehicle in the platoon, causing incorrect decisions regarding following distance and braking. | E19: Through Compromised OBU or V2X Network Injection | F19: Network | G19: The tampered speed or position values are transmitted via compromised CAM messages over the V2X network, impacting multiple vehicles in the platoon. | H19: Severe | I19: Incorrect speed or following distance could lead to rear-end collisions, potentially involving multiple vehicles. The threat is especially critical in high-speed platoons, where reaction times are reduced. | J19: Severe | K19: High financial costs due to vehicle damage, logistics delays, and potential legal claims against the platoon operator or OEMs. Multi-vehicle accidents could result in significant repair and insurance claims. | L19: Major | M19: Disruption of platoon operations can lead to traffic congestion and delays in delivery schedules. Recovery and realignment of the platoon could require manual intervention. | N19: Severe | O19: If the tampering results in accidents or near-misses, regulatory investigations could result in legal liability for V2X system operators. OEMs may face privacy and safety-related fines or penalties. | P19: =IF(AC19>=Reference!$H$2, Reference!$G$2, IF(AC19>=Reference!$H$3, Reference!$G$3, IF(AC19>=Reference!$H$4, Reference!$G$4, IF(AC19>=Reference!$H$5, Reference!$G$5, "")))) -> Severe | Q19: =IF(F19="Physical", "Very Low", IF(F19="Local", "Low", IF(F19="Adjacent", "Medium", IF(F19="Network", "High", "")))) -> High | R19: =IF(AE19>=Reference!$D$2, Reference!$G$2, IF(AE19>=Reference!$D$3, Reference!$E$3, IF(AE19>=Reference!$D$4, Reference!$E$4, IF(AE19>=Reference!$D$5, Reference!$E$5, "")))) -> Severe | S19: Mitigation | T19: Digital Signatures and Message Authentication,Cross-Validation with Onboard Sensors,Anomaly Detection Systems,Adaptive Following Distance Control,SSP-Based Permissions | U19: High Frequency (HF) Container (Speed & Position Data),V2X Communication Protocols ,Platoon Control Systems,Distance Monitoring Systems | V19: Best approach, involving strong cryptographic protections and anomaly detection mechanisms. | Y19: =IF(H19=Reference!$A$12, Reference!$C$12, IF(H19=Reference!$A$11, Reference!$C$11, IF(H19=Reference!$A$10, Reference!$C$10, IF(H19=Reference!$A$9, Reference!$C$9, 0)))) -> 10 | Z19: =IF(J19=Reference!$A$20, Reference!$C$20, IF(J19=Reference!$A$19, Reference!$C$19, IF(J19=Reference!$A$18, Reference!$C$18, IF(J19=Reference!$A$17, Reference!$C$17, 0)))) -> 10 | AA19: =IF(L19=Reference!$A$28, Reference!$C$28, IF(L19=Reference!$A$27, Reference!$C$27, IF(L19=Reference!$A$26, Reference!$C$26, IF(L19=Reference!$A$25, Reference!$C$25, 0)))) -> 7 | AB19: =IF(N19=Reference!$A$36, Reference!$C$36, IF(N19=Reference!$A$35, Reference!$C$35, IF(N19=Reference!$A$34, Reference!$C$34, IF(N19=Reference!$A$33, Reference!$C$33, 0)))) -> 10 | AC19: =(Reference!$B$2*Y19 + Reference!$B$3*AA19 + Reference!$B$4*Z19 + Reference!$B$5 * AB19)/4 -> 16.125 | AD19: =IF(Q19=Reference!$C$41, Reference!$D$41, IF(Q19=Reference!$C$42, Reference!$D$42, IF(Q19=Reference!$C$43, Reference!$D$43, IF(Q19=Reference!$C$44, Reference!$D$44, 0)))) -> 10 | AE19: =1 + (AC19 * AD19) -> 162.25
A20: High Frequency (HF) Container in CAM Messages | B20: Tampering | C20: Integrity | D20: The attacker modifies the brake status or deceleration value in the High Frequency (HF) Container of CAM messages, falsely indicating either a sudden braking event or masking an actual emergency brake. | E20: Through Compromised OBU or Network Injection of Tampered CAMs | F20: Network | G20: The tampered brake light status is transmitted via compromised CAM messages over the V2X network, leading to incorrect vehicle responses. | H20: Severe | I20: False emergency braking could cause rear-end collisions, particularly at high speeds. Suppressing actual brake warnings could lead to severe collisions with life-threatening injuries. | J20: Severe | K20: Rear-end collisions and multi-vehicle pile-ups could result in extensive vehicle damage, legal claims, and insurance costs. | L20: Severe | M20: Chain-reaction braking could cause major traffic congestion and disrupt vehicle flows on highways or major roads. | N20: Major | O20: OEMs and traffic management systems could face regulatory investigations and legal liability for not securing brake warnings in V2X communications | P20: =IF(AC20>=Reference!$H$2, Reference!$G$2, IF(AC20>=Reference!$H$3, Reference!$G$3, IF(AC20>=Reference!$H$4, Reference!$G$4, IF(AC20>=Reference!$H$5, Reference!$G$5, "")))) -> Severe | Q20: =IF(F20="Physical", "Very Low", IF(F20="Local", "Low", IF(F20="Adjacent", "Medium", IF(F20="Network", "High", "")))) -> High | R20: =IF(AE20>=Reference!$D$2, Reference!$G$2, IF(AE20>=Reference!$D$3, Reference!$E$3, IF(AE20>=Reference!$D$4, Reference!$E$4, IF(AE20>=Reference!$D$5, Reference!$E$5, "")))) -> Severe | S20: Mitigation | T20: Digital signatures, cross-validation, and anomaly detection. | U20: High Frequency (HF) Container (Brake Status & Deceleration),Autonomous Emergency Braking (AEB) Systems | V20: Best approach, involving cryptographic protections, cross-validation, and anomaly detection. | Y20: =IF(H20=Reference!$A$12, Reference!$C$12, IF(H20=Reference!$A$11, Reference!$C$11, IF(H20=Reference!$A$10, Reference!$C$10, IF(H20=Reference!$A$9, Reference!$C$9, 0)))) -> 10 | Z20: =IF(J20=Reference!$A$20, Reference!$C$20, IF(J20=Reference!$A$19, Reference!$C$19, IF(J20=Reference!$A$18, Reference!$C$18, IF(J20=Reference!$A$17, Reference!$C$17, 0)))) -> 10 | AA20: =IF(L20=Reference!$A$28, Reference!$C$28, IF(L20=Reference!$A$27, Reference!$C$27, IF(L20=Reference!$A$26, Reference!$C$26, IF(L20=Reference!$A$25, Reference!$C$25, 0)))) -> 10 | AB20: =IF(N20=Reference!$A$36, Reference!$C$36, IF(N20=Reference!$A$35, Reference!$C$35, IF(N20=Reference!$A$34, Reference!$C$34, IF(N20=Reference!$A$33, Reference!$C$33, 0)))) -> 7 | AC20: =(Reference!$B$2*Y20 + Reference!$B$3*AA20 + Reference!$B$4*Z20 + Reference!$B$5 * AB20)/4 -> 16.6875 | AD20: =IF(Q20=Reference!$C$41, Reference!$D$41, IF(Q20=Reference!$C$42, Reference!$D$42, IF(Q20=Reference!$C$43, Reference!$D$43, IF(Q20=Reference!$C$44, Reference!$D$44, 0)))) -> 10 | AE20: =1 + (AC20 * AD20) -> 167.875
A21: Basic Container of CAM messages | B21: Spoofing | C21: Integrity | D21: An attacker spoofs the Station ID or the vehicle’s reference position (latitude, longitude, altitude) in outgoing CAM messages, causing nearby vehicles or RSUs to incorrectly interpret the vehicle’s identity or location. | E21: Through Compromised OBU or External Spoofing | F21: Network | G21: The spoofed Station ID and reference position data are transmitted through tampered CAM messages over the V2X network, affecting vehicles, RSUs, and traffic management systems. | H21: Major | I21: Incorrect position data could cause vehicles to maneuver unsafely, leading to side collisions, wrong turns, or near-misses in intersections. Misleading position data could prevent effective collision avoidance | J21: Major | K21: High financial losses could result from vehicle damage, legal claims, and resource misallocation due to traffic congestion. Spoofed identities could also trigger liability concerns for OEMs. | L21: Major | M21: Misleading position data could cause disruptions in vehicle routing, platooning, or lane assignments, resulting in major traffic delays or congestion. | N21: Severe | O21: Misuse of pseudonym IDs could lead to privacy violations, legal investigations, and reputation damage for V2X system operators. Persistent spoofing may require regulatory responses or fines. | P21: =IF(AC21>=Reference!$H$2, Reference!$G$2, IF(AC21>=Reference!$H$3, Reference!$G$3, IF(AC21>=Reference!$H$4, Reference!$G$4, IF(AC21>=Reference!$H$5, Reference!$G$5, "")))) -> Severe | Q21: =IF(F21="Physical", "Very Low", IF(F21="Local", "Low", IF(F21="Adjacent", "Medium", IF(F21="Network", "High", "")))) -> High | R21: =IF(AE21>=Reference!$D$2, Reference!$G$2, IF(AE21>=Reference!$D$3, Reference!$E$3, IF(AE21>=Reference!$D$4, Reference!$E$4, IF(AE21>=Reference!$D$5, Reference!$E$5, "")))) -> Severe | S21: Mitigation | T21: Digital signatures, pseudonym management, and anomaly detection. | U21: Basic Container (Station ID, Reference Position),V2X Authentication Mechanisms,Event Processing Systems in Vehicles | V21: Best approach, involving digital signatures, cross-verification, and anomaly detection. | Y21: =IF(H21=Reference!$A$12, Reference!$C$12, IF(H21=Reference!$A$11, Reference!$C$11, IF(H21=Reference!$A$10, Reference!$C$10, IF(H21=Reference!$A$9, Reference!$C$9, 0)))) -> 7 | Z21: =IF(J21=Reference!$A$20, Reference!$C$20, IF(J21=Reference!$A$19, Reference!$C$19, IF(J21=Reference!$A$18, Reference!$C$18, IF(J21=Reference!$A$17, Reference!$C$17, 0)))) -> 7 | AA21: =IF(L21=Reference!$A$28, Reference!$C$28, IF(L21=Reference!$A$27, Reference!$C$27, IF(L21=Reference!$A$26, Reference!$C$26, IF(L21=Reference!$A$25, Reference!$C$25, 0)))) -> 7 | AB21: =IF(N21=Reference!$A$36, Reference!$C$36, IF(N21=Reference!$A$35, Reference!$C$35, IF(N21=Reference!$A$34, Reference!$C$34, IF(N21=Reference!$A$33, Reference!$C$33, 0)))) -> 10 | AC21: =(Reference!$B$2*Y21 + Reference!$B$3*AA21 + Reference!$B$4*Z21 + Reference!$B$5 * AB21)/4 -> 12 | AD21: =IF(Q21=Reference!$C$41, Reference!$D$41, IF(Q21=Reference!$C$42, Reference!$D$42, IF(Q21=Reference!$C$43, Reference!$D$43, IF(Q21=Reference!$C$44, Reference!$D$44, 0)))) -> 10 | AE21: =1 + (AC21 * AD21) -> 121
A22: CAM Channel Availability & Congestion Control Mechanism | B22: Tampering | C22: Integrity | D22: An attacker manipulates the CAM generation logic of their ITS-S, reducing the generation interval below the defined T_GenCamMin = 100 ms. This causes the ITS-S to broadcast CAMs excessively and overwhelm the shared wireless V2X channel. | E22: The attacker either directly modifies the CA service logic (e.g., via firmware hacking or malicious configuration) or exploits the CAM triggering conditions by falsely simulating high dynamic changes (e.g., position, speed, heading) to repeatedly trigger CAM emissions | F22: Local | G22: The attacker directly modifies the configuration of their own vehicle’s ITS-S (e.g., via debug access, firmware manipulation) to override T_GenCamMin or simulate rapid dynamics to trigger CAMs continuously. | H22: Moderate | I22: Critical safety-related CAMs (e.g., emergency braking, vehicle position) may be dropped or delayed. | J22: Moderate | K22: Minimal financial impact unless the issue becomes systemic or persistent. | L22: Major | M22: ITS services dependent on CAMs become unreliable; congestion, collision warnings, and cooperative functions are impaired. | N22: Moderate | O22: Violates standard ETSI CAM transmission rules and DCC compliance, potentially causing certification failure or fines. | P22: =IF(AC22>=Reference!$H$2, Reference!$G$2, IF(AC22>=Reference!$H$3, Reference!$G$3, IF(AC22>=Reference!$H$4, Reference!$G$4, IF(AC22>=Reference!$H$5, Reference!$G$5, "")))) -> Major | Q22: =IF(F22="Physical", "Very Low", IF(F22="Local", "Low", IF(F22="Adjacent", "Medium", IF(F22="Network", "High", "")))) -> Low | R22: =IF(AE22>=Reference!$D$2, Reference!$G$2, IF(AE22>=Reference!$D$3, Reference!$E$3, IF(AE22>=Reference!$D$4, Reference!$E$4, IF(AE22>=Reference!$D$5, Reference!$E$5, "")))) -> Medium | S22: Mitigation | T22: Enforce DCC Policies: Ensure that the DCC service always enforces T_GenCamMin and overrides any locally manipulated values. Rate Limiting at Network Layer: Drop CAMs exceeding a threshold at the network interface layer. Misbehavior Detection (MBD): Detect ITS-Ss sending abnormally frequent CAMs and report them to the central authority for revocation. Secure Firmware and Debug Access: Prevent unauthorized local access to firmware settings that manage CA timing logic. | U22: CA Service (CAM Generation Logic) DCC Parameters (T_GenCamMin, T_GenCamMax, T_GenCam_Dcc) Channel Load Monitoring System ITS Networking & Transport Layer (delivery and suppression of messages) | V22: Mitigation is appropriate because this threat has a moderate safety and high operational impact, and can be systematically addressed with technical countermeasures like DCC enforcement, rate monitoring, and misbehavior reporting. Total avoidance is not feasible due to the importance of real-time dynamics in CAM logic, and acceptance is not viable due to potential safety degradation. | W22: G1 – Ensure authenticity of ITS messages (CAMs must be valid and not artificially triggered). G3 – Ensure availability of the V2X communication channel. G4 – Preserve integrity of network timing policies (DCC parameters). G8 – Ensure compliance with ETSI EN 302 637-2 and DCC constraints. | Y22: =IF(H22=Reference!$A$12, Reference!$C$12, IF(H22=Reference!$A$11, Reference!$C$11, IF(H22=Reference!$A$10, Reference!$C$10, IF(H22=Reference!$A$9, Reference!$C$9, 0)))) -> 4 | Z22: =IF(J22=Reference!$A$20, Reference!$C$20, IF(J22=Reference!$A$19, Reference!$C$19, IF(J22=Reference!$A$18, Reference!$C$18, IF(J22=Reference!$A$17, Reference!$C$17, 0)))) -> 4 | AA22: =IF(L22=Reference!$A$28, Reference!$C$28, IF(L22=Reference!$A$27, Reference!$C$27, IF(L22=Reference!$A$26, Reference!$C$26, IF(L22=Reference!$A$25, Reference!$C$25, 0)))) -> 7 | AB22: =IF(N22=Reference!$A$36, Reference!$C$36, IF(N22=Reference!$A$35, Reference!$C$35, IF(N22=Reference!$A$34, Reference!$C$34, IF(N22=Reference!$A$33, Reference!$C$33, 0)))) -> 4 | AC22: =(Reference!$B$2*Y22 + Reference!$B$3*AA22 + Reference!$B$4*Z22 + Reference!$B$5 * AB22)/4 -> 7.5 | AD22: =IF(Q22=Reference!$C$41, Reference!$D$41, IF(Q22=Reference!$C$42, Reference!$D$42, IF(Q22=Reference!$C$43, Reference!$D$43, IF(Q22=Reference!$C$44, Reference!$D$44, 0)))) -> 4 | AE22: =1 + (AC22 * AD22) -> 31
B23: Denial of service | C23: Availability | D23: An attacker manipulates the CAM generation logic of their ITS-S, reducing the generation interval below the defined T_GenCamMin = 100 ms. This causes the ITS-S to broadcast CAMs excessively and overwhelm the shared wireless V2X channel. | E23: The attacker either directly modifies the CA service logic (e.g., via firmware hacking or malicious configuration) or exploits the CAM triggering conditions by falsely simulating high dynamic changes (e.g., position, speed, heading) to repeatedly trigger CAM emissions | F23: Adjacent | G23: A rogue device is deployed near traffic (e.g., roadside or parked vehicle) and floods the air with high-frequency CAMs within the communication range, exploiting shared channel access and degrading service to other ITS stations. | H23: Moderate | I23: Critical safety-related CAMs (e.g., emergency braking, vehicle position) may be dropped or delayed. | J23: Moderate | K23: Minimal financial impact unless the issue becomes systemic or persistent. | L23: Major | M23: ITS services dependent on CAMs become unreliable; congestion, collision warnings, and cooperative functions are impaired. | N23: Moderate | O23: Violates standard ETSI CAM transmission rules and DCC compliance, potentially causing certification failure or fines. | P23: =IF(AC23>=Reference!$H$2, Reference!$G$2, IF(AC23>=Reference!$H$3, Reference!$G$3, IF(AC23>=Reference!$H$4, Reference!$G$4, IF(AC23>=Reference!$H$5, Reference!$G$5, "")))) -> Major | Q23: =IF(F23="Physical", "Very Low", IF(F23="Local", "Low", IF(F23="Adjacent", "Medium", IF(F23="Network", "High", "")))) -> Medium | R23: =IF(AE23>=Reference!$D$2, Reference!$G$2, IF(AE23>=Reference!$D$3, Reference!$E$3, IF(AE23>=Reference!$D$4, Reference!$E$4, IF(AE23>=Reference!$D$5, Reference!$E$5, "")))) -> High | S23: Mitigation | T23: Enforce DCC Policies: Ensure that the DCC service always enforces T_GenCamMin and overrides any locally manipulated values. Rate Limiting at Network Layer: Drop CAMs exceeding a threshold at the network interface layer. Misbehavior Detection (MBD): Detect ITS-Ss sending abnormally frequent CAMs and report them to the central authority for revocation. Secure Firmware and Debug Access: Prevent unauthorized local access to firmware settings that manage CA timing logic. | U23: CA Service (CAM Generation Logic) DCC Parameters (T_GenCamMin, T_GenCamMax, T_GenCam_Dcc) Channel Load Monitoring System ITS Networking & Transport Layer (delivery and suppression of messages) | V23: Mitigation is appropriate because this threat has a moderate safety and high operational impact, and can be systematically addressed with technical countermeasures like DCC enforcement, rate monitoring, and misbehavior reporting. Total avoidance is not feasible due to the importance of real-time dynamics in CAM logic, and acceptance is not viable due to potential safety degradation. | W23: G1 – Ensure authenticity of ITS messages (CAMs must be valid and not artificially triggered). G3 – Ensure availability of the V2X communication channel. G4 – Preserve integrity of network timing policies (DCC parameters). G8 – Ensure compliance with ETSI EN 302 637-2 and DCC constraints. | Y23: =IF(H23=Reference!$A$12, Reference!$C$12, IF(H23=Reference!$A$11, Reference!$C$11, IF(H23=Reference!$A$10, Reference!$C$10, IF(H23=Reference!$A$9, Reference!$C$9, 0)))) -> 4 | Z23: =IF(J23=Reference!$A$20, Reference!$C$20, IF(J23=Reference!$A$19, Reference!$C$19, IF(J23=Reference!$A$18, Reference!$C$18, IF(J23=Reference!$A$17, Reference!$C$17, 0)))) -> 4 | AA23: =IF(L23=Reference!$A$28, Reference!$C$28, IF(L23=Reference!$A$27, Reference!$C$27, IF(L23=Reference!$A$26, Reference!$C$26, IF(L23=Reference!$A$25, Reference!$C$25, 0)))) -> 7 | AB23: =IF(N23=Reference!$A$36, Reference!$C$36, IF(N23=Reference!$A$35, Reference!$C$35, IF(N23=Reference!$A$34, Reference!$C$34, IF(N23=Reference!$A$33, Reference!$C$33, 0)))) -> 4 | AC23: =(Reference!$B$2*Y23 + Reference!$B$3*AA23 + Reference!$B$4*Z23 + Reference!$B$5 * AB23)/4 -> 7.5 | AD23: =IF(Q23=Reference!$C$41, Reference!$D$41, IF(Q23=Reference!$C$42, Reference!$D$42, IF(Q23=Reference!$C$43, Reference!$D$43, IF(Q23=Reference!$C$44, Reference!$D$44, 0)))) -> 7 | AE23: =1 + (AC23 * AD23) -> 53.5
A24: CAM Timestamp and Generation Time | B24: Tampering | C24: Integrity | D24: An attacker alters the CAM generation time or timestamp field of the message to create inconsistency between the claimed and actual timing of the vehicle’s status. This can mislead other ITS stations into making incorrect real-time decisions. | E24: The attacker, via firmware compromise or local misconfiguration, injects manipulated timestamps or delays the actual message generation. These timestamps do not correspond to when the position/speed data were captured, violating synchronization assumptions. | F24: Local | G24: In the Local attack, malware within the ITS-S or tampered CA logic deliberately modifies or delays timestamps. | H24: Major | I24: Misaligned timestamps can result in delayed braking or lane-changing, due to incorrect assumptions about nearby vehicle positions or velocities. | J24: Major | K24: Misinterpretation of traffic behavior may cause accidents or unnecessary service interventions. | L24: Major | M24: System-wide disruption in cooperative awareness logic. Could invalidate relative position predictions, undermining V2X coordination. | N24: Major | O24: Legal and regulatory concerns arise if vehicles cannot be accurately time-reconstructed during forensics or liability assessment. | P24: =IF(AC24>=Reference!$H$2, Reference!$G$2, IF(AC24>=Reference!$H$3, Reference!$G$3, IF(AC24>=Reference!$H$4, Reference!$G$4, IF(AC24>=Reference!$H$5, Reference!$G$5, "")))) -> Severe | Q24: =IF(F24="Physical", "Very Low", IF(F24="Local", "Low", IF(F24="Adjacent", "Medium", IF(F24="Network", "High", "")))) -> Low | R24: =IF(AE24>=Reference!$D$2, Reference!$G$2, IF(AE24>=Reference!$D$3, Reference!$E$3, IF(AE24>=Reference!$D$4, Reference!$E$4, IF(AE24>=Reference!$D$5, Reference!$E$5, "")))) -> Medium | S24: Mitigation | T24: Secure Time Synchronization (e.g., GNSS-based or secured NTP within the ITS station). CAM Timestamp Validation: Cross-check timestamps against local clock and expected message intervals. Deny-listing Misbehaving ITS-S: If a device repeatedly sends CAMs with out-of-sync timestamps, flag it as non-trustworthy. | U24: CAM Generation Time Field CAM Timestamp Field CA Service (CAM generation logic) Networking & Transport Layer Interface | V24: Time inconsistencies corrupt the foundation of CAM-based awareness, as position, speed, and heading are meaningful only when aligned with a reliable timestamp. Inter-vehicle coordination and safety mechanisms degrade significantly when timing trust is broken. | W24: Integrity – Ensure timing data reflects true generation moment. Authenticity – Ensure the timing was generated by the claimed source. Reliability – Support time-based decision making in V2X networks. | Y24: =IF(H24=Reference!$A$12, Reference!$C$12, IF(H24=Reference!$A$11, Reference!$C$11, IF(H24=Reference!$A$10, Reference!$C$10, IF(H24=Reference!$A$9, Reference!$C$9, 0)))) -> 7 | Z24: =IF(J24=Reference!$A$20, Reference!$C$20, IF(J24=Reference!$A$19, Reference!$C$19, IF(J24=Reference!$A$18, Reference!$C$18, IF(J24=Reference!$A$17, Reference!$C$17, 0)))) -> 7 | AA24: =IF(L24=Reference!$A$28, Reference!$C$28, IF(L24=Reference!$A$27, Reference!$C$27, IF(L24=Reference!$A$26, Reference!$C$26, IF(L24=Reference!$A$25, Reference!$C$25, 0)))) -> 7 | AB24: =IF(N24=Reference!$A$36, Reference!$C$36, IF(N24=Reference!$A$35, Reference!$C$35, IF(N24=Reference!$A$34, Reference!$C$34, IF(N24=Reference!$A$33, Reference!$C$33, 0)))) -> 7 | AC24: =(Reference!$B$2*Y24 + Reference!$B$3*AA24 + Reference!$B$4*Z24 + Reference!$B$5 * AB24)/4 -> 11.8125 | AD24: =IF(Q24=Reference!$C$41, Reference!$D$41, IF(Q24=Reference!$C$42, Reference!$D$42, IF(Q24=Reference!$C$43, Reference!$D$43, IF(Q24=Reference!$C$44, Reference!$D$44, 0)))) -> 4 | AE24: =1 + (AC24 * AD24) -> 48.25
A25: CAM Timestamp and Generation Time | B25: Repudiation | C25: Availability | D25: An attacker alters the CAM generation time or timestamp field of the message to create inconsistency between the claimed and actual timing of the vehicle’s status. This can mislead other ITS stations into making incorrect real-time decisions. | E25: The attacker, via firmware compromise or local misconfiguration, injects manipulated timestamps or delays the actual message generation. These timestamps do not correspond to when the position/speed data were captured, violating synchronization assumptions. | F25: Adjacent | G25: In the Adjacent attack, a compromised RSU or vehicle injects CAMs with outdated timestamps or altered data via V2X to confuse timing-based decision-making. | H25: Major | I25: Misaligned timestamps can result in delayed braking or lane-changing, due to incorrect assumptions about nearby vehicle positions or velocities. | J25: Major | K25: Misinterpretation of traffic behavior may cause accidents or unnecessary service interventions. | L25: Major | M25: System-wide disruption in cooperative awareness logic. Could invalidate relative position predictions, undermining V2X coordination. | N25: Major | O25: Legal and regulatory concerns arise if vehicles cannot be accurately time-reconstructed during forensics or liability assessment. | P25: =IF(AC25>=Reference!$H$2, Reference!$G$2, IF(AC25>=Reference!$H$3, Reference!$G$3, IF(AC25>=Reference!$H$4, Reference!$G$4, IF(AC25>=Reference!$H$5, Reference!$G$5, "")))) -> Severe | Q25: =IF(F25="Physical", "Very Low", IF(F25="Local", "Low", IF(F25="Adjacent", "Medium", IF(F25="Network", "High", "")))) -> Medium | R25: =IF(AE25>=Reference!$D$2, Reference!$G$2, IF(AE25>=Reference!$D$3, Reference!$E$3, IF(AE25>=Reference!$D$4, Reference!$E$4, IF(AE25>=Reference!$D$5, Reference!$E$5, "")))) -> High | S25: Mitigation | T25: Secure Time Synchronization (e.g., GNSS-based or secured NTP within the ITS station). CAM Timestamp Validation: Cross-check timestamps against local clock and expected message intervals. Deny-listing Misbehaving ITS-S: If a device repeatedly sends CAMs with out-of-sync timestamps, flag it as non-trustworthy. | U25: CAM Generation Time Field CAM Timestamp Field CA Service (CAM generation logic) Networking & Transport Layer Interface | V25: Time inconsistencies corrupt the foundation of CAM-based awareness, as position, speed, and heading are meaningful only when aligned with a reliable timestamp. Inter-vehicle coordination and safety mechanisms degrade significantly when timing trust is broken. | W25: Integrity – Ensure timing data reflects true generation moment. Authenticity – Ensure the timing was generated by the claimed source. Reliability – Support time-based decision making in V2X networks. | Y25: =IF(H25=Reference!$A$12, Reference!$C$12, IF(H25=Reference!$A$11, Reference!$C$11, IF(H25=Reference!$A$10, Reference!$C$10, IF(H25=Reference!$A$9, Reference!$C$9, 0)))) -> 7 | Z25: =IF(J25=Reference!$A$20, Reference!$C$20, IF(J25=Reference!$A$19, Reference!$C$19, IF(J25=Reference!$A$18, Reference!$C$18, IF(J25=Reference!$A$17, Reference!$C$17, 0)))) -> 7 | AA25: =IF(L25=Reference!$A$28, Reference!$C$28, IF(L25=Reference!$A$27, Reference!$C$27, IF(L25=Reference!$A$26, Reference!$C$26, IF(L25=Reference!$A$25, Reference!$C$25, 0)))) -> 7 | AB25: =IF(N25=Reference!$A$36, Reference!$C$36, IF(N25=Reference!$A$35, Reference!$C$35, IF(N25=Reference!$A$34, Reference!$C$34, IF(N25=Reference!$A$33, Reference!$C$33, 0)))) -> 7 | AC25: =(Reference!$B$2*Y25 + Reference!$B$3*AA25 + Reference!$B$4*Z25 + Reference!$B$5 * AB25)/4 -> 11.8125 | AD25: =IF(Q25=Reference!$C$41, Reference!$D$41, IF(Q25=Reference!$C$42, Reference!$D$42, IF(Q25=Reference!$C$43, Reference!$D$43, IF(Q25=Reference!$C$44, Reference!$D$44, 0)))) -> 7 | AE25: =1 + (AC25 * AD25) -> 83.6875
A26: DENM Message Container (Adverse Conditions - Situation Container) | B26: Tampering | C26: Integrity | D26: The attacker injects false reports of adverse weather conditions (e.g., heavy rain, fog, or icy roads) to disrupt traffic patterns or cause unnecessary caution among drivers. | E26: The attacker gains access to the On-Board Unit (OBU) or V2X Communication Stack and tampers with the Adverse Conditions field in the DENM before transmission. | F26: Network | G26: The attacker aims to create traffic congestion or panic by falsely reporting hazardous weather conditions, potentially benefiting from the disruption (e.g., in targeted areas or during high-traffic events). | H26: Moderate | I26: False adverse condition warnings may cause sudden and unnecessary braking or rerouting, increasing the risk of collisions. | J26: Moderate | K26: The organization may face costs related to insurance claims, traffic congestion mitigation, and potential legal liabilities due to traffic incidents. | L26: Moderate | M26: Severe traffic congestion from unnecessary rerouting or slow driving. | N26: Negligible | O26: The attack does not involve personal data but may violate traffic management regulations. | P26: =IF(AC26>=Reference!$H$2, Reference!$G$2, IF(AC26>=Reference!$H$3, Reference!$G$3, IF(AC26>=Reference!$H$4, Reference!$G$4, IF(AC26>=Reference!$H$5, Reference!$G$5, "")))) -> Major | Q26: =IF(F26="Physical", "Very Low", IF(F26="Local", "Low", IF(F26="Adjacent", "Medium", IF(F26="Network", "High", "")))) -> High | R26: =IF(AE26>=Reference!$D$2, Reference!$G$2, IF(AE26>=Reference!$D$3, Reference!$E$3, IF(AE26>=Reference!$D$4, Reference!$E$4, IF(AE26>=Reference!$D$5, Reference!$E$5, "")))) -> High | S26: Avoidance | T26: Digital signatures to ensure message authenticity,Redundant verification using multiple data sources (e.g., crowd-sourced vehicle sensor data),Monitor for patterns of mass false alerts (e.g., multiple false warnings from a single source). | U26: V2X Communication Stack (OBU, RSU),Adverse Condition Detection and Reporting Module,Cryptographic and Integrity Checking Systems,Traffic Management Systems (N2V) | V26: Implement anomaly detection for unusual patterns of adverse condition reports. | Y26: =IF(H26=Reference!$A$12, Reference!$C$12, IF(H26=Reference!$A$11, Reference!$C$11, IF(H26=Reference!$A$10, Reference!$C$10, IF(H26=Reference!$A$9, Reference!$C$9, 0)))) -> 4 | Z26: =IF(J26=Reference!$A$20, Reference!$C$20, IF(J26=Reference!$A$19, Reference!$C$19, IF(J26=Reference!$A$18, Reference!$C$18, IF(J26=Reference!$A$17, Reference!$C$17, 0)))) -> 4 | AA26: =IF(L26=Reference!$A$28, Reference!$C$28, IF(L26=Reference!$A$27, Reference!$C$27, IF(L26=Reference!$A$26, Reference!$C$26, IF(L26=Reference!$A$25, Reference!$C$25, 0)))) -> 4 | AB26: =IF(N26=Reference!$A$36, Reference!$C$36, IF(N26=Reference!$A$35, Reference!$C$35, IF(N26=Reference!$A$34, Reference!$C$34, IF(N26=Reference!$A$33, Reference!$C$33, 0)))) -> 1 | AC26: =(Reference!$B$2*Y26 + Reference!$B$3*AA26 + Reference!$B$4*Z26 + Reference!$B$5 * AB26)/4 -> 6.5625 | AD26: =IF(Q26=Reference!$C$41, Reference!$D$41, IF(Q26=Reference!$C$42, Reference!$D$42, IF(Q26=Reference!$C$43, Reference!$D$43, IF(Q26=Reference!$C$44, Reference!$D$44, 0)))) -> 10 | AE26: =1 + (AC26 * AD26) -> 66.625
B27: Tampering | C27: Integrity | D27: The attacker suppresses reports of actual adverse weather conditions (e.g., icy roads or heavy fog) to prevent drivers from taking necessary precautions, increasing the risk of accidents. | E27: The attacker gains access to the OBU or V2X communication stack and prevents DENM messages from reporting actual hazardous weather conditions. | F27: Network | G27: The attacker may aim to cause accidents or disruptions by concealing hazardous conditions, such as black ice, from nearby drivers via real-time V2X broadcast system. | H27: Severe | I27: Suppressing warnings about hazardous conditions (e.g., icy roads) could cause high-speed collisions and multi-vehicle pile-ups. | J27: Major | K27: Severe accidents can result in significant damage, insurance claims, and legal liabilities. | L27: Severe | M27: Loss of core vehicle functions (Value: 10) - Failure to adjust automated driving behaviors or assistive alerts in real-time. | N27: Moderate | O27: Non-compliance with traffic safety regulations may lead to regulatory penalties. | P27: =IF(AC27>=Reference!$H$2, Reference!$G$2, IF(AC27>=Reference!$H$3, Reference!$G$3, IF(AC27>=Reference!$H$4, Reference!$G$4, IF(AC27>=Reference!$H$5, Reference!$G$5, "")))) -> Severe | Q27: =IF(F27="Physical", "Very Low", IF(F27="Local", "Low", IF(F27="Adjacent", "Medium", IF(F27="Network", "High", "")))) -> High | R27: =IF(AE27>=Reference!$D$2, Reference!$G$2, IF(AE27>=Reference!$D$3, Reference!$E$3, IF(AE27>=Reference!$D$4, Reference!$E$4, IF(AE27>=Reference!$D$5, Reference!$E$5, "")))) -> Severe | S27: Mitigation | T27: Secure communication protocols with end-to-end encryption,Redundant warnings from roadside units (RSUs) and third-party weather services,Use machine learning to detect anomalies, such as sudden drops in adverse condition reports despite consistent sensor data. | U27: V2X Communication Stack (OBU, RSU),Adverse Condition Detection and Reporting Module,Cryptographic and Integrity Checking Systems,Traffic Management Systems (N2V) | V27: Implement cross-verification of messages with onboard sensors (e.g., traction control for icy roads). | Y27: =IF(H27=Reference!$A$12, Reference!$C$12, IF(H27=Reference!$A$11, Reference!$C$11, IF(H27=Reference!$A$10, Reference!$C$10, IF(H27=Reference!$A$9, Reference!$C$9, 0)))) -> 10 | Z27: =IF(J27=Reference!$A$20, Reference!$C$20, IF(J27=Reference!$A$19, Reference!$C$19, IF(J27=Reference!$A$18, Reference!$C$18, IF(J27=Reference!$A$17, Reference!$C$17, 0)))) -> 7 | AA27: =IF(L27=Reference!$A$28, Reference!$C$28, IF(L27=Reference!$A$27, Reference!$C$27, IF(L27=Reference!$A$26, Reference!$C$26, IF(L27=Reference!$A$25, Reference!$C$25, 0)))) -> 10 | AB27: =IF(N27=Reference!$A$36, Reference!$C$36, IF(N27=Reference!$A$35, Reference!$C$35, IF(N27=Reference!$A$34, Reference!$C$34, IF(N27=Reference!$A$33, Reference!$C$33, 0)))) -> 4 | AC27: =(Reference!$B$2*Y27 + Reference!$B$3*AA27 + Reference!$B$4*Z27 + Reference!$B$5 * AB27)/4 -> 16.125 | AD27: =IF(Q27=Reference!$C$41, Reference!$D$41, IF(Q27=Reference!$C$42, Reference!$D$42, IF(Q27=Reference!$C$43, Reference!$D$43, IF(Q27=Reference!$C$44, Reference!$D$44, 0)))) -> 10 | AE27: =1 + (AC27 * AD27) -> 162.25
A28: DENM Situation Container (Wrong Way Driving Notification - Cause Code and SubCause Code) | B28: Tampering | C28: Integrity | D28: The attacker injects false causeCode and subCauseCode values into the DENM message, creating non-existent wrong-way driving alerts. | E28: The attacker accesses the vehicle’s OBU or RSU and alters the Cause Code fields within the DENM message before broadcast | F28: Network | G28: The attack exploits the causeCode and subCauseCode fields in the situation container creating false ghost-driver warnings leading to panic, disrupting in traffic flow. | H28: Moderate | I28: Drivers may brake suddenly or take unsafe maneuvers, increasing the risk of collisions. | J28: Moderate | K28: Costs for deploying emergency services, managing traffic, and addressing insurance claims due to disruption (High operational costs but manageable). | L28: Major | M28: Severe traffic congestion and delays affecting key transportation routes, impairing important vehicle functions | N28: Negligible | O28: Since the attack involves only the modification of traffic-related messages, there is no direct compromise of sensitive personal data. | P28: =IF(AC28>=Reference!$H$2, Reference!$G$2, IF(AC28>=Reference!$H$3, Reference!$G$3, IF(AC28>=Reference!$H$4, Reference!$G$4, IF(AC28>=Reference!$H$5, Reference!$G$5, "")))) -> Major | Q28: =IF(F28="Physical", "Very Low", IF(F28="Local", "Low", IF(F28="Adjacent", "Medium", IF(F28="Network", "High", "")))) -> High | R28: =IF(AE28>=Reference!$D$2, Reference!$G$2, IF(AE28>=Reference!$D$3, Reference!$E$3, IF(AE28>=Reference!$D$4, Reference!$E$4, IF(AE28>=Reference!$D$5, Reference!$E$5, "")))) -> High | S28: Mitigation | T28: Employ cryptographic message signing and end-to-end encryption. Implement OBU anomaly detection and RSU behavioral analytics. Enable continuous monitoring and alert verification protocols. | U28: OBU firmware and security modules. RSU alerting systems and backend DENM verification services. Communication stacks for secure V2X message exchanges. | V28: Mitigating false alerts is crucial for preventing traffic disruptions, maintaining road safety, and ensuring efficient emergency response operations. | W28: Integrity: Prevent message tampering and ensure authenticity,Availability: Maintain reliable communication of alerts,Non-repudiation: Ensure message traceability and accountability. | Y28: =IF(H28=Reference!$A$12, Reference!$C$12, IF(H28=Reference!$A$11, Reference!$C$11, IF(H28=Reference!$A$10, Reference!$C$10, IF(H28=Reference!$A$9, Reference!$C$9, 0)))) -> 4 | Z28: =IF(J28=Reference!$A$20, Reference!$C$20, IF(J28=Reference!$A$19, Reference!$C$19, IF(J28=Reference!$A$18, Reference!$C$18, IF(J28=Reference!$A$17, Reference!$C$17, 0)))) -> 4 | AA28: =IF(L28=Reference!$A$28, Reference!$C$28, IF(L28=Reference!$A$27, Reference!$C$27, IF(L28=Reference!$A$26, Reference!$C$26, IF(L28=Reference!$A$25, Reference!$C$25, 0)))) -> 7 | AB28: =IF(N28=Reference!$A$36, Reference!$C$36, IF(N28=Reference!$A$35, Reference!$C$35, IF(N28=Reference!$A$34, Reference!$C$34, IF(N28=Reference!$A$33, Reference!$C$33, 0)))) -> 1 | AC28: =(Reference!$B$2*Y28 + Reference!$B$3*AA28 + Reference!$B$4*Z28 + Reference!$B$5 * AB28)/4 -> 7.3125 | AD28: =IF(Q28=Reference!$C$41, Reference!$D$41, IF(Q28=Reference!$C$42, Reference!$D$42, IF(Q28=Reference!$C$43, Reference!$D$43, IF(Q28=Reference!$C$44, Reference!$D$44, 0)))) -> 10 | AE28: =1 + (AC28 * AD28) -> 74.125
B29: Tampering | C29: Integrity&Availability | D29: The attacker suppresses legitimate wrong-way driving alerts by modifying or deleting causeCode values, preventing the alert from being broadcasted. | E29: Tampering with OBU or RSU to disrupt transmission of alerts or cause code suppression. | F29: Network | G29: The attacker intends to create road hazards or enable criminal activities by preventing essential safety warnings from reaching road users. | H29: Severe | I29: Failure to alert drivers can lead to fatal collisions or multi-vehicle accidents. (S3) | J29: Severe | K29: Major costs due to accidents, insurance claims, and potential legal liabilities | L29: Major | M29: Severe disruptions for emergency services and traffic management, leading to delays and significant driver inconvenience | N29: Negligible | O29: No privacy exposure. | P29: =IF(AC29>=Reference!$H$2, Reference!$G$2, IF(AC29>=Reference!$H$3, Reference!$G$3, IF(AC29>=Reference!$H$4, Reference!$G$4, IF(AC29>=Reference!$H$5, Reference!$G$5, "")))) -> Severe | Q29: =IF(F29="Physical", "Very Low", IF(F29="Local", "Low", IF(F29="Adjacent", "Medium", IF(F29="Network", "High", "")))) -> High | R29: =IF(AE29>=Reference!$D$2, Reference!$G$2, IF(AE29>=Reference!$D$3, Reference!$E$3, IF(AE29>=Reference!$D$4, Reference!$E$4, IF(AE29>=Reference!$D$5, Reference!$E$5, "")))) -> Severe | S29: Mitigation | T29: Secure message transmission with encrypted channels (TLS for V2X),Use blockchain or distributed ledger technology for tamper-evident logs,Implement multi-channel broadcasting (OBU, RSU, mobile apps) for redundancy. | U29: OBU firmware and digital signing modules,RSU alerting services and backend alert validation platforms,V2X communication channels and traffic management systems. | V29: Suppressing safety alerts increases collision risks and undermines trust in V2X communication systems. Countermeasures ensure continuous alert delivery and secure reporting of road hazards. | W29: ,Availability: Guarantee continuous transmission of safety-critical alerts,Non-repudiation: Maintain traceability and accountability of transmitted messages. | Y29: =IF(H29=Reference!$A$12, Reference!$C$12, IF(H29=Reference!$A$11, Reference!$C$11, IF(H29=Reference!$A$10, Reference!$C$10, IF(H29=Reference!$A$9, Reference!$C$9, 0)))) -> 10 | Z29: =IF(J29=Reference!$A$20, Reference!$C$20, IF(J29=Reference!$A$19, Reference!$C$19, IF(J29=Reference!$A$18, Reference!$C$18, IF(J29=Reference!$A$17, Reference!$C$17, 0)))) -> 10 | AA29: =IF(L29=Reference!$A$28, Reference!$C$28, IF(L29=Reference!$A$27, Reference!$C$27, IF(L29=Reference!$A$26, Reference!$C$26, IF(L29=Reference!$A$25, Reference!$C$25, 0)))) -> 7 | AB29: =IF(N29=Reference!$A$36, Reference!$C$36, IF(N29=Reference!$A$35, Reference!$C$35, IF(N29=Reference!$A$34, Reference!$C$34, IF(N29=Reference!$A$33, Reference!$C$33, 0)))) -> 1 | AC29: =(Reference!$B$2*Y29 + Reference!$B$3*AA29 + Reference!$B$4*Z29 + Reference!$B$5 * AB29)/4 -> 15.5625 | AD29: =IF(Q29=Reference!$C$41, Reference!$D$41, IF(Q29=Reference!$C$42, Reference!$D$42, IF(Q29=Reference!$C$43, Reference!$D$43, IF(Q29=Reference!$C$44, Reference!$D$44, 0)))) -> 10 | AE29: =1 + (AC29 * AD29) -> 156.625
A30: DENM Situation Container (Rescue and Recovery Work Notification - Cause Code and SubCause Code) | B30: Tampering | C30: Integrity | D30: The attacker injects false causeCode and subCauseCode values into the DENM message, falsely reporting an active rescue and recovery operation on the road. | E30: The attacker exploits access to the OBU or RSU to manipulate the Cause Code fields before transmission. | F30: Network | G30: The attacker aims to disrupt traffic, create congestion, or divert vehicles from a critical route, potentially for criminal activities or to cause economic loss. | H30: Moderate | I30: Drivers may brake suddenly or reroute abruptly, increasing the risk of accidents. Emergency vehicles could face delays due to unexpected traffic congestion. | J30: Moderate | K30: Primarily limited to minor traffic disruptions and small-scale reputational impact with minimal direct financial loss. | L30: Moderate | M30: Moderate disruption in traffic flow due to unnecessary rerouting or congestion. Potential delays in actual emergency responses. | N30: Negligible | O30: No exposure of personal data, but potential regulatory penalties for false emergency alerts. | P30: =IF(AC30>=Reference!$H$2, Reference!$G$2, IF(AC30>=Reference!$H$3, Reference!$G$3, IF(AC30>=Reference!$H$4, Reference!$G$4, IF(AC30>=Reference!$H$5, Reference!$G$5, "")))) -> Major | Q30: =IF(F30="Physical", "Very Low", IF(F30="Local", "Low", IF(F30="Adjacent", "Medium", IF(F30="Network", "High", "")))) -> High | R30: =IF(AE30>=Reference!$D$2, Reference!$G$2, IF(AE30>=Reference!$D$3, Reference!$E$3, IF(AE30>=Reference!$D$4, Reference!$E$4, IF(AE30>=Reference!$D$5, Reference!$E$5, "")))) -> High | S30: Mitigation | T30: Cryptographic signing of messages,OBU and RSU anomaly detection with AI-based behavioral analytics,Multi-source verification of emergency alerts (e.g., cross-checking with local authorities or CCTV). | U30: OBU firmware (for secure messaging and anomaly detection),RSU alerting systems (for real-time analysis and cross-verification),DENM message validation protocols. | V30: Mitigating false alerts reduces unnecessary panic, traffic congestion, and delays for genuine emergency responders. Ensuring message integrity is vital for maintaining trust in V2X communication systems. | W30: 1.Prevent false information from being injected into the system 2.Ensure real alerts reach drivers and authorities promptly 3.Guarantee that alerts are verifiable and traceable to their source. | Y30: =IF(H30=Reference!$A$12, Reference!$C$12, IF(H30=Reference!$A$11, Reference!$C$11, IF(H30=Reference!$A$10, Reference!$C$10, IF(H30=Reference!$A$9, Reference!$C$9, 0)))) -> 4 | Z30: =IF(J30=Reference!$A$20, Reference!$C$20, IF(J30=Reference!$A$19, Reference!$C$19, IF(J30=Reference!$A$18, Reference!$C$18, IF(J30=Reference!$A$17, Reference!$C$17, 0)))) -> 4 | AA30: =IF(L30=Reference!$A$28, Reference!$C$28, IF(L30=Reference!$A$27, Reference!$C$27, IF(L30=Reference!$A$26, Reference!$C$26, IF(L30=Reference!$A$25, Reference!$C$25, 0)))) -> 4 | AB30: =IF(N30=Reference!$A$36, Reference!$C$36, IF(N30=Reference!$A$35, Reference!$C$35, IF(N30=Reference!$A$34, Reference!$C$34, IF(N30=Reference!$A$33, Reference!$C$33, 0)))) -> 1 | AC30: =(Reference!$B$2*Y30 + Reference!$B$3*AA30 + Reference!$B$4*Z30 + Reference!$B$5 * AB30)/4 -> 6.5625 | AD30: =IF(Q30=Reference!$C$41, Reference!$D$41, IF(Q30=Reference!$C$42, Reference!$D$42, IF(Q30=Reference!$C$43, Reference!$D$43, IF(Q30=Reference!$C$44, Reference!$D$44, 0)))) -> 10 | AE30: =1 + (AC30 * AD30) -> 66.625
B31: Tampering | C31: Integrity | D31: The attacker intercepts and suppresses a genuine rescue and recovery operation alert, preventing it from reaching nearby drivers. | E31: The attacker exploits vulnerabilities in the OBU or RSU to block or delete DENM messages before they are broadcast. | F31: Network | G31: The attacker may aim to cause accidents, increase traffic hazards, or obstruct emergency operations for malicious purposes. | H31: Severe | I31: Drivers remain unaware of rescue operations ahead, increasing the risk of collisions, especially in high-speed zones. Emergency responders may be endangered. | J31: Severe | K31: Suppression of alerts can cause life-threatening accidents, leading to high legal, reputational, and settlement costs. Indirect damages such as brand trust erosion and increased insurance premiums are also substantial. | L31: Major | M31: Traffic disruptions due to accidents, delays in emergency responses, and increased congestion. | N31: Negligible | O31: No direct privacy impact, but potential legal consequences for disrupting critical emergency operations. | P31: =IF(AC31>=Reference!$H$2, Reference!$G$2, IF(AC31>=Reference!$H$3, Reference!$G$3, IF(AC31>=Reference!$H$4, Reference!$G$4, IF(AC31>=Reference!$H$5, Reference!$G$5, "")))) -> Severe | Q31: =IF(F31="Physical", "Very Low", IF(F31="Local", "Low", IF(F31="Adjacent", "Medium", IF(F31="Network", "High", "")))) -> High | R31: =IF(AE31>=Reference!$D$2, Reference!$G$2, IF(AE31>=Reference!$D$3, Reference!$E$3, IF(AE31>=Reference!$D$4, Reference!$E$4, IF(AE31>=Reference!$D$5, Reference!$E$5, "")))) -> Severe | S31: Mitigation | T31: Strong end-to-end encryption for DENM messages,Redundant alerting through multiple channels (e.g., V2X and cellular networks),Regular security patches for OBU and RSU firmware to prevent message interception. | U31: OBU security modules (to prevent message tampering), RSU alert transmission systems (to ensure redundancy), Backend data aggregation and cross-verification services. | V31: Suppressing legitimate alerts can lead to severe road accidents and loss of life. Effective security measures ensure that emergency alerts are timely and accurate, supporting quick and safe navigation for drivers and first responders. | W31: 1.Ensure alerts are genuine and unaltered. 2. Guarantee that alerts are received by intended recipients without suppression. 3.Maintain a verifiable record of alert broadcasts. | Y31: =IF(H31=Reference!$A$12, Reference!$C$12, IF(H31=Reference!$A$11, Reference!$C$11, IF(H31=Reference!$A$10, Reference!$C$10, IF(H31=Reference!$A$9, Reference!$C$9, 0)))) -> 10 | Z31: =IF(J31=Reference!$A$20, Reference!$C$20, IF(J31=Reference!$A$19, Reference!$C$19, IF(J31=Reference!$A$18, Reference!$C$18, IF(J31=Reference!$A$17, Reference!$C$17, 0)))) -> 10 | AA31: =IF(L31=Reference!$A$28, Reference!$C$28, IF(L31=Reference!$A$27, Reference!$C$27, IF(L31=Reference!$A$26, Reference!$C$26, IF(L31=Reference!$A$25, Reference!$C$25, 0)))) -> 7 | AB31: =IF(N31=Reference!$A$36, Reference!$C$36, IF(N31=Reference!$A$35, Reference!$C$35, IF(N31=Reference!$A$34, Reference!$C$34, IF(N31=Reference!$A$33, Reference!$C$33, 0)))) -> 1 | AC31: =(Reference!$B$2*Y31 + Reference!$B$3*AA31 + Reference!$B$4*Z31 + Reference!$B$5 * AB31)/4 -> 15.5625 | AD31: =IF(Q31=Reference!$C$41, Reference!$D$41, IF(Q31=Reference!$C$42, Reference!$D$42, IF(Q31=Reference!$C$43, Reference!$D$43, IF(Q31=Reference!$C$44, Reference!$D$44, 0)))) -> 10 | AE31: =1 + (AC31 * AD31) -> 156.625
A32: DENM Situation Container (Vehicle Breakdown Notification - Cause Code and SubCause Code) | B32: Tampering | C32: Integrity | D32: The attacker tampers with the causeCode or subCauseCode of the vehicle breakdown message, injecting false vehicle breakdown alerts, causing unnecessary traffic congestion and misallocation of roadside assistance. | E32: The attacker gains access to the vehicle’s On-Board Unit (OBU) or the V2X communication stack to modify the DENM message before transmitting it over the V2X network. | F32: Network | G32: The attacker aims to create traffic congestion or safety risks by misinforming vehicles and traffic management systems about non-existent breakdown events. | H32: Moderate | I32: Sudden slowing down or rerouting by nearby vehicles can lead to minor collisions or near misses. | J32: Moderate | K32: The organization may face financial losses due to increased congestion,minor accidents, repair costs, and legal liabilities related to incorrect traffic management. | L32: Major | M32: Traffic congestion from unnecessary slowdowns and rerouting, delaying legitimate services. | N32: Negligible | O32: No personal or privacy-sensitive data is directly compromised. The threat primarily concerns event information rather than individual identification. | P32: =IF(AC32>=Reference!$H$2, Reference!$G$2, IF(AC32>=Reference!$H$3, Reference!$G$3, IF(AC32>=Reference!$H$4, Reference!$G$4, IF(AC32>=Reference!$H$5, Reference!$G$5, "")))) -> Major | Q32: =IF(F32="Physical", "Very Low", IF(F32="Local", "Low", IF(F32="Adjacent", "Medium", IF(F32="Network", "High", "")))) -> High | R32: =IF(AE32>=Reference!$D$2, Reference!$G$2, IF(AE32>=Reference!$D$3, Reference!$E$3, IF(AE32>=Reference!$D$4, Reference!$E$4, IF(AE32>=Reference!$D$5, Reference!$E$5, "")))) -> High | S32: Mitigation | T32: Digital signature verification to ensure the authenticity and integrity of breakdown notifications,Cross-referencing with redundant sensor data (e.g., CAM messages or roadside cameras) to validate breakdown events,Implementing anomaly detection systems to flag suspicious patterns in vehicle breakdown notifications. | U32: V2X Communication Stack (OBU, RSU) DENM Situation Container and Event Reporting System Cryptographic Integrity Checking Systems Traffic Management and Breakdown Recovery Coordination Systems | V32: Implement message authentication mechanisms to prevent tampering with causeCode and subCauseCode. | W32: Ensure message integrity, support non-repudiation through digital signatures, and maintain availability by preventing network congestion due to false alerts. | Y32: =IF(H32=Reference!$A$12, Reference!$C$12, IF(H32=Reference!$A$11, Reference!$C$11, IF(H32=Reference!$A$10, Reference!$C$10, IF(H32=Reference!$A$9, Reference!$C$9, 0)))) -> 4 | Z32: =IF(J32=Reference!$A$20, Reference!$C$20, IF(J32=Reference!$A$19, Reference!$C$19, IF(J32=Reference!$A$18, Reference!$C$18, IF(J32=Reference!$A$17, Reference!$C$17, 0)))) -> 4 | AA32: =IF(L32=Reference!$A$28, Reference!$C$28, IF(L32=Reference!$A$27, Reference!$C$27, IF(L32=Reference!$A$26, Reference!$C$26, IF(L32=Reference!$A$25, Reference!$C$25, 0)))) -> 7 | AB32: =IF(N32=Reference!$A$36, Reference!$C$36, IF(N32=Reference!$A$35, Reference!$C$35, IF(N32=Reference!$A$34, Reference!$C$34, IF(N32=Reference!$A$33, Reference!$C$33, 0)))) -> 1 | AC32: =(Reference!$B$2*Y32 + Reference!$B$3*AA32 + Reference!$B$4*Z32 + Reference!$B$5 * AB32)/4 -> 7.3125 | AD32: =IF(Q32=Reference!$C$41, Reference!$D$41, IF(Q32=Reference!$C$42, Reference!$D$42, IF(Q32=Reference!$C$43, Reference!$D$43, IF(Q32=Reference!$C$44, Reference!$D$44, 0)))) -> 10 | AE32: =1 + (AC32 * AD32) -> 74.125
B33: Tampering | C33: Integrity | D33: The attacker tampers with the causeCode or subCauseCode of the vehicle breakdown message, suppressing genuine vehicle breakdown alerts, preventing affected vehicles from receiving timely assistance and causing safety hazards. | E33: By compromising the OBU or V2X stack, the attacker modifies or deletes breakdown messages before they are broadcasted to other vehicles and infrastructure. | F33: Network | G33: The attacker may aim to create unsafe road conditions, delay emergency responses, or exploit breakdown situations for criminal activities like theft or vandalism. | H33: Major | I33: Delayed breakdown assistance can leave vehicles stranded in hazardous locations, risking collisions or injuries. | J33: Major | K33: High costs from accidents, insurance claims, and penalties for failure to respond to breakdowns. | L33: Severe | M33: Traffic disruptions due to unattended broken-down vehicles, delaying emergency and maintenance services. | N33: Negligible | O33: No direct privacy risk, as message suppression does not expose user data. | P33: =IF(AC33>=Reference!$H$2, Reference!$G$2, IF(AC33>=Reference!$H$3, Reference!$G$3, IF(AC33>=Reference!$H$4, Reference!$G$4, IF(AC33>=Reference!$H$5, Reference!$G$5, "")))) -> Severe | Q33: =IF(F33="Physical", "Very Low", IF(F33="Local", "Low", IF(F33="Adjacent", "Medium", IF(F33="Network", "High", "")))) -> High | R33: =IF(AE33>=Reference!$D$2, Reference!$G$2, IF(AE33>=Reference!$D$3, Reference!$E$3, IF(AE33>=Reference!$D$4, Reference!$E$4, IF(AE33>=Reference!$D$5, Reference!$E$5, "")))) -> Severe | S33: Mitigation | T33: Establish periodic integrity checks for transmitted messages, enforce strict access controls on OBUs, and log transmission failures for auditing. | U33: OBU security modules, V2X data transmission protocols, RSU alert validation, backend incident management platforms. | V33: Suppression of breakdown alerts endangers vehicle occupants and disrupts traffic, necessitating strong safeguards for reliable message transmission. | W33: Maintain integrity to prevent tampering, ensure availability by guaranteeing that breakdown alerts reach intended recipients, and support non-repudiation for accountability in communication networks. | Y33: =IF(H33=Reference!$A$12, Reference!$C$12, IF(H33=Reference!$A$11, Reference!$C$11, IF(H33=Reference!$A$10, Reference!$C$10, IF(H33=Reference!$A$9, Reference!$C$9, 0)))) -> 7 | Z33: =IF(J33=Reference!$A$20, Reference!$C$20, IF(J33=Reference!$A$19, Reference!$C$19, IF(J33=Reference!$A$18, Reference!$C$18, IF(J33=Reference!$A$17, Reference!$C$17, 0)))) -> 7 | AA33: =IF(L33=Reference!$A$28, Reference!$C$28, IF(L33=Reference!$A$27, Reference!$C$27, IF(L33=Reference!$A$26, Reference!$C$26, IF(L33=Reference!$A$25, Reference!$C$25, 0)))) -> 10 | AB33: =IF(N33=Reference!$A$36, Reference!$C$36, IF(N33=Reference!$A$35, Reference!$C$35, IF(N33=Reference!$A$34, Reference!$C$34, IF(N33=Reference!$A$33, Reference!$C$33, 0)))) -> 1 | AC33: =(Reference!$B$2*Y33 + Reference!$B$3*AA33 + Reference!$B$4*Z33 + Reference!$B$5 * AB33)/4 -> 12.1875 | AD33: =IF(Q33=Reference!$C$41, Reference!$D$41, IF(Q33=Reference!$C$42, Reference!$D$42, IF(Q33=Reference!$C$43, Reference!$D$43, IF(Q33=Reference!$C$44, Reference!$D$44, 0)))) -> 10 | AE33: =1 + (AC33 * AD33) -> 122.875
A34: DENM Situation Container (Human Problem Notification - Cause Code and SubCause Code) | B34: Tampering | C34: Integrity | D34: An attacker injects false human problem notifications, such as driver glycemia or heart problems, prompting unnecessary stops, slowdowns, or emergency responses. | E34: The attacker gains access to the On-Board Unit (OBU) of the vehicle or the roadside unit (RSU) to modify or inject a false DENM message related to a driver’s health status before it is broadcast over the V2X network | F34: Network | G34: The attacker may aim to disrupt traffic flow, cause unnecessary panic, or divert emergency resources for malicious purposes. | H34: Moderate | I34: Unnecessary stops or slowdowns may cause minor accidents or traffic issues. | J34: Moderate | K34: Financial losses may arise due to false medical emergency response, minor collisions, and traffic delays | L34: Major | M34: Traffic congestion due to false alerts. | N34: Major | O34: Health data of a driver is highly sensitive. Unauthorized manipulation or suppression of such data poses serious privacy risks, potential legal violations (e.g., GDPR), and reputational damage for OEMs or service providers. | P34: =IF(AC34>=Reference!$H$2, Reference!$G$2, IF(AC34>=Reference!$H$3, Reference!$G$3, IF(AC34>=Reference!$H$4, Reference!$G$4, IF(AC34>=Reference!$H$5, Reference!$G$5, "")))) -> Major | Q34: =IF(F34="Physical", "Very Low", IF(F34="Local", "Low", IF(F34="Adjacent", "Medium", IF(F34="Network", "High", "")))) -> High | R34: =IF(AE34>=Reference!$D$2, Reference!$G$2, IF(AE34>=Reference!$D$3, Reference!$E$3, IF(AE34>=Reference!$D$4, Reference!$E$4, IF(AE34>=Reference!$D$5, Reference!$E$5, "")))) -> High | S34: Mitigation | T34: Digital signatures on human problem notifications to ensure they have not been tampered with,Real-time verification through onboard driver monitoring systems (e.g., biometric sensors) or external validation via roadside cameras or RSUs,Cross-checking health-related DENM messages with other vehicle-generated messages (e.g., braking or swerving patterns from CAMs) to ensure accuracy. | U34: V2X Communication Stack (OBU, RSU),DENM Situation Container and Driver Monitoring Systems,Cryptographic Integrity Checking Systems,Traffic Management and Emergency Response Coordination | V34: Apply cryptographic signatures to authenticate the integrity of messages | W34: Maintain the integrity of V2X communications, ensure availability of critical safety alerts, and guarantee non-repudiation for all transmitted health-related notifications. | Y34: =IF(H34=Reference!$A$12, Reference!$C$12, IF(H34=Reference!$A$11, Reference!$C$11, IF(H34=Reference!$A$10, Reference!$C$10, IF(H34=Reference!$A$9, Reference!$C$9, 0)))) -> 4 | Z34: =IF(J34=Reference!$A$20, Reference!$C$20, IF(J34=Reference!$A$19, Reference!$C$19, IF(J34=Reference!$A$18, Reference!$C$18, IF(J34=Reference!$A$17, Reference!$C$17, 0)))) -> 4 | AA34: =IF(L34=Reference!$A$28, Reference!$C$28, IF(L34=Reference!$A$27, Reference!$C$27, IF(L34=Reference!$A$26, Reference!$C$26, IF(L34=Reference!$A$25, Reference!$C$25, 0)))) -> 7 | AB34: =IF(N34=Reference!$A$36, Reference!$C$36, IF(N34=Reference!$A$35, Reference!$C$35, IF(N34=Reference!$A$34, Reference!$C$34, IF(N34=Reference!$A$33, Reference!$C$33, 0)))) -> 7 | AC34: =(Reference!$B$2*Y34 + Reference!$B$3*AA34 + Reference!$B$4*Z34 + Reference!$B$5 * AB34)/4 -> 7.6875 | AD34: =IF(Q34=Reference!$C$41, Reference!$D$41, IF(Q34=Reference!$C$42, Reference!$D$42, IF(Q34=Reference!$C$43, Reference!$D$43, IF(Q34=Reference!$C$44, Reference!$D$44, 0)))) -> 10 | AE34: =1 + (AC34 * AD34) -> 77.875
B35: Tampering | C35: Integrity | D35: An attacker suppresses legitimate human problem notifications, preventing critical alerts about drivers experiencing health issues from reaching nearby vehicles or emergency services. | E35: Tampering with the OBU or RSU to delete or modify genuine driver health status alerts before they are broadcast over the V2X network. | F35: Network | G35: The attacker may seek to endanger lives by allowing incapacitated drivers to continue unnoticed, potentially causing severe accidents. | H35: Severe | I35: Failure to report genuine health issues can lead to life-threatening accidents. | J35: Severe | K35: Accident-related costs, medical expenses, and legal actions due to unreported health issues. | L35: Severe | M35: Delays in medical response and potential road blockages. | N35: Major | O35: Health data of a driver is highly sensitive. Unauthorized manipulation or suppression of such data poses serious privacy risks, potential legal violations (e.g., GDPR), and reputational damage for OEMs or service providers. | P35: =IF(AC35>=Reference!$H$2, Reference!$G$2, IF(AC35>=Reference!$H$3, Reference!$G$3, IF(AC35>=Reference!$H$4, Reference!$G$4, IF(AC35>=Reference!$H$5, Reference!$G$5, "")))) -> Severe | Q35: =IF(F35="Physical", "Very Low", IF(F35="Local", "Low", IF(F35="Adjacent", "Medium", IF(F35="Network", "High", "")))) -> High | R35: =IF(AE35>=Reference!$D$2, Reference!$G$2, IF(AE35>=Reference!$D$3, Reference!$E$3, IF(AE35>=Reference!$D$4, Reference!$E$4, IF(AE35>=Reference!$D$5, Reference!$E$5, "")))) -> Severe | S35: Mitigation | T35: Digital signatures on human problem notifications to ensure they have not been tampered with,Real-time verification through onboard driver monitoring systems (e.g., biometric sensors) or external validation via roadside cameras or RSUs,Cross-checking health-related DENM messages with other vehicle-generated messages (e.g., braking or swerving patterns from CAMs) to ensure accuracy. | U35: V2X Communication Stack (OBU, RSU),DENM Situation Container and Driver Monitoring Systems,Cryptographic Integrity Checking Systems,Traffic Management and Emergency Response Coordination | V35: Apply cryptographic signatures to authenticate the integrity of messages | W35: Maintain the integrity of V2X communications, ensure availability of critical safety alerts, and guarantee non-repudiation for all transmitted health-related notifications. | Y35: =IF(H35=Reference!$A$12, Reference!$C$12, IF(H35=Reference!$A$11, Reference!$C$11, IF(H35=Reference!$A$10, Reference!$C$10, IF(H35=Reference!$A$9, Reference!$C$9, 0)))) -> 10 | Z35: =IF(J35=Reference!$A$20, Reference!$C$20, IF(J35=Reference!$A$19, Reference!$C$19, IF(J35=Reference!$A$18, Reference!$C$18, IF(J35=Reference!$A$17, Reference!$C$17, 0)))) -> 10 | AA35: =IF(L35=Reference!$A$28, Reference!$C$28, IF(L35=Reference!$A$27, Reference!$C$27, IF(L35=Reference!$A$26, Reference!$C$26, IF(L35=Reference!$A$25, Reference!$C$25, 0)))) -> 10 | AB35: =IF(N35=Reference!$A$36, Reference!$C$36, IF(N35=Reference!$A$35, Reference!$C$35, IF(N35=Reference!$A$34, Reference!$C$34, IF(N35=Reference!$A$33, Reference!$C$33, 0)))) -> 7 | AC35: =(Reference!$B$2*Y35 + Reference!$B$3*AA35 + Reference!$B$4*Z35 + Reference!$B$5 * AB35)/4 -> 16.6875 | AD35: =IF(Q35=Reference!$C$41, Reference!$D$41, IF(Q35=Reference!$C$42, Reference!$D$42, IF(Q35=Reference!$C$43, Reference!$D$43, IF(Q35=Reference!$C$44, Reference!$D$44, 0)))) -> 10 | AE35: =1 + (AC35 * AD35) -> 167.875
A36: DENM Situation Container (Signal Violation Notification - Cause Code and SubCause Code) | B36: Tampering | C36: Integrity | D36: The attacker suppresses legitimate signal violation notifications, preventing accurate detection of traffic rule breaches, increasing collision risks. | E36: Tampering with the OBU or RSU to delete or modify signal violation data before transmission over the V2X network. | F36: Network | G36: The attacker may aim to enable reckless driving, avoid penalties for traffic violations, or create unsafe road conditions for malicious purposes. | H36: Severe | I36: Suppressing signal violations (e.g., running red lights) can lead to high-speed intersection collisions, risking severe injuries or fatalities. | J36: Severe | K36: Legal liabilities, insurance claims, and financial losses due to severe accidents and potential lawsuits. | L36: Major | M36: Disruption of traffic law enforcement and loss of trust in traffic management systems, leading to operational inefficiencies. | N36: Moderate | O36: If signal violation data includes identifying information (e.g., location and time), it could lead to privacy breaches if accessed or misused. | P36: =IF(AC36>=Reference!$H$2, Reference!$G$2, IF(AC36>=Reference!$H$3, Reference!$G$3, IF(AC36>=Reference!$H$4, Reference!$G$4, IF(AC36>=Reference!$H$5, Reference!$G$5, "")))) -> Severe | Q36: =IF(F36="Physical", "Very Low", IF(F36="Local", "Low", IF(F36="Adjacent", "Medium", IF(F36="Network", "High", "")))) -> High | R36: =IF(AE36>=Reference!$D$2, Reference!$G$2, IF(AE36>=Reference!$D$3, Reference!$E$3, IF(AE36>=Reference!$D$4, Reference!$E$4, IF(AE36>=Reference!$D$5, Reference!$E$5, "")))) -> Severe | S36: Mitigation | T36: Integrate secure firmware with message integrity checks, deploy backup RSUs for cross-verification, and use machine learning models to detect missing traffic events. | U36: V2X Communication Stack (OBU, RSU),DENM Situation Container and Signal Violation Monitoring Systems,Cryptographic Integrity Checking Systems,Traffic Management and Intersection Control Systems | V36: Ensuring that signal violations are accurately reported is critical for road safety, legal enforcement, and maintaining traffic order. | W36: Maintain integrity, availability, and non-repudiation of traffic violation data within the V2X ecosystem. | Y36: =IF(H36=Reference!$A$12, Reference!$C$12, IF(H36=Reference!$A$11, Reference!$C$11, IF(H36=Reference!$A$10, Reference!$C$10, IF(H36=Reference!$A$9, Reference!$C$9, 0)))) -> 10 | Z36: =IF(J36=Reference!$A$20, Reference!$C$20, IF(J36=Reference!$A$19, Reference!$C$19, IF(J36=Reference!$A$18, Reference!$C$18, IF(J36=Reference!$A$17, Reference!$C$17, 0)))) -> 10 | AA36: =IF(L36=Reference!$A$28, Reference!$C$28, IF(L36=Reference!$A$27, Reference!$C$27, IF(L36=Reference!$A$26, Reference!$C$26, IF(L36=Reference!$A$25, Reference!$C$25, 0)))) -> 7 | AB36: =IF(N36=Reference!$A$36, Reference!$C$36, IF(N36=Reference!$A$35, Reference!$C$35, IF(N36=Reference!$A$34, Reference!$C$34, IF(N36=Reference!$A$33, Reference!$C$33, 0)))) -> 4 | AC36: =(Reference!$B$2*Y36 + Reference!$B$3*AA36 + Reference!$B$4*Z36 + Reference!$B$5 * AB36)/4 -> 15.75 | AD36: =IF(Q36=Reference!$C$41, Reference!$D$41, IF(Q36=Reference!$C$42, Reference!$D$42, IF(Q36=Reference!$C$43, Reference!$D$43, IF(Q36=Reference!$C$44, Reference!$D$44, 0)))) -> 10 | AE36: =1 + (AC36 * AD36) -> 158.5
B37: Tampering | C37: Integrity | D37: The attacker injects false signal violation messages (e.g., non-existent red light violations), causing unnecessary braking, rerouting, and traffic delays. | E37: The attacker gains unauthorized access to the vehicle’s OBU or RSU to manipulate Cause Code and SubCause Code for signal violation data before broadcast over the V2X network. | F37: Network | G37: The attacker aims to disrupt traffic flow, induce unnecessary braking, or exploit the created congestion for malicious purposes such as diversion during criminal activity. | H37: Moderate | I37: Sudden braking or rerouting due to false signal violations may lead to rear-end collisions, increasing the risk of accidents, especially at busy intersections. | J37: Moderate | K37: Increased costs due to delayed deliveries, fuel wastage, and possible insurance claims from minor collisions caused by abrupt stops or reroutes. | L37: Major | M37: Significant traffic disruptions, delays, and loss of efficiency in traffic management systems due to frequent false alerts. | N37: Moderate | O37: If signal violation data includes identifying information (e.g., location and time), it could lead to privacy breaches if accessed or misused. | P37: =IF(AC37>=Reference!$H$2, Reference!$G$2, IF(AC37>=Reference!$H$3, Reference!$G$3, IF(AC37>=Reference!$H$4, Reference!$G$4, IF(AC37>=Reference!$H$5, Reference!$G$5, "")))) -> Major | Q37: =IF(F37="Physical", "Very Low", IF(F37="Local", "Low", IF(F37="Adjacent", "Medium", IF(F37="Network", "High", "")))) -> High | R37: =IF(AE37>=Reference!$D$2, Reference!$G$2, IF(AE37>=Reference!$D$3, Reference!$E$3, IF(AE37>=Reference!$D$4, Reference!$E$4, IF(AE37>=Reference!$D$5, Reference!$E$5, "")))) -> High | S37: Mitigation | T37: Use cryptographic validation of all signal violation messages, deploy real-time monitoring systems in RSUs, and enforce strict access controls for OBU firmware updates. | U37: OBU and RSU firmware, DENM message processing systems, and traffic management control algorithms. | V37: False signal violation reports can severely affect traffic flow and road safety, making robust validation and anomaly detection necessary. | W37: Ensure data integrity, availability, and secure communication across V2X networks. | Y37: =IF(H37=Reference!$A$12, Reference!$C$12, IF(H37=Reference!$A$11, Reference!$C$11, IF(H37=Reference!$A$10, Reference!$C$10, IF(H37=Reference!$A$9, Reference!$C$9, 0)))) -> 4 | Z37: =IF(J37=Reference!$A$20, Reference!$C$20, IF(J37=Reference!$A$19, Reference!$C$19, IF(J37=Reference!$A$18, Reference!$C$18, IF(J37=Reference!$A$17, Reference!$C$17, 0)))) -> 4 | AA37: =IF(L37=Reference!$A$28, Reference!$C$28, IF(L37=Reference!$A$27, Reference!$C$27, IF(L37=Reference!$A$26, Reference!$C$26, IF(L37=Reference!$A$25, Reference!$C$25, 0)))) -> 7 | AB37: =IF(N37=Reference!$A$36, Reference!$C$36, IF(N37=Reference!$A$35, Reference!$C$35, IF(N37=Reference!$A$34, Reference!$C$34, IF(N37=Reference!$A$33, Reference!$C$33, 0)))) -> 4 | AC37: =(Reference!$B$2*Y37 + Reference!$B$3*AA37 + Reference!$B$4*Z37 + Reference!$B$5 * AB37)/4 -> 7.5 | AD37: =IF(Q37=Reference!$C$41, Reference!$D$41, IF(Q37=Reference!$C$42, Reference!$D$42, IF(Q37=Reference!$C$43, Reference!$D$43, IF(Q37=Reference!$C$44, Reference!$D$44, 0)))) -> 10 | AE37: =1 + (AC37 * AD37) -> 76
A38: DENM Situation Container (Collision Risk Notification - Cause Code and SubCause Code) | B38: Tampering | C38: Integrity | D38: The attacker injects false collision risk notifications such as longitudinal, crossing, lateral, or vulnerable road user collision risks, causing unnecessary braking, evasive maneuvers, or traffic congestion. | E38: The attacker gains unauthorized access to the OBU or RSU to manipulate collision risk data before broadcasting over the V2X network. | F38: Network | G38: The attacker aims to create confusion and panic, induce unnecessary vehicle responses, or exploit the resulting traffic disruptions for malicious purposes | H38: Major | I38: False collision risk alerts may cause sudden braking, swerving, or evasive maneuvers, increasing the potential for multi-vehicle collisions or accidents | J38: Moderate | K38: Financial losses from traffic disruptions, delayed deliveries, fuel wastage, and potential minor accident claims due to abrupt vehicle responses. | L38: Major | M38: Major operational impact due to unnecessary vehicle responses, reduced traffic flow efficiency, and increased workload for traffic management systems. | N38: Moderate | O38: Misuse of location-specific collision risk data could lead to privacy breaches or violations of regulations related to traffic data usage and safety obligations. | P38: =IF(AC38>=Reference!$H$2, Reference!$G$2, IF(AC38>=Reference!$H$3, Reference!$G$3, IF(AC38>=Reference!$H$4, Reference!$G$4, IF(AC38>=Reference!$H$5, Reference!$G$5, "")))) -> Severe | Q38: =IF(F38="Physical", "Very Low", IF(F38="Local", "Low", IF(F38="Adjacent", "Medium", IF(F38="Network", "High", "")))) -> High | R38: =IF(AE38>=Reference!$D$2, Reference!$G$2, IF(AE38>=Reference!$D$3, Reference!$E$3, IF(AE38>=Reference!$D$4, Reference!$E$4, IF(AE38>=Reference!$D$5, Reference!$E$5, "")))) -> Severe | S38: Mitigation | T38: Deploy cryptographic message signing, integrate real-time monitoring of V2X communications, and enforce secure firmware updates for OBUs and RSUs. | U38: OBU and RSU firmware, DENM message processing modules, and collision risk assessment algorithms. | V38: Preventing false collision risk notifications is crucial to maintaining road safety and ensuring the effectiveness of traffic management systems. | W38: Ensure data integrity, availability, and secure communication within the V2X ecosystem. | Y38: =IF(H38=Reference!$A$12, Reference!$C$12, IF(H38=Reference!$A$11, Reference!$C$11, IF(H38=Reference!$A$10, Reference!$C$10, IF(H38=Reference!$A$9, Reference!$C$9, 0)))) -> 7 | Z38: =IF(J38=Reference!$A$20, Reference!$C$20, IF(J38=Reference!$A$19, Reference!$C$19, IF(J38=Reference!$A$18, Reference!$C$18, IF(J38=Reference!$A$17, Reference!$C$17, 0)))) -> 4 | AA38: =IF(L38=Reference!$A$28, Reference!$C$28, IF(L38=Reference!$A$27, Reference!$C$27, IF(L38=Reference!$A$26, Reference!$C$26, IF(L38=Reference!$A$25, Reference!$C$25, 0)))) -> 7 | AB38: =IF(N38=Reference!$A$36, Reference!$C$36, IF(N38=Reference!$A$35, Reference!$C$35, IF(N38=Reference!$A$34, Reference!$C$34, IF(N38=Reference!$A$33, Reference!$C$33, 0)))) -> 4 | AC38: =(Reference!$B$2*Y38 + Reference!$B$3*AA38 + Reference!$B$4*Z38 + Reference!$B$5 * AB38)/4 -> 11.25 | AD38: =IF(Q38=Reference!$C$41, Reference!$D$41, IF(Q38=Reference!$C$42, Reference!$D$42, IF(Q38=Reference!$C$43, Reference!$D$43, IF(Q38=Reference!$C$44, Reference!$D$44, 0)))) -> 10 | AE38: =1 + (AC38 * AD38) -> 113.5
B39: Tampering | C39: Integrity | D39: The attacker suppresses legitimate collision risk alerts (e.g., longitudinal, crossing, lateral, or vulnerable road user collisions), preventing drivers from receiving critical warnings. | E39: Tampering with the OBU or RSU to delete or modify collision risk notifications before they are broadcast over the V2X network. | F39: Network | G39: The attacker may aim to cause accidents, facilitate reckless driving, or compromise traffic safety by removing essential collision warnings. | H39: Severe | I39: Suppressing collision risk notifications can result in vehicles being unaware of imminent collisions, leading to severe accidents or fatalities. | J39: Severe | K39: High financial losses due to accident-related damages, insurance claims, legal liabilities, and potential lawsuits from collision victims. | L39: Severe | M39: Disruption of traffic safety protocols, increased accident rates, and loss of trust in automated traffic management and collision avoidance systems. | N39: Severe | O39: Legal consequences due to viloation of safety and disruption of traffic causing significant consequences for business operations and finance as well as media attention | P39: =IF(AC39>=Reference!$H$2, Reference!$G$2, IF(AC39>=Reference!$H$3, Reference!$G$3, IF(AC39>=Reference!$H$4, Reference!$G$4, IF(AC39>=Reference!$H$5, Reference!$G$5, "")))) -> Severe | Q39: =IF(F39="Physical", "Very Low", IF(F39="Local", "Low", IF(F39="Adjacent", "Medium", IF(F39="Network", "High", "")))) -> High | R39: =IF(AE39>=Reference!$D$2, Reference!$G$2, IF(AE39>=Reference!$D$3, Reference!$E$3, IF(AE39>=Reference!$D$4, Reference!$E$4, IF(AE39>=Reference!$D$5, Reference!$E$5, "")))) -> Severe | S39: Mitigation | T39: Integrate secure OBU firmware with integrity checks, establish backup RSUs for alert validation, and apply machine learning-based anomaly detection for collision risks. | U39: OBU firmware, RSU alerting mechanisms, backend traffic management systems, and collision risk processing algorithms. | V39: Ensuring accurate and timely collision risk notifications is essential for road safety and preventing high-impact traffic incidents. | W39: Maintain the integrity, availability, and non-repudiation of collision risk notifications across the V2X network. | Y39: =IF(H39=Reference!$A$12, Reference!$C$12, IF(H39=Reference!$A$11, Reference!$C$11, IF(H39=Reference!$A$10, Reference!$C$10, IF(H39=Reference!$A$9, Reference!$C$9, 0)))) -> 10 | Z39: =IF(J39=Reference!$A$20, Reference!$C$20, IF(J39=Reference!$A$19, Reference!$C$19, IF(J39=Reference!$A$18, Reference!$C$18, IF(J39=Reference!$A$17, Reference!$C$17, 0)))) -> 10 | AA39: =IF(L39=Reference!$A$28, Reference!$C$28, IF(L39=Reference!$A$27, Reference!$C$27, IF(L39=Reference!$A$26, Reference!$C$26, IF(L39=Reference!$A$25, Reference!$C$25, 0)))) -> 10 | AB39: =IF(N39=Reference!$A$36, Reference!$C$36, IF(N39=Reference!$A$35, Reference!$C$35, IF(N39=Reference!$A$34, Reference!$C$34, IF(N39=Reference!$A$33, Reference!$C$33, 0)))) -> 10 | AC39: =(Reference!$B$2*Y39 + Reference!$B$3*AA39 + Reference!$B$4*Z39 + Reference!$B$5 * AB39)/4 -> 16.875 | AD39: =IF(Q39=Reference!$C$41, Reference!$D$41, IF(Q39=Reference!$C$42, Reference!$D$42, IF(Q39=Reference!$C$43, Reference!$D$43, IF(Q39=Reference!$C$44, Reference!$D$44, 0)))) -> 10 | AE39: =1 + (AC39 * AD39) -> 169.75
A40: DENM Situation Container (Dangerous Situation Notification - Cause Code and SubCause Code) | B40: Tampering | C40: Integrity | D40: The attacker injects false emergency brake light activation signals, causing vehicles to respond with sudden braking or unnecessary caution. | E40: The attacker exploits access to the vehicle’s OBU or RSU to modify the Dangerous Situation fields before broadcasting them over the V2X network. | F40: Network | G40: The attacker aims to disrupt traffic flow, cause panic, or exploit the resulting traffic congestion for malicious purposes. | H40: Major | I40: Sudden and unnecessary braking can lead to rear-end collisions, especially in high-speed or congested areas. | J40: Moderate | K40: False emergency alerts may cause minor operational costs due to unnecessary checks or system diagnostics, but these would not significantly strain financial resources. | | L40: Moderate | M40: Traffic disruptions from unnecessary braking and reduced traffic flow efficiency. | N40: Moderate | O40: False emergency alerts do not directly disclose personal data, but repeated false alarms may cause minor violations of traffic management regulations without severe financial or operational penalties (e.g., warnings, minor legal scrutiny). | | P40: =IF(AC40>=Reference!$H$2, Reference!$G$2, IF(AC40>=Reference!$H$3, Reference!$G$3, IF(AC40>=Reference!$H$4, Reference!$G$4, IF(AC40>=Reference!$H$5, Reference!$G$5, "")))) -> Severe | Q40: =IF(F40="Physical", "Very Low", IF(F40="Local", "Low", IF(F40="Adjacent", "Medium", IF(F40="Network", "High", "")))) -> High | R40: =IF(AE40>=Reference!$D$2, Reference!$G$2, IF(AE40>=Reference!$D$3, Reference!$E$3, IF(AE40>=Reference!$D$4, Reference!$E$4, IF(AE40>=Reference!$D$5, Reference!$E$5, "")))) -> Severe | S40: Mitigation | T40: Integrate secure communication protocols (e.g., IEEE 1609.2) for all V2X messages,Regular OBU and RSU firmware updates with secure boot mechanisms,Continuous traffic monitoring and correlation with other vehicle data to validate emergency alerts. | U40: OBU firmware and communication stack,RSU alerting systems and traffic management backends,DENM message validation protocols and infrastructure. | V40: Ensures accurate and reliable dissemination of critical road safety information, protecting drivers and road users.Reduces false alerts that can cause panic or traffic disruptions, and prevents suppression of genuine alerts that could lead to accidents. | W40: Guarantee the accuracy and authenticity of DENM messages.(Integrity).Ensure timely and reliable delivery of critical safety information.(Availability).Confirm that messages come from legitimate sources and have not been altered.(Non-repudiation) | Y40: =IF(H40=Reference!$A$12, Reference!$C$12, IF(H40=Reference!$A$11, Reference!$C$11, IF(H40=Reference!$A$10, Reference!$C$10, IF(H40=Reference!$A$9, Reference!$C$9, 0)))) -> 7 | Z40: =IF(J40=Reference!$A$20, Reference!$C$20, IF(J40=Reference!$A$19, Reference!$C$19, IF(J40=Reference!$A$18, Reference!$C$18, IF(J40=Reference!$A$17, Reference!$C$17, 0)))) -> 4 | AA40: =IF(L40=Reference!$A$28, Reference!$C$28, IF(L40=Reference!$A$27, Reference!$C$27, IF(L40=Reference!$A$26, Reference!$C$26, IF(L40=Reference!$A$25, Reference!$C$25, 0)))) -> 4 | AB40: =IF(N40=Reference!$A$36, Reference!$C$36, IF(N40=Reference!$A$35, Reference!$C$35, IF(N40=Reference!$A$34, Reference!$C$34, IF(N40=Reference!$A$33, Reference!$C$33, 0)))) -> 4 | AC40: =(Reference!$B$2*Y40 + Reference!$B$3*AA40 + Reference!$B$4*Z40 + Reference!$B$5 * AB40)/4 -> 10.5 | AD40: =IF(Q40=Reference!$C$41, Reference!$D$41, IF(Q40=Reference!$C$42, Reference!$D$42, IF(Q40=Reference!$C$43, Reference!$D$43, IF(Q40=Reference!$C$44, Reference!$D$44, 0)))) -> 10 | AE40: =1 + (AC40 * AD40) -> 106
B41: Tampering | C41: Integrity | D41: The attacker suppresses genuine emergency brake light activation signals, preventing vehicles from responding to real hazards. | E41: The attacker compromises the OBU or RSU to block or alter legitimate Dangerous Situation messages before transmission. | F41: Network | G41: The attacker may seek to increase accident rates, create chaos, or exploit the resulting damage for financial or competitive gain. | H41: Severe | I41: Failure to alert nearby vehicles to emergency braking can lead to high-speed collisions and life-threatening injuries. | J41: Major | K41: Suppressing critical alerts can lead to substantial financial losses. Accidents caused by missing emergency brake signals may result in high repair costs, legal liabilities, increased insurance premiums, and potential regulatory fines, though the financial stability of the organization is not at risk. | L41: Major | M41: Accidents and traffic blockages from unreported hazards can cause widespread delays. | N41: Major | O41: Suppressing genuine emergency alerts may lead to legal consequences for traffic management authorities due to failure in ensuring road safety, with potential financial penalties and public criticism, impacting the reputation of infrastructure operators or vehicle manufacturers. | P41: =IF(AC41>=Reference!$H$2, Reference!$G$2, IF(AC41>=Reference!$H$3, Reference!$G$3, IF(AC41>=Reference!$H$4, Reference!$G$4, IF(AC41>=Reference!$H$5, Reference!$G$5, "")))) -> Severe | Q41: =IF(F41="Physical", "Very Low", IF(F41="Local", "Low", IF(F41="Adjacent", "Medium", IF(F41="Network", "High", "")))) -> High | R41: =IF(AE41>=Reference!$D$2, Reference!$G$2, IF(AE41>=Reference!$D$3, Reference!$E$3, IF(AE41>=Reference!$D$4, Reference!$E$4, IF(AE41>=Reference!$D$5, Reference!$E$5, "")))) -> Severe | S41: Mitigation | T41: Integrate secure communication protocols (e.g., IEEE 1609.2) for all V2X messages,Regular OBU and RSU firmware updates with secure boot mechanisms,Continuous traffic monitoring and correlation with other vehicle data to validate emergency alerts. | U41: OBU firmware and communication stack,RSU alerting systems and traffic management backends,DENM message validation protocols and infrastructure. | V41: Ensures accurate and reliable dissemination of critical road safety information, protecting drivers and road users.Reduces false alerts that can cause panic or traffic disruptions, and prevents suppression of genuine alerts that could lead to accidents. | W41: Guarantee the accuracy and authenticity of DENM messages.(Integrity).Ensure timely and reliable delivery of critical safety information.(Availability).Confirm that messages come from legitimate sources and have not been altered.(Non-repudiation) | Y41: =IF(H41=Reference!$A$12, Reference!$C$12, IF(H41=Reference!$A$11, Reference!$C$11, IF(H41=Reference!$A$10, Reference!$C$10, IF(H41=Reference!$A$9, Reference!$C$9, 0)))) -> 10 | Z41: =IF(J41=Reference!$A$20, Reference!$C$20, IF(J41=Reference!$A$19, Reference!$C$19, IF(J41=Reference!$A$18, Reference!$C$18, IF(J41=Reference!$A$17, Reference!$C$17, 0)))) -> 7 | AA41: =IF(L41=Reference!$A$28, Reference!$C$28, IF(L41=Reference!$A$27, Reference!$C$27, IF(L41=Reference!$A$26, Reference!$C$26, IF(L41=Reference!$A$25, Reference!$C$25, 0)))) -> 7 | AB41: =IF(N41=Reference!$A$36, Reference!$C$36, IF(N41=Reference!$A$35, Reference!$C$35, IF(N41=Reference!$A$34, Reference!$C$34, IF(N41=Reference!$A$33, Reference!$C$33, 0)))) -> 7 | AC41: =(Reference!$B$2*Y41 + Reference!$B$3*AA41 + Reference!$B$4*Z41 + Reference!$B$5 * AB41)/4 -> 15.5625 | AD41: =IF(Q41=Reference!$C$41, Reference!$D$41, IF(Q41=Reference!$C$42, Reference!$D$42, IF(Q41=Reference!$C$43, Reference!$D$43, IF(Q41=Reference!$C$44, Reference!$D$44, 0)))) -> 10 | AE41: =1 + (AC41 * AD41) -> 156.625
B42: Tampering | C42: Integrity | D42: The attacker sends false pre-crash activation messages, prompting unnecessary evasive actions by vehicles. | E42: The attacker manipulates OBU firmware or RSU transmissions to insert false pre-crash alerts. | F42: Network | G42: The attacker could aim to induce unnecessary vehicle maneuvers, leading to traffic disruptions or accidents. | H42: Major | I42: False pre-crash activations may cause abrupt lane changes or braking, increasing accident risk. | J42: Moderate | K42: Misleading pre-crash alerts would incur low financial impact. Minor operational disruptions or investigations into false alerts would result in manageable financial costs for the organization, remaining within tolerable limits. | L42: Moderate | M42: Traffic delays and confusion due to unnecessary emergency responses. | N42: Moderate | O42: Pre-crash system activations involve operational data rather than personal data. However, misuse of such alerts may violate safety regulations, leading to minor legal implications (e.g., warnings or fines) without major financial impact. | P42: =IF(AC42>=Reference!$H$2, Reference!$G$2, IF(AC42>=Reference!$H$3, Reference!$G$3, IF(AC42>=Reference!$H$4, Reference!$G$4, IF(AC42>=Reference!$H$5, Reference!$G$5, "")))) -> Severe | Q42: =IF(F42="Physical", "Very Low", IF(F42="Local", "Low", IF(F42="Adjacent", "Medium", IF(F42="Network", "High", "")))) -> High | R42: =IF(AE42>=Reference!$D$2, Reference!$G$2, IF(AE42>=Reference!$D$3, Reference!$E$3, IF(AE42>=Reference!$D$4, Reference!$E$4, IF(AE42>=Reference!$D$5, Reference!$E$5, "")))) -> Severe | S42: Mitigation | T42: Integrate secure communication protocols (e.g., IEEE 1609.2) for all V2X messages,Regular OBU and RSU firmware updates with secure boot mechanisms,Continuous traffic monitoring and correlation with other vehicle data to validate emergency alerts. | U42: OBU firmware and communication stack,RSU alerting systems and traffic management backends,DENM message validation protocols and infrastructure. | V42: Ensures accurate and reliable dissemination of critical road safety information, protecting drivers and road users.Reduces false alerts that can cause panic or traffic disruptions, and prevents suppression of genuine alerts that could lead to accidents. | W42: Guarantee the accuracy and authenticity of DENM messages.(Integrity).Ensure timely and reliable delivery of critical safety information.(Availability).Confirm that messages come from legitimate sources and have not been altered.(Non-repudiation) | Y42: =IF(H42=Reference!$A$12, Reference!$C$12, IF(H42=Reference!$A$11, Reference!$C$11, IF(H42=Reference!$A$10, Reference!$C$10, IF(H42=Reference!$A$9, Reference!$C$9, 0)))) -> 7 | Z42: =IF(J42=Reference!$A$20, Reference!$C$20, IF(J42=Reference!$A$19, Reference!$C$19, IF(J42=Reference!$A$18, Reference!$C$18, IF(J42=Reference!$A$17, Reference!$C$17, 0)))) -> 4 | AA42: =IF(L42=Reference!$A$28, Reference!$C$28, IF(L42=Reference!$A$27, Reference!$C$27, IF(L42=Reference!$A$26, Reference!$C$26, IF(L42=Reference!$A$25, Reference!$C$25, 0)))) -> 4 | AB42: =IF(N42=Reference!$A$36, Reference!$C$36, IF(N42=Reference!$A$35, Reference!$C$35, IF(N42=Reference!$A$34, Reference!$C$34, IF(N42=Reference!$A$33, Reference!$C$33, 0)))) -> 4 | AC42: =(Reference!$B$2*Y42 + Reference!$B$3*AA42 + Reference!$B$4*Z42 + Reference!$B$5 * AB42)/4 -> 10.5 | AD42: =IF(Q42=Reference!$C$41, Reference!$D$41, IF(Q42=Reference!$C$42, Reference!$D$42, IF(Q42=Reference!$C$43, Reference!$D$43, IF(Q42=Reference!$C$44, Reference!$D$44, 0)))) -> 10 | AE42: =1 + (AC42 * AD42) -> 106
A43: DENM Manager Container- referenceTime | B43: Tampering | C43: Integrity | D43: The attacker injects a false referenceTime set to a current timestamp, tricking receiving ITS-S into believing a fictitious event (e.g., road accident, obstruction) has just been triggered. This falsely initiates a new DENM trigger message. | E43: Network compromise through RSU or OBU to falsify transmitted DENM packets. | F43: Network | G43: To disrupt normal traffic patterns, cause unnecessary rerouting, congestion, or emergency service responses. | H43: Moderate | I43: Potential minor accidents due to unexpected maneuvers or braking. | J43: Moderate | K43: Minor disruptions tolerable financially, indirect costs manageable by OEM. | L43: Moderate | M43: Temporary and partial degradation of traffic flow and efficiency | N43: Moderate | O43: Minimal legislative impact; negligible privacy concerns. | P43: =IF(AC43>=Reference!$H$2, Reference!$G$2, IF(AC43>=Reference!$H$3, Reference!$G$3, IF(AC43>=Reference!$H$4, Reference!$G$4, IF(AC43>=Reference!$H$5, Reference!$G$5, "")))) -> Major | Q43: =IF(F43="Physical", "Very Low", IF(F43="Local", "Low", IF(F43="Adjacent", "Medium", IF(F43="Network", "High", "")))) -> High | R43: =IF(AE43>=Reference!$D$2, Reference!$G$2, IF(AE43>=Reference!$D$3, Reference!$E$3, IF(AE43>=Reference!$D$4, Reference!$E$4, IF(AE43>=Reference!$D$5, Reference!$E$5, "")))) -> High | S43: Mitigation | T43: Integrity checks via cryptographic signatures for DENM messages.Implement anomaly detection algorithms within OBU and RSU.Backend cross-verification of newly triggered events. | U43: OBU firmware (message signing).RSU verification systems.Backend validation services | V43: Reducing false trigger events maintains accurate traffic conditions, preventing unnecessary disruption and potential safety hazards. | W43: Integrity, Availability, Non-repudiation | Y43: =IF(H43=Reference!$A$12, Reference!$C$12, IF(H43=Reference!$A$11, Reference!$C$11, IF(H43=Reference!$A$10, Reference!$C$10, IF(H43=Reference!$A$9, Reference!$C$9, 0)))) -> 4 | Z43: =IF(J43=Reference!$A$20, Reference!$C$20, IF(J43=Reference!$A$19, Reference!$C$19, IF(J43=Reference!$A$18, Reference!$C$18, IF(J43=Reference!$A$17, Reference!$C$17, 0)))) -> 4 | AA43: =IF(L43=Reference!$A$28, Reference!$C$28, IF(L43=Reference!$A$27, Reference!$C$27, IF(L43=Reference!$A$26, Reference!$C$26, IF(L43=Reference!$A$25, Reference!$C$25, 0)))) -> 4 | AB43: =IF(N43=Reference!$A$36, Reference!$C$36, IF(N43=Reference!$A$35, Reference!$C$35, IF(N43=Reference!$A$34, Reference!$C$34, IF(N43=Reference!$A$33, Reference!$C$33, 0)))) -> 4 | AC43: =(Reference!$B$2*Y43 + Reference!$B$3*AA43 + Reference!$B$4*Z43 + Reference!$B$5 * AB43)/4 -> 6.75 | AD43: =IF(Q43=Reference!$C$41, Reference!$D$41, IF(Q43=Reference!$C$42, Reference!$D$42, IF(Q43=Reference!$C$43, Reference!$D$43, IF(Q43=Reference!$C$44, Reference!$D$44, 0)))) -> 10 | AE43: =1 + (AC43 * AD43) -> 68.5
B44: Tampering | C44: Integrity | D44: An attacker modifies referenceTime for update-type DENMs, falsely communicating that an ongoing event (e.g., road blockage) has been recently updated, either prematurely indicating event resolution or delaying the update of critical event information. | E44: Unauthorized network access through compromised RSU/OBU infrastructure to alter timestamps in DENM updates. | F44: Network | G44: Intentional misinformation to direct traffic into unresolved hazards or unnecessarily prolong traffic restrictions. | H44: Major | I44: Increased likelihood of severe collisions or incidents from outdated event information. | J44: Major | K44: Significant indirect costs, including legal liabilities, reputation damage, and insurance claims. | L44: Major | M44: Substantial disruption, delays in emergency services, and prolonged traffic congestion. | N44: Moderate | O44: Minimal legislative concern; negligible privacy concerns. | P44: =IF(AC44>=Reference!$H$2, Reference!$G$2, IF(AC44>=Reference!$H$3, Reference!$G$3, IF(AC44>=Reference!$H$4, Reference!$G$4, IF(AC44>=Reference!$H$5, Reference!$G$5, "")))) -> Severe | Q44: =IF(F44="Physical", "Very Low", IF(F44="Local", "Low", IF(F44="Adjacent", "Medium", IF(F44="Network", "High", "")))) -> High | R44: =IF(AE44>=Reference!$D$2, Reference!$G$2, IF(AE44>=Reference!$D$3, Reference!$E$3, IF(AE44>=Reference!$D$4, Reference!$E$4, IF(AE44>=Reference!$D$5, Reference!$E$5, "")))) -> Severe | S44: Mitigation | T44: Secure timestamp protocols and cryptographic signing.Anomaly detection of suspicious updates at the backend and OBU/RSU.Cross-check updates using multiple independent ITS-S sources. | U44: RSU update-management system.OBU software integrity.Backend validation architecture | V44: Accurate and timely event updates are critical for safe and efficient traffic management. | W44: Integrity, Availability, Non-repudiation | Y44: =IF(H44=Reference!$A$12, Reference!$C$12, IF(H44=Reference!$A$11, Reference!$C$11, IF(H44=Reference!$A$10, Reference!$C$10, IF(H44=Reference!$A$9, Reference!$C$9, 0)))) -> 7 | Z44: =IF(J44=Reference!$A$20, Reference!$C$20, IF(J44=Reference!$A$19, Reference!$C$19, IF(J44=Reference!$A$18, Reference!$C$18, IF(J44=Reference!$A$17, Reference!$C$17, 0)))) -> 7 | AA44: =IF(L44=Reference!$A$28, Reference!$C$28, IF(L44=Reference!$A$27, Reference!$C$27, IF(L44=Reference!$A$26, Reference!$C$26, IF(L44=Reference!$A$25, Reference!$C$25, 0)))) -> 7 | AB44: =IF(N44=Reference!$A$36, Reference!$C$36, IF(N44=Reference!$A$35, Reference!$C$35, IF(N44=Reference!$A$34, Reference!$C$34, IF(N44=Reference!$A$33, Reference!$C$33, 0)))) -> 4 | AC44: =(Reference!$B$2*Y44 + Reference!$B$3*AA44 + Reference!$B$4*Z44 + Reference!$B$5 * AB44)/4 -> 11.625 | AD44: =IF(Q44=Reference!$C$41, Reference!$D$41, IF(Q44=Reference!$C$42, Reference!$D$42, IF(Q44=Reference!$C$43, Reference!$D$43, IF(Q44=Reference!$C$44, Reference!$D$44, 0)))) -> 10 | AE44: =1 + (AC44 * AD44) -> 117.25
B45: Tampering | C45: Integrity | D45: The attacker manipulates the referenceTime field in cancellation or negation DENMs, falsely declaring an active event (such as a hazardous situation or accident) terminated prematurely or incorrectly invalidating an active alert. | E45: Compromise of the network interface via unauthorized RSU/OBU access, modifying DENM cancellation packets. | F45: Network | G45: Maliciously exposing road users to ongoing hazards by falsely declaring areas safe. | H45: Severe | I45: Significant potential for fatal accidents due to misinformation. | J45: Major | K45: Substantial direct and indirect financial damage from major accidents, legal action, and brand reputation harm. | L45: Major | M45: Severe operational disruptions due to accident management, emergency response delays, and prolonged congestion. | N45: Major | O45: Legislative risks from failing safety standards, significant fines, and regulatory actions possible. | P45: =IF(AC45>=Reference!$H$2, Reference!$G$2, IF(AC45>=Reference!$H$3, Reference!$G$3, IF(AC45>=Reference!$H$4, Reference!$G$4, IF(AC45>=Reference!$H$5, Reference!$G$5, "")))) -> Severe | Q45: =IF(F45="Physical", "Very Low", IF(F45="Local", "Low", IF(F45="Adjacent", "Medium", IF(F45="Network", "High", "")))) -> High | R45: =IF(AE45>=Reference!$D$2, Reference!$G$2, IF(AE45>=Reference!$D$3, Reference!$E$3, IF(AE45>=Reference!$D$4, Reference!$E$4, IF(AE45>=Reference!$D$5, Reference!$E$5, "")))) -> Severe | S45: Mitigation | T45: Use cryptographic message signing to ensure timestamp integrity.Employ backend validation against multiple sources before allowing cancellations.Implement real-time monitoring systems for anomalies. | U45: RSU and OBU message validation mechanisms.Secure backend systems | V45: The integrity of event termination data is critical, as incorrect terminations can directly cause severe safety hazards. | W45: Integrity, Availability, Non-repudiation, Compliance | Y45: =IF(H45=Reference!$A$12, Reference!$C$12, IF(H45=Reference!$A$11, Reference!$C$11, IF(H45=Reference!$A$10, Reference!$C$10, IF(H45=Reference!$A$9, Reference!$C$9, 0)))) -> 10 | Z45: =IF(J45=Reference!$A$20, Reference!$C$20, IF(J45=Reference!$A$19, Reference!$C$19, IF(J45=Reference!$A$18, Reference!$C$18, IF(J45=Reference!$A$17, Reference!$C$17, 0)))) -> 7 | AA45: =IF(L45=Reference!$A$28, Reference!$C$28, IF(L45=Reference!$A$27, Reference!$C$27, IF(L45=Reference!$A$26, Reference!$C$26, IF(L45=Reference!$A$25, Reference!$C$25, 0)))) -> 7 | AB45: =IF(N45=Reference!$A$36, Reference!$C$36, IF(N45=Reference!$A$35, Reference!$C$35, IF(N45=Reference!$A$34, Reference!$C$34, IF(N45=Reference!$A$33, Reference!$C$33, 0)))) -> 7 | AC45: =(Reference!$B$2*Y45 + Reference!$B$3*AA45 + Reference!$B$4*Z45 + Reference!$B$5 * AB45)/4 -> 15.5625 | AD45: =IF(Q45=Reference!$C$41, Reference!$D$41, IF(Q45=Reference!$C$42, Reference!$D$42, IF(Q45=Reference!$C$43, Reference!$D$43, IF(Q45=Reference!$C$44, Reference!$D$44, 0)))) -> 10 | AE45: =1 + (AC45 * AD45) -> 156.625
A46: DENM Manager Container- EventPosition | B46: Tampering | C46: Integrity | D46: An attacker modifies the EventPosition data to falsely relocate an existing hazard or accident to an incorrect geographical position (e.g., several kilometers away from its actual location). | E46: Attacker exploits vulnerabilities in the vehicle’s OBU or RSU via wireless network interfaces transmitting manipulated geographical coordinates before broadcasting. | F46: Network | G46: Remote wireless attack on V2X interfaces without physical restrictions. Intended confusion or operational disruption by causing vehicles and emergency responders to reroute away from the actual event location. | H46: Major | I46: Significant confusion can cause collisions, near-miss incidents, or severe accidents due to sudden rerouting or braking (severe injuries probable). | J46: Major | K46: Substantial financial implications from emergency service inefficiencies, higher operational costs, potential liabilities, and significant reputational harm to OEM or ITS operator. | L46: Major | M46: Critical disruptions to traffic flow, improper allocation of emergency resources, delayed responses, and overall traffic management inefficiencies. | N46: Moderate | O46: Moderate legislative penalties and regulatory implications for inaccurate or misleading DENM information broadcasted by compromised ITS systems. Privacy implications minimal. | P46: =IF(AC46>=Reference!$H$2, Reference!$G$2, IF(AC46>=Reference!$H$3, Reference!$G$3, IF(AC46>=Reference!$H$4, Reference!$G$4, IF(AC46>=Reference!$H$5, Reference!$G$5, "")))) -> Severe | Q46: =IF(F46="Physical", "Very Low", IF(F46="Local", "Low", IF(F46="Adjacent", "Medium", IF(F46="Network", "High", "")))) -> High | R46: =IF(AE46>=Reference!$D$2, Reference!$G$2, IF(AE46>=Reference!$D$3, Reference!$E$3, IF(AE46>=Reference!$D$4, Reference!$E$4, IF(AE46>=Reference!$D$5, Reference!$E$5, "")))) -> Severe | S46: Mitigation | T46: Digital signatures for message authentication and integrity checks.Real-time verification through cross-validation of reported positions with other sensor data or independent reporting units.Geofencing and plausibility checks for automatic detection of anomalous positions.Regular firmware/software updates of OBUs and RSUs to protect against vulnerabilities. | U46: OBU and RSU firmware security and validation algorithms.Backend verification and anomaly detection infrastructure.Cryptographic key management and message-signing processes. | V46: Preventing incorrect rerouting of traffic and avoiding unnecessary risks to public safety are critical objectives. The integrity of location data directly affects safety-critical decisions and emergency response effectiveness. | W46: Integrity, Availability, Non-repudiation, Compliance. | Y46: =IF(H46=Reference!$A$12, Reference!$C$12, IF(H46=Reference!$A$11, Reference!$C$11, IF(H46=Reference!$A$10, Reference!$C$10, IF(H46=Reference!$A$9, Reference!$C$9, 0)))) -> 7 | Z46: =IF(J46=Reference!$A$20, Reference!$C$20, IF(J46=Reference!$A$19, Reference!$C$19, IF(J46=Reference!$A$18, Reference!$C$18, IF(J46=Reference!$A$17, Reference!$C$17, 0)))) -> 7 | AA46: =IF(L46=Reference!$A$28, Reference!$C$28, IF(L46=Reference!$A$27, Reference!$C$27, IF(L46=Reference!$A$26, Reference!$C$26, IF(L46=Reference!$A$25, Reference!$C$25, 0)))) -> 7 | AB46: =IF(N46=Reference!$A$36, Reference!$C$36, IF(N46=Reference!$A$35, Reference!$C$35, IF(N46=Reference!$A$34, Reference!$C$34, IF(N46=Reference!$A$33, Reference!$C$33, 0)))) -> 4 | AC46: =(Reference!$B$2*Y46 + Reference!$B$3*AA46 + Reference!$B$4*Z46 + Reference!$B$5 * AB46)/4 -> 11.625 | AD46: =IF(Q46=Reference!$C$41, Reference!$D$41, IF(Q46=Reference!$C$42, Reference!$D$42, IF(Q46=Reference!$C$43, Reference!$D$43, IF(Q46=Reference!$C$44, Reference!$D$44, 0)))) -> 10 | AE46: =1 + (AC46 * AD46) -> 117.25
B47: Spoofing | C47: Integrity | D47: An attacker injects false geographical coordinates into the EventPosition field, fabricating a non-existent hazard (e.g., fake accident or blockage) at a strategically chosen high-traffic area to deliberately cause significant congestion or panic. | E47: Compromise OBU or RSU remotely through the network stack to insert and transmit falsified DENM messages. | F47: Network | G47: Malicious intent to create operational chaos, massive disruption, or economic impact. Attack might have a criminal or political motive (e.g., disrupt major transportation routes or infrastructures). | H47: Major | I47: High likelihood of serious accidents or injuries due to sudden braking, confusion, and panic reactions from falsely perceived hazards. | J47: Major | K47: Major financial impact due to significant traffic disruption costs, emergency service deployments, reputational damage, and potential regulatory penalties. | L47: Major | M47: Severe operational disruptions, extensive congestion, inefficient emergency services resource allocation, and broad-scale impact on traffic management. | N47: Moderate | O47: Potential regulatory consequences from broadcasting false safety-critical information. Minimal privacy impact. | P47: =IF(AC47>=Reference!$H$2, Reference!$G$2, IF(AC47>=Reference!$H$3, Reference!$G$3, IF(AC47>=Reference!$H$4, Reference!$G$4, IF(AC47>=Reference!$H$5, Reference!$G$5, "")))) -> Severe | Q47: =IF(F47="Physical", "Very Low", IF(F47="Local", "Low", IF(F47="Adjacent", "Medium", IF(F47="Network", "High", "")))) -> High | R47: =IF(AE47>=Reference!$D$2, Reference!$G$2, IF(AE47>=Reference!$D$3, Reference!$E$3, IF(AE47>=Reference!$D$4, Reference!$E$4, IF(AE47>=Reference!$D$5, Reference!$E$5, "")))) -> Severe | S47: Mitigation | T47: Enforce strong cryptographic message protection (digital signatures, message integrity).Advanced anomaly detection using cooperative V2X communication (cross-validation of data from multiple vehicles/RSUs).Geofencing and sanity checks within ITS infrastructure to immediately flag inconsistent or improbable event locations. | U47: OBU and RSU security features, firmware validation, and cryptographic key management.Backend anomaly detection services, geographical plausibility modules, and verification algorithms. | V47: The deliberate fabrication of false hazards in critical traffic areas poses severe threats to public safety, traffic efficiency, and economic stability. Such events require immediate mitigation due to their high impact on safety and public trust. | W47: Integrity, Availability, Non-repudiation, Compliance. | Y47: =IF(H47=Reference!$A$12, Reference!$C$12, IF(H47=Reference!$A$11, Reference!$C$11, IF(H47=Reference!$A$10, Reference!$C$10, IF(H47=Reference!$A$9, Reference!$C$9, 0)))) -> 7 | Z47: =IF(J47=Reference!$A$20, Reference!$C$20, IF(J47=Reference!$A$19, Reference!$C$19, IF(J47=Reference!$A$18, Reference!$C$18, IF(J47=Reference!$A$17, Reference!$C$17, 0)))) -> 7 | AA47: =IF(L47=Reference!$A$28, Reference!$C$28, IF(L47=Reference!$A$27, Reference!$C$27, IF(L47=Reference!$A$26, Reference!$C$26, IF(L47=Reference!$A$25, Reference!$C$25, 0)))) -> 7 | AB47: =IF(N47=Reference!$A$36, Reference!$C$36, IF(N47=Reference!$A$35, Reference!$C$35, IF(N47=Reference!$A$34, Reference!$C$34, IF(N47=Reference!$A$33, Reference!$C$33, 0)))) -> 4 | AC47: =(Reference!$B$2*Y47 + Reference!$B$3*AA47 + Reference!$B$4*Z47 + Reference!$B$5 * AB47)/4 -> 11.625 | AD47: =IF(Q47=Reference!$C$41, Reference!$D$41, IF(Q47=Reference!$C$42, Reference!$D$42, IF(Q47=Reference!$C$43, Reference!$D$43, IF(Q47=Reference!$C$44, Reference!$D$44, 0)))) -> 10 | AE47: =1 + (AC47 * AD47) -> 117.25
B48: Tampering | C48: Integrity | D48: An attacker injects false geographical coordinates into the EventPosition field, fabricating a non-existent hazard (e.g., fake accident or blockage) at a strategically chosen high-traffic area to deliberately cause significant congestion or panic. | E48: Compromise OBU or RSU remotely through the network stack to insert and transmit falsified DENM messages. | F48: Network | G48: Malicious intent to create operational chaos, massive disruption, or economic impact. Attack might have a criminal or political motive (e.g., disrupt major transportation routes or infrastructures). | H48: Major | I48: High likelihood of serious accidents or injuries due to sudden braking, confusion, and panic reactions from falsely perceived hazards. | J48: Major | K48: Major financial impact due to significant traffic disruption costs, emergency service deployments, reputational damage, and potential regulatory penalties. | L48: Major | M48: Severe operational disruptions, extensive congestion, inefficient emergency services resource allocation, and broad-scale impact on traffic management. | N48: Moderate | O48: Potential regulatory consequences from broadcasting false safety-critical information. Minimal privacy impact. | P48: =IF(AC48>=Reference!$H$2, Reference!$G$2, IF(AC48>=Reference!$H$3, Reference!$G$3, IF(AC48>=Reference!$H$4, Reference!$G$4, IF(AC48>=Reference!$H$5, Reference!$G$5, "")))) -> Severe | Q48: =IF(F48="Physical", "Very Low", IF(F48="Local", "Low", IF(F48="Adjacent", "Medium", IF(F48="Network", "High", "")))) -> High | R48: =IF(AE48>=Reference!$D$2, Reference!$G$2, IF(AE48>=Reference!$D$3, Reference!$E$3, IF(AE48>=Reference!$D$4, Reference!$E$4, IF(AE48>=Reference!$D$5, Reference!$E$5, "")))) -> Severe | S48: Mitigation | T48: Enforce strong cryptographic message protection (digital signatures, message integrity).Advanced anomaly detection using cooperative V2X communication (cross-validation of data from multiple vehicles/RSUs).Geofencing and sanity checks within ITS infrastructure to immediately flag inconsistent or improbable event locations. | U48: OBU and RSU security features, firmware validation, and cryptographic key management.Backend anomaly detection services, geographical plausibility modules, and verification algorithms. | V48: The deliberate fabrication of false hazards in critical traffic areas poses severe threats to public safety, traffic efficiency, and economic stability. Such events require immediate mitigation due to their high impact on safety and public trust. | W48: Integrity, Availability, Non-repudiation, Compliance. | Y48: =IF(H48=Reference!$A$12, Reference!$C$12, IF(H48=Reference!$A$11, Reference!$C$11, IF(H48=Reference!$A$10, Reference!$C$10, IF(H48=Reference!$A$9, Reference!$C$9, 0)))) -> 7 | Z48: =IF(J48=Reference!$A$20, Reference!$C$20, IF(J48=Reference!$A$19, Reference!$C$19, IF(J48=Reference!$A$18, Reference!$C$18, IF(J48=Reference!$A$17, Reference!$C$17, 0)))) -> 7 | AA48: =IF(L48=Reference!$A$28, Reference!$C$28, IF(L48=Reference!$A$27, Reference!$C$27, IF(L48=Reference!$A$26, Reference!$C$26, IF(L48=Reference!$A$25, Reference!$C$25, 0)))) -> 7 | AB48: =IF(N48=Reference!$A$36, Reference!$C$36, IF(N48=Reference!$A$35, Reference!$C$35, IF(N48=Reference!$A$34, Reference!$C$34, IF(N48=Reference!$A$33, Reference!$C$33, 0)))) -> 4 | AC48: =(Reference!$B$2*Y48 + Reference!$B$3*AA48 + Reference!$B$4*Z48 + Reference!$B$5 * AB48)/4 -> 11.625 | AD48: =IF(Q48=Reference!$C$41, Reference!$D$41, IF(Q48=Reference!$C$42, Reference!$D$42, IF(Q48=Reference!$C$43, Reference!$D$43, IF(Q48=Reference!$C$44, Reference!$D$44, 0)))) -> 10 | AE48: =1 + (AC48 * AD48) -> 117.25
A49: DENM Management Container-DetectionTime | B49: Tampering | C49: Integrity | D49: An attacker delays the DetectionTime reported in the DENM message, causing receiving vehicles to perceive recent hazards as outdated or less urgent, thus potentially ignoring or underestimating the danger. | E49: Compromising OBU or RSU software via network vulnerabilities to manipulate the timestamp data within outgoing DENM messages. | F49: Network | G49: Motivated by malicious intent to disrupt timely emergency responses, increasing risks of accidents due to incorrect driver perception of urgency. | H49: Major | I49: Underestimated urgency can lead to serious collisions due to inadequate reaction to real hazards. | J49: Major | K49: Substantial financial costs due to potential accidents, liability, reputation damage, and emergency responses. | L49: Major | M49: Significant disruption to traffic and emergency management operations due to delayed or inappropriate responses. | N49: Moderate | O49: Minimal privacy concerns; legislative impacts limited to potential regulatory warnings without major consequences. | P49: =IF(AC49>=Reference!$H$2, Reference!$G$2, IF(AC49>=Reference!$H$3, Reference!$G$3, IF(AC49>=Reference!$H$4, Reference!$G$4, IF(AC49>=Reference!$H$5, Reference!$G$5, "")))) -> Severe | Q49: =IF(F49="Physical", "Very Low", IF(F49="Local", "Low", IF(F49="Adjacent", "Medium", IF(F49="Network", "High", "")))) -> High | R49: =IF(AE49>=Reference!$D$2, Reference!$G$2, IF(AE49>=Reference!$D$3, Reference!$E$3, IF(AE49>=Reference!$D$4, Reference!$E$4, IF(AE49>=Reference!$D$5, Reference!$E$5, "")))) -> Severe | S49: Mitigation | T49: Cryptographic message authentication (digital signatures) to ensure timestamp integrity.Cross-validation of DetectionTime through multiple independent sensors or adjacent vehicles (cooperative validation).Real-time anomaly detection algorithms to detect unusual timestamp delays. | U49: Cryptographic validation in OBU firmware.Timestamp validation and synchronization mechanisms in RSU backend services.Cooperative V2X systems for cross-verification of event timing. | V49: Ensuring timely and accurate hazard warnings is critical for maintaining safety and effective traffic management. | W49: Integrity, Availability, Non-repudiation. | Y49: =IF(H49=Reference!$A$12, Reference!$C$12, IF(H49=Reference!$A$11, Reference!$C$11, IF(H49=Reference!$A$10, Reference!$C$10, IF(H49=Reference!$A$9, Reference!$C$9, 0)))) -> 7 | Z49: =IF(J49=Reference!$A$20, Reference!$C$20, IF(J49=Reference!$A$19, Reference!$C$19, IF(J49=Reference!$A$18, Reference!$C$18, IF(J49=Reference!$A$17, Reference!$C$17, 0)))) -> 7 | AA49: =IF(L49=Reference!$A$28, Reference!$C$28, IF(L49=Reference!$A$27, Reference!$C$27, IF(L49=Reference!$A$26, Reference!$C$26, IF(L49=Reference!$A$25, Reference!$C$25, 0)))) -> 7 | AB49: =IF(N49=Reference!$A$36, Reference!$C$36, IF(N49=Reference!$A$35, Reference!$C$35, IF(N49=Reference!$A$34, Reference!$C$34, IF(N49=Reference!$A$33, Reference!$C$33, 0)))) -> 4 | AC49: =(Reference!$B$2*Y49 + Reference!$B$3*AA49 + Reference!$B$4*Z49 + Reference!$B$5 * AB49)/4 -> 11.625 | AD49: =IF(Q49=Reference!$C$41, Reference!$D$41, IF(Q49=Reference!$C$42, Reference!$D$42, IF(Q49=Reference!$C$43, Reference!$D$43, IF(Q49=Reference!$C$44, Reference!$D$44, 0)))) -> 10 | AE49: =1 + (AC49 * AD49) -> 117.25
B50: Spoofing | C50: Integrity | D50: An attacker manipulates DetectionTime to falsely indicate events as having just occurred, creating panic or unnecessary urgency, causing hazardous driver behavior such as abrupt braking or dangerous rerouting. | E50: Wireless manipulation through compromised OBU or RSU to inject salse, advanced DetectionTime data. | F50: Network | G50: Intent to cause disruption, panic, or accidents in targeted traffic areas. | H50: Major | I50: Immediate panic reactions or sudden maneuvers can cause collisions and injuries. | J50: Major | K50: High costs from emergency deployments, accidents, liability claims, and brand damage. | L50: Major | M50: Operational chaos from misdirected emergency resources, traffic disruptions, congestion, and delays. | N50: Moderate | O50: Regulatory penalties and warnings possible due to propagation of false safety-critical information. | P50: =IF(AC50>=Reference!$H$2, Reference!$G$2, IF(AC50>=Reference!$H$3, Reference!$G$3, IF(AC50>=Reference!$H$4, Reference!$G$4, IF(AC50>=Reference!$H$5, Reference!$G$5, "")))) -> Severe | Q50: =IF(F50="Physical", "Very Low", IF(F50="Local", "Low", IF(F50="Adjacent", "Medium", IF(F50="Network", "High", "")))) -> High | R50: =IF(AE50>=Reference!$D$2, Reference!$G$2, IF(AE50>=Reference!$D$3, Reference!$E$3, IF(AE50>=Reference!$D$4, Reference!$E$4, IF(AE50>=Reference!$D$5, Reference!$E$5, "")))) -> Severe | S50: Mitigation | T50: Use digital signatures and timestamps verification.Employ advanced real-time anomaly detection to identify and discard implausibly advanced timestamps.Incorporate secure time synchronization protocols (e.g., secure NTP) within ITS infrastructures. | U50: Secure synchronization protocols in OBU and RSU software.Backend anomaly detection and validation algorithms for DetectionTime.Cryptographic message authentication in OBU. | V50: Preventing false alerts that lead to unsafe driving behaviors and operational disruption is crucial for safety and efficiency. | W50: Integrity, Availability, Non-repudiation. | Y50: =IF(H50=Reference!$A$12, Reference!$C$12, IF(H50=Reference!$A$11, Reference!$C$11, IF(H50=Reference!$A$10, Reference!$C$10, IF(H50=Reference!$A$9, Reference!$C$9, 0)))) -> 7 | Z50: =IF(J50=Reference!$A$20, Reference!$C$20, IF(J50=Reference!$A$19, Reference!$C$19, IF(J50=Reference!$A$18, Reference!$C$18, IF(J50=Reference!$A$17, Reference!$C$17, 0)))) -> 7 | AA50: =IF(L50=Reference!$A$28, Reference!$C$28, IF(L50=Reference!$A$27, Reference!$C$27, IF(L50=Reference!$A$26, Reference!$C$26, IF(L50=Reference!$A$25, Reference!$C$25, 0)))) -> 7 | AB50: =IF(N50=Reference!$A$36, Reference!$C$36, IF(N50=Reference!$A$35, Reference!$C$35, IF(N50=Reference!$A$34, Reference!$C$34, IF(N50=Reference!$A$33, Reference!$C$33, 0)))) -> 4 | AC50: =(Reference!$B$2*Y50 + Reference!$B$3*AA50 + Reference!$B$4*Z50 + Reference!$B$5 * AB50)/4 -> 11.625 | AD50: =IF(Q50=Reference!$C$41, Reference!$D$41, IF(Q50=Reference!$C$42, Reference!$D$42, IF(Q50=Reference!$C$43, Reference!$D$43, IF(Q50=Reference!$C$44, Reference!$D$44, 0)))) -> 10 | AE50: =1 + (AC50 * AD50) -> 117.25
A51: DENM Management Container-ValidityDuration (B.55) | B51: Tampering | C51: Integrity | D51: An attacker shortens the ValidityDuration field, causing legitimate safety events to appear as quickly resolved or irrelevant, thus prematurely removing warnings from receiving vehicles. | E51: Attacker gains remote access to OBU or RSU via network vulnerabilities to alter ValidityDuration to an artificially short duration before DENM transmission. | F51: Network | G51: Attacker intends to reduce the effectiveness of V2X safety warnings, potentially leading to unnoticed hazards and traffic incidents. | H51: Major | I51: Vehicles prematurely lose hazard awareness, potentially causing severe collisions and injuries. | J51: Major | K51: Financially significant impacts include liability from resulting accidents, increased insurance costs, and reputational damage for service providers. | L51: Major | M51: Operational disruptions due to incorrect timing of safety alerts, emergency resource misallocation, and increased congestion from accidents. | N51: Moderate | O51: Legislative repercussions from non-compliance in safety-critical notifications. Regulatory attention and fines could result due to compromised safety functionalities. | P51: =IF(AC51>=Reference!$H$2, Reference!$G$2, IF(AC51>=Reference!$H$3, Reference!$G$3, IF(AC51>=Reference!$H$4, Reference!$G$4, IF(AC51>=Reference!$H$5, Reference!$G$5, "")))) -> Severe | Q51: =IF(F51="Physical", "Very Low", IF(F51="Local", "Low", IF(F51="Adjacent", "Medium", IF(F51="Network", "High", "")))) -> High | R51: =IF(AE51>=Reference!$D$2, Reference!$G$2, IF(AE51>=Reference!$D$3, Reference!$E$3, IF(AE51>=Reference!$D$4, Reference!$E$4, IF(AE51>=Reference!$D$5, Reference!$E$5, "")))) -> Severe | S51: Mitigation | T51: Apply cryptographic signatures to validate ValidityDuration field integrity.Implement plausibility checks (cross-reference reported event duration with known hazard types).Real-time anomaly detection in RSU and backend systems to identify abnormal ValidityDuration alterations. | U51: OBU message authentication modules.Backend validation and monitoring systems.RSU software responsible for DENM validation and propagation. | V51: Ensuring accuracy and reliability of ValidityDuration is critical to maintain driver trust in DENM warnings and ensure appropriate reaction to hazards. | W51: Integrity, Availability, Non-repudiation. | Y51: =IF(H51=Reference!$A$12, Reference!$C$12, IF(H51=Reference!$A$11, Reference!$C$11, IF(H51=Reference!$A$10, Reference!$C$10, IF(H51=Reference!$A$9, Reference!$C$9, 0)))) -> 7 | Z51: =IF(J51=Reference!$A$20, Reference!$C$20, IF(J51=Reference!$A$19, Reference!$C$19, IF(J51=Reference!$A$18, Reference!$C$18, IF(J51=Reference!$A$17, Reference!$C$17, 0)))) -> 7 | AA51: =IF(L51=Reference!$A$28, Reference!$C$28, IF(L51=Reference!$A$27, Reference!$C$27, IF(L51=Reference!$A$26, Reference!$C$26, IF(L51=Reference!$A$25, Reference!$C$25, 0)))) -> 7 | AB51: =IF(N51=Reference!$A$36, Reference!$C$36, IF(N51=Reference!$A$35, Reference!$C$35, IF(N51=Reference!$A$34, Reference!$C$34, IF(N51=Reference!$A$33, Reference!$C$33, 0)))) -> 4 | AC51: =(Reference!$B$2*Y51 + Reference!$B$3*AA51 + Reference!$B$4*Z51 + Reference!$B$5 * AB51)/4 -> 11.625 | AD51: =IF(Q51=Reference!$C$41, Reference!$D$41, IF(Q51=Reference!$C$42, Reference!$D$42, IF(Q51=Reference!$C$43, Reference!$D$43, IF(Q51=Reference!$C$44, Reference!$D$44, 0)))) -> 10 | AE51: =1 + (AC51 * AD51) -> 117.25
B52: Spoofing | C52: Integrity | D52: An attacker artificially extends the ValidityDuration, causing obsolete or resolved events to persist as active warnings. This results in unnecessary rerouting or reduced effectiveness of V2X alerts. | E52: Remote compromise of the OBU or RSU via network exploitation to inject manipulated extended ValidityDuration data into DENM before broadcast. | F52: Network | G52: Intended to create traffic disruption, confusion, congestion, or to degrade trust in the V2X alerting system. | H52: Moderate | I52: Persistent false alerts lead to driver frustration or complacency, moderately raising collision risk due to distraction or unnecessary rerouting. | J52: Moderate | K52: Limited direct financial damages; primarily operational inefficiencies, but manageable by organizations involved. | L52: Major | M52: Significant disruption in traffic flow, emergency management inefficiencies, and congestion caused by prolonged erroneous alerts. | N52: Moderate | O52: Minor legislative implications; no significant privacy concerns, as personal data is unaffected. | P52: =IF(AC52>=Reference!$H$2, Reference!$G$2, IF(AC52>=Reference!$H$3, Reference!$G$3, IF(AC52>=Reference!$H$4, Reference!$G$4, IF(AC52>=Reference!$H$5, Reference!$G$5, "")))) -> Major | Q52: =IF(F52="Physical", "Very Low", IF(F52="Local", "Low", IF(F52="Adjacent", "Medium", IF(F52="Network", "High", "")))) -> High | R52: =IF(AE52>=Reference!$D$2, Reference!$G$2, IF(AE52>=Reference!$D$3, Reference!$E$3, IF(AE52>=Reference!$D$4, Reference!$E$4, IF(AE52>=Reference!$D$5, Reference!$E$5, "")))) -> High | S52: Mitigation | T52: Digital signatures and timestamp validation to protect DENM integrity.Plausibility algorithms (comparing standard event durations) to detect extended validity anomalies.RSU/Backend analytics for monitoring and corrective action (removal of outdated DENMs). | U52: OBU cryptographic verification modules.DENM timing management systems at RSU and backend.Anomaly detection and correction algorithms in the central traffic management system. | V52: Preventing the prolongation of obsolete alerts is crucial for maintaining driver trust and traffic operational efficiency. | W52: Integrity, Availability, Non-repudiation. | Y52: =IF(H52=Reference!$A$12, Reference!$C$12, IF(H52=Reference!$A$11, Reference!$C$11, IF(H52=Reference!$A$10, Reference!$C$10, IF(H52=Reference!$A$9, Reference!$C$9, 0)))) -> 4 | Z52: =IF(J52=Reference!$A$20, Reference!$C$20, IF(J52=Reference!$A$19, Reference!$C$19, IF(J52=Reference!$A$18, Reference!$C$18, IF(J52=Reference!$A$17, Reference!$C$17, 0)))) -> 4 | AA52: =IF(L52=Reference!$A$28, Reference!$C$28, IF(L52=Reference!$A$27, Reference!$C$27, IF(L52=Reference!$A$26, Reference!$C$26, IF(L52=Reference!$A$25, Reference!$C$25, 0)))) -> 7 | AB52: =IF(N52=Reference!$A$36, Reference!$C$36, IF(N52=Reference!$A$35, Reference!$C$35, IF(N52=Reference!$A$34, Reference!$C$34, IF(N52=Reference!$A$33, Reference!$C$33, 0)))) -> 4 | AC52: =(Reference!$B$2*Y52 + Reference!$B$3*AA52 + Reference!$B$4*Z52 + Reference!$B$5 * AB52)/4 -> 7.5 | AD52: =IF(Q52=Reference!$C$41, Reference!$D$41, IF(Q52=Reference!$C$42, Reference!$D$42, IF(Q52=Reference!$C$43, Reference!$D$43, IF(Q52=Reference!$C$44, Reference!$D$44, 0)))) -> 10 | AE52: =1 + (AC52 * AD52) -> 76
A53: DENM Location Container - Traces Subcontainer | B53: Tampering | C53: Integrity | D53: An attacker injects fabricated waypoint data, leading vehicles to perceive incorrect routing paths or to misinterpret the event location, causing traffic disruption. | E53: Attacker gains unauthorized access to the OBU or RSU, manipulating the Traces data within the DENM before transmission. | F53: Network | G53: The attacker seeks to cause traffic confusion or rerouting, either to create congestion, panic, or delay critical responses such as emergency vehicles. | H53: Major | I53: Misguided vehicles may cause accidents or unsafe driving behavior due to incorrect navigation or abrupt rerouting. | J53: Major | K53: Substantial financial losses due to increased fuel consumption, potential accident liability, and reputation loss from incidents. | L53: Major | M53: Significant disruption of traffic flows, leading to widespread congestion and delayed emergency response. | N53: Negligible | O53: No direct privacy violation from manipulation of waypoint data. | P53: =IF(AC53>=Reference!$H$2, Reference!$G$2, IF(AC53>=Reference!$H$3, Reference!$G$3, IF(AC53>=Reference!$H$4, Reference!$G$4, IF(AC53>=Reference!$H$5, Reference!$G$5, "")))) -> Severe | Q53: =IF(F53="Physical", "Very Low", IF(F53="Local", "Low", IF(F53="Adjacent", "Medium", IF(F53="Network", "High", "")))) -> High | R53: =IF(AE53>=Reference!$D$2, Reference!$G$2, IF(AE53>=Reference!$D$3, Reference!$E$3, IF(AE53>=Reference!$D$4, Reference!$E$4, IF(AE53>=Reference!$D$5, Reference!$E$5, "")))) -> Severe | S53: Mitigation | T53: Cryptographic validation (digital signatures) for waypoint authenticity,Real-time anomaly detection to verify the consistency of the provided waypoints,Cross-validation by multiple RSUs and OBUs. | U53: OBU/RSU firmware handling Traces data,DENM validation and integrity-check mechanisms. | V53: The integrity of navigation data is critical to prevent accidents, maintain public trust in automated routing systems, and ensure rapid emergency response. | W53: Maintain integrity, availability, and authenticity of location referencing information. | Y53: =IF(H53=Reference!$A$12, Reference!$C$12, IF(H53=Reference!$A$11, Reference!$C$11, IF(H53=Reference!$A$10, Reference!$C$10, IF(H53=Reference!$A$9, Reference!$C$9, 0)))) -> 7 | Z53: =IF(J53=Reference!$A$20, Reference!$C$20, IF(J53=Reference!$A$19, Reference!$C$19, IF(J53=Reference!$A$18, Reference!$C$18, IF(J53=Reference!$A$17, Reference!$C$17, 0)))) -> 7 | AA53: =IF(L53=Reference!$A$28, Reference!$C$28, IF(L53=Reference!$A$27, Reference!$C$27, IF(L53=Reference!$A$26, Reference!$C$26, IF(L53=Reference!$A$25, Reference!$C$25, 0)))) -> 7 | AB53: =IF(N53=Reference!$A$36, Reference!$C$36, IF(N53=Reference!$A$35, Reference!$C$35, IF(N53=Reference!$A$34, Reference!$C$34, IF(N53=Reference!$A$33, Reference!$C$33, 0)))) -> 1 | AC53: =(Reference!$B$2*Y53 + Reference!$B$3*AA53 + Reference!$B$4*Z53 + Reference!$B$5 * AB53)/4 -> 11.4375 | AD53: =IF(Q53=Reference!$C$41, Reference!$D$41, IF(Q53=Reference!$C$42, Reference!$D$42, IF(Q53=Reference!$C$43, Reference!$D$43, IF(Q53=Reference!$C$44, Reference!$D$44, 0)))) -> 10 | AE53: =1 + (AC53 * AD53) -> 115.375
B54: Tampering | C54: Integrity | D54: An attacker modifies legitimate waypoint data in the Traces subcontainer to slightly shift or distort the actual route towards hazardous or congested areas. | E54: Network-based manipulation via compromised RSU or OBU software/firmware to alter legitimate data. | F54: Network | G54: The attacker aims to indirectly cause congestion, confusion, or minor accidents by subtly misguiding vehicles without raising immediate suspicion. | H54: Moderate | I54: Subtle shifts in routes might increase risk of minor collisions or driver confusion but not immediate severe threats. | J54: Moderate | K54: Substantial indirect financial costs through increased operational costs, minor accidents, and reduced operational efficiency. | L54: Major | M54: Persistent traffic congestion, confusion, and slower emergency responses due to suboptimal routing. | N54: Negligible | O54: No privacy concerns directly involved from route manipulation. | P54: =IF(AC54>=Reference!$H$2, Reference!$G$2, IF(AC54>=Reference!$H$3, Reference!$G$3, IF(AC54>=Reference!$H$4, Reference!$G$4, IF(AC54>=Reference!$H$5, Reference!$G$5, "")))) -> Major | Q54: =IF(F54="Physical", "Very Low", IF(F54="Local", "Low", IF(F54="Adjacent", "Medium", IF(F54="Network", "High", "")))) -> High | R54: =IF(AE54>=Reference!$D$2, Reference!$G$2, IF(AE54>=Reference!$D$3, Reference!$E$3, IF(AE54>=Reference!$D$4, Reference!$E$4, IF(AE54>=Reference!$D$5, Reference!$E$5, "")))) -> High | S54: Mitigation | T54: Enhanced cryptographic checks and frequent authenticity verification of waypoint data, Implementation of geofencing and anomaly detection to flag suspicious changes in routing data. | U54: Waypoint handling logic in OBUs and RSUs,DENM verification and routing algorithms. | V54: Ensuring reliable route data is essential to maintain efficient traffic management, safety, and emergency response. | W54: Preserve integrity and availability of accurate navigation data. | Y54: =IF(H54=Reference!$A$12, Reference!$C$12, IF(H54=Reference!$A$11, Reference!$C$11, IF(H54=Reference!$A$10, Reference!$C$10, IF(H54=Reference!$A$9, Reference!$C$9, 0)))) -> 4 | Z54: =IF(J54=Reference!$A$20, Reference!$C$20, IF(J54=Reference!$A$19, Reference!$C$19, IF(J54=Reference!$A$18, Reference!$C$18, IF(J54=Reference!$A$17, Reference!$C$17, 0)))) -> 4 | AA54: =IF(L54=Reference!$A$28, Reference!$C$28, IF(L54=Reference!$A$27, Reference!$C$27, IF(L54=Reference!$A$26, Reference!$C$26, IF(L54=Reference!$A$25, Reference!$C$25, 0)))) -> 7 | AB54: =IF(N54=Reference!$A$36, Reference!$C$36, IF(N54=Reference!$A$35, Reference!$C$35, IF(N54=Reference!$A$34, Reference!$C$34, IF(N54=Reference!$A$33, Reference!$C$33, 0)))) -> 1 | AC54: =(Reference!$B$2*Y54 + Reference!$B$3*AA54 + Reference!$B$4*Z54 + Reference!$B$5 * AB54)/4 -> 7.3125 | AD54: =IF(Q54=Reference!$C$41, Reference!$D$41, IF(Q54=Reference!$C$42, Reference!$D$42, IF(Q54=Reference!$C$43, Reference!$D$43, IF(Q54=Reference!$C$44, Reference!$D$44, 0)))) -> 10 | AE54: =1 + (AC54 * AD54) -> 74.125
A55: DENM Location Container - eventSpeed | B55: Tampering | C55: Integrity | D55: An attacker artificially increases the speed value reported in the eventSpeed field, making the detected event appear as a high-speed hazard, causing nearby vehicles to react unnecessarily or dangerously (e.g., sudden braking or evasive maneuvers). | E55: Network-level compromise or unauthorized access to OBU/RSU data processing units, manipulating eventSpeed values. | F55: Network | G55: The attacker aims to create panic or disruptive traffic conditions, possibly as a precursor to another attack or to divert emergency services unnecessarily. | H55: Major | I55: Sudden vehicle maneuvers (e.g., braking or evasive actions) could lead to collisions or hazardous driving conditions. | J55: Major | K55: Financial repercussions include potential insurance claims, accident liabilities, operational disruptions, and reputational damage. | L55: Major | M55: Severe traffic disruptions and emergency-response delays due to exaggerated threat perception. | N55: Negligible | O55: No direct privacy issues from speed manipulation alone. | P55: =IF(AC55>=Reference!$H$2, Reference!$G$2, IF(AC55>=Reference!$H$3, Reference!$G$3, IF(AC55>=Reference!$H$4, Reference!$G$4, IF(AC55>=Reference!$H$5, Reference!$G$5, "")))) -> Severe | Q55: =IF(F55="Physical", "Very Low", IF(F55="Local", "Low", IF(F55="Adjacent", "Medium", IF(F55="Network", "High", "")))) -> High | R55: =IF(AE55>=Reference!$D$2, Reference!$G$2, IF(AE55>=Reference!$D$3, Reference!$E$3, IF(AE55>=Reference!$D$4, Reference!$E$4, IF(AE55>=Reference!$D$5, Reference!$E$5, "")))) -> Severe | S55: Mitigation | T55: Cryptographic digital signatures ensuring data integrity for reported speeds,Real-time anomaly detection comparing reported speeds to realistic vehicle behaviors and event contexts,Cross-verification by neighboring RSUs or vehicles to validate eventSpeed data accuracy. | U55: RSU and OBU firmware handling DENM speed data,Event-speed validation logic and anomaly detection systems. | V55: Reliable event-speed data is essential to maintain safe traffic flow, prevent accidents, and ensure efficient emergency responses. | W55: Ensure data integrity, reliability, and non-repudiation. | Y55: =IF(H55=Reference!$A$12, Reference!$C$12, IF(H55=Reference!$A$11, Reference!$C$11, IF(H55=Reference!$A$10, Reference!$C$10, IF(H55=Reference!$A$9, Reference!$C$9, 0)))) -> 7 | Z55: =IF(J55=Reference!$A$20, Reference!$C$20, IF(J55=Reference!$A$19, Reference!$C$19, IF(J55=Reference!$A$18, Reference!$C$18, IF(J55=Reference!$A$17, Reference!$C$17, 0)))) -> 7 | AA55: =IF(L55=Reference!$A$28, Reference!$C$28, IF(L55=Reference!$A$27, Reference!$C$27, IF(L55=Reference!$A$26, Reference!$C$26, IF(L55=Reference!$A$25, Reference!$C$25, 0)))) -> 7 | AB55: =IF(N55=Reference!$A$36, Reference!$C$36, IF(N55=Reference!$A$35, Reference!$C$35, IF(N55=Reference!$A$34, Reference!$C$34, IF(N55=Reference!$A$33, Reference!$C$33, 0)))) -> 1 | AC55: =(Reference!$B$2*Y55 + Reference!$B$3*AA55 + Reference!$B$4*Z55 + Reference!$B$5 * AB55)/4 -> 11.4375 | AD55: =IF(Q55=Reference!$C$41, Reference!$D$41, IF(Q55=Reference!$C$42, Reference!$D$42, IF(Q55=Reference!$C$43, Reference!$D$43, IF(Q55=Reference!$C$44, Reference!$D$44, 0)))) -> 10 | AE55: =1 + (AC55 * AD55) -> 115.375
B56: Tampering | C56: Integrity | D56: An attacker sets eventSpeed values near zero, falsely indicating that a hazard or event is stationary or moving slowly, causing approaching vehicles to underestimate the risk and possibly collide with high-speed hazards. | E56: Unauthorized data injection or modification via compromised RSUs or OBUs. | F56: Network | G56: The attacker intends to cause dangerous vehicle behavior by manipulating hazard perception, creating a scenario where drivers fail to respond adequately to fast-moving obstacles or hazards. | H56: Severe | I56: High likelihood of severe accidents due to underestimation of hazard speed, causing drivers to react inadequately. | J56: Severe | K56: Substantial financial consequences through potential vehicle accidents, legal liabilities, recalls, and loss of brand trust. | L56: Severe | M56: Traffic delays and severe disruptions resulting from accidents and emergency-response complexities. | N56: Negligible | O56: No direct privacy issues involved from speed data manipulation. | P56: =IF(AC56>=Reference!$H$2, Reference!$G$2, IF(AC56>=Reference!$H$3, Reference!$G$3, IF(AC56>=Reference!$H$4, Reference!$G$4, IF(AC56>=Reference!$H$5, Reference!$G$5, "")))) -> Severe | Q56: =IF(F56="Physical", "Very Low", IF(F56="Local", "Low", IF(F56="Adjacent", "Medium", IF(F56="Network", "High", "")))) -> High | R56: =IF(AE56>=Reference!$D$2, Reference!$G$2, IF(AE56>=Reference!$D$3, Reference!$E$3, IF(AE56>=Reference!$D$4, Reference!$E$4, IF(AE56>=Reference!$D$5, Reference!$E$5, "")))) -> Severe | S56: Mitigation | T56: Strong authentication and integrity checks on data transmissions to prevent unauthorized manipulation,Cross-referencing eventSpeed values with contextual data such as eventPosition, nearby vehicles' speed, and historical data patterns,Implementation of anomaly detection and fail-safe mechanisms alerting drivers of uncertain or suspicious information. | U56: Speed verification algorithms in OBUs and RSUs,Event validation processes and alert mechanisms within DENM systems. | V56: Ensuring accuracy of speed reporting prevents severe safety risks, accidents, and significant financial and operational impacts. | W56: Maintain data integrity, safety, and operational reliability. | Y56: =IF(H56=Reference!$A$12, Reference!$C$12, IF(H56=Reference!$A$11, Reference!$C$11, IF(H56=Reference!$A$10, Reference!$C$10, IF(H56=Reference!$A$9, Reference!$C$9, 0)))) -> 10 | Z56: =IF(J56=Reference!$A$20, Reference!$C$20, IF(J56=Reference!$A$19, Reference!$C$19, IF(J56=Reference!$A$18, Reference!$C$18, IF(J56=Reference!$A$17, Reference!$C$17, 0)))) -> 10 | AA56: =IF(L56=Reference!$A$28, Reference!$C$28, IF(L56=Reference!$A$27, Reference!$C$27, IF(L56=Reference!$A$26, Reference!$C$26, IF(L56=Reference!$A$25, Reference!$C$25, 0)))) -> 10 | AB56: =IF(N56=Reference!$A$36, Reference!$C$36, IF(N56=Reference!$A$35, Reference!$C$35, IF(N56=Reference!$A$34, Reference!$C$34, IF(N56=Reference!$A$33, Reference!$C$33, 0)))) -> 1 | AC56: =(Reference!$B$2*Y56 + Reference!$B$3*AA56 + Reference!$B$4*Z56 + Reference!$B$5 * AB56)/4 -> 16.3125 | AD56: =IF(Q56=Reference!$C$41, Reference!$D$41, IF(Q56=Reference!$C$42, Reference!$D$42, IF(Q56=Reference!$C$43, Reference!$D$43, IF(Q56=Reference!$C$44, Reference!$D$44, 0)))) -> 10 | AE56: =1 + (AC56 * AD56) -> 164.125
B57: Tampering | C57: Integrity | D57: The attacker subtly manipulates eventSpeed data, indicating slightly higher speeds than reality in urban areas, potentially causing vehicles to accelerate unnecessarily or inadequately perceive risk levels (e.g., near pedestrian crossings). | E57: Leveraging minor security gaps in network communication or data validation systems within the ITS infrastructure. | F57: Network | G57: The attacker’s goal is to subtly degrade system reliability, potentially causing minor incidents or reducing driver trust in ITS data. | H57: Moderate | I57: Incrementally higher risk of minor accidents or pedestrian-related incidents due to misjudged approach speeds. | J57: Moderate | K57: Limited financial consequences primarily involving minor accidents, moderate liability risks, and potential minor reputation costs. | L57: Moderate | M57: Occasional confusion or minor disruptions in urban traffic, impacting driving efficiency and slightly reducing overall traffic flow. | N57: Negligible | O57: No meaningful privacy impact from minor eventSpeed discrepancies. | P57: =IF(AC57>=Reference!$H$2, Reference!$G$2, IF(AC57>=Reference!$H$3, Reference!$G$3, IF(AC57>=Reference!$H$4, Reference!$G$4, IF(AC57>=Reference!$H$5, Reference!$G$5, "")))) -> Major | Q57: =IF(F57="Physical", "Very Low", IF(F57="Local", "Low", IF(F57="Adjacent", "Medium", IF(F57="Network", "High", "")))) -> High | R57: =IF(AE57>=Reference!$D$2, Reference!$G$2, IF(AE57>=Reference!$D$3, Reference!$E$3, IF(AE57>=Reference!$D$4, Reference!$E$4, IF(AE57>=Reference!$D$5, Reference!$E$5, "")))) -> High | S57: Acceptance | T57: mproved validation mechanisms using onboard sensors and periodic cross-checks with roadside infrastructure,Real-time anomaly detection tuned to identify subtle, consistent discrepancies,Periodic security audits and software updates targeting known vulnerabilities. | U57: Traffic management algorithms and onboard driver-assistance calibration,Infrastructure-to-vehicle communication validation protocols. | V57: Maintaining accuracy of eventSpeed information is important to retain driver confidence and ensure minor issues do not cumulatively lead to more significant problems. | W57: Enhance the integrity, reliability, and effectiveness of speed-related information to support safe vehicle operation and traffic flow. | Y57: =IF(H57=Reference!$A$12, Reference!$C$12, IF(H57=Reference!$A$11, Reference!$C$11, IF(H57=Reference!$A$10, Reference!$C$10, IF(H57=Reference!$A$9, Reference!$C$9, 0)))) -> 4 | Z57: =IF(J57=Reference!$A$20, Reference!$C$20, IF(J57=Reference!$A$19, Reference!$C$19, IF(J57=Reference!$A$18, Reference!$C$18, IF(J57=Reference!$A$17, Reference!$C$17, 0)))) -> 4 | AA57: =IF(L57=Reference!$A$28, Reference!$C$28, IF(L57=Reference!$A$27, Reference!$C$27, IF(L57=Reference!$A$26, Reference!$C$26, IF(L57=Reference!$A$25, Reference!$C$25, 0)))) -> 4 | AB57: =IF(N57=Reference!$A$36, Reference!$C$36, IF(N57=Reference!$A$35, Reference!$C$35, IF(N57=Reference!$A$34, Reference!$C$34, IF(N57=Reference!$A$33, Reference!$C$33, 0)))) -> 1 | AC57: =(Reference!$B$2*Y57 + Reference!$B$3*AA57 + Reference!$B$4*Z57 + Reference!$B$5 * AB57)/4 -> 6.5625 | AD57: =IF(Q57=Reference!$C$41, Reference!$D$41, IF(Q57=Reference!$C$42, Reference!$D$42, IF(Q57=Reference!$C$43, Reference!$D$43, IF(Q57=Reference!$C$44, Reference!$D$44, 0)))) -> 10 | AE57: =1 + (AC57 * AD57) -> 66.625
A58: DENM Location Container – eventPositionHeading | B58: Tampering | C58: Integrity | D58: The attacker significantly alters the heading direction reported in the eventPositionHeading, causing vehicles to misinterpret the actual direction of the hazard, leading to unsafe maneuvers such as incorrect lane changes or inappropriate braking. | E58: Network-level unauthorized access or compromise of OBU or RSU data handling event heading information. | F58: Network | G58: Attacker seeks to cause hazardous traffic scenarios, disruption, or confusion among drivers, possibly to create opportunities for further attacks or criminal activities. | H58: Major | I58: Significant risk of collisions or accidents caused by vehicles making incorrect maneuvers based on false heading data. | J58: Major | K58: Accidents, insurance liabilities, legal claims, reputation damages, and potential recall or compliance costs. | L58: Major | M58: Traffic disruptions and delays from accidents and incorrect hazard avoidance actions. | N58: Moderate | O58: No direct privacy issues due to heading manipulation. | P58: =IF(AC58>=Reference!$H$2, Reference!$G$2, IF(AC58>=Reference!$H$3, Reference!$G$3, IF(AC58>=Reference!$H$4, Reference!$G$4, IF(AC58>=Reference!$H$5, Reference!$G$5, "")))) -> Severe | Q58: =IF(F58="Physical", "Very Low", IF(F58="Local", "Low", IF(F58="Adjacent", "Medium", IF(F58="Network", "High", "")))) -> High | R58: =IF(AE58>=Reference!$D$2, Reference!$G$2, IF(AE58>=Reference!$D$3, Reference!$E$3, IF(AE58>=Reference!$D$4, Reference!$E$4, IF(AE58>=Reference!$D$5, Reference!$E$5, "")))) -> Severe | S58: Mitigation | T58: Utilize cryptographic digital signatures to secure transmitted heading data.Implement real-time validation by correlating event heading data with position, speed, and environmental context.Cross-validation of event heading through cooperative perception among multiple ITS stations or vehicles. | U58: Integrity checking algorithms in OBU firmware and RSU applications handling event position heading.Real-time data fusion and anomaly detection systems. | V58: Accurate directional information is critical for effective hazard avoidance, road safety, and smooth traffic operations. | W58: Integrity, availability, and non-repudiation of transmitted heading data. | Y58: =IF(H58=Reference!$A$12, Reference!$C$12, IF(H58=Reference!$A$11, Reference!$C$11, IF(H58=Reference!$A$10, Reference!$C$10, IF(H58=Reference!$A$9, Reference!$C$9, 0)))) -> 7 | Z58: =IF(J58=Reference!$A$20, Reference!$C$20, IF(J58=Reference!$A$19, Reference!$C$19, IF(J58=Reference!$A$18, Reference!$C$18, IF(J58=Reference!$A$17, Reference!$C$17, 0)))) -> 7 | AA58: =IF(L58=Reference!$A$28, Reference!$C$28, IF(L58=Reference!$A$27, Reference!$C$27, IF(L58=Reference!$A$26, Reference!$C$26, IF(L58=Reference!$A$25, Reference!$C$25, 0)))) -> 7 | AB58: =IF(N58=Reference!$A$36, Reference!$C$36, IF(N58=Reference!$A$35, Reference!$C$35, IF(N58=Reference!$A$34, Reference!$C$34, IF(N58=Reference!$A$33, Reference!$C$33, 0)))) -> 4 | AC58: =(Reference!$B$2*Y58 + Reference!$B$3*AA58 + Reference!$B$4*Z58 + Reference!$B$5 * AB58)/4 -> 11.625 | AD58: =IF(Q58=Reference!$C$41, Reference!$D$41, IF(Q58=Reference!$C$42, Reference!$D$42, IF(Q58=Reference!$C$43, Reference!$D$43, IF(Q58=Reference!$C$44, Reference!$D$44, 0)))) -> 10 | AE58: =1 + (AC58 * AD58) -> 117.25
B59: Tampering | C59: Integrity | D59: The attacker subtly modifies the heading information in the eventPositionHeading field, causing vehicles to gradually deviate from their proper paths, resulting in confusion, reduced driver trust in the system, or unnecessary route recalculations. | E59: Unauthorized access or compromise of event-position data within OBU or RSU through network vulnerabilities. | F59: Network | G59: Attacker intends to undermine driver confidence in ITS functionalities or induce subtle traffic disturbances for extended periods, complicating detection. | H59: Moderate | I59: Gradual confusion and minor maneuvers pose a moderate risk of incidents | J59: Moderate | K59: Manageable financial impact involving minimal liability, limited reputational damage, and modest corrective costs. | L59: Moderate | M59: Occasional route miscalculations and disruptions, manageable by traffic systems but with some degradation in efficiency. | N59: Negligible | O59: No direct privacy concerns due to minor heading adjustments. | P59: =IF(AC59>=Reference!$H$2, Reference!$G$2, IF(AC59>=Reference!$H$3, Reference!$G$3, IF(AC59>=Reference!$H$4, Reference!$G$4, IF(AC59>=Reference!$H$5, Reference!$G$5, "")))) -> Major | Q59: =IF(F59="Physical", "Very Low", IF(F59="Local", "Low", IF(F59="Adjacent", "Medium", IF(F59="Network", "High", "")))) -> High | R59: =IF(AE59>=Reference!$D$2, Reference!$G$2, IF(AE59>=Reference!$D$3, Reference!$E$3, IF(AE59>=Reference!$D$4, Reference!$E$4, IF(AE59>=Reference!$D$5, Reference!$E$5, "")))) -> High | S59: Mitigation | T59: Enhanced precision checks for transmitted heading values within strict tolerances,Regular software updates and firmware patches to prevent network-level vulnerabilities exploitation,Introduction of confidence scoring for heading data, ensuring drivers and automated systems are aware of uncertain or potentially compromised data. | U59: Heading verification algorithms in OBU and RSU,Data confidence indicators and alerting logic in ITS applications. | V59: Ensuring correct event heading data maintains driver trust, optimizes traffic flow, and prevents cumulative safety risks. | W59: Ensure high integrity, availability, and operational trustworthiness of the system. | Y59: =IF(H59=Reference!$A$12, Reference!$C$12, IF(H59=Reference!$A$11, Reference!$C$11, IF(H59=Reference!$A$10, Reference!$C$10, IF(H59=Reference!$A$9, Reference!$C$9, 0)))) -> 4 | Z59: =IF(J59=Reference!$A$20, Reference!$C$20, IF(J59=Reference!$A$19, Reference!$C$19, IF(J59=Reference!$A$18, Reference!$C$18, IF(J59=Reference!$A$17, Reference!$C$17, 0)))) -> 4 | AA59: =IF(L59=Reference!$A$28, Reference!$C$28, IF(L59=Reference!$A$27, Reference!$C$27, IF(L59=Reference!$A$26, Reference!$C$26, IF(L59=Reference!$A$25, Reference!$C$25, 0)))) -> 4 | AB59: =IF(N59=Reference!$A$36, Reference!$C$36, IF(N59=Reference!$A$35, Reference!$C$35, IF(N59=Reference!$A$34, Reference!$C$34, IF(N59=Reference!$A$33, Reference!$C$33, 0)))) -> 1 | AC59: =(Reference!$B$2*Y59 + Reference!$B$3*AA59 + Reference!$B$4*Z59 + Reference!$B$5 * AB59)/4 -> 6.5625 | AD59: =IF(Q59=Reference!$C$41, Reference!$D$41, IF(Q59=Reference!$C$42, Reference!$D$42, IF(Q59=Reference!$C$43, Reference!$D$43, IF(Q59=Reference!$C$44, Reference!$D$44, 0)))) -> 10 | AE59: =1 + (AC59 * AD59) -> 66.625
A60: DENM Location Container – roadType | B60: Tampering | C60: Integrity | D60: The attacker alters the roadType field to misrepresent an urban street as a highway or vice versa, causing vehicles to adopt inappropriate speeds or driving behaviors that do not match the actual environment. | E60: Unauthorized access through network vulnerabilities within OBU or RSU handling the DENM road type data. | F60: Network | G60: Attacker aims to create confusion, safety hazards, or traffic congestion by causing inappropriate driving responses (e.g., excessive speeding or unexpected braking). | H60: Major | I60: Incorrect road type indication may prompt vehicles to adopt speeds or maneuvers unsuited to the actual road conditions, potentially causing severe accidents. | J60: Major | K60: Costs associated with potential accidents, increased liability, insurance claims, regulatory fines, and reputational damages. | L60: Severe | M60: Significant disruption to traffic flow, congestion, and delays due to accidents or inappropriate vehicle speeds. | N60: Moderate | O60: No direct impact on privacy from manipulation of road type information. | P60: =IF(AC60>=Reference!$H$2, Reference!$G$2, IF(AC60>=Reference!$H$3, Reference!$G$3, IF(AC60>=Reference!$H$4, Reference!$G$4, IF(AC60>=Reference!$H$5, Reference!$G$5, "")))) -> Severe | Q60: =IF(F60="Physical", "Very Low", IF(F60="Local", "Low", IF(F60="Adjacent", "Medium", IF(F60="Network", "High", "")))) -> High | R60: =IF(AE60>=Reference!$D$2, Reference!$G$2, IF(AE60>=Reference!$D$3, Reference!$E$3, IF(AE60>=Reference!$D$4, Reference!$E$4, IF(AE60>=Reference!$D$5, Reference!$E$5, "")))) -> Severe | S60: Mitigation | T60: Secure data transmission with cryptographic signatures to ensure integrity of the road type field,Real-time cross-validation with onboard sensors or infrastructure maps to detect inconsistencies,Deploy anomaly detection mechanisms to identify unusual or suspicious road type reporting. | U60: Road type classification and verification algorithms,Firmware integrity and data validation processes within OBUs and RSUs,Advanced driver-assistance systems (ADAS) calibration and response logic. | V60: Correct road type identification is crucial to maintaining appropriate driving behavior, safety, and efficient traffic flow. | W60: Ensure integrity, availability, and reliability of critical road-type information. | Y60: =IF(H60=Reference!$A$12, Reference!$C$12, IF(H60=Reference!$A$11, Reference!$C$11, IF(H60=Reference!$A$10, Reference!$C$10, IF(H60=Reference!$A$9, Reference!$C$9, 0)))) -> 7 | Z60: =IF(J60=Reference!$A$20, Reference!$C$20, IF(J60=Reference!$A$19, Reference!$C$19, IF(J60=Reference!$A$18, Reference!$C$18, IF(J60=Reference!$A$17, Reference!$C$17, 0)))) -> 7 | AA60: =IF(L60=Reference!$A$28, Reference!$C$28, IF(L60=Reference!$A$27, Reference!$C$27, IF(L60=Reference!$A$26, Reference!$C$26, IF(L60=Reference!$A$25, Reference!$C$25, 0)))) -> 10 | AB60: =IF(N60=Reference!$A$36, Reference!$C$36, IF(N60=Reference!$A$35, Reference!$C$35, IF(N60=Reference!$A$34, Reference!$C$34, IF(N60=Reference!$A$33, Reference!$C$33, 0)))) -> 4 | AC60: =(Reference!$B$2*Y60 + Reference!$B$3*AA60 + Reference!$B$4*Z60 + Reference!$B$5 * AB60)/4 -> 12.375 | AD60: =IF(Q60=Reference!$C$41, Reference!$D$41, IF(Q60=Reference!$C$42, Reference!$D$42, IF(Q60=Reference!$C$43, Reference!$D$43, IF(Q60=Reference!$C$44, Reference!$D$44, 0)))) -> 10 | AE60: =1 + (AC60 * AD60) -> 124.75
