Workbook

Sheet TARA strict intersection
A1: Asset | B1: Threat type | C1: Security Attribute | D1: Damage Scenario | E1: Attack Path | F1: Attack vector | G1: Attack Vector Note / Motiv | H1: Safety Impact | I1: Safety Note / Motiv | J1: Financial Impact | K1: Financial Note / Motiv | L1: Operational Impact | M1: Operational Note / Motiv | N1: Privacy and Legislative Impact | O1: Privacy Note / Motiv | P1: Severity Level | Q1: Feasibility Level | R1: Risk Value | S1: Treatment Options | T1: Measures | U1: Affected Design Elements | V1: Justification (Treatment) | W1: Cybersecurity Goals | X1: Medini threat ID | Y1: s | Z1: f | AA1: o | AB1: p | AC1: impact | AD1: feasibility val | AE1: Risk score | AF1: Theme, agreement and source
A2: 1. Cameras (mono + stereo) | B2: Spoofing | C2: Authenticity | D2: Fabricated or replayed images reach the detection pipeline, either through a forged stream injected on the camera link or through a rogue camera node, so the system perceives an accident that does not exist or fails to see a real one. | E2: The attacker reaches the camera link on the roadside network, for example through the camera management interface or a network tap, and replaces the stream sent to the computing unit. | F2: Adjacent | G2: The camera stream travels on the roadside network segment; the attacker needs a foothold there, not physical access to the optics. | H2: Major | I2: A fabricated accident triggers unnecessary emergency braking; a suppressed real accident removes the warning that should prevent a secondary collision (S2). | J2: Moderate | K2: Investigation and remediation costs; liability only if a collision follows. | L2: Major | M2: The perception input of the whole chain is untrusted, so every warning from this station must be questioned. | N2: Negligible | O2: The injected stream itself contains no personal data of real road users. | P2: =IF(AC2>=Reference!$H$2, Reference!$G$2, IF(AC2>=Reference!$H$3, Reference!$G$3, IF(AC2>=Reference!$H$4, Reference!$G$4, IF(AC2>=Reference!$H$5, Reference!$G$5, "")))) -> Severe | Q2: =IF(F2="Physical", "Very Low", IF(F2="Local", "Low", IF(F2="Adjacent", "Medium", IF(F2="Network", "High", "")))) -> Medium | R2: =IF(AE2>=Reference!$D$2, Reference!$E$2, IF(AE2>=Reference!$D$3, Reference!$E$3, IF(AE2>=Reference!$D$4, Reference!$E$4, IF(AE2>=Reference!$D$5, Reference!$E$5, "")))) -> High | S2: Mitigation | T2: Authenticate and encrypt the camera stream (for example RTSP over TLS with client certificates), segment the camera VLAN, monitor stream continuity and timestamps, detect frozen or repeated frames. | U2: Cameras, roadside network, computing unit input stage (Steps 1-2). | V2: The detection chain trusts its sensor input implicitly; without stream authentication every downstream control can be bypassed at the source. | W2: Authenticity, Integrity. | X2: T004 | Y2: =IF(H2=Reference!$A$12, Reference!$C$12, IF(H2=Reference!$A$11, Reference!$C$11, IF(H2=Reference!$A$10, Reference!$C$10, IF(H2=Reference!$A$9, Reference!$C$9, 0)))) -> 7 | Z2: =IF(J2=Reference!$A$20, Reference!$C$20, IF(J2=Reference!$A$19, Reference!$C$19, IF(J2=Reference!$A$18, Reference!$C$18, IF(J2=Reference!$A$17, Reference!$C$17, 0)))) -> 4 | AA2: =IF(L2=Reference!$A$28, Reference!$C$28, IF(L2=Reference!$A$27, Reference!$C$27, IF(L2=Reference!$A$26, Reference!$C$26, IF(L2=Reference!$A$25, Reference!$C$25, 0)))) -> 7 | AB2: =IF(N2=Reference!$A$36, Reference!$C$36, IF(N2=Reference!$A$35, Reference!$C$35, IF(N2=Reference!$A$34, Reference!$C$34, IF(N2=Reference!$A$33, Reference!$C$33, 0)))) -> 1 | AC2: =(Reference!$B$2*Y2 + Reference!$B$3*AA2 + Reference!$B$4*Z2 + Reference!$B$5 * AB2)/4 -> 11.0625 | AD2: =IF(Q2=Reference!$C$41, Reference!$D$41, IF(Q2=Reference!$C$42, Reference!$D$42, IF(Q2=Reference!$C$43, Reference!$D$43, IF(Q2=Reference!$C$44, Reference!$D$44, 0)))) -> 7 | AE2: =1 + (AC2 * AD2) -> 78.4375 | AF2: Raised by all six model outputs; medini T004 (Mono + Stereo | Spoofing); copied from row 9 of the full analysis
A3: 1. Cameras (mono + stereo) | B3: Tampering | C3: Integrity | D3: The camera is re-aimed, or its stored position and orientation are changed, so the event location computed for the DENM no longer matches reality and warnings are sent for the wrong road section. | E3: Physical access to the pole, or modification of the camera configuration stored on the computing unit. | F3: Physical | G3: Turning the camera requires presence at the installation; the configuration variant would be Adjacent. | H3: Major | I3: Drivers are warned about a hazard at a place where there is none, and the real hazard stays unannounced (S2). | J3: Moderate | K3: Site visit, recalibration and investigation. | L3: Major | M3: Every warning from this station points at the wrong location until the pose is restored. | N3: Negligible | O3: No personal data is affected. | P3: =IF(AC3>=Reference!$H$2, Reference!$G$2, IF(AC3>=Reference!$H$3, Reference!$G$3, IF(AC3>=Reference!$H$4, Reference!$G$4, IF(AC3>=Reference!$H$5, Reference!$G$5, "")))) -> Severe | Q3: =IF(F3="Physical", "Very Low", IF(F3="Local", "Low", IF(F3="Adjacent", "Medium", IF(F3="Network", "High", "")))) -> Very Low | R3: =IF(AE3>=Reference!$D$2, Reference!$E$2, IF(AE3>=Reference!$D$3, Reference!$E$3, IF(AE3>=Reference!$D$4, Reference!$E$4, IF(AE3>=Reference!$D$5, Reference!$E$5, "")))) -> Low | S3: Mitigation | T3: Tamper-resistant mounting, automatic detection of view changes against a reference image, signed and monitored calibration data, alarm to the operator on deviation. | U3: Camera mounting, calibration data on the computing unit, monitoring. | V3: Cheap for an attacker and easy to miss, because the system keeps producing plausible messages. | W3: Integrity, Authenticity. | X3: T002 | Y3: =IF(H3=Reference!$A$12, Reference!$C$12, IF(H3=Reference!$A$11, Reference!$C$11, IF(H3=Reference!$A$10, Reference!$C$10, IF(H3=Reference!$A$9, Reference!$C$9, 0)))) -> 7 | Z3: =IF(J3=Reference!$A$20, Reference!$C$20, IF(J3=Reference!$A$19, Reference!$C$19, IF(J3=Reference!$A$18, Reference!$C$18, IF(J3=Reference!$A$17, Reference!$C$17, 0)))) -> 4 | AA3: =IF(L3=Reference!$A$28, Reference!$C$28, IF(L3=Reference!$A$27, Reference!$C$27, IF(L3=Reference!$A$26, Reference!$C$26, IF(L3=Reference!$A$25, Reference!$C$25, 0)))) -> 7 | AB3: =IF(N3=Reference!$A$36, Reference!$C$36, IF(N3=Reference!$A$35, Reference!$C$35, IF(N3=Reference!$A$34, Reference!$C$34, IF(N3=Reference!$A$33, Reference!$C$33, 0)))) -> 1 | AC3: =(Reference!$B$2*Y3 + Reference!$B$3*AA3 + Reference!$B$4*Z3 + Reference!$B$5 * AB3)/4 -> 11.0625 | AD3: =IF(Q3=Reference!$C$41, Reference!$D$41, IF(Q3=Reference!$C$42, Reference!$D$42, IF(Q3=Reference!$C$43, Reference!$D$43, IF(Q3=Reference!$C$44, Reference!$D$44, 0)))) -> 1 | AE3: =1 + (AC3 * AD3) -> 12.0625 | AF3: Raised by all six model outputs; medini T002 (Mono + Stereo | Tampering); copied from row 24 of the full analysis
A4: 1. Cameras (mono + stereo) | B4: Denial of service | C4: Availability | D4: The camera is blinded with a laser or strong light, covered, sprayed, misaligned or disconnected, so accidents in its field of view are never detected and no warning is issued. | E4: The attacker reaches the pole or illuminates the camera from the roadside; power or network cables can also be cut. | F4: Physical | G4: Physical presence at the roadside installation is required. | H4: Major | I4: A real accident stays unannounced, so approaching drivers are not warned and secondary collisions are not prevented (S2). | J4: Moderate | K4: Repair or replacement of the unit and a site visit. | L4: Severe | M4: The core function of the roadside station is lost for the affected field of view until the camera is restored. | N4: Negligible | O4: No personal data is disclosed. | P4: =IF(AC4>=Reference!$H$2, Reference!$G$2, IF(AC4>=Reference!$H$3, Reference!$G$3, IF(AC4>=Reference!$H$4, Reference!$G$4, IF(AC4>=Reference!$H$5, Reference!$G$5, "")))) -> Severe | Q4: =IF(F4="Physical", "Very Low", IF(F4="Local", "Low", IF(F4="Adjacent", "Medium", IF(F4="Network", "High", "")))) -> Very Low | R4: =IF(AE4>=Reference!$D$2, Reference!$E$2, IF(AE4>=Reference!$D$3, Reference!$E$3, IF(AE4>=Reference!$D$4, Reference!$E$4, IF(AE4>=Reference!$D$5, Reference!$E$5, "")))) -> Low | S4: Mitigation | T4: Tamper-resistant mounting and housing, monitoring of stream health, brightness and alignment, automatic alarm to the operator when the view changes or the feed stops, redundant camera coverage at critical sites. | U4: Camera hardware and mounting, computing unit health monitoring, operator back-end alerting. | V4: Detection of the failure matters more than prevention: the operator must know that the site is blind. | W4: Availability, Integrity. | X4: T003 | Y4: =IF(H4=Reference!$A$12, Reference!$C$12, IF(H4=Reference!$A$11, Reference!$C$11, IF(H4=Reference!$A$10, Reference!$C$10, IF(H4=Reference!$A$9, Reference!$C$9, 0)))) -> 7 | Z4: =IF(J4=Reference!$A$20, Reference!$C$20, IF(J4=Reference!$A$19, Reference!$C$19, IF(J4=Reference!$A$18, Reference!$C$18, IF(J4=Reference!$A$17, Reference!$C$17, 0)))) -> 4 | AA4: =IF(L4=Reference!$A$28, Reference!$C$28, IF(L4=Reference!$A$27, Reference!$C$27, IF(L4=Reference!$A$26, Reference!$C$26, IF(L4=Reference!$A$25, Reference!$C$25, 0)))) -> 10 | AB4: =IF(N4=Reference!$A$36, Reference!$C$36, IF(N4=Reference!$A$35, Reference!$C$35, IF(N4=Reference!$A$34, Reference!$C$34, IF(N4=Reference!$A$33, Reference!$C$33, 0)))) -> 1 | AC4: =(Reference!$B$2*Y4 + Reference!$B$3*AA4 + Reference!$B$4*Z4 + Reference!$B$5 * AB4)/4 -> 11.8125 | AD4: =IF(Q4=Reference!$C$41, Reference!$D$41, IF(Q4=Reference!$C$42, Reference!$D$42, IF(Q4=Reference!$C$43, Reference!$D$43, IF(Q4=Reference!$C$44, Reference!$D$44, 0)))) -> 1 | AE4: =1 + (AC4 * AD4) -> 12.8125 | AF4: Raised by all six model outputs; medini T003 (Mono + Stereo | Denial of Service); copied from row 14 of the full analysis
A5: 8. DENM encoder (ASN.1 UPER payload) | B5: Tampering | C5: Integrity | D5: The encoder software or its ASN.1 definitions are modified, so the station produces syntactically valid messages whose meaning differs from the detected event. | E5: Access to the computing unit through the roadside network or an unsigned update, followed by modification of the encoder or its schema files. | F5: Adjacent | G5: Access to the roadside network segment or to the update path is required. | H5: Major | I5: Every message of the station carries altered content while appearing correct (S2). | J5: Major | K5: Liability and the effort of verifying all deployed stations. | L5: Severe | M5: The station keeps operating while producing wrong messages, which is harder to detect than an outage. | N5: Negligible | O5: No personal data is affected. | P5: =IF(AC5>=Reference!$H$2, Reference!$G$2, IF(AC5>=Reference!$H$3, Reference!$G$3, IF(AC5>=Reference!$H$4, Reference!$G$4, IF(AC5>=Reference!$H$5, Reference!$G$5, "")))) -> Severe | Q5: =IF(F5="Physical", "Very Low", IF(F5="Local", "Low", IF(F5="Adjacent", "Medium", IF(F5="Network", "High", "")))) -> Medium | R5: =IF(AE5>=Reference!$D$2, Reference!$E$2, IF(AE5>=Reference!$D$3, Reference!$E$3, IF(AE5>=Reference!$D$4, Reference!$E$4, IF(AE5>=Reference!$D$5, Reference!$E$5, "")))) -> High | S5: Mitigation | T5: Signed software and schema files, integrity verification at start-up, read-only deployment, comparison of encoded output against the agent output before signing. | U5: Computing unit software, ASN.1 schema files, update pipeline (Step 8). | V5: Together with the model file row, this covers the software supply chain of the roadside station. | W5: Integrity, Authenticity. | X5: T098 | Y5: =IF(H5=Reference!$A$12, Reference!$C$12, IF(H5=Reference!$A$11, Reference!$C$11, IF(H5=Reference!$A$10, Reference!$C$10, IF(H5=Reference!$A$9, Reference!$C$9, 0)))) -> 7 | Z5: =IF(J5=Reference!$A$20, Reference!$C$20, IF(J5=Reference!$A$19, Reference!$C$19, IF(J5=Reference!$A$18, Reference!$C$18, IF(J5=Reference!$A$17, Reference!$C$17, 0)))) -> 7 | AA5: =IF(L5=Reference!$A$28, Reference!$C$28, IF(L5=Reference!$A$27, Reference!$C$27, IF(L5=Reference!$A$26, Reference!$C$26, IF(L5=Reference!$A$25, Reference!$C$25, 0)))) -> 10 | AB5: =IF(N5=Reference!$A$36, Reference!$C$36, IF(N5=Reference!$A$35, Reference!$C$35, IF(N5=Reference!$A$34, Reference!$C$34, IF(N5=Reference!$A$33, Reference!$C$33, 0)))) -> 1 | AC5: =(Reference!$B$2*Y5 + Reference!$B$3*AA5 + Reference!$B$4*Z5 + Reference!$B$5 * AB5)/4 -> 12.1875 | AD5: =IF(Q5=Reference!$C$41, Reference!$D$41, IF(Q5=Reference!$C$42, Reference!$D$42, IF(Q5=Reference!$C$43, Reference!$D$43, IF(Q5=Reference!$C$44, Reference!$D$44, 0)))) -> 7 | AE5: =1 + (AC5 * AD5) -> 86.3125 | AF5: Raised by all six model outputs; medini T098 (ASN.1 UPER payload | Tampering); copied from row 29 of the full analysis
A6: 9. RSU (PC5 radio, signing keys in HSM) | B6: Spoofing | C6: Authenticity | D6: A rogue roadside device broadcasts DENMs that claim to originate from the legitimate RSU, announcing an accident that does not exist or cancelling a real one. Every vehicle in radio range shows a false hazard warning to the driver. | E6: The attacker operates a C-V2X radio inside the coverage area and either holds valid ITS credentials (stolen, extracted or issued to a rogue node) or exploits receivers that do not verify message signatures. | F6: Network | G6: The attack is carried out over the PC5 sidelink; no physical access to the roadside station is needed, only presence in the radio coverage area. | H6: Major | I6: A false accident warning at motorway speed can trigger hard braking and rear-end collisions; injuries are severe but survival is probable (S2). | J6: Major | K6: Liability claims after a provoked collision, incident response costs and possible suspension of the warning service in the affected area. | L6: Major | M6: The hazard warning function becomes untrustworthy and the operator may have to disable it locally until the source is identified. | N6: Negligible | O6: The forged message carries no personal data of road users. | P6: =IF(AC6>=Reference!$H$2, Reference!$G$2, IF(AC6>=Reference!$H$3, Reference!$G$3, IF(AC6>=Reference!$H$4, Reference!$G$4, IF(AC6>=Reference!$H$5, Reference!$G$5, "")))) -> Severe | Q6: =IF(F6="Physical", "Very Low", IF(F6="Local", "Low", IF(F6="Adjacent", "Medium", IF(F6="Network", "High", "")))) -> High | R6: =IF(AE6>=Reference!$D$2, Reference!$E$2, IF(AE6>=Reference!$D$3, Reference!$E$3, IF(AE6>=Reference!$D$4, Reference!$E$4, IF(AE6>=Reference!$D$5, Reference!$E$5, "")))) -> Critical | S6: Mitigation | T6: Verify IEEE 1609.2 / ETSI TS 103 097 signatures and certificate permissions in the OBU before a warning is displayed; plausibility and misbehaviour detection (position, cause code, event history); revocation of misbehaving certificates. | U6: RSU signing chain, OBU verification stack, PKI trust list, vehicle warning logic (Step 12). | V6: The scenario cannot be avoided, because receiving DENMs is the purpose of the function; mitigation through authentication and misbehaviour detection is the only practical option. | W6: Authenticity, Integrity, Non-repudiation. | X6: T115 | Y6: =IF(H6=Reference!$A$12, Reference!$C$12, IF(H6=Reference!$A$11, Reference!$C$11, IF(H6=Reference!$A$10, Reference!$C$10, IF(H6=Reference!$A$9, Reference!$C$9, 0)))) -> 7 | Z6: =IF(J6=Reference!$A$20, Reference!$C$20, IF(J6=Reference!$A$19, Reference!$C$19, IF(J6=Reference!$A$18, Reference!$C$18, IF(J6=Reference!$A$17, Reference!$C$17, 0)))) -> 7 | AA6: =IF(L6=Reference!$A$28, Reference!$C$28, IF(L6=Reference!$A$27, Reference!$C$27, IF(L6=Reference!$A$26, Reference!$C$26, IF(L6=Reference!$A$25, Reference!$C$25, 0)))) -> 7 | AB6: =IF(N6=Reference!$A$36, Reference!$C$36, IF(N6=Reference!$A$35, Reference!$C$35, IF(N6=Reference!$A$34, Reference!$C$34, IF(N6=Reference!$A$33, Reference!$C$33, 0)))) -> 1 | AC6: =(Reference!$B$2*Y6 + Reference!$B$3*AA6 + Reference!$B$4*Z6 + Reference!$B$5 * AB6)/4 -> 11.4375 | AD6: =IF(Q6=Reference!$C$41, Reference!$D$41, IF(Q6=Reference!$C$42, Reference!$D$42, IF(Q6=Reference!$C$43, Reference!$D$43, IF(Q6=Reference!$C$44, Reference!$D$44, 0)))) -> 10 | AE6: =1 + (AC6 * AD6) -> 115.375 | AF6: Raised by all six model outputs; medini T115 (Signs, PC5, HSM | Spoofing); copied from row 1 of the full analysis
A7: 9. RSU (firmware and configuration) | B7: Tampering | C7: Integrity | D7: The firmware or the configuration of the roadside unit is modified, so it alters, drops or re-orders the messages it signs and broadcasts while continuing to appear operational. | E7: Access to the management interface of the unit over the operator network, using default or weak credentials, or an unsigned firmware update. | F7: Network | G7: The management services of the unit are reachable over the network; no physical access is required. | H7: Major | I7: The content broadcast to every vehicle in range no longer corresponds to the detected event (S2). | J7: Major | K7: Liability for a resulting collision and verification of every deployed unit. | L7: Severe | M7: The station keeps running while producing manipulated output, which is harder to detect than an outage. | N7: Negligible | O7: No personal data is affected. | P7: =IF(AC7>=Reference!$H$2, Reference!$G$2, IF(AC7>=Reference!$H$3, Reference!$G$3, IF(AC7>=Reference!$H$4, Reference!$G$4, IF(AC7>=Reference!$H$5, Reference!$G$5, "")))) -> Severe | Q7: =IF(F7="Physical", "Very Low", IF(F7="Local", "Low", IF(F7="Adjacent", "Medium", IF(F7="Network", "High", "")))) -> High | R7: =IF(AE7>=Reference!$D$2, Reference!$E$2, IF(AE7>=Reference!$D$3, Reference!$E$3, IF(AE7>=Reference!$D$4, Reference!$E$4, IF(AE7>=Reference!$D$5, Reference!$E$5, "")))) -> Critical | S7: Mitigation | T7: Signed firmware and configuration, secure boot, removal of default credentials, management access only from a dedicated network, integrity monitoring and alerting on configuration change. | U7: RSU firmware and configuration, operator management network, update process (Step 9). | V7: Distinct from the privilege escalation row: here the unit is reconfigured, there the attacker uses its signing key directly. | W7: Integrity, Authenticity. | X7: T113 | Y7: =IF(H7=Reference!$A$12, Reference!$C$12, IF(H7=Reference!$A$11, Reference!$C$11, IF(H7=Reference!$A$10, Reference!$C$10, IF(H7=Reference!$A$9, Reference!$C$9, 0)))) -> 7 | Z7: =IF(J7=Reference!$A$20, Reference!$C$20, IF(J7=Reference!$A$19, Reference!$C$19, IF(J7=Reference!$A$18, Reference!$C$18, IF(J7=Reference!$A$17, Reference!$C$17, 0)))) -> 7 | AA7: =IF(L7=Reference!$A$28, Reference!$C$28, IF(L7=Reference!$A$27, Reference!$C$27, IF(L7=Reference!$A$26, Reference!$C$26, IF(L7=Reference!$A$25, Reference!$C$25, 0)))) -> 10 | AB7: =IF(N7=Reference!$A$36, Reference!$C$36, IF(N7=Reference!$A$35, Reference!$C$35, IF(N7=Reference!$A$34, Reference!$C$34, IF(N7=Reference!$A$33, Reference!$C$33, 0)))) -> 1 | AC7: =(Reference!$B$2*Y7 + Reference!$B$3*AA7 + Reference!$B$4*Z7 + Reference!$B$5 * AB7)/4 -> 12.1875 | AD7: =IF(Q7=Reference!$C$41, Reference!$D$41, IF(Q7=Reference!$C$42, Reference!$D$42, IF(Q7=Reference!$C$43, Reference!$D$43, IF(Q7=Reference!$C$44, Reference!$D$44, 0)))) -> 10 | AE7: =1 + (AC7 * AD7) -> 122.875 | AF7: Raised by all six model outputs; medini T113 (Signs, PC5, HSM | Tampering); written for this sheet
A8: 9. RSU signing keys (HSM) | B8: Information disclosure | C8: Confidentiality | D8: The private signing key of the RSU is extracted, for example because it is generated or stored outside the security module or through a physical side-channel attack, after which the attacker can sign forged DENMs indefinitely. | E8: Physical access to the pole-mounted RSU or to a decommissioned unit, combined with a misconfiguration that keeps key material outside the FIPS 140-2 level 3 module. | F8: Physical | G8: The attack path requires physical possession of, or direct access to, the roadside unit. | H8: Major | I8: The stolen key enables forged warnings with valid signatures; the effect equals a rogue RSU broadcast and persists until the certificate is revoked (S2). | J8: Major | K8: Revocation and replacement of the unit, investigation costs and liability if forged warnings were issued. | L8: Major | M8: Until revocation, every message signed with this key must be treated as untrusted. | N8: Negligible | O8: The key material itself exposes no personal data of road users. | P8: =IF(AC8>=Reference!$H$2, Reference!$G$2, IF(AC8>=Reference!$H$3, Reference!$G$3, IF(AC8>=Reference!$H$4, Reference!$G$4, IF(AC8>=Reference!$H$5, Reference!$G$5, "")))) -> Severe | Q8: =IF(F8="Physical", "Very Low", IF(F8="Local", "Low", IF(F8="Adjacent", "Medium", IF(F8="Network", "High", "")))) -> Very Low | R8: =IF(AE8>=Reference!$D$2, Reference!$E$2, IF(AE8>=Reference!$D$3, Reference!$E$3, IF(AE8>=Reference!$D$4, Reference!$E$4, IF(AE8>=Reference!$D$5, Reference!$E$5, "")))) -> Low | S8: Mitigation | T8: Generate and keep keys inside the HSM, enable tamper detection and zeroisation, physically secure the cabinet, monitor enclosure opening, revoke certificates as soon as tampering is detected. | U8: RSU hardware, HSM configuration, key management procedures, revocation service. | V8: Feasibility is low because physical access is required, which is why the risk value stays below the network-based rows even though the impact is comparable. | W8: Confidentiality, Authenticity, Integrity. | X8: T112 | Y8: =IF(H8=Reference!$A$12, Reference!$C$12, IF(H8=Reference!$A$11, Reference!$C$11, IF(H8=Reference!$A$10, Reference!$C$10, IF(H8=Reference!$A$9, Reference!$C$9, 0)))) -> 7 | Z8: =IF(J8=Reference!$A$20, Reference!$C$20, IF(J8=Reference!$A$19, Reference!$C$19, IF(J8=Reference!$A$18, Reference!$C$18, IF(J8=Reference!$A$17, Reference!$C$17, 0)))) -> 7 | AA8: =IF(L8=Reference!$A$28, Reference!$C$28, IF(L8=Reference!$A$27, Reference!$C$27, IF(L8=Reference!$A$26, Reference!$C$26, IF(L8=Reference!$A$25, Reference!$C$25, 0)))) -> 7 | AB8: =IF(N8=Reference!$A$36, Reference!$C$36, IF(N8=Reference!$A$35, Reference!$C$35, IF(N8=Reference!$A$34, Reference!$C$34, IF(N8=Reference!$A$33, Reference!$C$33, 0)))) -> 1 | AC8: =(Reference!$B$2*Y8 + Reference!$B$3*AA8 + Reference!$B$4*Z8 + Reference!$B$5 * AB8)/4 -> 11.4375 | AD8: =IF(Q8=Reference!$C$41, Reference!$D$41, IF(Q8=Reference!$C$42, Reference!$D$42, IF(Q8=Reference!$C$43, Reference!$D$43, IF(Q8=Reference!$C$44, Reference!$D$44, 0)))) -> 1 | AE8: =1 + (AC8 * AD8) -> 12.4375 | AF8: Raised by all six model outputs; medini T112 (Signs, PC5, HSM | Information Disclosure); copied from row 5 of the full analysis
A9: 9 -> 11. PC5 sidelink (RSU to OBU) | B9: Tampering | C9: Integrity | D9: Messages in flight on the sidelink are altered, for example by transmitting a stronger modified copy that overshadows the legitimate one, so vehicles receive different content from what the roadside unit sent. | E9: A C-V2X transmitter inside the coverage area, timed against the legitimate transmission. | F9: Network | G9: The attack is carried out over the air and requires no access to any system. | H9: Major | I9: The altered warning can send drivers the wrong hazard type, position or lane status (S2). | J9: Moderate | K9: Investigation and, for a persistent source, the cost of locating it. | L9: Major | M9: The delivered content of the warning service cannot be trusted in the affected area. | N9: Negligible | O9: No personal data is affected. | P9: =IF(AC9>=Reference!$H$2, Reference!$G$2, IF(AC9>=Reference!$H$3, Reference!$G$3, IF(AC9>=Reference!$H$4, Reference!$G$4, IF(AC9>=Reference!$H$5, Reference!$G$5, "")))) -> Severe | Q9: =IF(F9="Physical", "Very Low", IF(F9="Local", "Low", IF(F9="Adjacent", "Medium", IF(F9="Network", "High", "")))) -> High | R9: =IF(AE9>=Reference!$D$2, Reference!$E$2, IF(AE9>=Reference!$D$3, Reference!$E$3, IF(AE9>=Reference!$D$4, Reference!$E$4, IF(AE9>=Reference!$D$5, Reference!$E$5, "")))) -> Critical | S9: Mitigation | T9: Verify the message signature in the vehicle before use, reject messages that fail verification, detect duplicated or conflicting messages for the same event, monitor the channel for anomalies. | U9: RSU radio, PC5 channel, OBU verification stack (Steps 9-11). | V9: Message signing already prevents the altered copy from being accepted, provided the vehicle actually verifies it. | W9: Integrity, Authenticity. | X9: T131 | Y9: =IF(H9=Reference!$A$12, Reference!$C$12, IF(H9=Reference!$A$11, Reference!$C$11, IF(H9=Reference!$A$10, Reference!$C$10, IF(H9=Reference!$A$9, Reference!$C$9, 0)))) -> 7 | Z9: =IF(J9=Reference!$A$20, Reference!$C$20, IF(J9=Reference!$A$19, Reference!$C$19, IF(J9=Reference!$A$18, Reference!$C$18, IF(J9=Reference!$A$17, Reference!$C$17, 0)))) -> 4 | AA9: =IF(L9=Reference!$A$28, Reference!$C$28, IF(L9=Reference!$A$27, Reference!$C$27, IF(L9=Reference!$A$26, Reference!$C$26, IF(L9=Reference!$A$25, Reference!$C$25, 0)))) -> 7 | AB9: =IF(N9=Reference!$A$36, Reference!$C$36, IF(N9=Reference!$A$35, Reference!$C$35, IF(N9=Reference!$A$34, Reference!$C$34, IF(N9=Reference!$A$33, Reference!$C$33, 0)))) -> 1 | AC9: =(Reference!$B$2*Y9 + Reference!$B$3*AA9 + Reference!$B$4*Z9 + Reference!$B$5 * AB9)/4 -> 11.0625 | AD9: =IF(Q9=Reference!$C$41, Reference!$D$41, IF(Q9=Reference!$C$42, Reference!$D$42, IF(Q9=Reference!$C$43, Reference!$D$43, IF(Q9=Reference!$C$44, Reference!$D$44, 0)))) -> 10 | AE9: =1 + (AC9 * AD9) -> 111.625 | AF9: Raised by all six model outputs; medini T131 (pc5_out ↔ pc5_in | Tampering); written for this sheet
A10: 9 -> 11. PC5 sidelink (RSU to OBU) | B10: Denial of service | C10: Availability | D10: The 5.9 GHz channel is jammed, or flooded with valid-format messages, so vehicles in the area do not receive the hazard warning even though the roadside station generated it correctly. | E10: The attacker operates a jammer or a C-V2X transmitter inside the coverage area of the roadside unit. | F10: Network | G10: The attack is carried out over the air inside the radio coverage area and needs no access to any system. | H10: Major | I10: The warning does not reach the driver at the moment it is needed, so a secondary collision is not prevented (S2). | J10: Moderate | K10: Investigation and, if the jamming is persistent, the cost of locating and removing the source. | L10: Severe | M10: The delivery path of the warning is lost; the function fails exactly where it is needed. | N10: Negligible | O10: No personal data is affected. | P10: =IF(AC10>=Reference!$H$2, Reference!$G$2, IF(AC10>=Reference!$H$3, Reference!$G$3, IF(AC10>=Reference!$H$4, Reference!$G$4, IF(AC10>=Reference!$H$5, Reference!$G$5, "")))) -> Severe | Q10: =IF(F10="Physical", "Very Low", IF(F10="Local", "Low", IF(F10="Adjacent", "Medium", IF(F10="Network", "High", "")))) -> High | R10: =IF(AE10>=Reference!$D$2, Reference!$E$2, IF(AE10>=Reference!$D$3, Reference!$E$3, IF(AE10>=Reference!$D$4, Reference!$E$4, IF(AE10>=Reference!$D$5, Reference!$E$5, "")))) -> Critical | S10: Mitigation | T10: Detect and report abnormal channel occupancy and message loss to the operator, use the cellular V2N path as an independent delivery route, apply congestion control and message filtering at the receiver, locate persistent jammers with the operator and the regulator. | U10: RSU radio, OBU radio, central ITS-S V2N path, monitoring. | V10: Jamming cannot be prevented on a shared radio channel; the treatment is detection plus an independent delivery path, which the architecture already provides through V2N. | W10: Availability. | X10: T132 | Y10: =IF(H10=Reference!$A$12, Reference!$C$12, IF(H10=Reference!$A$11, Reference!$C$11, IF(H10=Reference!$A$10, Reference!$C$10, IF(H10=Reference!$A$9, Reference!$C$9, 0)))) -> 7 | Z10: =IF(J10=Reference!$A$20, Reference!$C$20, IF(J10=Reference!$A$19, Reference!$C$19, IF(J10=Reference!$A$18, Reference!$C$18, IF(J10=Reference!$A$17, Reference!$C$17, 0)))) -> 4 | AA10: =IF(L10=Reference!$A$28, Reference!$C$28, IF(L10=Reference!$A$27, Reference!$C$27, IF(L10=Reference!$A$26, Reference!$C$26, IF(L10=Reference!$A$25, Reference!$C$25, 0)))) -> 10 | AB10: =IF(N10=Reference!$A$36, Reference!$C$36, IF(N10=Reference!$A$35, Reference!$C$35, IF(N10=Reference!$A$34, Reference!$C$34, IF(N10=Reference!$A$33, Reference!$C$33, 0)))) -> 1 | AC10: =(Reference!$B$2*Y10 + Reference!$B$3*AA10 + Reference!$B$4*Z10 + Reference!$B$5 * AB10)/4 -> 11.8125 | AD10: =IF(Q10=Reference!$C$41, Reference!$D$41, IF(Q10=Reference!$C$42, Reference!$D$42, IF(Q10=Reference!$C$43, Reference!$D$43, IF(Q10=Reference!$C$44, Reference!$D$44, 0)))) -> 10 | AE10: =1 + (AC10 * AD10) -> 119.125 | AF10: Raised by all six model outputs; medini T132 (pc5_out ↔ pc5_in | Denial of Service); copied from row 15 of the full analysis
A11: 11. OBU (station identity) | B11: Spoofing | C11: Authenticity | D11: A rogue device presents itself as a legitimate on-board unit towards the roadside unit and the back-end, for example to obtain services, to inject false status information or to appear as several vehicles at once. | E11: Use of stolen or cloned credentials, or exploitation of a back-end interface that does not verify the station identity. | F11: Network | G11: The attack is carried out over the radio and cellular interfaces. | H11: Moderate | I11: In this architecture the vehicle mainly receives, so the direct safety effect is limited; false status can still distort the operator view (S1). | J11: Moderate | K11: Investigation and possible revocation of credentials. | L11: Moderate | M11: Trust in vehicle-provided information is degraded. | N11: Moderate | O11: Cloned identities can be used to observe or impersonate a specific vehicle. | P11: =IF(AC11>=Reference!$H$2, Reference!$G$2, IF(AC11>=Reference!$H$3, Reference!$G$3, IF(AC11>=Reference!$H$4, Reference!$G$4, IF(AC11>=Reference!$H$5, Reference!$G$5, "")))) -> Major | Q11: =IF(F11="Physical", "Very Low", IF(F11="Local", "Low", IF(F11="Adjacent", "Medium", IF(F11="Network", "High", "")))) -> High | R11: =IF(AE11>=Reference!$D$2, Reference!$E$2, IF(AE11>=Reference!$D$3, Reference!$E$3, IF(AE11>=Reference!$D$4, Reference!$E$4, IF(AE11>=Reference!$D$5, Reference!$E$5, "")))) -> High | S11: Mitigation | T11: Verify station certificates and their permissions, detect several stations using the same identity, bind credentials to the hardware security element, revoke on detection. | U11: OBU credentials, RSU and back-end verification, PKI (Steps 10-11). | V11: Lower risk here than in architectures where vehicles also generate warnings, which is worth stating explicitly. | W11: Authenticity. | X11: T142 | Y11: =IF(H11=Reference!$A$12, Reference!$C$12, IF(H11=Reference!$A$11, Reference!$C$11, IF(H11=Reference!$A$10, Reference!$C$10, IF(H11=Reference!$A$9, Reference!$C$9, 0)))) -> 4 | Z11: =IF(J11=Reference!$A$20, Reference!$C$20, IF(J11=Reference!$A$19, Reference!$C$19, IF(J11=Reference!$A$18, Reference!$C$18, IF(J11=Reference!$A$17, Reference!$C$17, 0)))) -> 4 | AA11: =IF(L11=Reference!$A$28, Reference!$C$28, IF(L11=Reference!$A$27, Reference!$C$27, IF(L11=Reference!$A$26, Reference!$C$26, IF(L11=Reference!$A$25, Reference!$C$25, 0)))) -> 4 | AB11: =IF(N11=Reference!$A$36, Reference!$C$36, IF(N11=Reference!$A$35, Reference!$C$35, IF(N11=Reference!$A$34, Reference!$C$34, IF(N11=Reference!$A$33, Reference!$C$33, 0)))) -> 4 | AC11: =(Reference!$B$2*Y11 + Reference!$B$3*AA11 + Reference!$B$4*Z11 + Reference!$B$5 * AB11)/4 -> 6.75 | AD11: =IF(Q11=Reference!$C$41, Reference!$D$41, IF(Q11=Reference!$C$42, Reference!$D$42, IF(Q11=Reference!$C$43, Reference!$D$43, IF(Q11=Reference!$C$44, Reference!$D$44, 0)))) -> 10 | AE11: =1 + (AC11 * AD11) -> 68.5 | AF11: Raised by all six model outputs; medini T142 (PC5 + Uumodem | Spoofing); copied from row 40 of the full analysis
A12: 11. OBU (V2X stack and ASN.1 decoder) | B12: Denial of service | C12: Availability | D12: Malformed or out-of-range DENM fields crash the receiving V2X stack or its ASN.1 decoder, so the vehicle stops processing warnings; a memory corruption in the decoder could also lead to code execution. | E12: The attacker broadcasts crafted messages on PC5, or the malformed content originates from the unvalidated model output of the roadside station itself. | F12: Network | G12: The messages are received over the air by every vehicle in range. | H12: Major | I12: A vehicle that stops processing V2X messages receives no further warnings; a code execution variant would raise this to the level of the previous row (S2). | J12: Moderate | K12: Software correction and field campaign for the affected units. | L12: Severe | M12: Loss of the reception function in every vehicle exposed to the message. | N12: Negligible | O12: No personal data is affected. | P12: =IF(AC12>=Reference!$H$2, Reference!$G$2, IF(AC12>=Reference!$H$3, Reference!$G$3, IF(AC12>=Reference!$H$4, Reference!$G$4, IF(AC12>=Reference!$H$5, Reference!$G$5, "")))) -> Severe | Q12: =IF(F12="Physical", "Very Low", IF(F12="Local", "Low", IF(F12="Adjacent", "Medium", IF(F12="Network", "High", "")))) -> High | R12: =IF(AE12>=Reference!$D$2, Reference!$E$2, IF(AE12>=Reference!$D$3, Reference!$E$3, IF(AE12>=Reference!$D$4, Reference!$E$4, IF(AE12>=Reference!$D$5, Reference!$E$5, "")))) -> Critical | S12: Mitigation | T12: Validate the DENM against the ASN.1 schema and plausibility rules before signing at the roadside, fuzz-test the receiving stack, apply memory-safe decoding, isolate the parser process, rate-limit malformed messages. | U12: DENM encoder (Step 8), OBU V2X stack and decoder (Step 11). | V12: The only row where the roadside station can harm vehicles without any attacker, because the model output is encoded and broadcast without a full validation step. | W12: Availability, Integrity. | X12: T141 | Y12: =IF(H12=Reference!$A$12, Reference!$C$12, IF(H12=Reference!$A$11, Reference!$C$11, IF(H12=Reference!$A$10, Reference!$C$10, IF(H12=Reference!$A$9, Reference!$C$9, 0)))) -> 7 | Z12: =IF(J12=Reference!$A$20, Reference!$C$20, IF(J12=Reference!$A$19, Reference!$C$19, IF(J12=Reference!$A$18, Reference!$C$18, IF(J12=Reference!$A$17, Reference!$C$17, 0)))) -> 4 | AA12: =IF(L12=Reference!$A$28, Reference!$C$28, IF(L12=Reference!$A$27, Reference!$C$27, IF(L12=Reference!$A$26, Reference!$C$26, IF(L12=Reference!$A$25, Reference!$C$25, 0)))) -> 10 | AB12: =IF(N12=Reference!$A$36, Reference!$C$36, IF(N12=Reference!$A$35, Reference!$C$35, IF(N12=Reference!$A$34, Reference!$C$34, IF(N12=Reference!$A$33, Reference!$C$33, 0)))) -> 1 | AC12: =(Reference!$B$2*Y12 + Reference!$B$3*AA12 + Reference!$B$4*Z12 + Reference!$B$5 * AB12)/4 -> 11.8125 | AD12: =IF(Q12=Reference!$C$41, Reference!$D$41, IF(Q12=Reference!$C$42, Reference!$D$42, IF(Q12=Reference!$C$43, Reference!$D$43, IF(Q12=Reference!$C$44, Reference!$D$44, 0)))) -> 10 | AE12: =1 + (AC12 * AD12) -> 119.125 | AF12: Raised by all six model outputs; medini T141 (PC5 + Uumodem | Denial of Service); copied from row 21 of the full analysis
A13: 12. Vehicle computer (signature verification and warning logic) | B13: Tampering | C13: Integrity | D13: Signature verification or the warning logic in the vehicle is modified so that unsigned or invalid DENMs are accepted, which makes every forged message effective even without stolen credentials. | E13: Physical or local access to the in-vehicle computing unit (debug port, unsigned software update) or compromise of the link between OBU and computer. | F13: Local | G13: The attacker needs direct access to the vehicle or to its internal network; the path is not reachable from the public network. | H13: Major | I13: The vehicle acts on forged warnings without any cryptographic barrier, which can provoke hard braking or wrong manoeuvres (S2). | J13: Moderate | K13: The scope is the individual vehicle rather than the deployment; warranty and liability costs. | L13: Major | M13: The verification function of the vehicle ITS station is lost. | N13: Negligible | O13: No personal data disclosure is involved. | P13: =IF(AC13>=Reference!$H$2, Reference!$G$2, IF(AC13>=Reference!$H$3, Reference!$G$3, IF(AC13>=Reference!$H$4, Reference!$G$4, IF(AC13>=Reference!$H$5, Reference!$G$5, "")))) -> Severe | Q13: =IF(F13="Physical", "Very Low", IF(F13="Local", "Low", IF(F13="Adjacent", "Medium", IF(F13="Network", "High", "")))) -> Low | R13: =IF(AE13>=Reference!$D$2, Reference!$E$2, IF(AE13>=Reference!$D$3, Reference!$E$3, IF(AE13>=Reference!$D$4, Reference!$E$4, IF(AE13>=Reference!$D$5, Reference!$E$5, "")))) -> Medium | S13: Mitigation | T13: Secure boot and signed software updates on the vehicle computer, disable debug interfaces in production, authenticate the link between OBU and computer, report verification failures to the back-end. | U13: OBU, in-vehicle computing unit (Steps 11-12), software update process. | V13: Per-vehicle scope and the local access requirement keep the risk lower, but the control is essential because it is the last line of defence. | W13: Integrity, Authenticity. | X13: T164 | Y13: =IF(H13=Reference!$A$12, Reference!$C$12, IF(H13=Reference!$A$11, Reference!$C$11, IF(H13=Reference!$A$10, Reference!$C$10, IF(H13=Reference!$A$9, Reference!$C$9, 0)))) -> 7 | Z13: =IF(J13=Reference!$A$20, Reference!$C$20, IF(J13=Reference!$A$19, Reference!$C$19, IF(J13=Reference!$A$18, Reference!$C$18, IF(J13=Reference!$A$17, Reference!$C$17, 0)))) -> 4 | AA13: =IF(L13=Reference!$A$28, Reference!$C$28, IF(L13=Reference!$A$27, Reference!$C$27, IF(L13=Reference!$A$26, Reference!$C$26, IF(L13=Reference!$A$25, Reference!$C$25, 0)))) -> 7 | AB13: =IF(N13=Reference!$A$36, Reference!$C$36, IF(N13=Reference!$A$35, Reference!$C$35, IF(N13=Reference!$A$34, Reference!$C$34, IF(N13=Reference!$A$33, Reference!$C$33, 0)))) -> 1 | AC13: =(Reference!$B$2*Y13 + Reference!$B$3*AA13 + Reference!$B$4*Z13 + Reference!$B$5 * AB13)/4 -> 11.0625 | AD13: =IF(Q13=Reference!$C$41, Reference!$D$41, IF(Q13=Reference!$C$42, Reference!$D$42, IF(Q13=Reference!$C$43, Reference!$D$43, IF(Q13=Reference!$C$44, Reference!$D$44, 0)))) -> 4 | AE13: =1 + (AC13 * AD13) -> 45.25 | AF13: Raised by all six model outputs; medini T164 (Verify, warning logic | Tampering); copied from row 7 of the full analysis
... A23: 10. Central ITS-S (operator console, PKI services) | B23: Elevation of privilege | C23: Authorization | D23: An attacker obtains administrative rights on the back-end and can issue or revoke certificates, push configuration to every roadside unit and publish or cancel warnings across the deployment. | E23: Compromise of an operator account, exploitation of the back-end application, or an insider with excessive rights. | F23: Network | G23: The console and the services are reachable over the network. | H23: Severe | I23: Control over every station and over the trust material can be used to fabricate or suppress warnings anywhere (S3). | J23: Severe | K23: Deployment-wide revocation, service interruption and regulatory consequences. | L23: Severe | M23: Every function of the deployment can be manipulated from one place. | N23: Major | O23: Operator and certificate records expose the identities of stations and vehicles. | P23: =IF(AC23>=Reference!$H$2, Reference!$G$2, IF(AC23>=Reference!$H$3, Reference!$G$3, IF(AC23>=Reference!$H$4, Reference!$G$4, IF(AC23>=Reference!$H$5, Reference!$G$5, "")))) -> Severe | Q23: =IF(F23="Physical", "Very Low", IF(F23="Local", "Low", IF(F23="Adjacent", "Medium", IF(F23="Network", "High", "")))) -> High | R23: =IF(AE23>=Reference!$D$2, Reference!$E$2, IF(AE23>=Reference!$D$3, Reference!$E$3, IF(AE23>=Reference!$D$4, Reference!$E$4, IF(AE23>=Reference!$D$5, Reference!$E$5, "")))) -> Critical | S23: Mitigation | T23: Multi-factor authentication and least privilege for operator accounts, separation of duties for certificate issuance, hardened and patched back-end, complete audit logging with alerting. | U23: Central ITS-S application and accounts, PKI services, RSU management interface (Step 10). | V23: Highest reach of the whole analysis, on a par with the certificate row. | W23: Authorization, Integrity, Availability. | X23: T209 | Y23: =IF(H23=Reference!$A$12, Reference!$C$12, IF(H23=Reference!$A$11, Reference!$C$11, IF(H23=Reference!$A$10, Reference!$C$10, IF(H23=Reference!$A$9, Reference!$C$9, 0)))) -> 10 | Z23: =IF(J23=Reference!$A$20, Reference!$C$20, IF(J23=Reference!$A$19, Reference!$C$19, IF(J23=Reference!$A$18, Reference!$C$18, IF(J23=Reference!$A$17, Reference!$C$17, 0)))) -> 10 | AA23: =IF(L23=Reference!$A$28, Reference!$C$28, IF(L23=Reference!$A$27, Reference!$C$27, IF(L23=Reference!$A$26, Reference!$C$26, IF(L23=Reference!$A$25, Reference!$C$25, 0)))) -> 10 | AB23: =IF(N23=Reference!$A$36, Reference!$C$36, IF(N23=Reference!$A$35, Reference!$C$35, IF(N23=Reference!$A$34, Reference!$C$34, IF(N23=Reference!$A$33, Reference!$C$33, 0)))) -> 7 | AC23: =(Reference!$B$2*Y23 + Reference!$B$3*AA23 + Reference!$B$4*Z23 + Reference!$B$5 * AB23)/4 -> 16.6875 | AD23: =IF(Q23=Reference!$C$41, Reference!$D$41, IF(Q23=Reference!$C$42, Reference!$D$42, IF(Q23=Reference!$C$43, Reference!$D$43, IF(Q23=Reference!$C$44, Reference!$D$44, 0)))) -> 10 | AE23: =1 + (AC23 * AD23) -> 167.875 | AF23: Raised by all six model outputs; medini T209 (PKI, operator | Elevation of Privilege); copied from row 33 of the full analysis

Sheet AI threat scenarios
A1: Asset | B1: Threat type | C1: Security Attribute | D1: Damage Scenario | E1: Attack Path | F1: Attack vector | G1: Attack Vector Note / Motiv | H1: Safety Impact | I1: Safety Note / Motiv | J1: Financial Impact | K1: Financial Note / Motiv | L1: Operational Impact | M1: Operational Note / Motiv | N1: Privacy and Legislative Impact | O1: Privacy Note / Motiv | P1: Severity Level | Q1: Feasibility Level | R1: Risk Value | S1: Treatment Options | T1: Measures | U1: Affected Design Elements | V1: Justification (Treatment) | W1: Cybersecurity Goals | X1: Medini threat ID | Y1: s | Z1: f | AA1: o | AB1: p | AC1: impact | AD1: feasibility val | AE1: Risk score | AF1: Theme, agreement and source
A2: 9. RSU (PC5 radio, signing keys in HSM) | B2: Spoofing | C2: Authenticity | D2: A rogue roadside device broadcasts DENMs that claim to originate from the legitimate RSU, announcing an accident that does not exist or cancelling a real one. Every vehicle in radio range shows a false hazard warning to the driver. | E2: The attacker operates a C-V2X radio inside the coverage area and either holds valid ITS credentials (stolen, extracted or issued to a rogue node) or exploits receivers that do not verify message signatures. | F2: Network | G2: The attack is carried out over the PC5 sidelink; no physical access to the roadside station is needed, only presence in the radio coverage area. | H2: Major | I2: A false accident warning at motorway speed can trigger hard braking and rear-end collisions; injuries are severe but survival is probable (S2). | J2: Major | K2: Liability claims after a provoked collision, incident response costs and possible suspension of the warning service in the affected area. | L2: Major | M2: The hazard warning function becomes untrustworthy and the operator may have to disable it locally until the source is identified. | N2: Negligible | O2: The forged message carries no personal data of road users. | P2: =IF(AC2>=Reference!$H$2, Reference!$G$2, IF(AC2>=Reference!$H$3, Reference!$G$3, IF(AC2>=Reference!$H$4, Reference!$G$4, IF(AC2>=Reference!$H$5, Reference!$G$5, "")))) -> Severe | Q2: =IF(F2="Physical", "Very Low", IF(F2="Local", "Low", IF(F2="Adjacent", "Medium", IF(F2="Network", "High", "")))) -> High | R2: =IF(AE2>=Reference!$D$2, Reference!$E$2, IF(AE2>=Reference!$D$3, Reference!$E$3, IF(AE2>=Reference!$D$4, Reference!$E$4, IF(AE2>=Reference!$D$5, Reference!$E$5, "")))) -> Critical | S2: Mitigation | T2: Verify IEEE 1609.2 / ETSI TS 103 097 signatures and certificate permissions in the OBU before a warning is displayed; plausibility and misbehaviour detection (position, cause code, event history); revocation of misbehaving certificates. | U2: RSU signing chain, OBU verification stack, PKI trust list, vehicle warning logic (Step 12). | V2: The scenario cannot be avoided, because receiving DENMs is the purpose of the function; mitigation through authentication and misbehaviour detection is the only practical option. | W2: Authenticity, Integrity, Non-repudiation. | X2: =IFERROR(INDEX(Mapping!$F$2:$F$44,MATCH(ROW(),Mapping!$A$2:$A$44,0)),"") -> T115 | Y2: =IF(H2=Reference!$A$12, Reference!$C$12, IF(H2=Reference!$A$11, Reference!$C$11, IF(H2=Reference!$A$10, Reference!$C$10, IF(H2=Reference!$A$9, Reference!$C$9, 0)))) -> 7 | Z2: =IF(J2=Reference!$A$20, Reference!$C$20, IF(J2=Reference!$A$19, Reference!$C$19, IF(J2=Reference!$A$18, Reference!$C$18, IF(J2=Reference!$A$17, Reference!$C$17, 0)))) -> 7 | AA2: =IF(L2=Reference!$A$28, Reference!$C$28, IF(L2=Reference!$A$27, Reference!$C$27, IF(L2=Reference!$A$26, Reference!$C$26, IF(L2=Reference!$A$25, Reference!$C$25, 0)))) -> 7 | AB2: =IF(N2=Reference!$A$36, Reference!$C$36, IF(N2=Reference!$A$35, Reference!$C$35, IF(N2=Reference!$A$34, Reference!$C$34, IF(N2=Reference!$A$33, Reference!$C$33, 0)))) -> 1 | AC2: =(Reference!$B$2*Y2 + Reference!$B$3*AA2 + Reference!$B$4*Z2 + Reference!$B$5 * AB2)/4 -> 11.4375 | AD2: =IF(Q2=Reference!$C$41, Reference!$D$41, IF(Q2=Reference!$C$42, Reference!$D$42, IF(Q2=Reference!$C$43, Reference!$D$43, IF(Q2=Reference!$C$44, Reference!$D$44, 0)))) -> 10 | AE2: =1 + (AC2 * AD2) -> 115.375 | AF2: Forged DENM or rogue RSU broadcast - 6/6 (consensus matrix)
A3: 8 -> 9. Link roadside computing unit to RSU (Ethernet/UDP) | B3: Spoofing | C3: Authenticity | D3: An attacker injects a forged DENM payload into the RSU input port. The RSU signs it with its legitimate key and broadcasts it, so receivers accept the false warning as authentic. | E3: The attacker gains a foothold in the roadside network, for example through the IP camera or an exposed maintenance port, and sends UDP packets to the RSU input port, which accepts any payload it receives. | F3: Adjacent | G3: The attack requires access to the roadside network segment; it cannot be executed from the public network. | H3: Major | I3: The effect equals a rogue RSU broadcast, but the message carries a valid signature, so on-board plausibility checks are the only remaining barrier (S2). | J3: Major | K3: Liability for a provoked collision and forensic effort to establish that the RSU itself was not compromised. | L3: Major | M3: All warnings from this roadside station must be treated as untrusted until the injection path is closed. | N3: Negligible | O3: No personal data is contained in the injected payload. | P3: =IF(AC3>=Reference!$H$2, Reference!$G$2, IF(AC3>=Reference!$H$3, Reference!$G$3, IF(AC3>=Reference!$H$4, Reference!$G$4, IF(AC3>=Reference!$H$5, Reference!$G$5, "")))) -> Severe | Q3: =IF(F3="Physical", "Very Low", IF(F3="Local", "Low", IF(F3="Adjacent", "Medium", IF(F3="Network", "High", "")))) -> Medium | R3: =IF(AE3>=Reference!$D$2, Reference!$E$2, IF(AE3>=Reference!$D$3, Reference!$E$3, IF(AE3>=Reference!$D$4, Reference!$E$4, IF(AE3>=Reference!$D$5, Reference!$E$5, "")))) -> High | S3: Mitigation | T3: Authenticate the source of payloads at the RSU input (mutual TLS or signed internal messages); restrict the port by ACL to the computing unit; segment the roadside LAN; log the origin of every signed payload. | U3: Roadside LAN, RSU input interface, computing unit (Steps 8-9), logging. | V3: The RSU signs whatever it receives, which turns a local network weakness into an authenticated false warning; source authentication removes the root cause. | W3: Authenticity, Integrity, Non-repudiation. | X3: =IFERROR(INDEX(Mapping!$F$2:$F$44,MATCH(ROW(),Mapping!$A$2:$A$44,0)),"") -> T110 | Y3: =IF(H3=Reference!$A$12, Reference!$C$12, IF(H3=Reference!$A$11, Reference!$C$11, IF(H3=Reference!$A$10, Reference!$C$10, IF(H3=Reference!$A$9, Reference!$C$9, 0)))) -> 7 | Z3: =IF(J3=Reference!$A$20, Reference!$C$20, IF(J3=Reference!$A$19, Reference!$C$19, IF(J3=Reference!$A$18, Reference!$C$18, IF(J3=Reference!$A$17, Reference!$C$17, 0)))) -> 7 | AA3: =IF(L3=Reference!$A$28, Reference!$C$28, IF(L3=Reference!$A$27, Reference!$C$27, IF(L3=Reference!$A$26, Reference!$C$26, IF(L3=Reference!$A$25, Reference!$C$25, 0)))) -> 7 | AB3: =IF(N3=Reference!$A$36, Reference!$C$36, IF(N3=Reference!$A$35, Reference!$C$35, IF(N3=Reference!$A$34, Reference!$C$34, IF(N3=Reference!$A$33, Reference!$C$33, 0)))) -> 1 | AC3: =(Reference!$B$2*Y3 + Reference!$B$3*AA3 + Reference!$B$4*Z3 + Reference!$B$5 * AB3)/4 -> 11.4375 | AD3: =IF(Q3=Reference!$C$41, Reference!$D$41, IF(Q3=Reference!$C$42, Reference!$D$42, IF(Q3=Reference!$C$43, Reference!$D$43, IF(Q3=Reference!$C$44, Reference!$D$44, 0)))) -> 7 | AE3: =1 + (AC3 * AD3) -> 81.0625 | AF3: Forged DENM or rogue RSU broadcast - 6/6; this attack path: 4/6 (ChatGPT, Sonnet 5, Opus 5 TS49, Copilot)
A4: 9. RSU (management interface, HSM) | B4: Elevation of privilege | C4: Authorization | D4: An attacker obtains administrative access to the RSU and uses the hardware security module as a signing oracle, producing an unlimited number of valid signed but fabricated DENMs, and can also suppress genuine ones. | E4: Exploitation of weak or default credentials, or of a vulnerability in the RSU management services reachable from the operator network. | F4: Network | G4: The management interface is reachable over the network, so no physical access is required. | H4: Severe | I4: The attacker controls what every vehicle in range is told, including suppression of a real accident warning, which can lead to life-threatening collisions (S3). | J4: Severe | K4: Fleet-wide loss of trust, certificate revocation campaign, regulatory consequences and liability for any resulting accident. | L4: Severe | M4: Complete loss of the warning function at the affected site, with the attacker in control of it. | N4: Moderate | O4: Administrative access exposes communication metadata and certificate information, but no direct personal data of road users. | P4: =IF(AC4>=Reference!$H$2, Reference!$G$2, IF(AC4>=Reference!$H$3, Reference!$G$3, IF(AC4>=Reference!$H$4, Reference!$G$4, IF(AC4>=Reference!$H$5, Reference!$G$5, "")))) -> Severe | Q4: =IF(F4="Physical", "Very Low", IF(F4="Local", "Low", IF(F4="Adjacent", "Medium", IF(F4="Network", "High", "")))) -> High | R4: =IF(AE4>=Reference!$D$2, Reference!$E$2, IF(AE4>=Reference!$D$3, Reference!$E$3, IF(AE4>=Reference!$D$4, Reference!$E$4, IF(AE4>=Reference!$D$5, Reference!$E$5, "")))) -> Critical | S4: Mitigation | T4: Remove default credentials, disable unused management services, restrict management access to a dedicated network, harden and update the firmware, bind HSM signing to authenticated request sources, monitor and log privileged operations. | U4: RSU firmware and management services, HSM key policy, operator network, logging. | V4: The highest-risk row of the theme, because it defeats both the signature check and the plausibility checks; standard hardening measures apply. | W4: Authenticity, Integrity, Availability, Non-repudiation. | X4: =IFERROR(INDEX(Mapping!$F$2:$F$44,MATCH(ROW(),Mapping!$A$2:$A$44,0)),"") -> T116 | Y4: =IF(H4=Reference!$A$12, Reference!$C$12, IF(H4=Reference!$A$11, Reference!$C$11, IF(H4=Reference!$A$10, Reference!$C$10, IF(H4=Reference!$A$9, Reference!$C$9, 0)))) -> 10 | Z4: =IF(J4=Reference!$A$20, Reference!$C$20, IF(J4=Reference!$A$19, Reference!$C$19, IF(J4=Reference!$A$18, Reference!$C$18, IF(J4=Reference!$A$17, Reference!$C$17, 0)))) -> 10 | AA4: =IF(L4=Reference!$A$28, Reference!$C$28, IF(L4=Reference!$A$27, Reference!$C$27, IF(L4=Reference!$A$26, Reference!$C$26, IF(L4=Reference!$A$25, Reference!$C$25, 0)))) -> 10 | AB4: =IF(N4=Reference!$A$36, Reference!$C$36, IF(N4=Reference!$A$35, Reference!$C$35, IF(N4=Reference!$A$34, Reference!$C$34, IF(N4=Reference!$A$33, Reference!$C$33, 0)))) -> 4 | AC4: =(Reference!$B$2*Y4 + Reference!$B$3*AA4 + Reference!$B$4*Z4 + Reference!$B$5 * AB4)/4 -> 16.5 | AD4: =IF(Q4=Reference!$C$41, Reference!$D$41, IF(Q4=Reference!$C$42, Reference!$D$42, IF(Q4=Reference!$C$43, Reference!$D$43, IF(Q4=Reference!$C$44, Reference!$D$44, 0)))) -> 10 | AE4: =1 + (AC4 * AD4) -> 166 | AF4: Forged DENM or rogue RSU broadcast - 6/6; this attack path: 5/6 (ChatGPT, Sonnet 5, Opus 5 TS58, Copilot, DeepSeek)
A5: 0. Security credentials and PKI (central ITS-S) | B5: Spoofing | C5: Authenticity | D5: Certificates are issued to, or stolen for, a rogue station, so its forged DENMs are accepted as genuine by every vehicle that trusts the PKI. | E5: Compromise of the authorization authority or of the operator console at the central ITS-S, or theft of enrolment credentials from a roadside unit. | F5: Network | G5: The PKI services and the operator console are reachable over the network. | H5: Severe | I5: Forged warnings can be produced anywhere in the deployment and are cryptographically valid, so on-board verification cannot reject them (S3). | J5: Severe | K5: Mass revocation and re-enrolment of stations, service interruption and regulatory reporting obligations. | L5: Severe | M5: The trust anchor of the whole C-ITS deployment is lost until certificates are reissued. | N5: Major | O5: Enrolment records and certificate metadata can link stations and vehicles to their operators. | P5: =IF(AC5>=Reference!$H$2, Reference!$G$2, IF(AC5>=Reference!$H$3, Reference!$G$3, IF(AC5>=Reference!$H$4, Reference!$G$4, IF(AC5>=Reference!$H$5, Reference!$G$5, "")))) -> Severe | Q5: =IF(F5="Physical", "Very Low", IF(F5="Local", "Low", IF(F5="Adjacent", "Medium", IF(F5="Network", "High", "")))) -> High | R5: =IF(AE5>=Reference!$D$2, Reference!$E$2, IF(AE5>=Reference!$D$3, Reference!$E$3, IF(AE5>=Reference!$D$4, Reference!$E$4, IF(AE5>=Reference!$D$5, Reference!$E$5, "")))) -> Critical | S5: Mitigation | T5: Protect CA keys in certified HSMs, separate enrolment and authorization authorities, issue short-lived authorization tickets, require multi-person approval and auditing for certificate issuance, monitor issuance anomalies, maintain a revocation process. | U5: Central ITS-S, PKI (enrolment and authorization authorities), trust list in RSU and OBU, credential storage. | V5: Low likelihood but the widest reach of all rows; the controls follow the C-ITS credential management requirements. | W5: Authenticity, Integrity, Non-repudiation. | X5: =IFERROR(INDEX(Mapping!$F$2:$F$44,MATCH(ROW(),Mapping!$A$2:$A$44,0)),"") -> T208 | Y5: =IF(H5=Reference!$A$12, Reference!$C$12, IF(H5=Reference!$A$11, Reference!$C$11, IF(H5=Reference!$A$10, Reference!$C$10, IF(H5=Reference!$A$9, Reference!$C$9, 0)))) -> 10 | Z5: =IF(J5=Reference!$A$20, Reference!$C$20, IF(J5=Reference!$A$19, Reference!$C$19, IF(J5=Reference!$A$18, Reference!$C$18, IF(J5=Reference!$A$17, Reference!$C$17, 0)))) -> 10 | AA5: =IF(L5=Reference!$A$28, Reference!$C$28, IF(L5=Reference!$A$27, Reference!$C$27, IF(L5=Reference!$A$26, Reference!$C$26, IF(L5=Reference!$A$25, Reference!$C$25, 0)))) -> 10 | AB5: =IF(N5=Reference!$A$36, Reference!$C$36, IF(N5=Reference!$A$35, Reference!$C$35, IF(N5=Reference!$A$34, Reference!$C$34, IF(N5=Reference!$A$33, Reference!$C$33, 0)))) -> 7 | AC5: =(Reference!$B$2*Y5 + Reference!$B$3*AA5 + Reference!$B$4*Z5 + Reference!$B$5 * AB5)/4 -> 16.6875 | AD5: =IF(Q5=Reference!$C$41, Reference!$D$41, IF(Q5=Reference!$C$42, Reference!$D$42, IF(Q5=Reference!$C$43, Reference!$D$43, IF(Q5=Reference!$C$44, Reference!$D$44, 0)))) -> 10 | AE5: =1 + (AC5 * AD5) -> 167.875 | AF5: PKI or CA compromise, rogue certificates - 6/6 (consensus matrix)
A6: 9. RSU signing keys (HSM) | B6: Information disclosure | C6: Confidentiality | D6: The private signing key of the RSU is extracted, for example because it is generated or stored outside the security module or through a physical side-channel attack, after which the attacker can sign forged DENMs indefinitely. | E6: Physical access to the pole-mounted RSU or to a decommissioned unit, combined with a misconfiguration that keeps key material outside the FIPS 140-2 level 3 module. | F6: Physical | G6: The attack path requires physical possession of, or direct access to, the roadside unit. | H6: Major | I6: The stolen key enables forged warnings with valid signatures; the effect equals a rogue RSU broadcast and persists until the certificate is revoked (S2). | J6: Major | K6: Revocation and replacement of the unit, investigation costs and liability if forged warnings were issued. | L6: Major | M6: Until revocation, every message signed with this key must be treated as untrusted. | N6: Negligible | O6: The key material itself exposes no personal data of road users. | P6: =IF(AC6>=Reference!$H$2, Reference!$G$2, IF(AC6>=Reference!$H$3, Reference!$G$3, IF(AC6>=Reference!$H$4, Reference!$G$4, IF(AC6>=Reference!$H$5, Reference!$G$5, "")))) -> Severe | Q6: =IF(F6="Physical", "Very Low", IF(F6="Local", "Low", IF(F6="Adjacent", "Medium", IF(F6="Network", "High", "")))) -> Very Low | R6: =IF(AE6>=Reference!$D$2, Reference!$E$2, IF(AE6>=Reference!$D$3, Reference!$E$3, IF(AE6>=Reference!$D$4, Reference!$E$4, IF(AE6>=Reference!$D$5, Reference!$E$5, "")))) -> Low | S6: Mitigation | T6: Generate and keep keys inside the HSM, enable tamper detection and zeroisation, physically secure the cabinet, monitor enclosure opening, revoke certificates as soon as tampering is detected. | U6: RSU hardware, HSM configuration, key management procedures, revocation service. | V6: Feasibility is low because physical access is required, which is why the risk value stays below the network-based rows even though the impact is comparable. | W6: Confidentiality, Authenticity, Integrity. | X6: =IFERROR(INDEX(Mapping!$F$2:$F$44,MATCH(ROW(),Mapping!$A$2:$A$44,0)),"") -> T112 | Y6: =IF(H6=Reference!$A$12, Reference!$C$12, IF(H6=Reference!$A$11, Reference!$C$11, IF(H6=Reference!$A$10, Reference!$C$10, IF(H6=Reference!$A$9, Reference!$C$9, 0)))) -> 7 | Z6: =IF(J6=Reference!$A$20, Reference!$C$20, IF(J6=Reference!$A$19, Reference!$C$19, IF(J6=Reference!$A$18, Reference!$C$18, IF(J6=Reference!$A$17, Reference!$C$17, 0)))) -> 7 | AA6: =IF(L6=Reference!$A$28, Reference!$C$28, IF(L6=Reference!$A$27, Reference!$C$27, IF(L6=Reference!$A$26, Reference!$C$26, IF(L6=Reference!$A$25, Reference!$C$25, 0)))) -> 7 | AB6: =IF(N6=Reference!$A$36, Reference!$C$36, IF(N6=Reference!$A$35, Reference!$C$35, IF(N6=Reference!$A$34, Reference!$C$34, IF(N6=Reference!$A$33, Reference!$C$33, 0)))) -> 1 | AC6: =(Reference!$B$2*Y6 + Reference!$B$3*AA6 + Reference!$B$4*Z6 + Reference!$B$5 * AB6)/4 -> 11.4375 | AD6: =IF(Q6=Reference!$C$41, Reference!$D$41, IF(Q6=Reference!$C$42, Reference!$D$42, IF(Q6=Reference!$C$43, Reference!$D$43, IF(Q6=Reference!$C$44, Reference!$D$44, 0)))) -> 1 | AE6: =1 + (AC6 * AD6) -> 12.4375 | AF6: Signing key or credential theft (HSM, PKI) - 6/6 (consensus matrix)
A7: 9 -> 11. PC5 sidelink (RSU to OBU) | B7: Spoofing | C7: Authenticity | D7: Previously captured, validly signed DENMs are replayed at another time or place, so vehicles warn their drivers about a hazard that no longer exists or that is located elsewhere. | E7: The attacker records DENM broadcasts with a C-V2X receiver and retransmits them later; the attack succeeds when freshness (timestamp) and relevance (position) checks are missing or too permissive. | F7: Network | G7: Recording and retransmission take place over the air, inside the radio coverage area. | H7: Moderate | I7: Unnecessary braking or driver distraction may cause light or moderate injuries (S1); repeated false warnings mainly degrade trust in the system. | J7: Moderate | K7: Costs of investigation and of adding replay protection; limited direct financial loss. | L7: Major | M7: Drivers stop trusting the warnings, which undermines the purpose of the function. | N7: Negligible | O7: No personal data is involved. | P7: =IF(AC7>=Reference!$H$2, Reference!$G$2, IF(AC7>=Reference!$H$3, Reference!$G$3, IF(AC7>=Reference!$H$4, Reference!$G$4, IF(AC7>=Reference!$H$5, Reference!$G$5, "")))) -> Major | Q7: =IF(F7="Physical", "Very Low", IF(F7="Local", "Low", IF(F7="Adjacent", "Medium", IF(F7="Network", "High", "")))) -> High | R7: =IF(AE7>=Reference!$D$2, Reference!$E$2, IF(AE7>=Reference!$D$3, Reference!$E$3, IF(AE7>=Reference!$D$4, Reference!$E$4, IF(AE7>=Reference!$D$5, Reference!$E$5, "")))) -> High | S7: Mitigation | T7: Check the generation time and validity duration of every DENM, apply position relevance checks in the vehicle, reject duplicated action identifiers, detect repeated identical messages. | U7: OBU verification stack, vehicle warning logic (Step 12), DENM management container handling. | V7: Cheap to execute and cheap to mitigate with the freshness and relevance checks already defined in the C-ITS standards. | W7: Authenticity, Integrity, Freshness. | X7: =IFERROR(INDEX(Mapping!$F$2:$F$44,MATCH(ROW(),Mapping!$A$2:$A$44,0)),"") -> T131 | Y7: =IF(H7=Reference!$A$12, Reference!$C$12, IF(H7=Reference!$A$11, Reference!$C$11, IF(H7=Reference!$A$10, Reference!$C$10, IF(H7=Reference!$A$9, Reference!$C$9, 0)))) -> 4 | Z7: =IF(J7=Reference!$A$20, Reference!$C$20, IF(J7=Reference!$A$19, Reference!$C$19, IF(J7=Reference!$A$18, Reference!$C$18, IF(J7=Reference!$A$17, Reference!$C$17, 0)))) -> 4 | AA7: =IF(L7=Reference!$A$28, Reference!$C$28, IF(L7=Reference!$A$27, Reference!$C$27, IF(L7=Reference!$A$26, Reference!$C$26, IF(L7=Reference!$A$25, Reference!$C$25, 0)))) -> 7 | AB7: =IF(N7=Reference!$A$36, Reference!$C$36, IF(N7=Reference!$A$35, Reference!$C$35, IF(N7=Reference!$A$34, Reference!$C$34, IF(N7=Reference!$A$33, Reference!$C$33, 0)))) -> 1 | AC7: =(Reference!$B$2*Y7 + Reference!$B$3*AA7 + Reference!$B$4*Z7 + Reference!$B$5 * AB7)/4 -> 7.3125 | AD7: =IF(Q7=Reference!$C$41, Reference!$D$41, IF(Q7=Reference!$C$42, Reference!$D$42, IF(Q7=Reference!$C$43, Reference!$D$43, IF(Q7=Reference!$C$44, Reference!$D$44, 0)))) -> 10 | AE7: =1 + (AC7 * AD7) -> 74.125 | AF7: DENM replay - 3/6 (consensus matrix)
A8: 12. Vehicle computer (signature verification and warning logic) | B8: Tampering | C8: Integrity | D8: Signature verification or the warning logic in the vehicle is modified so that unsigned or invalid DENMs are accepted, which makes every forged message effective even without stolen credentials. | E8: Physical or local access to the in-vehicle computing unit (debug port, unsigned software update) or compromise of the link between OBU and computer. | F8: Local | G8: The attacker needs direct access to the vehicle or to its internal network; the path is not reachable from the public network. | H8: Major | I8: The vehicle acts on forged warnings without any cryptographic barrier, which can provoke hard braking or wrong manoeuvres (S2). | J8: Moderate | K8: The scope is the individual vehicle rather than the deployment; warranty and liability costs. | L8: Major | M8: The verification function of the vehicle ITS station is lost. | N8: Negligible | O8: No personal data disclosure is involved. | P8: =IF(AC8>=Reference!$H$2, Reference!$G$2, IF(AC8>=Reference!$H$3, Reference!$G$3, IF(AC8>=Reference!$H$4, Reference!$G$4, IF(AC8>=Reference!$H$5, Reference!$G$5, "")))) -> Severe | Q8: =IF(F8="Physical", "Very Low", IF(F8="Local", "Low", IF(F8="Adjacent", "Medium", IF(F8="Network", "High", "")))) -> Low | R8: =IF(AE8>=Reference!$D$2, Reference!$E$2, IF(AE8>=Reference!$D$3, Reference!$E$3, IF(AE8>=Reference!$D$4, Reference!$E$4, IF(AE8>=Reference!$D$5, Reference!$E$5, "")))) -> Medium | S8: Mitigation | T8: Secure boot and signed software updates on the vehicle computer, disable debug interfaces in production, authenticate the link between OBU and computer, report verification failures to the back-end. | U8: OBU, in-vehicle computing unit (Steps 11-12), software update process. | V8: Per-vehicle scope and the local access requirement keep the risk lower, but the control is essential because it is the last line of defence. | W8: Integrity, Authenticity. | X8: =IFERROR(INDEX(Mapping!$F$2:$F$44,MATCH(ROW(),Mapping!$A$2:$A$44,0)),"") -> T164 | Y8: =IF(H8=Reference!$A$12, Reference!$C$12, IF(H8=Reference!$A$11, Reference!$C$11, IF(H8=Reference!$A$10, Reference!$C$10, IF(H8=Reference!$A$9, Reference!$C$9, 0)))) -> 7 | Z8: =IF(J8=Reference!$A$20, Reference!$C$20, IF(J8=Reference!$A$19, Reference!$C$19, IF(J8=Reference!$A$18, Reference!$C$18, IF(J8=Reference!$A$17, Reference!$C$17, 0)))) -> 4 | AA8: =IF(L8=Reference!$A$28, Reference!$C$28, IF(L8=Reference!$A$27, Reference!$C$27, IF(L8=Reference!$A$26, Reference!$C$26, IF(L8=Reference!$A$25, Reference!$C$25, 0)))) -> 7 | AB8: =IF(N8=Reference!$A$36, Reference!$C$36, IF(N8=Reference!$A$35, Reference!$C$35, IF(N8=Reference!$A$34, Reference!$C$34, IF(N8=Reference!$A$33, Reference!$C$33, 0)))) -> 1 | AC8: =(Reference!$B$2*Y8 + Reference!$B$3*AA8 + Reference!$B$4*Z8 + Reference!$B$5 * AB8)/4 -> 11.0625 | AD8: =IF(Q8=Reference!$C$41, Reference!$D$41, IF(Q8=Reference!$C$42, Reference!$D$42, IF(Q8=Reference!$C$43, Reference!$D$43, IF(Q8=Reference!$C$44, Reference!$D$44, 0)))) -> 4 | AE8: =1 + (AC8 * AD8) -> 45.25 | AF8: In-vehicle warning logic or verification tampering - 6/6 (consensus matrix)
A9: 9. RSU event log and signed message records | B9: Repudiation | C9: Non-repudiation | D9: Because the RSU signs every payload it receives without authenticating or logging its origin, a harmful DENM cannot be attributed to the component or operator that produced it, and the operator cannot prove which messages it did or did not issue. | E9: The attacker exploits the missing origin authentication and logging; no capability beyond the injection path of row 3 is required. | F9: Adjacent | G9: The weakness is exploited from inside the roadside network, on the same path as the payload injection. | H9: Negligible | I9: No direct safety effect; the consequence is the inability to investigate an incident afterwards (S0). | J9: Major | K9: Liability cannot be allocated after an incident, which exposes the operator to claims it cannot defend. | L9: Moderate | M9: Incident response and forensics are degraded, but the warning function keeps working. | N9: Negligible | O9: No personal data of road users is affected. | P9: =IF(AC9>=Reference!$H$2, Reference!$G$2, IF(AC9>=Reference!$H$3, Reference!$G$3, IF(AC9>=Reference!$H$4, Reference!$G$4, IF(AC9>=Reference!$H$5, Reference!$G$5, "")))) -> Moderate | Q9: =IF(F9="Physical", "Very Low", IF(F9="Local", "Low", IF(F9="Adjacent", "Medium", IF(F9="Network", "High", "")))) -> Medium | R9: =IF(AE9>=Reference!$D$2, Reference!$E$2, IF(AE9>=Reference!$D$3, Reference!$E$3, IF(AE9>=Reference!$D$4, Reference!$E$4, IF(AE9>=Reference!$D$5, Reference!$E$5, "")))) -> Medium | S9: Mitigation | T9: Log the authenticated origin, the input frame, the model version and the signed payload of every DENM; protect the logs against modification; synchronise time; retain logs according to the operator policy. | U9: RSU logging, computing unit logging (Steps 8-9), time synchronisation, back-end log storage. | V9: Directly linked to the AI part of the system: without this chain, a false warning cannot be traced back to the model output that caused it. | W9: Non-repudiation, Integrity. | X9: =IFERROR(INDEX(Mapping!$F$2:$F$44,MATCH(ROW(),Mapping!$A$2:$A$44,0)),"") -> T117 | Y9: =IF(H9=Reference!$A$12, Reference!$C$12, IF(H9=Reference!$A$11, Reference!$C$11, IF(H9=Reference!$A$10, Reference!$C$10, IF(H9=Reference!$A$9, Reference!$C$9, 0)))) -> 1 | Z9: =IF(J9=Reference!$A$20, Reference!$C$20, IF(J9=Reference!$A$19, Reference!$C$19, IF(J9=Reference!$A$18, Reference!$C$18, IF(J9=Reference!$A$17, Reference!$C$17, 0)))) -> 7 | AA9: =IF(L9=Reference!$A$28, Reference!$C$28, IF(L9=Reference!$A$27, Reference!$C$27, IF(L9=Reference!$A$26, Reference!$C$26, IF(L9=Reference!$A$25, Reference!$C$25, 0)))) -> 4 | AB9: =IF(N9=Reference!$A$36, Reference!$C$36, IF(N9=Reference!$A$35, Reference!$C$35, IF(N9=Reference!$A$34, Reference!$C$34, IF(N9=Reference!$A$33, Reference!$C$33, 0)))) -> 1 | AC9: =(Reference!$B$2*Y9 + Reference!$B$3*AA9 + Reference!$B$4*Z9 + Reference!$B$5 * AB9)/4 -> 3.1875 | AD9: =IF(Q9=Reference!$C$41, Reference!$D$41, IF(Q9=Reference!$C$42, Reference!$D$42, IF(Q9=Reference!$C$43, Reference!$D$43, IF(Q9=Reference!$C$44, Reference!$D$44, 0)))) -> 7 | AE9: =1 + (AC9 * AD9) -> 23.3125 | AF9: Missing audit trail, RSU side - 6/6 (consensus matrix)
A10: 1 -> 2. Video link cameras to computing unit | B10: Spoofing | C10: Authenticity | D10: A forged or previously recorded video stream is fed into the detection pipeline, so the system reports an accident that does not exist and broadcasts a DENM for it; the same path can replay footage of an empty road to hide a real accident. | E10: The attacker reaches the camera link on the roadside network, for example through the camera management interface or a network tap, and replaces the stream sent to the computing unit. | F10: Adjacent | G10: The camera stream travels on the roadside network segment; the attacker needs a foothold there, not physical access to the optics. | H10: Major | I10: A fabricated accident triggers unnecessary emergency braking; a suppressed real accident removes the warning that should prevent a secondary collision (S2). | J10: Moderate | K10: Investigation and remediation costs; liability only if a collision follows. | L10: Major | M10: The perception input of the whole chain is untrusted, so every warning from this station must be questioned. | N10: Negligible | O10: The injected stream itself contains no personal data of real road users. | P10: =IF(AC10>=Reference!$H$2, Reference!$G$2, IF(AC10>=Reference!$H$3, Reference!$G$3, IF(AC10>=Reference!$H$4, Reference!$G$4, IF(AC10>=Reference!$H$5, Reference!$G$5, "")))) -> Severe | Q10: =IF(F10="Physical", "Very Low", IF(F10="Local", "Low", IF(F10="Adjacent", "Medium", IF(F10="Network", "High", "")))) -> Medium | R10: =IF(AE10>=Reference!$D$2, Reference!$E$2, IF(AE10>=Reference!$D$3, Reference!$E$3, IF(AE10>=Reference!$D$4, Reference!$E$4, IF(AE10>=Reference!$D$5, Reference!$E$5, "")))) -> High | S10: Mitigation | T10: Authenticate and encrypt the camera stream (for example RTSP over TLS with client certificates), segment the camera VLAN, monitor stream continuity and timestamps, detect frozen or repeated frames. | U10: Cameras, roadside network, computing unit input stage (Steps 1-2). | V10: The detection chain trusts its sensor input implicitly; without stream authentication every downstream control can be bypassed at the source. | W10: Authenticity, Integrity. | X10: =IFERROR(INDEX(Mapping!$F$2:$F$44,MATCH(ROW(),Mapping!$A$2:$A$44,0)),"") -> T011 | Y10: =IF(H10=Reference!$A$12, Reference!$C$12, IF(H10=Reference!$A$11, Reference!$C$11, IF(H10=Reference!$A$10, Reference!$C$10, IF(H10=Reference!$A$9, Reference!$C$9, 0)))) -> 7 | Z10: =IF(J10=Reference!$A$20, Reference!$C$20, IF(J10=Reference!$A$19, Reference!$C$19, IF(J10=Reference!$A$18, Reference!$C$18, IF(J10=Reference!$A$17, Reference!$C$17, 0)))) -> 4 | AA10: =IF(L10=Reference!$A$28, Reference!$C$28, IF(L10=Reference!$A$27, Reference!$C$27, IF(L10=Reference!$A$26, Reference!$C$26, IF(L10=Reference!$A$25, Reference!$C$25, 0)))) -> 7 | AB10: =IF(N10=Reference!$A$36, Reference!$C$36, IF(N10=Reference!$A$35, Reference!$C$35, IF(N10=Reference!$A$34, Reference!$C$34, IF(N10=Reference!$A$33, Reference!$C$33, 0)))) -> 1 | AC10: =(Reference!$B$2*Y10 + Reference!$B$3*AA10 + Reference!$B$4*Z10 + Reference!$B$5 * AB10)/4 -> 11.0625 | AD10: =IF(Q10=Reference!$C$41, Reference!$D$41, IF(Q10=Reference!$C$42, Reference!$D$42, IF(Q10=Reference!$C$43, Reference!$D$43, IF(Q10=Reference!$C$44, Reference!$D$44, 0)))) -> 7 | AE10: =1 + (AC10 * AD10) -> 78.4375 | AF10: Camera feed injection or replay - 6/6 (consensus matrix); keyword cross-check 6/6
A11: 2. Edge detector, YOLOv5 (perception input) | B11: Spoofing | C11: Authenticity | D11: Adversarial patterns placed in the scene (printed patches on vehicles, clothing or signs) make the detector report objects that are not there, or hide real ones, so a false DENM is generated or a real accident is never forwarded to the agents. | E11: The attacker prints and places a physical pattern in the camera field of view; no access to the system is required. | F11: Physical | G11: The attack is carried out in the physical environment of the camera. Note: the attack vector scale of this TARA maps such attacks to 'Physical' (lowest feasibility) although they need no access to the system, so the resulting risk value is likely to be understated. | H11: Major | I11: A fabricated or suppressed detection has the same safety effect as a forged warning, but is limited to the field of view of one camera (S2). | J11: Moderate | K11: Limited direct loss; cost of retraining or hardening the detector. | L11: Major | M11: The reliability of the perception layer is degraded for as long as the pattern is in place. | N11: Negligible | O11: No personal data is involved. | P11: =IF(AC11>=Reference!$H$2, Reference!$G$2, IF(AC11>=Reference!$H$3, Reference!$G$3, IF(AC11>=Reference!$H$4, Reference!$G$4, IF(AC11>=Reference!$H$5, Reference!$G$5, "")))) -> Severe | Q11: =IF(F11="Physical", "Very Low", IF(F11="Local", "Low", IF(F11="Adjacent", "Medium", IF(F11="Network", "High", "")))) -> Very Low | R11: =IF(AE11>=Reference!$D$2, Reference!$E$2, IF(AE11>=Reference!$D$3, Reference!$E$3, IF(AE11>=Reference!$D$4, Reference!$E$4, IF(AE11>=Reference!$D$5, Reference!$E$5, "")))) -> Low | S11: Mitigation | T11: Cross-check the YOLOv5 detection with the MLLM verdict and with the stereo depth, use adversarial training or input filtering, apply temporal consistency checks across frames, alert on implausible detection patterns. | U11: YOLOv5 model, MLLM verification step, computing unit (Steps 2-4). | V11: Purely AI-specific threat with no counterpart in the classic V2X catalogue; the two-stage detection (fast path plus MLLM) is itself a mitigation. | W11: Integrity, Authenticity. | X11: =IFERROR(INDEX(Mapping!$F$2:$F$44,MATCH(ROW(),Mapping!$A$2:$A$44,0)),"") -> T016 | Y11: =IF(H11=Reference!$A$12, Reference!$C$12, IF(H11=Reference!$A$11, Reference!$C$11, IF(H11=Reference!$A$10, Reference!$C$10, IF(H11=Reference!$A$9, Reference!$C$9, 0)))) -> 7 | Z11: =IF(J11=Reference!$A$20, Reference!$C$20, IF(J11=Reference!$A$19, Reference!$C$19, IF(J11=Reference!$A$18, Reference!$C$18, IF(J11=Reference!$A$17, Reference!$C$17, 0)))) -> 4 | AA11: =IF(L11=Reference!$A$28, Reference!$C$28, IF(L11=Reference!$A$27, Reference!$C$27, IF(L11=Reference!$A$26, Reference!$C$26, IF(L11=Reference!$A$25, Reference!$C$25, 0)))) -> 7 | AB11: =IF(N11=Reference!$A$36, Reference!$C$36, IF(N11=Reference!$A$35, Reference!$C$35, IF(N11=Reference!$A$34, Reference!$C$34, IF(N11=Reference!$A$33, Reference!$C$33, 0)))) -> 1 | AC11: =(Reference!$B$2*Y11 + Reference!$B$3*AA11 + Reference!$B$4*Z11 + Reference!$B$5 * AB11)/4 -> 11.0625 | AD11: =IF(Q11=Reference!$C$41, Reference!$D$41, IF(Q11=Reference!$C$42, Reference!$D$42, IF(Q11=Reference!$C$43, Reference!$D$43, IF(Q11=Reference!$C$44, Reference!$D$44, 0)))) -> 1 | AE11: =1 + (AC11 * AD11) -> 12.0625 | AF11: Adversarial examples against perception models - 6/6 (consensus matrix); keyword cross-check 6/6
A12: 3. Situation detection agent (prompt and image input) | B12: Spoofing | C12: Authenticity | D12: Text visible in the camera image (a sign, sticker or vehicle wrap) is interpreted by the multimodal model as an instruction, so the agent reports an incident that does not exist or fills the DENM with attacker-chosen values such as a wrong cause code or closed lanes. | E12: The attacker places readable text in the field of view; the prompt and the image are concatenated in the same model request, so the model cannot separate data from instructions. | F12: Physical | G12: As for adversarial patterns, the attacker acts in the physical environment. The same reservation about the attack vector scale applies. | H12: Major | I12: A fabricated hazard or a manipulated speed limit and lane status can provoke hard braking or wrong manoeuvres (S2). | J12: Moderate | K12: Costs of investigation and of hardening the prompt handling; liability only if a collision follows. | L12: Major | M12: The message generation step can no longer be trusted to describe the real situation. | N12: Negligible | O12: No personal data is involved. | P12: =IF(AC12>=Reference!$H$2, Reference!$G$2, IF(AC12>=Reference!$H$3, Reference!$G$3, IF(AC12>=Reference!$H$4, Reference!$G$4, IF(AC12>=Reference!$H$5, Reference!$G$5, "")))) -> Severe | Q12: =IF(F12="Physical", "Very Low", IF(F12="Local", "Low", IF(F12="Adjacent", "Medium", IF(F12="Network", "High", "")))) -> Very Low | R12: =IF(AE12>=Reference!$D$2, Reference!$E$2, IF(AE12>=Reference!$D$3, Reference!$E$3, IF(AE12>=Reference!$D$4, Reference!$E$4, IF(AE12>=Reference!$D$5, Reference!$E$5, "")))) -> Low | S12: Mitigation | T12: Separate instructions from image content, constrain the output to a schema with allowed values, validate every DENM field against plausibility rules before encoding, cross-check the situation type against the YOLOv5 detection, log prompt and response. | U12: Situation detection agent, message generation agent, DENM encoder (Steps 3-8). | V12: Specific to the use of language models in the detection chain; schema validation before signing is the decisive control. The same weakness applies to the message generation agent (Step 6). | W12: Integrity, Authenticity. | X12: =IFERROR(INDEX(Mapping!$F$2:$F$44,MATCH(ROW(),Mapping!$A$2:$A$44,0)),"") -> T031 | Y12: =IF(H12=Reference!$A$12, Reference!$C$12, IF(H12=Reference!$A$11, Reference!$C$11, IF(H12=Reference!$A$10, Reference!$C$10, IF(H12=Reference!$A$9, Reference!$C$9, 0)))) -> 7 | Z12: =IF(J12=Reference!$A$20, Reference!$C$20, IF(J12=Reference!$A$19, Reference!$C$19, IF(J12=Reference!$A$18, Reference!$C$18, IF(J12=Reference!$A$17, Reference!$C$17, 0)))) -> 4 | AA12: =IF(L12=Reference!$A$28, Reference!$C$28, IF(L12=Reference!$A$27, Reference!$C$27, IF(L12=Reference!$A$26, Reference!$C$26, IF(L12=Reference!$A$25, Reference!$C$25, 0)))) -> 7 | AB12: =IF(N12=Reference!$A$36, Reference!$C$36, IF(N12=Reference!$A$35, Reference!$C$35, IF(N12=Reference!$A$34, Reference!$C$34, IF(N12=Reference!$A$33, Reference!$C$33, 0)))) -> 1 | AC12: =(Reference!$B$2*Y12 + Reference!$B$3*AA12 + Reference!$B$4*Z12 + Reference!$B$5 * AB12)/4 -> 11.0625 | AD12: =IF(Q12=Reference!$C$41, Reference!$D$41, IF(Q12=Reference!$C$42, Reference!$D$42, IF(Q12=Reference!$C$43, Reference!$D$43, IF(Q12=Reference!$C$44, Reference!$D$44, 0)))) -> 1 | AE12: =1 + (AC12 * AD12) -> 12.0625 | AF12: Prompt injection against MLLM agents - 5/6 (consensus matrix); keyword cross-check 5/6
A13: 3-7. Link computing unit to Gemini API (5G Uu) | B13: Spoofing | C13: Authenticity | D13: An attacker impersonates the cloud model endpoint, or intercepts the session, and returns forged detection verdicts and DENM parameters, so the roadside station generates warnings that the model never produced. | E13: DNS manipulation on the roadside network, a compromised proxy or gateway, a rogue base station, or a client that does not validate the server certificate. | F13: Network | G13: The request path crosses the public network; the attacker does not need access to the roadside station itself. | H13: Major | I13: The attacker controls the content of the warnings generated by the station, which can provoke hard braking or mask a real hazard (S2). | J13: Major | K13: Liability after a provoked collision and the cost of interrupting the service until the path is secured. | L13: Major | M13: Every warning generated while the session is intercepted is unreliable. | N13: Major | O13: The same position also exposes the transmitted camera images, which contain faces and licence plates. | P13: =IF(AC13>=Reference!$H$2, Reference!$G$2, IF(AC13>=Reference!$H$3, Reference!$G$3, IF(AC13>=Reference!$H$4, Reference!$G$4, IF(AC13>=Reference!$H$5, Reference!$G$5, "")))) -> Severe | Q13: =IF(F13="Physical", "Very Low", IF(F13="Local", "Low", IF(F13="Adjacent", "Medium", IF(F13="Network", "High", "")))) -> High | R13: =IF(AE13>=Reference!$D$2, Reference!$E$2, IF(AE13>=Reference!$D$3, Reference!$E$3, IF(AE13>=Reference!$D$4, Reference!$E$4, IF(AE13>=Reference!$D$5, Reference!$E$5, "")))) -> Critical | S13: Mitigation | T13: Enforce TLS with certificate pinning and validation, use a dedicated APN or VPN for the roadside station, resolve the endpoint through a trusted resolver, monitor for certificate changes, validate model responses against a schema. | U13: Computing unit network stack, 5G modem and subscription, cloud endpoint configuration (Steps 3-7). | V13: The cloud dependency introduced by the MLLM turns a transport weakness into control over the safety message content. | W13: Authenticity, Integrity, Confidentiality. | X13: =IFERROR(INDEX(Mapping!$F$2:$F$44,MATCH(ROW(),Mapping!$A$2:$A$44,0)),"") -> T190 | Y13: =IF(H13=Reference!$A$12, Reference!$C$12, IF(H13=Reference!$A$11, Reference!$C$11, IF(H13=Reference!$A$10, Reference!$C$10, IF(H13=Reference!$A$9, Reference!$C$9, 0)))) -> 7 | Z13: =IF(J13=Reference!$A$20, Reference!$C$20, IF(J13=Reference!$A$19, Reference!$C$19, IF(J13=Reference!$A$18, Reference!$C$18, IF(J13=Reference!$A$17, Reference!$C$17, 0)))) -> 7 | AA13: =IF(L13=Reference!$A$28, Reference!$C$28, IF(L13=Reference!$A$27, Reference!$C$27, IF(L13=Reference!$A$26, Reference!$C$26, IF(L13=Reference!$A$25, Reference!$C$25, 0)))) -> 7 | AB13: =IF(N13=Reference!$A$36, Reference!$C$36, IF(N13=Reference!$A$35, Reference!$C$35, IF(N13=Reference!$A$34, Reference!$C$34, IF(N13=Reference!$A$33, Reference!$C$33, 0)))) -> 7 | AC13: =(Reference!$B$2*Y13 + Reference!$B$3*AA13 + Reference!$B$4*Z13 + Reference!$B$5 * AB13)/4 -> 11.8125 | AD13: =IF(Q13=Reference!$C$41, Reference!$D$41, IF(Q13=Reference!$C$42, Reference!$D$42, IF(Q13=Reference!$C$43, Reference!$D$43, IF(Q13=Reference!$C$44, Reference!$D$44, 0)))) -> 10 | AE13: =1 + (AC13 * AD13) -> 119.125 | AF13: Cloud MLLM endpoint spoofing or MitM - 6/6 (consensus matrix); keyword cross-check 4/6 - verify
... A44: 11 -> 12. Link OBU to vehicle computer (Ethernet/UDP) | B44: Tampering | C44: Integrity | D44: Messages forwarded from the on-board unit to the vehicle computer are modified or injected on the internal link, which goes undetected when only the OBU verifies signatures. | E44: A device connected to the in-vehicle network, or a compromised component on the same bus. | F44: Local | G44: Access to the internal network of the vehicle is required. | H44: Major | I44: The vehicle computer acts on content that no longer corresponds to any verified message (S2). | J44: Moderate | K44: Field campaign and investigation for the affected vehicles. | L44: Major | M44: The verification performed by the OBU loses its value. | N44: Negligible | O44: No personal data is affected. | P44: =IF(AC44>=Reference!$H$2, Reference!$G$2, IF(AC44>=Reference!$H$3, Reference!$G$3, IF(AC44>=Reference!$H$4, Reference!$G$4, IF(AC44>=Reference!$H$5, Reference!$G$5, "")))) -> Severe | Q44: =IF(F44="Physical", "Very Low", IF(F44="Local", "Low", IF(F44="Adjacent", "Medium", IF(F44="Network", "High", "")))) -> Low | R44: =IF(AE44>=Reference!$D$2, Reference!$E$2, IF(AE44>=Reference!$D$3, Reference!$E$3, IF(AE44>=Reference!$D$4, Reference!$E$4, IF(AE44>=Reference!$D$5, Reference!$E$5, "")))) -> Medium | S44: Mitigation | T44: Authenticate the internal link, pass the verification result together with the message, verify signatures in the vehicle computer as well, restrict which devices may reach the port. | U44: OBU output interface, in-vehicle network, vehicle computer input (Steps 11-12). | V44: Shows why the trust boundary must be drawn behind the verification step, not in front of it. | W44: Integrity, Authenticity. | X44: =IFERROR(INDEX(Mapping!$F$2:$F$44,MATCH(ROW(),Mapping!$A$2:$A$44,0)),"") -> T158 | Y44: =IF(H44=Reference!$A$12, Reference!$C$12, IF(H44=Reference!$A$11, Reference!$C$11, IF(H44=Reference!$A$10, Reference!$C$10, IF(H44=Reference!$A$9, Reference!$C$9, 0)))) -> 7 | Z44: =IF(J44=Reference!$A$20, Reference!$C$20, IF(J44=Reference!$A$19, Reference!$C$19, IF(J44=Reference!$A$18, Reference!$C$18, IF(J44=Reference!$A$17, Reference!$C$17, 0)))) -> 4 | AA44: =IF(L44=Reference!$A$28, Reference!$C$28, IF(L44=Reference!$A$27, Reference!$C$27, IF(L44=Reference!$A$26, Reference!$C$26, IF(L44=Reference!$A$25, Reference!$C$25, 0)))) -> 7 | AB44: =IF(N44=Reference!$A$36, Reference!$C$36, IF(N44=Reference!$A$35, Reference!$C$35, IF(N44=Reference!$A$34, Reference!$C$34, IF(N44=Reference!$A$33, Reference!$C$33, 0)))) -> 1 | AC44: =(Reference!$B$2*Y44 + Reference!$B$3*AA44 + Reference!$B$4*Z44 + Reference!$B$5 * AB44)/4 -> 11.0625 | AD44: =IF(Q44=Reference!$C$41, Reference!$D$41, IF(Q44=Reference!$C$42, Reference!$D$42, IF(Q44=Reference!$C$43, Reference!$D$43, IF(Q44=Reference!$C$44, Reference!$D$44, 0)))) -> 4 | AE44: =1 + (AC44 * AD44) -> 45.25 | AF44: In-vehicle link manipulation - keyword scan 1/6 of the model outputs; check against the consensus matrix

Sheet Rare findings (1-2 models)
A1: Asset | B1: Threat type | C1: Security Attribute | D1: Damage Scenario | E1: Attack Path | F1: Attack vector | G1: Attack Vector Note / Motiv | H1: Safety Impact | I1: Safety Note / Motiv | J1: Financial Impact | K1: Financial Note / Motiv | L1: Operational Impact | M1: Operational Note / Motiv | N1: Privacy and Legislative Impact | O1: Privacy Note / Motiv | P1: Severity Level | Q1: Feasibility Level | R1: Risk Value | S1: Treatment Options | T1: Measures | U1: Affected Design Elements | V1: Justification (Treatment) | W1: Cybersecurity Goals | X1: Medini threat ID | Y1: s | Z1: f | AA1: o | AB1: p | AC1: impact | AD1: feasibility val | AE1: Risk score | AF1: Found by (models) | AG1: Model wording (as generated)
A2: 1. Cameras (firmware and management interface) | B2: Elevation of privilege | C2: Authorization | D2: Default credentials or a firmware vulnerability on the infrastructure camera give an attacker administrative access to the device and a foothold on the roadside network, from which the computing unit and the RSU can be attacked. | E2: Scan of the roadside network, login with default credentials or exploitation of an unpatched camera firmware. | F2: Adjacent | G2: The camera and its management interface are reachable from the roadside network segment. | H2: Major | I2: The foothold enables manipulation of the detection chain, so warnings can be fabricated or suppressed (S2). | J2: Major | K2: Replacement or reflashing of devices and a full review of the roadside network. | L2: Severe | M2: Every component behind the camera must be treated as potentially compromised. | N2: Severe | O2: Administrative access to the camera exposes live and stored images of identifiable road users. | P2: =IF(AC2>=Reference!$H$2, Reference!$G$2, IF(AC2>=Reference!$H$3, Reference!$G$3, IF(AC2>=Reference!$H$4, Reference!$G$4, IF(AC2>=Reference!$H$5, Reference!$G$5, "")))) -> Severe | Q2: =IF(F2="Physical", "Very Low", IF(F2="Local", "Low", IF(F2="Adjacent", "Medium", IF(F2="Network", "High", "")))) -> Medium | R2: =IF(AE2>=Reference!$D$2, Reference!$E$2, IF(AE2>=Reference!$D$3, Reference!$E$3, IF(AE2>=Reference!$D$4, Reference!$E$4, IF(AE2>=Reference!$D$5, Reference!$E$5, "")))) -> High | S2: Mitigation | T2: Change default credentials, keep camera firmware patched, place cameras in an isolated VLAN with no route to the computing unit management plane, monitor logins and firmware versions. | U2: Camera firmware and management interface, roadside network segmentation (Step 1). | V2: Classic infrastructure weakness that the AI models mostly overlooked, although it is the cheapest entry point into the whole station. | W2: Authorization, Confidentiality, Integrity. | X2: T005 | Y2: =IF(H2=Reference!$A$12, Reference!$C$12, IF(H2=Reference!$A$11, Reference!$C$11, IF(H2=Reference!$A$10, Reference!$C$10, IF(H2=Reference!$A$9, Reference!$C$9, 0)))) -> 7 | Z2: =IF(J2=Reference!$A$20, Reference!$C$20, IF(J2=Reference!$A$19, Reference!$C$19, IF(J2=Reference!$A$18, Reference!$C$18, IF(J2=Reference!$A$17, Reference!$C$17, 0)))) -> 7 | AA2: =IF(L2=Reference!$A$28, Reference!$C$28, IF(L2=Reference!$A$27, Reference!$C$27, IF(L2=Reference!$A$26, Reference!$C$26, IF(L2=Reference!$A$25, Reference!$C$25, 0)))) -> 10 | AB2: =IF(N2=Reference!$A$36, Reference!$C$36, IF(N2=Reference!$A$35, Reference!$C$35, IF(N2=Reference!$A$34, Reference!$C$34, IF(N2=Reference!$A$33, Reference!$C$33, 0)))) -> 10 | AC2: =(Reference!$B$2*Y2 + Reference!$B$3*AA2 + Reference!$B$4*Z2 + Reference!$B$5 * AB2)/4 -> 12.75 | AD2: =IF(Q2=Reference!$C$41, Reference!$D$41, IF(Q2=Reference!$C$42, Reference!$D$42, IF(Q2=Reference!$C$43, Reference!$D$43, IF(Q2=Reference!$C$44, Reference!$D$44, 0)))) -> 7 | AE2: =1 + (AC2 * AD2) -> 90.25 | AF2: 2 of 6: Claude Opus 5, Copilot | AG2: Claude: default credentials or vulnerable firmware on the IP infrastructure camera are exploited to gain a foothold on the roadside network. Copilot: exploitation of camera firmware vulnerabilities grants administrative access to the roadside network.
A3: 1. Cameras (origin of the footage) | B3: Repudiation | C3: Accountability | D3: Nothing proves that a stored or transmitted frame really came from the genuine camera, so after an incident it cannot be shown whether the footage behind a warning was authentic or injected. | E3: The weakness exists by design; an attacker who injects frames benefits from the absence of evidence. | F3: Adjacent | G3: Frames are injected or replaced on the roadside network, where the evidence would also have to be collected. | H3: Negligible | I3: No direct safety effect (S0). | J3: Moderate | K3: An investigation cannot establish whether the system or an attacker produced a wrong warning. | L3: Moderate | M3: Incident analysis is impaired; operation continues. | N3: Negligible | O3: Evidence should reference frames rather than store them, to respect the privacy rows. | P3: =IF(AC3>=Reference!$H$2, Reference!$G$2, IF(AC3>=Reference!$H$3, Reference!$G$3, IF(AC3>=Reference!$H$4, Reference!$G$4, IF(AC3>=Reference!$H$5, Reference!$G$5, "")))) -> Moderate | Q3: =IF(F3="Physical", "Very Low", IF(F3="Local", "Low", IF(F3="Adjacent", "Medium", IF(F3="Network", "High", "")))) -> Medium | R3: =IF(AE3>=Reference!$D$2, Reference!$E$2, IF(AE3>=Reference!$D$3, Reference!$E$3, IF(AE3>=Reference!$D$4, Reference!$E$4, IF(AE3>=Reference!$D$5, Reference!$E$5, "")))) -> Medium | S3: Mitigation | T3: Sign or hash frames at the camera where supported, record stream identifiers and continuity counters, keep the hash of the frame that triggered each warning, protect the records. | U3: Camera, video link, computing unit logging (Steps 1-2). | V3: Completes the traceability chain at its first stage: without it, every later record starts from unverified input. | W3: Accountability, Authenticity. | X3: T006 | Y3: =IF(H3=Reference!$A$12, Reference!$C$12, IF(H3=Reference!$A$11, Reference!$C$11, IF(H3=Reference!$A$10, Reference!$C$10, IF(H3=Reference!$A$9, Reference!$C$9, 0)))) -> 1 | Z3: =IF(J3=Reference!$A$20, Reference!$C$20, IF(J3=Reference!$A$19, Reference!$C$19, IF(J3=Reference!$A$18, Reference!$C$18, IF(J3=Reference!$A$17, Reference!$C$17, 0)))) -> 4 | AA3: =IF(L3=Reference!$A$28, Reference!$C$28, IF(L3=Reference!$A$27, Reference!$C$27, IF(L3=Reference!$A$26, Reference!$C$26, IF(L3=Reference!$A$25, Reference!$C$25, 0)))) -> 4 | AB3: =IF(N3=Reference!$A$36, Reference!$C$36, IF(N3=Reference!$A$35, Reference!$C$35, IF(N3=Reference!$A$34, Reference!$C$34, IF(N3=Reference!$A$33, Reference!$C$33, 0)))) -> 1 | AC3: =(Reference!$B$2*Y3 + Reference!$B$3*AA3 + Reference!$B$4*Z3 + Reference!$B$5 * AB3)/4 -> 2.8125 | AD3: =IF(Q3=Reference!$C$41, Reference!$D$41, IF(Q3=Reference!$C$42, Reference!$D$42, IF(Q3=Reference!$C$43, Reference!$D$43, IF(Q3=Reference!$C$44, Reference!$D$44, 0)))) -> 7 | AE3: =1 + (AC3 * AD3) -> 20.6875 | AF3: 1 of 6: Copilot | AG3: Copilot: no audit trail exists to prove whether captured footage originated from the genuine camera.
A4: 3. Situation detection agent (decision records) | B4: Repudiation | C4: Accountability | D4: The prompt, the model version, the input frame and the response behind each detection decision are not recorded, so a false or missed detection cannot be attributed to the model, to the input or to an attacker. | E4: No attack is required; an attacker who manipulates the input benefits from the missing records. | F4: Network | G4: The decision spans the roadside unit and the cloud service, so evidence would have to be collected across the network path. | H4: Negligible | I4: No direct safety effect (S0). | J4: Major | K4: Liability between operator, model provider and vehicle cannot be allocated after an incident. | L4: Moderate | M4: Analysis and improvement of the detection quality are both impaired. | N4: Negligible | O4: Records should hold references, not copies of the images. | P4: =IF(AC4>=Reference!$H$2, Reference!$G$2, IF(AC4>=Reference!$H$3, Reference!$G$3, IF(AC4>=Reference!$H$4, Reference!$G$4, IF(AC4>=Reference!$H$5, Reference!$G$5, "")))) -> Moderate | Q4: =IF(F4="Physical", "Very Low", IF(F4="Local", "Low", IF(F4="Adjacent", "Medium", IF(F4="Network", "High", "")))) -> High | R4: =IF(AE4>=Reference!$D$2, Reference!$E$2, IF(AE4>=Reference!$D$3, Reference!$E$3, IF(AE4>=Reference!$D$4, Reference!$E$4, IF(AE4>=Reference!$D$5, Reference!$E$5, "")))) -> Medium | S4: Mitigation | T4: Log prompt version, model name and version, input frame reference and raw response for every decision; protect the log and synchronise time. | U4: Agent orchestration, cloud interface, log storage (Steps 3-4). | V4: Only two models raised it, yet it is the record that makes any later dispute about an AI decision decidable. | W4: Accountability, Non-repudiation. | X4: T033 | Y4: =IF(H4=Reference!$A$12, Reference!$C$12, IF(H4=Reference!$A$11, Reference!$C$11, IF(H4=Reference!$A$10, Reference!$C$10, IF(H4=Reference!$A$9, Reference!$C$9, 0)))) -> 1 | Z4: =IF(J4=Reference!$A$20, Reference!$C$20, IF(J4=Reference!$A$19, Reference!$C$19, IF(J4=Reference!$A$18, Reference!$C$18, IF(J4=Reference!$A$17, Reference!$C$17, 0)))) -> 7 | AA4: =IF(L4=Reference!$A$28, Reference!$C$28, IF(L4=Reference!$A$27, Reference!$C$27, IF(L4=Reference!$A$26, Reference!$C$26, IF(L4=Reference!$A$25, Reference!$C$25, 0)))) -> 4 | AB4: =IF(N4=Reference!$A$36, Reference!$C$36, IF(N4=Reference!$A$35, Reference!$C$35, IF(N4=Reference!$A$34, Reference!$C$34, IF(N4=Reference!$A$33, Reference!$C$33, 0)))) -> 1 | AC4: =(Reference!$B$2*Y4 + Reference!$B$3*AA4 + Reference!$B$4*Z4 + Reference!$B$5 * AB4)/4 -> 3.1875 | AD4: =IF(Q4=Reference!$C$41, Reference!$D$41, IF(Q4=Reference!$C$42, Reference!$D$42, IF(Q4=Reference!$C$43, Reference!$D$43, IF(Q4=Reference!$C$44, Reference!$D$44, 0)))) -> 10 | AE4: =1 + (AC4 * AD4) -> 32.875 | AF4: 2 of 6: Claude Opus 5, Copilot | AG4: Claude: the prompt, model version, input frame and response behind each detection decision are not logged. Copilot: agent decisions cannot be traced back to specific prompts, responses, or model versions.
A5: 5. Distance estimate agent (sensor input) | B5: Spoofing | C5: Authenticity | D5: Manipulated stereo or depth input makes the agent compute a false distance to a vehicle or pedestrian, so the hazard is placed at a wrong point of the road in the warning message. | E5: Projected patterns, reflective surfaces or a manipulated stereo stream presented to the camera. | F5: Physical | G5: The manipulation happens in the physical environment of the camera; the scale maps this to the lowest feasibility even though no system access is needed. | H5: Major | I5: Vehicles are warned about a hazard at the wrong distance, so they brake in the wrong place or not at all (S2). | J5: Moderate | K5: Investigation and hardening of the distance estimation. | L5: Major | M5: The position field of every affected message is unreliable. | N5: Negligible | O5: No personal data is affected. | P5: =IF(AC5>=Reference!$H$2, Reference!$G$2, IF(AC5>=Reference!$H$3, Reference!$G$3, IF(AC5>=Reference!$H$4, Reference!$G$4, IF(AC5>=Reference!$H$5, Reference!$G$5, "")))) -> Severe | Q5: =IF(F5="Physical", "Very Low", IF(F5="Local", "Low", IF(F5="Adjacent", "Medium", IF(F5="Network", "High", "")))) -> Very Low | R5: =IF(AE5>=Reference!$D$2, Reference!$E$2, IF(AE5>=Reference!$D$3, Reference!$E$3, IF(AE5>=Reference!$D$4, Reference!$E$4, IF(AE5>=Reference!$D$5, Reference!$E$5, "")))) -> Low | S5: Mitigation | T5: Compare the monocular estimate with the stereo depth, apply plausibility limits from the camera geometry, reject events outside the monitored road section. | U5: Distance estimate agent, stereo camera, camera geometry data (Step 5). | V5: Two models framed it as spoofing of the sensor input rather than tampering with the model, which is why it did not reach the agreed set. | W5: Authenticity, Integrity. | X5: T058 | Y5: =IF(H5=Reference!$A$12, Reference!$C$12, IF(H5=Reference!$A$11, Reference!$C$11, IF(H5=Reference!$A$10, Reference!$C$10, IF(H5=Reference!$A$9, Reference!$C$9, 0)))) -> 7 | Z5: =IF(J5=Reference!$A$20, Reference!$C$20, IF(J5=Reference!$A$19, Reference!$C$19, IF(J5=Reference!$A$18, Reference!$C$18, IF(J5=Reference!$A$17, Reference!$C$17, 0)))) -> 4 | AA5: =IF(L5=Reference!$A$28, Reference!$C$28, IF(L5=Reference!$A$27, Reference!$C$27, IF(L5=Reference!$A$26, Reference!$C$26, IF(L5=Reference!$A$25, Reference!$C$25, 0)))) -> 7 | AB5: =IF(N5=Reference!$A$36, Reference!$C$36, IF(N5=Reference!$A$35, Reference!$C$35, IF(N5=Reference!$A$34, Reference!$C$34, IF(N5=Reference!$A$33, Reference!$C$33, 0)))) -> 1 | AC5: =(Reference!$B$2*Y5 + Reference!$B$3*AA5 + Reference!$B$4*Z5 + Reference!$B$5 * AB5)/4 -> 11.0625 | AD5: =IF(Q5=Reference!$C$41, Reference!$D$41, IF(Q5=Reference!$C$42, Reference!$D$42, IF(Q5=Reference!$C$43, Reference!$D$43, IF(Q5=Reference!$C$44, Reference!$D$44, 0)))) -> 1 | AE5: =1 + (AC5 * AD5) -> 12.0625 | AF5: 2 of 6: ChatGPT, Copilot | AG5: ChatGPT: a manipulated stereo/depth input causes the component to estimate a false distance. Copilot: fake sensor inputs cause incorrect distance calculations.
A6: 5. Distance estimate agent (depth maps and intermediate data) | B6: Information disclosure | C6: Confidentiality | D6: Depth maps and intermediate spatial data are exposed, revealing the structure of the scene and the position of vehicles observed by the roadside camera. | E6: Access to the computing unit storage, to debug outputs or to log files that keep intermediate results. | F6: Adjacent | G6: The data rests on the roadside computing unit, reachable from the roadside network. | H6: Negligible | I6: No direct safety effect. | J6: Moderate | K6: Investigation and clean-up of debug artefacts. | L6: Negligible | M6: Operation is not affected. | N6: Major | O6: Spatial data reveals where vehicles and persons were, although it identifies them less directly than the images. | P6: =IF(AC6>=Reference!$H$2, Reference!$G$2, IF(AC6>=Reference!$H$3, Reference!$G$3, IF(AC6>=Reference!$H$4, Reference!$G$4, IF(AC6>=Reference!$H$5, Reference!$G$5, "")))) -> Negligible | Q6: =IF(F6="Physical", "Very Low", IF(F6="Local", "Low", IF(F6="Adjacent", "Medium", IF(F6="Network", "High", "")))) -> Medium | R6: =IF(AE6>=Reference!$D$2, Reference!$E$2, IF(AE6>=Reference!$D$3, Reference!$E$3, IF(AE6>=Reference!$D$4, Reference!$E$4, IF(AE6>=Reference!$D$5, Reference!$E$5, "")))) -> Medium | S6: Mitigation | T6: Disable debug outputs in production, keep intermediate results in memory only, restrict access to the unit, apply retention limits to any stored artefacts. | U6: Computing unit storage and logging, distance estimate agent (Step 5). | V6: A reminder that the intermediate products of an AI pipeline are data assets in their own right, which the architecture model does not show. | W6: Confidentiality. | X6: T055 | Y6: =IF(H6=Reference!$A$12, Reference!$C$12, IF(H6=Reference!$A$11, Reference!$C$11, IF(H6=Reference!$A$10, Reference!$C$10, IF(H6=Reference!$A$9, Reference!$C$9, 0)))) -> 1 | Z6: =IF(J6=Reference!$A$20, Reference!$C$20, IF(J6=Reference!$A$19, Reference!$C$19, IF(J6=Reference!$A$18, Reference!$C$18, IF(J6=Reference!$A$17, Reference!$C$17, 0)))) -> 4 | AA6: =IF(L6=Reference!$A$28, Reference!$C$28, IF(L6=Reference!$A$27, Reference!$C$27, IF(L6=Reference!$A$26, Reference!$C$26, IF(L6=Reference!$A$25, Reference!$C$25, 0)))) -> 1 | AB6: =IF(N6=Reference!$A$36, Reference!$C$36, IF(N6=Reference!$A$35, Reference!$C$35, IF(N6=Reference!$A$34, Reference!$C$34, IF(N6=Reference!$A$33, Reference!$C$33, 0)))) -> 7 | AC6: =(Reference!$B$2*Y6 + Reference!$B$3*AA6 + Reference!$B$4*Z6 + Reference!$B$5 * AB6)/4 -> 2.4375 | AD6: =IF(Q6=Reference!$C$41, Reference!$D$41, IF(Q6=Reference!$C$42, Reference!$D$42, IF(Q6=Reference!$C$43, Reference!$D$43, IF(Q6=Reference!$C$44, Reference!$D$44, 0)))) -> 7 | AE6: =1 + (AC6 * AD6) -> 18.0625 | AF6: 2 of 6: ChatGPT, Copilot | AG6: ChatGPT: depth maps or intermediate spatial data are exposed, revealing the structure of scenes captured by roadside cameras. Copilot: environmental and vehicle location information is leaked through outputs.
A7: 5. Distance estimate agent (model serving process) | B7: Elevation of privilege | C7: Authorization | D7: A vulnerability in the process that serves the depth model is exploited to execute code with its privileges and to reach other services on the roadside unit. | E7: Crafted input to the model server, or an unpatched dependency of the serving framework. | F7: Adjacent | G7: The serving process is reached from the roadside network or through the data it consumes. | H7: Major | I7: Code execution on the unit allows detection results and messages to be manipulated (S2). | J7: Major | K7: Rebuild of the unit and review of every station using the same image. | L7: Severe | M7: All functions hosted on the computing unit are affected. | N7: Moderate | O7: Access to the unit exposes camera-derived data held there. | P7: =IF(AC7>=Reference!$H$2, Reference!$G$2, IF(AC7>=Reference!$H$3, Reference!$G$3, IF(AC7>=Reference!$H$4, Reference!$G$4, IF(AC7>=Reference!$H$5, Reference!$G$5, "")))) -> Severe | Q7: =IF(F7="Physical", "Very Low", IF(F7="Local", "Low", IF(F7="Adjacent", "Medium", IF(F7="Network", "High", "")))) -> Medium | R7: =IF(AE7>=Reference!$D$2, Reference!$E$2, IF(AE7>=Reference!$D$3, Reference!$E$3, IF(AE7>=Reference!$D$4, Reference!$E$4, IF(AE7>=Reference!$D$5, Reference!$E$5, "")))) -> High | S7: Mitigation | T7: Run inference in a sandbox or container with least privilege, patch serving frameworks, validate input dimensions and types, separate the inference process from the message generation process. | U7: Model serving process, computing unit operating system (Step 5). | V7: The only model that raised it looked at the AI components as ordinary software, which is exactly the view a tool-based analysis takes. | W7: Authorization, Integrity. | X7: T059 | Y7: =IF(H7=Reference!$A$12, Reference!$C$12, IF(H7=Reference!$A$11, Reference!$C$11, IF(H7=Reference!$A$10, Reference!$C$10, IF(H7=Reference!$A$9, Reference!$C$9, 0)))) -> 7 | Z7: =IF(J7=Reference!$A$20, Reference!$C$20, IF(J7=Reference!$A$19, Reference!$C$19, IF(J7=Reference!$A$18, Reference!$C$18, IF(J7=Reference!$A$17, Reference!$C$17, 0)))) -> 7 | AA7: =IF(L7=Reference!$A$28, Reference!$C$28, IF(L7=Reference!$A$27, Reference!$C$27, IF(L7=Reference!$A$26, Reference!$C$26, IF(L7=Reference!$A$25, Reference!$C$25, 0)))) -> 10 | AB7: =IF(N7=Reference!$A$36, Reference!$C$36, IF(N7=Reference!$A$35, Reference!$C$35, IF(N7=Reference!$A$34, Reference!$C$34, IF(N7=Reference!$A$33, Reference!$C$33, 0)))) -> 4 | AC7: =(Reference!$B$2*Y7 + Reference!$B$3*AA7 + Reference!$B$4*Z7 + Reference!$B$5 * AB7)/4 -> 12.375 | AD7: =IF(Q7=Reference!$C$41, Reference!$D$41, IF(Q7=Reference!$C$42, Reference!$D$42, IF(Q7=Reference!$C$43, Reference!$D$43, IF(Q7=Reference!$C$44, Reference!$D$44, 0)))) -> 7 | AE7: =1 + (AC7 * AD7) -> 87.625 | AF7: 1 of 6: Copilot | AG7: Copilot: model-serving vulnerabilities permit escalation to privileged roadside services.
A8: 5. Distance estimate agent (calculation records) | B8: Repudiation | C8: Accountability | D8: How a distance value was produced is not recorded, so a wrong event position in a message cannot be traced back to the input, the model or a manipulation. | E8: The weakness exists by design. | F8: Adjacent | G8: The records would be produced on the roadside computing unit. | H8: Negligible | I8: No direct safety effect (S0). | J8: Moderate | K8: A dispute about a wrong event position cannot be settled with evidence. | L8: Moderate | M8: Root cause analysis of position errors is not possible. | N8: Negligible | O8: No personal data is affected if references are stored instead of images. | P8: =IF(AC8>=Reference!$H$2, Reference!$G$2, IF(AC8>=Reference!$H$3, Reference!$G$3, IF(AC8>=Reference!$H$4, Reference!$G$4, IF(AC8>=Reference!$H$5, Reference!$G$5, "")))) -> Moderate | Q8: =IF(F8="Physical", "Very Low", IF(F8="Local", "Low", IF(F8="Adjacent", "Medium", IF(F8="Network", "High", "")))) -> Medium | R8: =IF(AE8>=Reference!$D$2, Reference!$E$2, IF(AE8>=Reference!$D$3, Reference!$E$3, IF(AE8>=Reference!$D$4, Reference!$E$4, IF(AE8>=Reference!$D$5, Reference!$E$5, "")))) -> Medium | S8: Mitigation | T8: Record the input reference, the model version and the resulting distance with each event, alongside the detection record. | U8: Distance estimate agent, computing unit logging (Step 5). | V8: Same gap as for the detection agent, one stage later in the chain. | W8: Accountability. | X8: T060 | Y8: =IF(H8=Reference!$A$12, Reference!$C$12, IF(H8=Reference!$A$11, Reference!$C$11, IF(H8=Reference!$A$10, Reference!$C$10, IF(H8=Reference!$A$9, Reference!$C$9, 0)))) -> 1 | Z8: =IF(J8=Reference!$A$20, Reference!$C$20, IF(J8=Reference!$A$19, Reference!$C$19, IF(J8=Reference!$A$18, Reference!$C$18, IF(J8=Reference!$A$17, Reference!$C$17, 0)))) -> 4 | AA8: =IF(L8=Reference!$A$28, Reference!$C$28, IF(L8=Reference!$A$27, Reference!$C$27, IF(L8=Reference!$A$26, Reference!$C$26, IF(L8=Reference!$A$25, Reference!$C$25, 0)))) -> 4 | AB8: =IF(N8=Reference!$A$36, Reference!$C$36, IF(N8=Reference!$A$35, Reference!$C$35, IF(N8=Reference!$A$34, Reference!$C$34, IF(N8=Reference!$A$33, Reference!$C$33, 0)))) -> 1 | AC8: =(Reference!$B$2*Y8 + Reference!$B$3*AA8 + Reference!$B$4*Z8 + Reference!$B$5 * AB8)/4 -> 2.8125 | AD8: =IF(Q8=Reference!$C$41, Reference!$D$41, IF(Q8=Reference!$C$42, Reference!$D$42, IF(Q8=Reference!$C$43, Reference!$D$43, IF(Q8=Reference!$C$44, Reference!$D$44, 0)))) -> 7 | AE8: =1 + (AC8 * AD8) -> 20.6875 | AF8: 1 of 6: Copilot | AG8: Copilot: insufficient logging prevents validation of how distance values were generated.
A9: 6. Message generation agent (message content) | B9: Information disclosure | C9: Confidentiality | D9: The generated message or its underlying context reveals more than the hazard itself, for example precise vehicle positions or details of the infrastructure that produced it. | E9: Passive reception of the broadcast messages, or access to the generation context kept on the unit. | F9: Network | G9: DENMs are broadcast openly to every receiver in range. | H9: Negligible | I9: No direct safety effect. | J9: Moderate | K9: Review of the message content policy and possible data protection consequences. | L9: Moderate | M9: Operation continues; the content may have to be reduced. | N9: Major | O9: Precise positions of the vehicles involved in an accident can identify the persons concerned. | P9: =IF(AC9>=Reference!$H$2, Reference!$G$2, IF(AC9>=Reference!$H$3, Reference!$G$3, IF(AC9>=Reference!$H$4, Reference!$G$4, IF(AC9>=Reference!$H$5, Reference!$G$5, "")))) -> Moderate | Q9: =IF(F9="Physical", "Very Low", IF(F9="Local", "Low", IF(F9="Adjacent", "Medium", IF(F9="Network", "High", "")))) -> High | R9: =IF(AE9>=Reference!$D$2, Reference!$E$2, IF(AE9>=Reference!$D$3, Reference!$E$3, IF(AE9>=Reference!$D$4, Reference!$E$4, IF(AE9>=Reference!$D$5, Reference!$E$5, "")))) -> Medium | S9: Mitigation | T9: Keep the message to the fields required by the standard, avoid free text, round positions to the precision needed for the warning, review what the model is allowed to include. | U9: Message generation agent, DENM content policy (Steps 6-8). | V9: A message that must be broadcast to be useful is also a message that anyone can read, which is easy to forget when a language model writes its content. | W9: Confidentiality, Data minimisation. | X9: T070 | Y9: =IF(H9=Reference!$A$12, Reference!$C$12, IF(H9=Reference!$A$11, Reference!$C$11, IF(H9=Reference!$A$10, Reference!$C$10, IF(H9=Reference!$A$9, Reference!$C$9, 0)))) -> 1 | Z9: =IF(J9=Reference!$A$20, Reference!$C$20, IF(J9=Reference!$A$19, Reference!$C$19, IF(J9=Reference!$A$18, Reference!$C$18, IF(J9=Reference!$A$17, Reference!$C$17, 0)))) -> 4 | AA9: =IF(L9=Reference!$A$28, Reference!$C$28, IF(L9=Reference!$A$27, Reference!$C$27, IF(L9=Reference!$A$26, Reference!$C$26, IF(L9=Reference!$A$25, Reference!$C$25, 0)))) -> 4 | AB9: =IF(N9=Reference!$A$36, Reference!$C$36, IF(N9=Reference!$A$35, Reference!$C$35, IF(N9=Reference!$A$34, Reference!$C$34, IF(N9=Reference!$A$33, Reference!$C$33, 0)))) -> 7 | AC9: =(Reference!$B$2*Y9 + Reference!$B$3*AA9 + Reference!$B$4*Z9 + Reference!$B$5 * AB9)/4 -> 3.1875 | AD9: =IF(Q9=Reference!$C$41, Reference!$D$41, IF(Q9=Reference!$C$42, Reference!$D$42, IF(Q9=Reference!$C$43, Reference!$D$43, IF(Q9=Reference!$C$44, Reference!$D$44, 0)))) -> 10 | AE9: =1 + (AC9 * AD9) -> 32.875 | AF9: 2 of 6: ChatGPT, Copilot | AG9: ChatGPT: the generated message or its underlying accident context reveals sensitive location or vehicle information. Copilot: generated messages expose confidential infrastructure information.
A10: 6. Message generation agent (agent credentials and interfaces) | B10: Elevation of privilege | C10: Authorization | D10: Prompt injection or stolen agent credentials give an attacker control over the message generation interface, so arbitrary DENMs can be produced through the legitimate path and signed by the RSU. | E10: Injected instructions in the image content, or credentials extracted from the computing unit. | F10: Network | G10: The interfaces and credentials are reachable over the network path of the agent. | H10: Severe | I10: The attacker decides what every vehicle in range is told, through a path that passes all downstream checks (S3). | J10: Major | K10: Liability for resulting collisions and a full review of the generation chain. | L10: Severe | M10: Control of the warning function is transferred to the attacker while the system appears healthy. | N10: Negligible | O10: No direct personal data effect beyond the other rows. | P10: =IF(AC10>=Reference!$H$2, Reference!$G$2, IF(AC10>=Reference!$H$3, Reference!$G$3, IF(AC10>=Reference!$H$4, Reference!$G$4, IF(AC10>=Reference!$H$5, Reference!$G$5, "")))) -> Severe | Q10: =IF(F10="Physical", "Very Low", IF(F10="Local", "Low", IF(F10="Adjacent", "Medium", IF(F10="Network", "High", "")))) -> High | R10: =IF(AE10>=Reference!$D$2, Reference!$E$2, IF(AE10>=Reference!$D$3, Reference!$E$3, IF(AE10>=Reference!$D$4, Reference!$E$4, IF(AE10>=Reference!$D$5, Reference!$E$5, "")))) -> Critical | S10: Mitigation | T10: Separate instructions from content, restrict the agent to a schema with allowed values, store credentials in a hardware-backed keystore, authenticate the call from the agent to the encoder, log every generated message with its origin. | U10: Message generation agent, credentials store, DENM encoder interface (Steps 6-8). | V10: The highest risk value of the rare set, which shows that low agreement between models does not mean low severity. | W10: Authorization, Integrity, Authenticity. | X10: T074 | Y10: =IF(H10=Reference!$A$12, Reference!$C$12, IF(H10=Reference!$A$11, Reference!$C$11, IF(H10=Reference!$A$10, Reference!$C$10, IF(H10=Reference!$A$9, Reference!$C$9, 0)))) -> 10 | Z10: =IF(J10=Reference!$A$20, Reference!$C$20, IF(J10=Reference!$A$19, Reference!$C$19, IF(J10=Reference!$A$18, Reference!$C$18, IF(J10=Reference!$A$17, Reference!$C$17, 0)))) -> 7 | AA10: =IF(L10=Reference!$A$28, Reference!$C$28, IF(L10=Reference!$A$27, Reference!$C$27, IF(L10=Reference!$A$26, Reference!$C$26, IF(L10=Reference!$A$25, Reference!$C$25, 0)))) -> 10 | AB10: =IF(N10=Reference!$A$36, Reference!$C$36, IF(N10=Reference!$A$35, Reference!$C$35, IF(N10=Reference!$A$34, Reference!$C$34, IF(N10=Reference!$A$33, Reference!$C$33, 0)))) -> 1 | AC10: =(Reference!$B$2*Y10 + Reference!$B$3*AA10 + Reference!$B$4*Z10 + Reference!$B$5 * AB10)/4 -> 15.9375 | AD10: =IF(Q10=Reference!$C$41, Reference!$D$41, IF(Q10=Reference!$C$42, Reference!$D$42, IF(Q10=Reference!$C$43, Reference!$D$43, IF(Q10=Reference!$C$44, Reference!$D$44, 0)))) -> 10 | AE10: =1 + (AC10 * AD10) -> 160.375 | AF10: 2 of 6: ChatGPT, Copilot | AG10: ChatGPT: prompt injection or compromised agent credentials allow unauthorized access to message-generation APIs or downstream ITS functions. Copilot: compromised agent obtains unauthorized control over DENM generation workflows.
A11: 8. DENM encoder (ASN.1 parsing on the encoder host) | B11: Elevation of privilege | C11: Authorization | D11: A parsing weakness in the ASN.1 implementation is exploited by crafted field values, leading to code execution on the host that builds and signs the messages. | E11: Out-of-range or malformed values reaching the encoder from the model response, or a crafted message processed during testing. | F11: Network | G11: The values arrive over the network path from the cloud model. | H11: Severe | I11: Code execution next to the signing path allows arbitrary signed messages, with the same consequences as a compromised RSU (S3). | J11: Major | K11: Rebuild and revalidation of the station software. | L11: Severe | M11: The message generation and signing chain is fully controlled by the attacker. | N11: Moderate | O11: Access to the host exposes the data it holds. | P11: =IF(AC11>=Reference!$H$2, Reference!$G$2, IF(AC11>=Reference!$H$3, Reference!$G$3, IF(AC11>=Reference!$H$4, Reference!$G$4, IF(AC11>=Reference!$H$5, Reference!$G$5, "")))) -> Severe | Q11: =IF(F11="Physical", "Very Low", IF(F11="Local", "Low", IF(F11="Adjacent", "Medium", IF(F11="Network", "High", "")))) -> High | R11: =IF(AE11>=Reference!$D$2, Reference!$E$2, IF(AE11>=Reference!$D$3, Reference!$E$3, IF(AE11>=Reference!$D$4, Reference!$E$4, IF(AE11>=Reference!$D$5, Reference!$E$5, "")))) -> Critical | S11: Mitigation | T11: Validate values against the schema before encoding, use a memory-safe or fuzz-tested encoder, isolate the encoder process, patch the ASN.1 library. | U11: DENM encoder process and library, computing unit isolation (Step 8). | V11: Mirrors the parser row on the receiving side: the same weakness exists where messages are built, not only where they are read. | W11: Authorization, Integrity. | X11: T101 | Y11: =IF(H11=Reference!$A$12, Reference!$C$12, IF(H11=Reference!$A$11, Reference!$C$11, IF(H11=Reference!$A$10, Reference!$C$10, IF(H11=Reference!$A$9, Reference!$C$9, 0)))) -> 10 | Z11: =IF(J11=Reference!$A$20, Reference!$C$20, IF(J11=Reference!$A$19, Reference!$C$19, IF(J11=Reference!$A$18, Reference!$C$18, IF(J11=Reference!$A$17, Reference!$C$17, 0)))) -> 7 | AA11: =IF(L11=Reference!$A$28, Reference!$C$28, IF(L11=Reference!$A$27, Reference!$C$27, IF(L11=Reference!$A$26, Reference!$C$26, IF(L11=Reference!$A$25, Reference!$C$25, 0)))) -> 10 | AB11: =IF(N11=Reference!$A$36, Reference!$C$36, IF(N11=Reference!$A$35, Reference!$C$35, IF(N11=Reference!$A$34, Reference!$C$34, IF(N11=Reference!$A$33, Reference!$C$33, 0)))) -> 4 | AC11: =(Reference!$B$2*Y11 + Reference!$B$3*AA11 + Reference!$B$4*Z11 + Reference!$B$5 * AB11)/4 -> 16.125 | AD11: =IF(Q11=Reference!$C$41, Reference!$D$41, IF(Q11=Reference!$C$42, Reference!$D$42, IF(Q11=Reference!$C$43, Reference!$D$43, IF(Q11=Reference!$C$44, Reference!$D$44, 0)))) -> 10 | AE11: =1 + (AC11 * AD11) -> 162.25 | AF11: 1 of 6: Copilot | AG11: Copilot: ASN.1 parsing vulnerabilities enable code execution on the encoder host.
A12: 3-7. Link computing unit to Gemini API (5G Uu) | B12: Elevation of privilege | C12: Authorization | D12: A compromise at network level on the path to the cloud service is used to reach other infrastructure services that trust the same connection, beyond the model interface itself. | E12: Compromise of the gateway, the APN or a shared network element used by the roadside station. | F12: Network | G12: The path crosses operator and provider networks that the station cannot control. | H12: Major | I12: Access to trusted services allows manipulation of the detection and messaging chain (S2). | J12: Major | K12: Incident response across the network infrastructure and possible service interruption. | L12: Severe | M12: Several stations can be affected at once through the shared path. | N12: Moderate | O12: Traffic on the path includes camera images. | P12: =IF(AC12>=Reference!$H$2, Reference!$G$2, IF(AC12>=Reference!$H$3, Reference!$G$3, IF(AC12>=Reference!$H$4, Reference!$G$4, IF(AC12>=Reference!$H$5, Reference!$G$5, "")))) -> Severe | Q12: =IF(F12="Physical", "Very Low", IF(F12="Local", "Low", IF(F12="Adjacent", "Medium", IF(F12="Network", "High", "")))) -> High | R12: =IF(AE12>=Reference!$D$2, Reference!$E$2, IF(AE12>=Reference!$D$3, Reference!$E$3, IF(AE12>=Reference!$D$4, Reference!$E$4, IF(AE12>=Reference!$D$5, Reference!$E$5, "")))) -> Critical | S12: Mitigation | T12: Terminate the station traffic in a dedicated APN or VPN, allow only the endpoints the station needs, apply mutual authentication, segment the network so that a compromise of one path does not grant access to other services. | U12: Cellular connection, gateways, network segmentation (Steps 3-7). | V12: Not enumerated by medini, because the tool generates no elevation of privilege threat for connections. | W12: Authorization, Integrity. | X12: not enumerated by medini | Y12: =IF(H12=Reference!$A$12, Reference!$C$12, IF(H12=Reference!$A$11, Reference!$C$11, IF(H12=Reference!$A$10, Reference!$C$10, IF(H12=Reference!$A$9, Reference!$C$9, 0)))) -> 7 | Z12: =IF(J12=Reference!$A$20, Reference!$C$20, IF(J12=Reference!$A$19, Reference!$C$19, IF(J12=Reference!$A$18, Reference!$C$18, IF(J12=Reference!$A$17, Reference!$C$17, 0)))) -> 7 | AA12: =IF(L12=Reference!$A$28, Reference!$C$28, IF(L12=Reference!$A$27, Reference!$C$27, IF(L12=Reference!$A$26, Reference!$C$26, IF(L12=Reference!$A$25, Reference!$C$25, 0)))) -> 10 | AB12: =IF(N12=Reference!$A$36, Reference!$C$36, IF(N12=Reference!$A$35, Reference!$C$35, IF(N12=Reference!$A$34, Reference!$C$34, IF(N12=Reference!$A$33, Reference!$C$33, 0)))) -> 4 | AC12: =(Reference!$B$2*Y12 + Reference!$B$3*AA12 + Reference!$B$4*Z12 + Reference!$B$5 * AB12)/4 -> 12.375 | AD12: =IF(Q12=Reference!$C$41, Reference!$D$41, IF(Q12=Reference!$C$42, Reference!$D$42, IF(Q12=Reference!$C$43, Reference!$D$43, IF(Q12=Reference!$C$44, Reference!$D$44, 0)))) -> 10 | AE12: =1 + (AC12 * AD12) -> 124.75 | AF12: 1 of 6: Copilot | AG12: Copilot: network-level compromise enables unauthorized access to trusted infrastructure services.
A13: 3-7. Link computing unit to Gemini API (5G Uu) | B13: Repudiation | C13: Non-repudiation | D13: Neither side can prove what was sent or received over the link, so the operator and the model provider can each deny responsibility for a request or a response behind a wrong warning. | E13: No signed or timestamped record of the exchange is kept on either side. | F13: Network | G13: The exchange crosses the public network between two administrative domains. | H13: Negligible | I13: No direct safety effect (S0). | J13: Major | K13: Disputes with the provider cannot be settled, and liability stays with the operator by default. | L13: Moderate | M13: Root cause analysis stops at the domain boundary. | N13: Negligible | O13: Records should reference content rather than copy it. | P13: =IF(AC13>=Reference!$H$2, Reference!$G$2, IF(AC13>=Reference!$H$3, Reference!$G$3, IF(AC13>=Reference!$H$4, Reference!$G$4, IF(AC13>=Reference!$H$5, Reference!$G$5, "")))) -> Moderate | Q13: =IF(F13="Physical", "Very Low", IF(F13="Local", "Low", IF(F13="Adjacent", "Medium", IF(F13="Network", "High", "")))) -> High | R13: =IF(AE13>=Reference!$D$2, Reference!$E$2, IF(AE13>=Reference!$D$3, Reference!$E$3, IF(AE13>=Reference!$D$4, Reference!$E$4, IF(AE13>=Reference!$D$5, Reference!$E$5, "")))) -> Medium | S13: Mitigation | T13: Keep signed and timestamped request and response records on the operator side, agree processing records or audit rights in the contract, prefer providers that return a model version with each response. | U13: Computing unit logging, provider contract (Steps 3-7). | V13: Not enumerated by medini, because the tool generates no repudiation threat for connections. | W13: Non-repudiation, Accountability. | X13: not enumerated by medini | Y13: =IF(H13=Reference!$A$12, Reference!$C$12, IF(H13=Reference!$A$11, Reference!$C$11, IF(H13=Reference!$A$10, Reference!$C$10, IF(H13=Reference!$A$9, Reference!$C$9, 0)))) -> 1 | Z13: =IF(J13=Reference!$A$20, Reference!$C$20, IF(J13=Reference!$A$19, Reference!$C$19, IF(J13=Reference!$A$18, Reference!$C$18, IF(J13=Reference!$A$17, Reference!$C$17, 0)))) -> 7 | AA13: =IF(L13=Reference!$A$28, Reference!$C$28, IF(L13=Reference!$A$27, Reference!$C$27, IF(L13=Reference!$A$26, Reference!$C$26, IF(L13=Reference!$A$25, Reference!$C$25, 0)))) -> 4 | AB13: =IF(N13=Reference!$A$36, Reference!$C$36, IF(N13=Reference!$A$35, Reference!$C$35, IF(N13=Reference!$A$34, Reference!$C$34, IF(N13=Reference!$A$33, Reference!$C$33, 0)))) -> 1 | AC13: =(Reference!$B$2*Y13 + Reference!$B$3*AA13 + Reference!$B$4*Z13 + Reference!$B$5 * AB13)/4 -> 3.1875 | AD13: =IF(Q13=Reference!$C$41, Reference!$D$41, IF(Q13=Reference!$C$42, Reference!$D$42, IF(Q13=Reference!$C$43, Reference!$D$43, IF(Q13=Reference!$C$44, Reference!$D$44, 0)))) -> 10 | AE13: =1 + (AC13 * AD13) -> 32.875 | AF13: 1 of 6: Copilot | AG13: Copilot: participants deny having transmitted or received safety-critical messages.
A14: 9 -> 11. PC5 sidelink (transmission records) | B14: Repudiation | C14: Non-repudiation | D14: Transmitted messages cannot be attributed to a particular roadside unit instance or to the operator who configured it, so an operator can deny having broadcast a wrong or malicious alert. | E14: Missing or insufficient security logging of what each unit signed and transmitted. | F14: Network | G14: The messages are broadcast over the air and are not recorded anywhere by default. | H14: Negligible | I14: No direct safety effect (S0). | J14: Major | K14: After an incident, responsibility between operator, integrator and manufacturer cannot be established. | L14: Moderate | M14: Supervision of the deployment loses evidential value. | N14: Negligible | O14: Transmission records contain no personal data beyond the message content. | P14: =IF(AC14>=Reference!$H$2, Reference!$G$2, IF(AC14>=Reference!$H$3, Reference!$G$3, IF(AC14>=Reference!$H$4, Reference!$G$4, IF(AC14>=Reference!$H$5, Reference!$G$5, "")))) -> Moderate | Q14: =IF(F14="Physical", "Very Low", IF(F14="Local", "Low", IF(F14="Adjacent", "Medium", IF(F14="Network", "High", "")))) -> High | R14: =IF(AE14>=Reference!$D$2, Reference!$E$2, IF(AE14>=Reference!$D$3, Reference!$E$3, IF(AE14>=Reference!$D$4, Reference!$E$4, IF(AE14>=Reference!$D$5, Reference!$E$5, "")))) -> Medium | S14: Mitigation | T14: Record every signed message with its certificate, timestamp and unit identifier, store the records centrally, protect them against modification and keep time synchronised. | U14: RSU logging, central ITS-S storage, time synchronisation (Steps 9-10). | V14: Not enumerated by medini, because the tool generates no repudiation threat for connections; the equivalent component threat is covered in the full analysis. | W14: Non-repudiation, Accountability. | X14: not enumerated by medini | Y14: =IF(H14=Reference!$A$12, Reference!$C$12, IF(H14=Reference!$A$11, Reference!$C$11, IF(H14=Reference!$A$10, Reference!$C$10, IF(H14=Reference!$A$9, Reference!$C$9, 0)))) -> 1 | Z14: =IF(J14=Reference!$A$20, Reference!$C$20, IF(J14=Reference!$A$19, Reference!$C$19, IF(J14=Reference!$A$18, Reference!$C$18, IF(J14=Reference!$A$17, Reference!$C$17, 0)))) -> 7 | AA14: =IF(L14=Reference!$A$28, Reference!$C$28, IF(L14=Reference!$A$27, Reference!$C$27, IF(L14=Reference!$A$26, Reference!$C$26, IF(L14=Reference!$A$25, Reference!$C$25, 0)))) -> 4 | AB14: =IF(N14=Reference!$A$36, Reference!$C$36, IF(N14=Reference!$A$35, Reference!$C$35, IF(N14=Reference!$A$34, Reference!$C$34, IF(N14=Reference!$A$33, Reference!$C$33, 0)))) -> 1 | AC14: =(Reference!$B$2*Y14 + Reference!$B$3*AA14 + Reference!$B$4*Z14 + Reference!$B$5 * AB14)/4 -> 3.1875 | AD14: =IF(Q14=Reference!$C$41, Reference!$D$41, IF(Q14=Reference!$C$42, Reference!$D$42, IF(Q14=Reference!$C$43, Reference!$D$43, IF(Q14=Reference!$C$44, Reference!$D$44, 0)))) -> 10 | AE14: =1 + (AC14 * AD14) -> 32.875 | AF14: 2 of 6: ChatGPT, Copilot | AG14: ChatGPT: insufficient security logging prevents attribution of signed or transmitted messages to a particular RSU instance or administrative operator. Copilot: RSU operators deny transmitting malicious or incorrect alerts.

Sheet Risk summary
A1: Risk summary - AI-generated threat scenarios
A3: Risk value | B3: Rows
A4: Critical | B4: =COUNTIF('AI threat scenarios'!$R$2:$R$44,A4) -> 10
A5: High | B5: =COUNTIF('AI threat scenarios'!$R$2:$R$44,A5) -> 12
A6: Medium | B6: =COUNTIF('AI threat scenarios'!$R$2:$R$44,A6) -> 14
A7: Low | B7: =COUNTIF('AI threat scenarios'!$R$2:$R$44,A7) -> 7
A8: Very Low | B8: =COUNTIF('AI threat scenarios'!$R$2:$R$44,A8) -> 0
A9: Total | B9: =SUM(B4:B8) -> 43
A11: STRIDE category | B11: Rows
A12: Spoofing | B12: =COUNTIF('AI threat scenarios'!$B$2:$B$44,A12) -> 9
A13: Tampering | B13: =COUNTIF('AI threat scenarios'!$B$2:$B$44,A13) -> 11
A14: Repudiation | B14: =COUNTIF('AI threat scenarios'!$B$2:$B$44,A14) -> 5
A15: Information disclosure | B15: =COUNTIF('AI threat scenarios'!$B$2:$B$44,A15) -> 6
A16: Denial of service | B16: =COUNTIF('AI threat scenarios'!$B$2:$B$44,A16) -> 9
A17: Elevation of privilege | B17: =COUNTIF('AI threat scenarios'!$B$2:$B$44,A17) -> 3
A18: Total | B18: =SUM(B12:B17) -> 43
A20: Attack vector | B20: Rows
A21: Network | B21: =COUNTIF('AI threat scenarios'!$F$2:$F$44,A21) -> 22
A22: Adjacent | B22: =COUNTIF('AI threat scenarios'!$F$2:$F$44,A22) -> 9
A23: Local | B23: =COUNTIF('AI threat scenarios'!$F$2:$F$44,A23) -> 5
A24: Physical | B24: =COUNTIF('AI threat scenarios'!$F$2:$F$44,A24) -> 7
A25: Total | B25: =SUM(B21:B24) -> 43
A27: Severity level | B27: Rows
A28: Severe | B28: =COUNTIF('AI threat scenarios'!$P$2:$P$44,A28) -> 27
A29: Major | B29: =COUNTIF('AI threat scenarios'!$P$2:$P$44,A29) -> 6
A30: Moderate | B30: =COUNTIF('AI threat scenarios'!$P$2:$P$44,A30) -> 10
A31: Negligible | B31: =COUNTIF('AI threat scenarios'!$P$2:$P$44,A31) -> 0
A32: Total | B32: =SUM(B28:B31) -> 43
A34: Average risk score | B34: =ROUND(AVERAGE('AI threat scenarios'!$AE$2:$AE$44),1) -> 65.9
A35: Highest risk score | B35: =ROUND(MAX('AI threat scenarios'!$AE$2:$AE$44),1) -> 167.9
A36: Scenarios analysed | B36: =COUNTA('AI threat scenarios'!$A$2:$A$44) -> 43
A38: Note | B38: Counts refer to the rows of the sheet 'AI threat scenarios'. One consensus theme can span several rows when it has several attack paths.

Sheet Medini threats
A1: ID | B1: Name | C1: Assets | D1: To Be Assessed | E1: Category | F1: Description | G1: Equipment | H1: Expertise | I1: Knowledge about TOE | J1: Window of Opportunity | K1: Likelihood Level | L1: Asset (clean) | M1: Key | N1: Component | O1: Element type | P1: AI scenarios | Q1: Covered by AI
A2: T001 | B2: Information Disclosure of Mono + Stereo | C2: • Mono + Stereo | D2: true | E2: Information Disclosure | L2: Mono + Stereo | M2: =L2&"|"&E2 -> Mono + Stereo|Information Disclosure | N2: Mono + Stereo | O2: Component | P2: =COUNTIF(Mapping!$G$2:$G$44,M2) -> 1 | Q2: =IF(P2>0,"Yes","No") -> Yes
A3: T002 | B3: Tampering of Mono + Stereo | C3: • Mono + Stereo | D3: true | E3: Tampering | L3: Mono + Stereo | M3: =L3&"|"&E3 -> Mono + Stereo|Tampering | N3: Mono + Stereo | O3: Component | P3: =COUNTIF(Mapping!$G$2:$G$44,M3) -> 1 | Q3: =IF(P3>0,"Yes","No") -> Yes
A4: T003 | B4: Denial of Service of Mono + Stereo | C4: • Mono + Stereo | D4: true | E4: Denial of Service | L4: Mono + Stereo | M4: =L4&"|"&E4 -> Mono + Stereo|Denial of Service | N4: Mono + Stereo | O4: Component | P4: =COUNTIF(Mapping!$G$2:$G$44,M4) -> 1 | Q4: =IF(P4>0,"Yes","No") -> Yes
A5: T004 | B5: Spoofing of Mono + Stereo | C5: • Mono + Stereo | D5: true | E5: Spoofing | L5: Mono + Stereo | M5: =L5&"|"&E5 -> Mono + Stereo|Spoofing | N5: Mono + Stereo | O5: Component | P5: =COUNTIF(Mapping!$G$2:$G$44,M5) -> 0 | Q5: =IF(P5>0,"Yes","No") -> No
A6: T005 | B6: Elevation of Privilege of Mono + Stereo | C6: • Mono + Stereo | D6: true | E6: Elevation of Privilege | L6: Mono + Stereo | M6: =L6&"|"&E6 -> Mono + Stereo|Elevation of Privilege | N6: Mono + Stereo | O6: Component | P6: =COUNTIF(Mapping!$G$2:$G$44,M6) -> 0 | Q6: =IF(P6>0,"Yes","No") -> No
A7: T006 | B7: Repudiation of Mono + Stereo | C7: • Mono + Stereo | D7: true | E7: Repudiation | L7: Mono + Stereo | M7: =L7&"|"&E7 -> Mono + Stereo|Repudiation | N7: Mono + Stereo | O7: Component | P7: =COUNTIF(Mapping!$G$2:$G$44,M7) -> 0 | Q7: =IF(P7>0,"Yes","No") -> No
A8: T007 | B8: Information Disclosure of image_out | C8: • Mono + Stereo::image_out | D8: true | E8: Information Disclosure | L8: Mono + Stereo::image_out | M8: =L8&"|"&E8 -> Mono + Stereo::image_out|Information Disclosure | N8: Mono + Stereo | O8: Port | P8: =COUNTIF(Mapping!$G$2:$G$44,M8) -> 0 | Q8: =IF(P8>0,"Yes","No") -> No
A9: T008 | B9: Tampering of image_out | C9: • Mono + Stereo::image_out | D9: true | E9: Tampering | L9: Mono + Stereo::image_out | M9: =L9&"|"&E9 -> Mono + Stereo::image_out|Tampering | N9: Mono + Stereo | O9: Port | P9: =COUNTIF(Mapping!$G$2:$G$44,M9) -> 0 | Q9: =IF(P9>0,"Yes","No") -> No
A10: T009 | B10: Denial of Service of image_out | C10: • Mono + Stereo::image_out | D10: true | E10: Denial of Service | L10: Mono + Stereo::image_out | M10: =L10&"|"&E10 -> Mono + Stereo::image_out|Denial of Service | N10: Mono + Stereo | O10: Port | P10: =COUNTIF(Mapping!$G$2:$G$44,M10) -> 0 | Q10: =IF(P10>0,"Yes","No") -> No
A11: T010 | B11: Information Disclosure of image_out ↔ image_in | C11: • image_out ↔ image_in | D11: true | E11: Information Disclosure | L11: image_out ↔ image_in | M11: =L11&"|"&E11 -> image_out ↔ image_in|Information Disclosure | N11: (connection) | O11: Connection | P11: =COUNTIF(Mapping!$G$2:$G$44,M11) -> 1 | Q11: =IF(P11>0,"Yes","No") -> Yes
A12: T011 | B12: Tampering of image_out ↔ image_in | C12: • image_out ↔ image_in | D12: true | E12: Tampering | L12: image_out ↔ image_in | M12: =L12&"|"&E12 -> image_out ↔ image_in|Tampering | N12: (connection) | O12: Connection | P12: =COUNTIF(Mapping!$G$2:$G$44,M12) -> 1 | Q12: =IF(P12>0,"Yes","No") -> Yes
A13: T012 | B13: Denial of Service of image_out ↔ image_in | C13: • image_out ↔ image_in | D13: true | E13: Denial of Service | L13: image_out ↔ image_in | M13: =L13&"|"&E13 -> image_out ↔ image_in|Denial of Service | N13: (connection) | O13: Connection | P13: =COUNTIF(Mapping!$G$2:$G$44,M13) -> 0 | Q13: =IF(P13>0,"Yes","No") -> No
... A226: T225 | B226: Denial of Service of uu_modem_out ↔ uu_modem | C226: • uu_modem_out ↔ uu_modem | D226: true | E226: Denial of Service | L226: uu_modem_out ↔ uu_modem | M226: =L226&"|"&E226 -> uu_modem_out ↔ uu_modem|Denial of Service | N226: (connection) | O226: Connection | P226: =COUNTIF(Mapping!$G$2:$G$44,M226) -> 0 | Q226: =IF(P226>0,"Yes","No") -> No

Sheet Mapping
A1: AI row | B1: AI asset | C1: AI STRIDE | D1: Medini asset (clean) | E1: Medini category | F1: Medini threat ID | G1: Key | H1: Match type | I1: Note
A2: 2 | B2: ='AI threat scenarios'!A2 -> 9. RSU (PC5 radio, signing keys in HSM) | C2: ='AI threat scenarios'!B2 -> Spoofing | D2: Signs, PC5, HSM | E2: Spoofing | F2: =IFERROR(INDEX('Medini threats'!$A$2:$A$226,MATCH(G2,'Medini threats'!$M$2:$M$226,0)),"not in model") -> T115 | G2: =D2&"|"&E2 -> Signs, PC5, HSM|Spoofing | H2: Exact (same element and category)
A3: 3 | B3: ='AI threat scenarios'!A3 -> 8 -> 9. Link roadside computing unit to RSU (Ethernet/UDP) | C3: ='AI threat scenarios'!B3 -> Spoofing | D3: denm_out ↔ denm_in | E3: Tampering | F3: =IFERROR(INDEX('Medini threats'!$A$2:$A$226,MATCH(G3,'Medini threats'!$M$2:$M$226,0)),"not in model") -> T110 | G3: =D3&"|"&E3 -> denm_out ↔ denm_in|Tampering | H3: Category adapted | I3: AI classifies the injection as Spoofing; medini generates only Tampering, Information Disclosure and Denial of Service for connections.
A4: 4 | B4: ='AI threat scenarios'!A4 -> 9. RSU (management interface, HSM) | C4: ='AI threat scenarios'!B4 -> Elevation of privilege | D4: Signs, PC5, HSM | E4: Elevation of Privilege | F4: =IFERROR(INDEX('Medini threats'!$A$2:$A$226,MATCH(G4,'Medini threats'!$M$2:$M$226,0)),"not in model") -> T116 | G4: =D4&"|"&E4 -> Signs, PC5, HSM|Elevation of Privilege | H4: Exact (same element and category)
A5: 5 | B5: ='AI threat scenarios'!A5 -> 0. Security credentials and PKI (central ITS-S) | C5: ='AI threat scenarios'!B5 -> Spoofing | D5: PKI, operator | E5: Spoofing | F5: =IFERROR(INDEX('Medini threats'!$A$2:$A$226,MATCH(G5,'Medini threats'!$M$2:$M$226,0)),"not in model") -> T208 | G5: =D5&"|"&E5 -> PKI, operator|Spoofing | H5: Exact (same element and category)
A6: 6 | B6: ='AI threat scenarios'!A6 -> 9. RSU signing keys (HSM) | C6: ='AI threat scenarios'!B6 -> Information disclosure | D6: Signs, PC5, HSM | E6: Information Disclosure | F6: =IFERROR(INDEX('Medini threats'!$A$2:$A$226,MATCH(G6,'Medini threats'!$M$2:$M$226,0)),"not in model") -> T112 | G6: =D6&"|"&E6 -> Signs, PC5, HSM|Information Disclosure | H6: Exact (same element and category)
A7: 7 | B7: ='AI threat scenarios'!A7 -> 9 -> 11. PC5 sidelink (RSU to OBU) | C7: ='AI threat scenarios'!B7 -> Spoofing | D7: pc5_out ↔ pc5_in | E7: Tampering | F7: =IFERROR(INDEX('Medini threats'!$A$2:$A$226,MATCH(G7,'Medini threats'!$M$2:$M$226,0)),"not in model") -> T131 | G7: =D7&"|"&E7 -> pc5_out ↔ pc5_in|Tampering | H7: Category adapted | I7: Replay is classified as Spoofing by the AI; no Spoofing category exists for connections in medini.
A8: 8 | B8: ='AI threat scenarios'!A8 -> 12. Vehicle computer (signature verification and warning logic) | C8: ='AI threat scenarios'!B8 -> Tampering | D8: Verify, warning logic | E8: Tampering | F8: =IFERROR(INDEX('Medini threats'!$A$2:$A$226,MATCH(G8,'Medini threats'!$M$2:$M$226,0)),"not in model") -> T164 | G8: =D8&"|"&E8 -> Verify, warning logic|Tampering | H8: Exact (same element and category)
A9: 9 | B9: ='AI threat scenarios'!A9 -> 9. RSU event log and signed message records | C9: ='AI threat scenarios'!B9 -> Repudiation | D9: Signs, PC5, HSM | E9: Repudiation | F9: =IFERROR(INDEX('Medini threats'!$A$2:$A$226,MATCH(G9,'Medini threats'!$M$2:$M$226,0)),"not in model") -> T117 | G9: =D9&"|"&E9 -> Signs, PC5, HSM|Repudiation | H9: Exact (same element and category)
A10: 10 | B10: ='AI threat scenarios'!A10 -> 1 -> 2. Video link cameras to computing unit | C10: ='AI threat scenarios'!B10 -> Spoofing | D10: image_out ↔ image_in | E10: Tampering | F10: =IFERROR(INDEX('Medini threats'!$A$2:$A$226,MATCH(G10,'Medini threats'!$M$2:$M$226,0)),"not in model") -> T011 | G10: =D10&"|"&E10 -> image_out ↔ image_in|Tampering | H10: Category adapted | I10: Feed injection is Spoofing for the AI; mapped to the Tampering threat of the connection.
A11: 11 | B11: ='AI threat scenarios'!A11 -> 2. Edge detector, YOLOv5 (perception input) | C11: ='AI threat scenarios'!B11 -> Spoofing | D11: YOLOv5 fast path | E11: Spoofing | F11: =IFERROR(INDEX('Medini threats'!$A$2:$A$226,MATCH(G11,'Medini threats'!$M$2:$M$226,0)),"not in model") -> T016 | G11: =D11&"|"&E11 -> YOLOv5 fast path|Spoofing | H11: Category adapted | I11: Adversarial patterns deceive the input of the detector. In medini, 'Spoofing of YOLOv5 fast path' means impersonation of the component, so the match is semantic rather than exact.
A12: 12 | B12: ='AI threat scenarios'!A12 -> 3. Situation detection agent (prompt and image input) | C12: ='AI threat scenarios'!B12 -> Spoofing | D12: Agent 1, MLLM call | E12: Spoofing | F12: =IFERROR(INDEX('Medini threats'!$A$2:$A$226,MATCH(G12,'Medini threats'!$M$2:$M$226,0)),"not in model") -> T031 | G12: =D12&"|"&E12 -> Agent 1, MLLM call|Spoofing | H12: Category adapted | I12: Prompt injection through image content. As above, the medini Spoofing threat of the agent means impersonation of the component; medini has no notion of prompt or model input.
A13: 13 | B13: ='AI threat scenarios'!A13 -> 3-7. Link computing unit to Gemini API (5G Uu) | C13: ='AI threat scenarios'!B13 -> Spoofing | D13: Gemini API | E13: Spoofing | F13: =IFERROR(INDEX('Medini threats'!$A$2:$A$226,MATCH(G13,'Medini threats'!$M$2:$M$226,0)),"not in model") -> T190 | G13: =D13&"|"&E13 -> Gemini API|Spoofing | H13: Exact (same element and category)
A14: 14 | B14: ='AI threat scenarios'!A14 -> 4 & 7. Cloud MLLM (Gemini API) | C14: ='AI threat scenarios'!B14 -> Information disclosure | D14: Gemini API | E14: Information Disclosure | F14: =IFERROR(INDEX('Medini threats'!$A$2:$A$226,MATCH(G14,'Medini threats'!$M$2:$M$226,0)),"not in model") -> T187 | G14: =D14&"|"&E14 -> Gemini API|Information Disclosure | H14: Exact (same element and category)
A15: 15 | B15: ='AI threat scenarios'!A15 -> 1. Cameras (mono + stereo) | C15: ='AI threat scenarios'!B15 -> Denial of service | D15: Mono + Stereo | E15: Denial of Service | F15: =IFERROR(INDEX('Medini threats'!$A$2:$A$226,MATCH(G15,'Medini threats'!$M$2:$M$226,0)),"not in model") -> T003 | G15: =D15&"|"&E15 -> Mono + Stereo|Denial of Service | H15: Exact (same element and category)
A16: 16 | B16: ='AI threat scenarios'!A16 -> 9 -> 11. PC5 sidelink (RSU to OBU) | C16: ='AI threat scenarios'!B16 -> Denial of service | D16: pc5_out ↔ pc5_in | E16: Denial of Service | F16: =IFERROR(INDEX('Medini threats'!$A$2:$A$226,MATCH(G16,'Medini threats'!$M$2:$M$226,0)),"not in model") -> T132 | G16: =D16&"|"&E16 -> pc5_out ↔ pc5_in|Denial of Service | H16: Exact (same element and category)
A17: 17 | B17: ='AI threat scenarios'!A17 -> 4 & 7. Cloud MLLM service (Gemini API) and its 5G Uu link | C17: ='AI threat scenarios'!B17 -> Denial of service | D17: Gemini API | E17: Denial of Service | F17: =IFERROR(INDEX('Medini threats'!$A$2:$A$226,MATCH(G17,'Medini threats'!$M$2:$M$226,0)),"not in model") -> T189 | G17: =D17&"|"&E17 -> Gemini API|Denial of Service | H17: Exact (same element and category)
A18: 18 | B18: ='AI threat scenarios'!A18 -> 2 & 5. AI model files on the roadside computing unit | C18: ='AI threat scenarios'!B18 -> Tampering | D18: YOLOv5 fast path | E18: Tampering | F18: =IFERROR(INDEX('Medini threats'!$A$2:$A$226,MATCH(G18,'Medini threats'!$M$2:$M$226,0)),"not in model") -> T014 | G18: =D18&"|"&E18 -> YOLOv5 fast path|Tampering | H18: Exact (same element and category) | I18: Covers the Depth Pro model file as well (Agent 2, Depth Pro | Tampering), which is not counted as a separate match.
A19: 19 | B19: ='AI threat scenarios'!A19 -> Gemini API key and cloud account | C19: ='AI threat scenarios'!B19 -> Information disclosure | F19: =IFERROR(INDEX('Medini threats'!$A$2:$A$226,MATCH(G19,'Medini threats'!$M$2:$M$226,0)),"not in model") -> not in model | G19: =D19&"|"&E19 -> | | H19: No element in the medini model | I19: The API key and the cloud account are not elements of the medini model; the AI scenario has no counterpart.
A20: 20 | B20: ='AI threat scenarios'!A20 -> 3-8. Records of the AI decision chain (prompt, model version, response) | C20: ='AI threat scenarios'!B20 -> Repudiation | D20: Agent 1, MLLM call | E20: Repudiation | F20: =IFERROR(INDEX('Medini threats'!$A$2:$A$226,MATCH(G20,'Medini threats'!$M$2:$M$226,0)),"not in model") -> T033 | G20: =D20&"|"&E20 -> Agent 1, MLLM call|Repudiation | H20: Exact (same element and category) | I20: Also applies to Agent 3, MLLM call | Repudiation.
A21: 21 | B21: ='AI threat scenarios'!A21 -> 12. Vehicle computer (in-vehicle interfaces) | C21: ='AI threat scenarios'!B21 -> Elevation of privilege | D21: Verify, warning logic | E21: Elevation of Privilege | F21: =IFERROR(INDEX('Medini threats'!$A$2:$A$226,MATCH(G21,'Medini threats'!$M$2:$M$226,0)),"not in model") -> T167 | G21: =D21&"|"&E21 -> Verify, warning logic|Elevation of Privilege | H21: Exact (same element and category)
A22: 22 | B22: ='AI threat scenarios'!A22 -> 11. OBU (V2X stack and ASN.1 decoder) | C22: ='AI threat scenarios'!B22 -> Denial of service | D22: PC5 + Uumodem | E22: Denial of Service | F22: =IFERROR(INDEX('Medini threats'!$A$2:$A$226,MATCH(G22,'Medini threats'!$M$2:$M$226,0)),"not in model") -> T141 | G22: =D22&"|"&E22 -> PC5 + Uumodem|Denial of Service | H22: Exact (same element and category)
A23: 23 | B23: ='AI threat scenarios'!A23 -> 13. Driver HMI | C23: ='AI threat scenarios'!B23 -> Denial of service | D23: Visual + audio alert | E23: Denial of Service | F23: =IFERROR(INDEX('Medini threats'!$A$2:$A$226,MATCH(G23,'Medini threats'!$M$2:$M$226,0)),"not in model") -> T180 | G23: =D23&"|"&E23 -> Visual + audio alert|Denial of Service | H23: Exact (same element and category)
A24: 24 | B24: ='AI threat scenarios'!A24 -> 1. Cameras (mono + stereo) | C24: ='AI threat scenarios'!B24 -> Information disclosure | D24: Mono + Stereo | E24: Information Disclosure | F24: =IFERROR(INDEX('Medini threats'!$A$2:$A$226,MATCH(G24,'Medini threats'!$M$2:$M$226,0)),"not in model") -> T001 | G24: =D24&"|"&E24 -> Mono + Stereo|Information Disclosure | H24: Exact (same element and category)
A25: 25 | B25: ='AI threat scenarios'!A25 -> 1. Cameras (mono + stereo) | C25: ='AI threat scenarios'!B25 -> Tampering | D25: Mono + Stereo | E25: Tampering | F25: =IFERROR(INDEX('Medini threats'!$A$2:$A$226,MATCH(G25,'Medini threats'!$M$2:$M$226,0)),"not in model") -> T002 | G25: =D25&"|"&E25 -> Mono + Stereo|Tampering | H25: Exact (same element and category)
A26: 26 | B26: ='AI threat scenarios'!A26 -> 2. Edge detector, YOLOv5 (roadside computing unit) | C26: ='AI threat scenarios'!B26 -> Denial of service | D26: YOLOv5 fast path | E26: Denial of Service | F26: =IFERROR(INDEX('Medini threats'!$A$2:$A$226,MATCH(G26,'Medini threats'!$M$2:$M$226,0)),"not in model") -> T015 | G26: =D26&"|"&E26 -> YOLOv5 fast path|Denial of Service | H26: Exact (same element and category)
A27: 27 | B27: ='AI threat scenarios'!A27 -> 3. Situation detection agent (MLLM call) | C27: ='AI threat scenarios'!B27 -> Denial of service | D27: Agent 1, MLLM call | E27: Denial of Service | F27: =IFERROR(INDEX('Medini threats'!$A$2:$A$226,MATCH(G27,'Medini threats'!$M$2:$M$226,0)),"not in model") -> T030 | G27: =D27&"|"&E27 -> Agent 1, MLLM call|Denial of Service | H27: Exact (same element and category)
A28: 28 | B28: ='AI threat scenarios'!A28 -> 5. Distance estimate agent (Depth Pro) | C28: ='AI threat scenarios'!B28 -> Tampering | D28: Agent 2, Depth Pro | E28: Tampering | F28: =IFERROR(INDEX('Medini threats'!$A$2:$A$226,MATCH(G28,'Medini threats'!$M$2:$M$226,0)),"not in model") -> T056 | G28: =D28&"|"&E28 -> Agent 2, Depth Pro|Tampering | H28: Exact (same element and category)
A29: 29 | B29: ='AI threat scenarios'!A29 -> 6. Message generation agent (MLLM call) | C29: ='AI threat scenarios'!B29 -> Tampering | D29: Agent 3, MLLM call | E29: Tampering | F29: =IFERROR(INDEX('Medini threats'!$A$2:$A$226,MATCH(G29,'Medini threats'!$M$2:$M$226,0)),"not in model") -> T071 | G29: =D29&"|"&E29 -> Agent 3, MLLM call|Tampering | H29: Exact (same element and category)
A30: 30 | B30: ='AI threat scenarios'!A30 -> 8. DENM encoder (ASN.1 UPER payload) | C30: ='AI threat scenarios'!B30 -> Tampering | D30: ASN.1 UPER payload | E30: Tampering | F30: =IFERROR(INDEX('Medini threats'!$A$2:$A$226,MATCH(G30,'Medini threats'!$M$2:$M$226,0)),"not in model") -> T098 | G30: =D30&"|"&E30 -> ASN.1 UPER payload|Tampering | H30: Exact (same element and category)
A31: 31 | B31: ='AI threat scenarios'!A31 -> 8. DENM encoder records | C31: ='AI threat scenarios'!B31 -> Repudiation | D31: ASN.1 UPER payload | E31: Repudiation | F31: =IFERROR(INDEX('Medini threats'!$A$2:$A$226,MATCH(G31,'Medini threats'!$M$2:$M$226,0)),"not in model") -> T102 | G31: =D31&"|"&E31 -> ASN.1 UPER payload|Repudiation | H31: Exact (same element and category)
A32: 32 | B32: ='AI threat scenarios'!A32 -> 9. RSU (services and radio front end) | C32: ='AI threat scenarios'!B32 -> Denial of service | D32: Signs, PC5, HSM | E32: Denial of Service | F32: =IFERROR(INDEX('Medini threats'!$A$2:$A$226,MATCH(G32,'Medini threats'!$M$2:$M$226,0)),"not in model") -> T114 | G32: =D32&"|"&E32 -> Signs, PC5, HSM|Denial of Service | H32: Exact (same element and category)
... A44: 44 | B44: ='AI threat scenarios'!A44 -> 11 -> 12. Link OBU to vehicle computer (Ethernet/UDP) | C44: ='AI threat scenarios'!B44 -> Tampering | D44: warning_out ↔ warning_in | E44: Tampering | F44: =IFERROR(INDEX('Medini threats'!$A$2:$A$226,MATCH(G44,'Medini threats'!$M$2:$M$226,0)),"not in model") -> T158 | G44: =D44&"|"&E44 -> warning_out ↔ warning_in|Tampering | H44: Exact (same element and category)

Sheet Comparison
A1: AI-generated TARA versus medini threat enumeration
A3: Headline | B3: Value
A4: Threats enumerated in medini | B4: =COUNTA('Medini threats'!$A$2:$A$226) -> 225
A5: AI threat scenarios analysed | B5: =COUNTA('AI threat scenarios'!$A$2:$A$44) -> 43
A6: Medini threats matched by an AI scenario | B6: =COUNTIF('Medini threats'!$Q$2:$Q$226,"Yes") -> 42
A7: Medini threats without an AI scenario | B7: =COUNTIF('Medini threats'!$Q$2:$Q$226,"No") -> 183
A8: Coverage of the medini list | B8: =ROUND(COUNTIF('Medini threats'!$Q$2:$Q$226,"Yes")/COUNTA('Medini threats'!$A$2:$A$226)*100,1) -> 18.7 | C8: %
A9: AI scenarios without a medini element | B9: =COUNTIF(Mapping!$F$2:$F$44,"not in model") -> 1
A10: AI scenarios mapped with an adapted category | B10: =COUNTIF(Mapping!$H$2:$H$44,"Category adapted") -> 5
A13: By STRIDE category | B13: Medini threats | C13: Matched | D13: AI scenarios
A14: Spoofing | B14: =COUNTIF('Medini threats'!$E$2:$E$226,$A14) -> 12 | C14: =COUNTIFS('Medini threats'!$E$2:$E$226,$A14,'Medini threats'!$Q$2:$Q$226,"Yes") -> 6 | D14: =COUNTIF(Mapping!$E$2:$E$44,$A14) -> 6
A15: Tampering | B15: =COUNTIF('Medini threats'!$E$2:$E$226,$A15) -> 63 | C15: =COUNTIFS('Medini threats'!$E$2:$E$226,$A15,'Medini threats'!$Q$2:$Q$226,"Yes") -> 14 | D15: =COUNTIF(Mapping!$E$2:$E$44,$A15) -> 14
A16: Repudiation | B16: =COUNTIF('Medini threats'!$E$2:$E$226,$A16) -> 12 | C16: =COUNTIFS('Medini threats'!$E$2:$E$226,$A16,'Medini threats'!$Q$2:$Q$226,"Yes") -> 5 | D16: =COUNTIF(Mapping!$E$2:$E$44,$A16) -> 5
A17: Information Disclosure | B17: =COUNTIF('Medini threats'!$E$2:$E$226,$A17) -> 63 | C17: =COUNTIFS('Medini threats'!$E$2:$E$226,$A17,'Medini threats'!$Q$2:$Q$226,"Yes") -> 5 | D17: =COUNTIF(Mapping!$E$2:$E$44,$A17) -> 5
A18: Denial of Service | B18: =COUNTIF('Medini threats'!$E$2:$E$226,$A18) -> 63 | C18: =COUNTIFS('Medini threats'!$E$2:$E$226,$A18,'Medini threats'!$Q$2:$Q$226,"Yes") -> 9 | D18: =COUNTIF(Mapping!$E$2:$E$44,$A18) -> 9
A19: Elevation of Privilege | B19: =COUNTIF('Medini threats'!$E$2:$E$226,$A19) -> 12 | C19: =COUNTIFS('Medini threats'!$E$2:$E$226,$A19,'Medini threats'!$Q$2:$Q$226,"Yes") -> 3 | D19: =COUNTIF(Mapping!$E$2:$E$44,$A19) -> 3
A21: By element type | B21: Medini threats | C21: Matched
A22: Component | B22: =COUNTIF('Medini threats'!$O$2:$O$226,$A22) -> 72 | C22: =COUNTIFS('Medini threats'!$O$2:$O$226,$A22,'Medini threats'!$Q$2:$Q$226,"Yes") -> 35
A23: Port | B23: =COUNTIF('Medini threats'!$O$2:$O$226,$A23) -> 102 | C23: =COUNTIFS('Medini threats'!$O$2:$O$226,$A23,'Medini threats'!$Q$2:$Q$226,"Yes") -> 0
A24: Connection | B24: =COUNTIF('Medini threats'!$O$2:$O$226,$A24) -> 51 | C24: =COUNTIFS('Medini threats'!$O$2:$O$226,$A24,'Medini threats'!$Q$2:$Q$226,"Yes") -> 7
A26: By component (component and its ports) | B26: Medini threats | C26: Matched
A27: Mono + Stereo | B27: =COUNTIF('Medini threats'!$N$2:$N$226,$A27) -> 9 | C27: =COUNTIFS('Medini threats'!$N$2:$N$226,$A27,'Medini threats'!$Q$2:$Q$226,"Yes") -> 3
A28: YOLOv5 fast path | B28: =COUNTIF('Medini threats'!$N$2:$N$226,$A28) -> 12 | C28: =COUNTIFS('Medini threats'!$N$2:$N$226,$A28,'Medini threats'!$Q$2:$Q$226,"Yes") -> 3
A29: Agent 1, MLLM call | B29: =COUNTIF('Medini threats'!$N$2:$N$226,$A29) -> 18 | C29: =COUNTIFS('Medini threats'!$N$2:$N$226,$A29,'Medini threats'!$Q$2:$Q$226,"Yes") -> 3
A30: Agent 2, Depth Pro | B30: =COUNTIF('Medini threats'!$N$2:$N$226,$A30) -> 12 | C30: =COUNTIFS('Medini threats'!$N$2:$N$226,$A30,'Medini threats'!$Q$2:$Q$226,"Yes") -> 1
A31: Agent 3, MLLM call | B31: =COUNTIF('Medini threats'!$N$2:$N$226,$A31) -> 18 | C31: =COUNTIFS('Medini threats'!$N$2:$N$226,$A31,'Medini threats'!$Q$2:$Q$226,"Yes") -> 1
A32: ASN.1 UPER payload | B32: =COUNTIF('Medini threats'!$N$2:$N$226,$A32) -> 12 | C32: =COUNTIFS('Medini threats'!$N$2:$N$226,$A32,'Medini threats'!$Q$2:$Q$226,"Yes") -> 2
A33: Signs, PC5, HSM | B33: =COUNTIF('Medini threats'!$N$2:$N$226,$A33) -> 18 | C33: =COUNTIFS('Medini threats'!$N$2:$N$226,$A33,'Medini threats'!$Q$2:$Q$226,"Yes") -> 5
A34: PC5 + Uumodem | B34: =COUNTIF('Medini threats'!$N$2:$N$226,$A34) -> 18 | C34: =COUNTIFS('Medini threats'!$N$2:$N$226,$A34,'Medini threats'!$Q$2:$Q$226,"Yes") -> 3
A35: Verify, warning logic | B35: =COUNTIF('Medini threats'!$N$2:$N$226,$A35) -> 12 | C35: =COUNTIFS('Medini threats'!$N$2:$N$226,$A35,'Medini threats'!$Q$2:$Q$226,"Yes") -> 2
A36: Visual + audio alert | B36: =COUNTIF('Medini threats'!$N$2:$N$226,$A36) -> 9 | C36: =COUNTIFS('Medini threats'!$N$2:$N$226,$A36,'Medini threats'!$Q$2:$Q$226,"Yes") -> 2
A37: Gemini API | B37: =COUNTIF('Medini threats'!$N$2:$N$226,$A37) -> 18 | C37: =COUNTIFS('Medini threats'!$N$2:$N$226,$A37,'Medini threats'!$Q$2:$Q$226,"Yes") -> 5
A38: PKI, operator | B38: =COUNTIF('Medini threats'!$N$2:$N$226,$A38) -> 18 | C38: =COUNTIFS('Medini threats'!$N$2:$N$226,$A38,'Medini threats'!$Q$2:$Q$226,"Yes") -> 5
A39: (connection) | B39: =COUNTIF('Medini threats'!$N$2:$N$226,$A39) -> 51 | C39: =COUNTIFS('Medini threats'!$N$2:$N$226,$A39,'Medini threats'!$Q$2:$Q$226,"Yes") -> 7
A41: Notes
A42: How the matching works | B42: Each AI scenario is mapped on the Mapping sheet to one medini element and one STRIDE category. The key 'element|category' is looked up in the medini list, which gives the threat ID. The medini sheet counts, for every threat, how many AI scenarios point at it (column P) and whether it is covered (column Q).
A43: Granularity differs | B43: Medini enumerates every element and category mechanically and produces no description, impact or feasibility. The AI produced concrete attack paths with ratings, and one scenario can span several elements. A low coverage percentage therefore does not mean the AI missed threats; it means the enumeration is much finer.
A44: Categories differ for connections | B44: Medini generates only Tampering, Information Disclosure and Denial of Service for ports and connections. Scenarios that the AI classified as Spoofing on a link (forged payload injection, DENM replay, camera feed injection) were mapped to the Tampering threat of that connection.
A45: Elements missing from the model | B45: The API key and the cloud account have no element in the medini model, so that AI scenario cannot be matched. The prompts, the model files and the physical scene in front of the camera are also absent as elements, and were mapped to the component that hosts them.
A46: Suggested next step | B46: Use the 'To Be Assessed' column of the medini export: keep the threats that an AI scenario matched, plus those the team judges relevant, and set the rest to false with a documented reason. That turns 225 enumerated threats into an assessable set.
A49: Strict intersection (all six model outputs and medini) | B49: Value
A50: Scenarios in the strict set | B50: =COUNTA('TARA strict intersection'!$A$2:$A$23) -> 22
A51: Critical | B51: =COUNTIF('TARA strict intersection'!$R$2:$R$23,"Critical") -> 9
A52: High | B52: =COUNTIF('TARA strict intersection'!$R$2:$R$23,"High") -> 5
A53: Medium | B53: =COUNTIF('TARA strict intersection'!$R$2:$R$23,"Medium") -> 5
A54: Low | B54: =COUNTIF('TARA strict intersection'!$R$2:$R$23,"Low") -> 3
A55: Average risk score | B55: =ROUND(AVERAGE('TARA strict intersection'!$AE$2:$AE$23),1) -> 80.7
A56: Pairs agreed by all six models | B56: 23
A57: Of which not enumerated by medini | B57: 1
A58: Excluded pair | B58: Spoofing on the PC5 sidelink: raised by all six models, but medini generates no Spoofing threat for connections.
A61: Rare findings (raised by one or two models) | B61: Value
A62: Scenarios in the rare set | B62: =COUNTA('Rare findings (1-2 models)'!$A$2:$A$14) -> 13
A63: Raised by one model only | B63: 6
A64: Raised by two models | B64: 7
A65: Enumerated by medini | B65: 10
A66: Not enumerated by medini | B66: 3
A67: Critical | B67: =COUNTIF('Rare findings (1-2 models)'!$R$2:$R$14,"Critical") -> 3
A68: High | B68: =COUNTIF('Rare findings (1-2 models)'!$R$2:$R$14,"High") -> 2
A69: Medium | B69: =COUNTIF('Rare findings (1-2 models)'!$R$2:$R$14,"Medium") -> 7
A70: Low | B70: =COUNTIF('Rare findings (1-2 models)'!$R$2:$R$14,"Low") -> 1
A71: Average risk score | B71: =ROUND(AVERAGE('Rare findings (1-2 models)'!$AE$2:$AE$14),1) -> 63.7
A72: Note | B72: Copilot contributes to 11 of the 13 rare findings and is the only source of 6 of them. The three not enumerated by medini are repudiation and elevation of privilege on connections, categories the tool does not generate for that element type.

Sheet Reference
A1: Impact Criteria | B1: Weight | D1: Lower Limit | E1: Risk Level | G1: Impact Rating | H1: Threshold Value
A2: Safety | B2: 5 | D2: 100 | E2: Critical | G2: Severe | H2: 8.3
A3: Operational | B3: 1 | D3: 49 | E3: High | G3: Major | H3: 5.1
A4: Financial | B4: 0.5 | D4: 16 | E4: Medium | G4: Moderate | H4: 2.5
A5: Privacy | B5: 0.25 | D5: 1 | E5: Low | G5: Negligible | H5: 1
D6: 0 | E6: Very Low
A7: Safety =>S
A8: Impact Rating | B8: Criteria for Safety Impact Rating | C8: Value
A9: Severe | B9: S3: Life-threatening injuries (survival uncertain), fatal injuries | C9: 10 | G9: Risk Assessment
A10: Major | B10: S2: Severe and life-threatening injuries (survival probable) | C10: 7 | E10: Impact Rating: | G10: Low | H10: Low | I10: Low | J10: Medium | K10: Negligible | L10: Impact Level=>l
A11: Moderate | B11: S1: Light and moderate injuries | C11: 4 | E11: (5*S + 1*O + 0.5*F + 0.25*P) / 4 | G11: Low | H11: Medium | I11: Medium | J11: Medium | K11: Moderate
A12: Negligible | B12: S0: No injuries | C12: 1 | E12: Risk Score: | G12: Low | H12: Medium | I12: High | J12: High | K12: Major
E13: R = 1 + I×F | G13: Medium | H13: High | I13: High | J13: Critical | K13: Severe
G14: Very Low | H14: Low | I14: Medium | J14: High
A15: Reputational => R | G15: Attack Feasibility Level => F
A16: Impact Rating | B16: Criteria for Reputational Impact Rating | C16: Value | E16: Threat category (STRIDE)
A17: Severe | B17: The reputational damage leads to catastrophic consequences which the affected road user might not overcome. | C17: 10 | E17: Spoofing | G17: Risk Score =>R | H17: R = 1 + I × F
A18: Major | B18: The reputational damage leads to substantial consequences which the affected road user will be able to overcome | C18: 7 | E18: Tampering | G18: Risk Appetite | H18: Low
A19: Moderate | B19: The reputational damage leads to inconvenient consequences which the affected road user will be able to overcome with limited resources | C19: 4 | E19: Repudiation | G19: RA Goal: | H19: Risk Reduction
A20: Negligible | B20: The reputational damage leads to no effect, negligible consequences or is irrelevant to the road user. | C20: 1 | E20: Information Disclosure
E21: Denial of Service
E22: Elevation of Privileges
A23: Operational => O
A24: Impact Rating | B24: Criteria for Operational Impact Rating | C24: Value
A25: Severe | B25: The operational damage leads to the loss or impairment of a core vehicle function. EXAMPLE 1 Vehicle not working or showing unexpected behaviour of core functions such as enabling of limp home mode or autonomous driving to an unintended location. | C25: 10
A26: Major | B26: The operational damage leads to the loss or impairment of an important vehicle function. EXAMPLE 2 Significant annoyance of the driver. | C26: 7
A27: Moderate | B27: The operational damage leads to partial degradation of a vehicle function. EXAMPLE 3 User satisfaction negatively affected. | C27: 4
A28: Negligible | B28: The operational damage leads to no impairment or non-perceivable impairment of a vehicle function. | C28: 1
A31: Privacy => P
A32: Impact Rating | B32: Criteria for Privacy Impact Rating | C32: Value
A33: Severe | B33: The privacy damage leads to significant or even irreversible impact to the road user. The information regarding the road user is highly sensitive and easy to link to a PII principal. | C33: 10
A34: Major | B34: The privacy damage leads to serious impact to the road user. The information regarding the road user is: a) highly sensitive and difficult to link to a PII principal; or b) sensitive and easy to link to a PII principal. | C34: 7
A35: Moderate | B35: The privacy damage leads to inconvenient consequences to the road user. The information regarding the road user is: a) sensitive but difficult to link to a PII principal; or b) not sensitive but easy to link to a PII principal. | C35: 4
A36: Negligible | B36: The privacy damage leads to no effect or, negligible consequences or is irrelevant to the road user. The information regarding the road user is not sensitive and difficult to link to a PII principal. | C36: 1
A39: Attack Feasibility Rating => F
A40: Attack Vector | B40: Description | C40: Level | D40: Value
A41: Network | B41: Potential attack path is bound to network stack without any limitation | C41: High | D41: 10
A42: Adjacent | B42: Potential attack path is bound to network stack; however, the connection is limited physically or logically. | C42: Medium | D42: 7
A43: Local | B43: Potential attack path is not bound to network stack and threat agents require direct access to the item for realizing the attack path. | C43: Low | D43: 4
A44: Physical | B44: Threat agents require physical access to realize the attack path. | C44: Very low | D44: 1
A46: Risk Treatment
A47: Method | B47: Description
A48: Risk Reduction | B48: The level of risk shall be managed by introducing, removing or altering security controls so that the residual risk can be assessed as being acceptable. Mitigation would be implemented
A49: Risk Retention | B49: The decision on retaining the risk without further action shall be taken depending on risk evaluation.
A50: Risk Avoidance | B50: The activity or condition that gives rise to the particular risk shall be avoided. EXAMPLE 1 Avoiding the risk by removing the risk sources, deciding not to start or continue with the activity that gives rise to the risk.
A51: Risk Transfer | B51: The risk shall be shared with another party that can most effectively manage the particular risk depending on risk evaluation. EXAMPLE 2 Sharing risk through contracts or transferring risk by buying insurance.

Sheet How to use
A1: TARA - AI-based accident detection (combined architecture)
A2: Scope | B2: All threat scenario themes that the six LLM outputs agreed on (consensus matrix of the paper), one row per distinct attack path. Column X gives the theme and how many models proposed it.
A3: Structure | B3: Columns and formulas are taken from TARA V3.xlsx; the Reference sheet is unchanged, so scales and weights are identical.
A5: Cells you edit | B5: A to O, S to X. Grey header columns are manual input; dropdowns are active in B, C, F, H, J, L, N and S.
A6: Cells you must not edit | B6: P, Q, R (yellow headers) and the helper columns Y to AE. They are formulas.
A8: Impact values | B8: Severe 10, Major 7, Moderate 4, Negligible 1 (Reference sheet, columns A to C).
A9: Impact formula | B9: Impact = (5*Safety + 1*Operational + 0.5*Financial + 0.25*Privacy) / 4
A10: Severity level | B10: Severe from 8.3, Major from 5.1, Moderate from 2.5, Negligible from 1 (Reference!G:H).
A11: Feasibility | B11: Attack vector to level and value: Network = High = 10, Adjacent = Medium = 7, Local = Low = 4, Physical = Very low = 1 (Reference!A39:D44).
A12: Risk score | B12: R = 1 + Impact x Feasibility. Risk value: Critical from 100, High from 49, Medium from 16, Low from 1 (Reference!D:E).
A14: Change against TARA V3 | B14: In TARA V3 the Risk Value formula returns Reference!$G$2 ('Severe') for scores of 100 and above instead of Reference!$E$2 ('Critical'). Only row 6 of Paper_1 used $E$2. This workbook uses $E$2 in every row, so scores of 100 and above read 'Critical'. Check this before comparing with older results.
A16: Provenance | B16: Column X records how many of the six LLM outputs proposed the scenario, based on 'processing of the LLM_JSON_Threads_analysis.docx'.
A17: Ratings | B17: The impact ratings and the notes in this workbook were proposed with AI assistance (Claude Opus 5) and must be reviewed and agreed by the team before use in the paper. See AI_usage_log.md, Entry 013.
... A23: Editing the mapping | B23: Change columns D and E of the Mapping sheet to re-point a scenario; every count updates automatically.
A25: Security attribute convention
A26: Spoofing | B26: Authenticity - the receiver cannot establish that the message or input really comes from the claimed source.
A27: Tampering | B27: Integrity - data or component behaviour is modified.
A28: Repudiation | B28: Non-repudiation when a party could deny an action towards others; Accountability when internal actions cannot be traced to their origin.
A29: Information disclosure | B29: Confidentiality.
A30: Denial of service | B30: Availability.
A31: Elevation of privilege | B31: Authorization - an actor obtains rights it should not have.
A32: Note | B32: Authorization was added beyond the three attributes requested, because otherwise the two elevation of privilege rows have no correct value. Remove it from the dropdown and use Integrity if the team prefers.
A34: Medini threat ID | B34: Column X now holds the medini threat number. On the full analysis sheet it is a formula that reads the Mapping sheet, so it follows any change of the mapping; on the strict sheet it is fixed. The previous content of column X (theme, agreement and source) moved to column AF.
A36: Rare findings sheet | B36: Threat scenarios that only one or two of the six model outputs raised. Column X holds the medini threat number where one exists, column AF names the models that raised it and column AG quotes their wording.
